Workbook

Sheet AGOSTO
A1: EQUIORIENTE LTDA
A2: SITUACION FINANCIERA
A3: FECHA: 30 AGOSTO DE 2021
A6: 1 | C6: ACTIVO
A8: 11 | C8: Efectivo y equivalentes al efectivo
A9: 1105 | C9: Caja | E9: =+D10 -> 31272301
A10: 110505 | C10: Caja general | D10: 31272301
A11: 1120 | C11: Cuentas de ahorro
A12: 112005 | C12: Bancos | E12: =+D13 -> 5634973
A13: 11200501 | C13: BBVA | D13: 5634973
A14: 11200502 | C14: Davivienda
A16: 13 | C16: Cuentas por cobrar (instrumentos financieros)
A17: 1305 | C17: Clientes | E17: =SUM(D19:D21) -> 7483662
A18: 130505 | C18: Nacionales
C19: Fenix Constructores | D19: 5855549
C20: Construcasa | D20: 1386670
C21: gonzalez bohorque | D21: 241443
A24: 130515 | C24: Deudores facturacion sin iva | E24: =+D25+D26 -> 6005402
C25: Miriam Serrano | D25: 4577126
C26: Clientes varios | D26: 1428276
A28: 1355 | C28: Anticipo de impuestos y contribuciones o saldos a favor | E28: =SUM(D29:D33) -> 2836193
A29: 135505 | C29: Anticipo de impuestos de renta y complementarios | D29: 1762000
A30: 135518 | C30: Reteica | D30: 51861
A31: 135515 | C31: Retención en la fuente | D31: 771332
A32: 135517 | C32: Impuesto a las ventas retenido | D32: 0
A33: 13559006 | C33: Autorretencion de renta | D33: 251000
A35: 14 | C35: Inventarios | E35: =+D36 -> 166485896
A36: 1435 | C36: Mercancías no fabricadas por la empresa | D36: 166485896
A39: 15 | C39: Propiedades planta y equipo | E39: =+D40+D42+D45+D47+D49+D51 -> 354443971
A40: 1512 | C40: Maquinaria y equipos en montaje | D40: =+D41 -> 10126196
A41: 151210 | C41: Equipo de oficina | D41: 10126196
A42: 1516 | C42: Construcciones y edificaciones | D42: =+D43+D44 -> 381000000
A43: 151605 | C43: Apto sion | D43: 91000000
A44: 151610 | C44: Apto tamara | D44: 290000000
A45: 1524 | C45: Equipo de oficina | D45: =+D46 -> 1070000
A46: 152410 | C46: Equipos | D46: 1070000
A47: 1528 | C47: Equipo de computación y comunicación | D47: =+D48 -> 3109000
A48: 152805 | C48: Equipo de procesamiento de datos | D48: 3109000
A49: 1540 | C49: Flota y equipo de transporte | D49: 34596000
A50: 154008 | C50: Camiones, volquetas y furgones | D50: 34596000
A51: 1592 | C51: Depreciación acumulada | D51: -75457225
A53: 16 | C53: Intangibles | E53: =+D54 -> 2548980
A54: 1635 | C54: Licencias | D54: 2548980
A56: TOTAL ACTIVO | E56: =SUM(E9:E54) -> 576711378
A60: 2365 | C60: Retención en la fuente | E60: =+D61+D62 -> 63000
A61: 236525 | C61: Retención en la fuente | D61: 55000
A62: 236706 | C62: Autorretencion | D62: 8000
A64: 2370 | C64: Retenciones y aportes de nómina | E64: =+D65+D66+D67 -> 282100
A65: 237005 | C65: Aportes a entidades promotoras de salud EPS | D65: 124700
A66: 237006 | C66: Aportes a administradoras de riesgos profesionales arp | D66: 32700
A67: 237010 | C67: Aportes al i.c.b.f, sena y cajas compensación | D67: 124700
A68: 2380 | C68: Acreedores varios | E68: =+D69 -> 498700
A69: 238030 | C69: Fondos de cesantías y/o pensiones | D69: 498700
A72: 24 | C72: Impuestos, gravámenes y tasas | E72: =+D73+D74 -> 437000
A73: 2408 | C73: Impuesto sobre las ventas por pagar | D73: 437000
A74: 2412 | C74: industria y comercio | D74: 0
A78: 26 | C78: Provisión de pasivos
A79: 2610 | C79: Para obligaciones laborales | E79: =SUM(D80:D85) -> 3454995
A80: 261005 | C80: Cesantías | D80: 1861238
A81: 261010 | C81: Intereses sobre cesantías | D81: 214175
A82: 261015 | C82: Vacaciones | D82: 465310
A83: 261020 | C83: Prima | D83: 914272
A87: 22 | C87: PROVEEDORES
A88: 2205 | C88: Nacionales | E88: =+D90+D91 -> 1264428
A89: 221005 | C89: Proveedores por debajo
C90: Olga gomez (metalmartinez) | D90: 1264428
A93: TOTAL PASIVO | E93: =SUM(E59:E92) -> 6000223
A96: 3 | C96: PATRIMONIO
A98: 31 | C98: Capital social | E98: =+D99 -> 574301990
A99: 3105 | C99: Capital suscrito y pagado | D99: 574301990
A100: 310505 | C100: Capital autorizado
A103: 36 | C103: Resultados del ejercicio | E103: =+D104 -> -3590834.6
A104: 3605 | C104: =+C105 -> Perdida del ejercicio | D104: =+D105 -> -3590834.6
A105: 360501 | C105: Perdida del ejercicio | D105: =+'PYG '!AF154 -> -3590834.6
A107: 37 | C107: UTILIDAD DEL EJERCICIO ANTERIORES | E107: =+D108+D109 -> 0
A108: 37 | C108: Utilidad de ejercicios anteriores
A111: TOTAL PATRIMONIO | E111: =+E98+E103+E107 -> 5.7071116e+08
A113: TOTAL PATRIMONIO Y PASIVO | E113: =+E111+E93 -> 5.7671138e+08
E115: 0
E116: =+E56-E93-E111 -> -0.36666667

Sheet PYG 
A1: EQUIORIENTE LTDA
A2: INFORMES AÑO 2021
C4: 44197 | G4: 44228 | J4: 44256 | N4: 44287 | R4: 44317 | V4: 44348 | Z4: 44378 | AD4: 44409
A5: Cuenta | C5: Mov. 02/01/2021 a 31/01/2021 | E5: Saldos a 31/01/1 | G5: Mov. 01/02/2021 a 28/02/2021 | I5: Saldos a 28/02/2021 | J5: Mov. 01/03/2021 a 31/03/2021 | L5: Saldos a 31/03/2021 | N5: Mov. 01/04/2021 a 30/04/2021 | P5: Saldos a 30/04/2021 | R5: Mov. 01/04/2021 a 30/04/2021 | T5: Saldos a 30/04/2021 | V5: Mov. 01/04/2021 a 30/04/2021 | X5: Saldos a 30/04/2021 | Z5: Mov. 01/04/2021 a 30/04/2021 | AB5: Saldos a 30/04/2021 | AD5: Mov. 01/04/2021 a 30/04/2021 | AF5: c vvvvvv
A6: Cód. | B6: Nombre | C6: Débitos | D6: Créditos | E6: Saldo actual | G6: Débitos | H6: Créditos | I6: Saldo actual | J6: Débitos | K6: Créditos | L6: Saldo actual | N6: Débitos | O6: Créditos | P6: Saldo actual | R6: Débitos | S6: Créditos | T6: Saldo actual | V6: Débitos | W6: Créditos | X6: Saldo actual | Z6: Débitos | AA6: Créditos | AB6: Saldo actual | AD6: Débitos | AE6: Créditos | AF6: Saldo actual
A7: 4 | B7: INGRESOS | C7: 0 | D7: =D8+D14 -> 11344635 | E7: =E8+E14 -> 11344635 | G7: 0 | H7: =H8+H14 -> 12286773 | I7: =E7+H7 -> 23631408 | J7: 0 | K7: =K8+K14 -> 14156650 | L7: =I7+K7 -> 37788058 | N7: 0 | O7: =O8+O14 -> 15531100 | P7: =L7+O7 -> 53319158 | R7: 0 | S7: =S8+S14 -> 14472469 | T7: =P7+S7 -> 67791627 | V7: 0 | W7: =W8+W14 -> 19253718 | X7: =T7+W7 -> 87045345 | Z7: 0 | AA7: =AA8+AA14 -> 12791478 | AB7: =X7+AA7 -> 99836823 | AD7: 0 | AE7: =AE8+AE14 -> 14702304 | AF7: =AB7+AE7 -> 114539127
A8: 41 | B8: Operacionales | C8: 0 | D8: =D9 -> 4088450 | E8: =E9 -> 4088450 | G8: 0 | H8: =H9 -> 3444630 | I8: =E8+H8 -> 7533080 | J8: 0 | K8: =K9 -> 4294490 | L8: =I8+K8 -> 11827570 | N8: 0 | O8: =O9 -> 3094715 | P8: =L8+O8 -> 14922285 | R8: 0 | S8: =S9 -> 3036250 | T8: =P8+S8 -> 17958535 | V8: 0 | W8: =W9 -> 3220640 | X8: =T8+W8 -> 21179175 | Z8: 0 | AA8: =AA9 -> 2982171 | AB8: =X8+AA8 -> 24161346 | AD8: 0 | AE8: =AE9 -> 2259634 | AF8: =AB8+AE8 -> 26420980
A9: 4155 | B9: Actividades inmobiliarias, empresariales y de alquiler | C9: 0 | D9: =+D10+D11+D12 -> 4088450 | E9: =D9 -> 4088450 | G9: 0 | H9: =H10+H11+H12 -> 3444630 | I9: =E9+H9 -> 7533080 | J9: 0 | K9: =K10+K11+K12 -> 4294490 | L9: =I9+K9 -> 11827570 | N9: 0 | O9: =O10+O11+O12 -> 3094715 | P9: =L9+O9 -> 14922285 | R9: 0 | S9: =S10+S11+S12 -> 3036250 | T9: =P9+S9 -> 17958535 | V9: 0 | W9: =W10+W11+W12 -> 3220640 | X9: =T9+W9 -> 21179175 | Z9: 0 | AA9: =AA10+AA11+AA12 -> 2982171 | AB9: =X9+AA9 -> 24161346 | AD9: 0 | AE9: =AE10+AE11+AE12 -> 2259634 | AF9: =AB9+AE9 -> 26420980
A10: 415520 | B10: Alquiler IVA | C10: 0 | D10: 4058450 | E10: =+D10 -> 4058450 | G10: 0 | H10: 3409630 | I10: =E10+H10 -> 7468080 | J10: 0 | K10: 4294490 | L10: =I10+K10 -> 11762570 | N10: 0 | O10: 3019715 | P10: =L10+O10 -> 14782285 | R10: 0 | S10: 3036250 | T10: =P10+S10 -> 17818535 | V10: 0 | W10: 3175640 | X10: =T10+W10 -> 20994175 | Z10: 0 | AA10: 2982171 | AB10: =X10+AA10 -> 23976346 | AD10: 0 | AE10: 2259634 | AF10: =AB10+AE10 -> 26235980
A11: 415525 | B11: VENTA EQUIPO | D11: 0 | E11: =+D11 -> 0 | G11: 0 | H11: 0 | I11: =E11+H11 -> 0 | K11: 0 | L11: =I11+K11 -> 0 | O11: 0 | P11: =L11+O11 -> 0 | S11: 0 | T11: =P11+S11 -> 0 | W11: 0 | X11: =T11+W11 -> 0 | AA11: 0 | AB11: =X11+AA11 -> 0 | AE11: 0 | AF11: =AB11+AE11 -> 0
A12: 415515 | B12: Transporte | C12: 0 | D12: 30000 | E12: =+D12 -> 30000 | G12: 0 | H12: 35000 | I12: =E12+H12 -> 65000 | J12: 0 | K12: 0 | L12: =I12+K12 -> 65000 | N12: 0 | O12: 75000 | P12: =L12+O12 -> 140000 | R12: 0 | S12: 0 | T12: =P12+S12 -> 140000 | V12: 0 | W12: 45000 | X12: =T12+W12 -> 185000 | Z12: 0 | AA12: 0 | AB12: =X12+AA12 -> 185000 | AD12: 0 | AE12: 0 | AF12: =AB12+AE12 -> 185000
L13: =I13+K13 -> 0
A14: 42 | B14: No operacionales | C14: 0 | D14: =D15+D19+D22+D24 -> 7256185 | E14: =+D14 -> 7256185 | G14: 0 | H14: =H15+H19+H22+H24 -> 8842143 | I14: =E14+H14 -> 16098328 | J14: 0 | K14: =K15+K19+K22+K24 -> 9862160 | L14: =I14+K14 -> 25960488 | N14: 0 | O14: =O15+O19+O22+O24 -> 12436385 | P14: =L14+O14 -> 38396873 | R14: 0 | S14: =S15+S19+S22+S24 -> 11436219 | T14: =P14+S14 -> 49833092 | V14: 0 | W14: =W15+W19+W22+W24 -> 16033078 | X14: =T14+W14 -> 65866170 | Z14: 0 | AA14: =AA15+AA19+AA22+AA24 -> 9809307 | AB14: =X14+AA14 -> 75675477 | AD14: 0 | AE14: =AE15+AE19+AE22+AE24 -> 12442670 | AF14: =AB14+AE14 -> 88118147
A15: 4210 | B15: Financieros | C15: 0 | D15: =+D16+D17 -> 3538 | E15: =+D15 -> 3538 | G15: 0 | H15: =+H16 -> 3553 | I15: =E15+H15 -> 7091 | J15: 0 | K15: =+K16+K17 -> 1206 | L15: =I15+K15 -> 8297 | N15: 0 | O15: =+O16+O17 -> 112 | P15: =L15+O15 -> 8409 | R15: 0 | S15: =+S16+S17 -> 444 | T15: =P15+S15 -> 8853 | V15: 0 | W15: =+W16+W17 -> 681 | X15: =T15+W15 -> 9534 | Z15: 0 | AA15: =+AA16+AA17 -> 570 | AB15: =X15+AA15 -> 10104 | AD15: 0 | AE15: =+AE16+AE17 -> 644 | AF15: =AB15+AE15 -> 10748
A16: 421005 | B16: Intereses | C16: 0 | D16: 3538 | E16: =+D16 -> 3538 | G16: 0 | H16: 3553 | I16: =E16+H16 -> 7091 | J16: 0 | K16: 1206 | L16: =I16+K16 -> 8297 | N16: 0 | O16: 112 | P16: =L16+O16 -> 8409 | R16: 0 | S16: 444 | T16: =P16+S16 -> 8853 | V16: 0 | W16: 681 | X16: =T16+W16 -> 9534 | Z16: 0 | AA16: 570 | AB16: =X16+AA16 -> 10104 | AD16: 0 | AE16: 644 | AF16: =AB16+AE16 -> 10748
A17: 421095 | B17: intereses prestamos socios | E17: =+D17 -> 0 | H17: 0 | I17: =E17+H17 -> 0 | K17: 0 | L17: =I17+K17 -> 0 | N17: 0 | O17: 0 | P17: =L17+O17 -> 0 | R17: 0 | S17: 0 | T17: =P17+S17 -> 0 | V17: 0 | W17: 0 | X17: =T17+W17 -> 0 | Z17: 0 | AA17: 0 | AB17: =X17+AA17 -> 0 | AD17: 0 | AE17: 0 | AF17: =AB17+AE17 -> 0
L18: =I18+K18 -> 0
A19: 4220 | B19: ARRENDAMIENTOS APARTAMENTOS | C19: 0 | D19: =D20 -> 1960600 | E19: =+D19 -> 1960600 | G19: 0 | H19: =+H20 -> 1960600 | I19: =E19+H19 -> 3921200 | J19: 0 | K19: =+K20 -> 1960600 | L19: =I19+K19 -> 5881800 | N19: 0 | O19: =O20 -> 1960600 | P19: =L19+O19 -> 7842400 | R19: 0 | S19: =S20 -> 1960600 | T19: =P19+S19 -> 9803000 | V19: 0 | W19: =W20 -> 1960600 | X19: =T19+W19 -> 11763600 | Z19: 0 | AA19: =AA20 -> 1960600 | AB19: =X19+AA19 -> 13724200 | AD19: 0 | AE19: =AE20 -> 1960600 | AF19: =AB19+AE19 -> 15684800
A20: 422010 | B20: Apartamentos Arrendados | C20: 0 | D20: 1960600 | E20: =+D20 -> 1960600 | G20: 0 | H20: =+K20 -> 1960600 | I20: =E20+H20 -> 3921200 | J20: 0 | K20: 1960600 | L20: =I20+K20 -> 5881800 | N20: 0 | O20: 1960600 | P20: =L20+O20 -> 7842400 | R20: 0 | S20: 1960600 | T20: =P20+S20 -> 9803000 | V20: 0 | W20: 1960600 | X20: =T20+W20 -> 11763600 | Z20: 0 | AA20: 1960600 | AB20: =X20+AA20 -> 13724200 | AD20: 0 | AE20: 1960600 | AF20: =AB20+AE20 -> 15684800
L21: =I21+K21 -> 0
A22: 4235 | B22: Servicios | C22: 0 | D22: =D23 -> 5292010 | E22: =+D22 -> 5292010 | G22: 0 | H22: =H23 -> 6877990 | I22: =E22+H22 -> 12170000 | J22: 0 | K22: =K23 -> 7900354 | L22: =I22+K22 -> 20070354 | N22: 0 | O22: =O23 -> 10475673 | P22: =L22+O22 -> 30546027 | R22: 0 | S22: =S23 -> 9475175 | T22: =P22+S22 -> 40021202 | V22: 0 | W22: =W23 -> 14071797 | X22: =T22+W22 -> 54092999 | Z22: 0 | AA22: =AA23 -> 7846784 | AB22: =X22+AA22 -> 61939783 | AD22: 0 | AE22: =AE23 -> 10481424 | AF22: =AB22+AE22 -> 72421207
A23: 423510 | B23: VENTAS SIN IVA | C23: 0 | D23: 5292010 | E23: =+D23 -> 5292010 | G23: 0 | H23: 6877990 | I23: =E23+H23 -> 12170000 | J23: 0 | K23: 7900354 | L23: =I23+K23 -> 20070354 | N23: 0 | O23: 10475673 | P23: =L23+O23 -> 30546027 | R23: 0 | S23: 9475175 | T23: =P23+S23 -> 40021202 | V23: 0 | W23: 14071797 | X23: =T23+W23 -> 54092999 | Z23: 0 | AA23: 7846784 | AB23: =X23+AA23 -> 61939783 | AD23: 0 | AE23: 10481424 | AF23: =AB23+AE23 -> 72421207
A24: 4295 | B24: DIVERSOS | C24: 0 | D24: =+D25 -> 37 | E24: =+D24 -> 37 | G24: 0 | H24: =+H25 -> 0 | I24: =E24+H24 -> 37 | J24: 0 | K24: =+K25 -> 0 | L24: =I24+K24 -> 37 | N24: 0 | O24: =+O25 -> 0 | P24: =L24+O24 -> 37 | R24: 0 | S24: =+S25 -> 0 | T24: =P24+S24 -> 37 | V24: 0 | W24: =+W25 -> 0 | X24: =T24+W24 -> 37 | Z24: 0 | AA24: =+AA25 -> 1353 | AB24: =X24+AA24 -> 1390 | AD24: 0 | AE24: =+AE25 -> 2 | AF24: =AB24+AE24 -> 1392 | AG24: 3
A25: 429581 | B25: Ajuste al peso | C25: 0 | D25: 37 | E25: =+D25 -> 37 | G25: 0 | I25: =E25+H25 -> 37 | J25: 0 | L25: =I25+K25 -> 37 | N25: 0 | O25: 0 | P25: =L25+O25 -> 37 | R25: 0 | S25: 0 | T25: =P25+S25 -> 37 | V25: 0 | W25: 0 | X25: =T25+W25 -> 37 | Z25: 0 | AA25: =1360-7 -> 1353 | AB25: =X25+AA25 -> 1390 | AD25: 0 | AE25: 2 | AF25: =AB25+AE25 -> 1392
A27: 5 | B27: GASTOS | C27: =C28+C140+C118 -> 9031235 | D27: 0 | E27: =+C27 -> 9031235 | G27: =G28+G140+G118 -> 12657564 | H27: 0 | I27: =E27+G27 -> 21688799 | J27: =J28+J140+J118 -> 14106743 | K27: 0 | L27: =I27+J27 -> 35795542 | N27: =N28+N140+N118 -> 17975576 | O27: 0 | P27: =L27+N27 -> 53771118 | R27: =R28+R140+R118 -> 12421885 | S27: 0 | T27: =P27+R27 -> 66193003 | V27: =V28+V140+V118 -> 13474748 | W27: 0 | X27: =T27+V27 -> 79667751 | Z27: =Z28+Z140+Z118 -> 14035260 | AA27: 0 | AB27: =X27+Z27 -> 93703011 | AD27: =AD28+AD140+AD118 -> 13118813 | AE27: 0 | AF27: =AB27+AD27 -> 1.0682182e+08
A28: 51 | B28: Operacionales de administración | C28: =C29+C45+C56+C50+C63+C66+C77+C83+C90+C104+C60+C96 -> 8946851 | D28: 0 | E28: =+C28 -> 8946851 | G28: =G29+G45+G56+G50+G63+G66+G77+G83+G90+G104+G60+G96 -> 12329940 | H28: 0 | I28: =E28+G28 -> 21276791 | J28: =J29+J45+J56+J50+J63+J66+J77+J83+J90+J104+J60+J96 -> 13307958 | K28: 0 | L28: =I28+J28 -> 34584749 | N28: =N29+N45+N56+N50+N63+N66+N77+N83+N90+N104+N60+N96 -> 16977646 | O28: 0 | P28: =L28+N28 -> 51562395 | R28: =R29+R45+R56+R50+R63+R66+R77+R83+R90+R104+R60+R96 -> 11666774 | S28: 0 | T28: =P28+R28 -> 63229169 | V28: =V29+V45+V56+V50+V63+V66+V77+V83+V90+V104+V60+V96 -> 12699979 | W28: 0 | X28: =T28+V28 -> 75929148 | Z28: =Z29+Z45+Z56+Z50+Z63+Z66+Z77+Z83+Z90+Z104+Z60+Z96 -> 13275217 | AA28: 0 | AB28: =X28+Z28 -> 89204365 | AD28: =AD29+AD45+AD56+AD50+AD63+AD66+AD77+AD83+AD90+AD104+AD60+AD96 -> 12322820 | AE28: 0 | AF28: =AB28+AD28 -> 1.0152718e+08
A29: 5105 | B29: Gastos de personal | C29: =+C38 -> 30000 | D29: 0 | E29: =+C29 -> 30000 | G29: =SUM(G30:G42) -> 4888998 | H29: 0 | I29: =E29+G29 -> 4918998 | J29: =SUM(J30:J42) -> 4803581 | K29: 0 | L29: =I29+J29 -> 9722579 | N29: =N30+N32+N33+N34+N35+N36+N37+N38+N39+N40+N41+N42 -> 4803967 | O29: 0 | P29: =L29+N29 -> 14526546 | R29: =R30+R32+R33+R34+R35+R36+R37+R38+R39+R40+R41+R42 -> 4902866 | S29: 0 | T29: =P29+R29 -> 19429412 | V29: =V30+V32+V33+V34+V35+V36+V37+V38+V39+V40+V41+V42 -> 4792542 | W29: 0 | X29: =T29+V29 -> 24221954 | Z29: =Z30+Z32+Z33+Z34+Z35+Z36+Z37+Z38+Z39+Z40+Z41+Z42 -> 4916046 | AA29: 0 | AB29: =X29+Z29 -> 29138000 | AD29: =AD30+AD32+AD33+AD34+AD35+AD36+AD37+AD38+AD39+AD40+AD41+AD42+AD31 -> 4800542 | AE29: 0 | AF29: =AB29+AD29 -> 33938542
A30: 510506 | B30: Sueldos | C30: 0 | D30: 0 | E30: =+C30 -> 0 | G30: 2908453 | H30: 0 | I30: =E30+G30 -> 2908453 | J30: 3116200 | K30: 0 | L30: =I30+J30 -> 6024653 | N30: 3116200 | O30: 0 | P30: =L30+N30 -> 9140853 | R30: 3116200 | S30: 0 | T30: =P30+R30 -> 12257053 | V30: 3116200 | W30: 0 | X30: =T30+V30 -> 15373253 | Z30: 3116200 | AA30: 0 | AB30: =X30+Z30 -> 18489453 | AD30: 3116200 | AE30: 0 | AF30: =AB30+AD30 -> 21605653
A31: 5105 | B31: Horas extras | C31: 0 | D31: 0 | E31: 0 | G31: 0 | H31: 0 | I31: 0 | J31: 0 | K31: 0 | L31: 0 | N31: 0 | O31: 0 | P31: 0 | R31: 0 | S31: 0 | T31: 0 | V31: 0 | W31: 0 | X31: 0 | Z31: 0 | AA31: 0 | AB31: 0 | AD31: 25000 | AE31: 0 | AF31: =+AD31 -> 25000
A32: 510527 | B32: Auxilio de transporte | C32: 0 | D32: 0 | E32: =+C32 -> 0 | G32: 99357 | H32: 0 | I32: =E32+G32 -> 99357 | J32: 106454 | K32: 0 | L32: =I32+J32 -> 205811 | N32: 106454 | O32: 0 | P32: =L32+N32 -> 312265 | R32: 106454 | S32: 0 | T32: =P32+R32 -> 418719 | V32: 106454 | W32: 0 | X32: =T32+V32 -> 525173 | Z32: 106454 | AA32: 0 | AB32: =X32+Z32 -> 631627 | AD32: 106454 | AE32: 0 | AF32: =AB32+AD32 -> 738081
A33: 510530 | B33: Cesantías | C33: 0 | D33: 0 | E33: =+C33 -> 0 | G33: 250550 | H33: 0 | I33: =E33+G33 -> 250550 | J33: 268448 | K33: 0 | L33: =I33+J33 -> 518998 | N33: 268448 | O33: 0 | P33: =L33+N33 -> 787446 | R33: 268448 | S33: 0 | T33: =P33+R33 -> 1055894 | V33: 268448 | W33: 0 | X33: =T33+V33 -> 1324342 | Z33: 268448 | AA33: 0 | AB33: =X33+Z33 -> 1592790 | AD33: 268448 | AE33: 0 | AF33: =AB33+AD33 -> 1861238
A34: 510533 | B34: Intereses sobre cesantías | C34: 0 | D34: 0 | E34: =+C34 -> 0 | G34: 20879 | H34: 0 | I34: =E34+G34 -> 20879 | J34: 32213 | K34: 0 | L34: =I34+J34 -> 53092 | N34: 32226 | O34: 0 | P34: =L34+N34 -> 85318 | R34: 32214 | S34: 0 | T34: =P34+R34 -> 117532 | V34: 32214 | W34: 0 | X34: =T34+V34 -> 149746 | Z34: 32214 | AA34: 0 | AB34: =X34+Z34 -> 181960 | AD34: 32214 | AE34: 0 | AF34: =AB34+AD34 -> 214174
A35: 510536 | B35: Prima de servicios | C35: 0 | D35: 0 | E35: =+C35 -> 0 | G35: 250550 | H35: 0 | I35: =E35+G35 -> 250550 | J35: 268448 | K35: 0 | L35: =I35+J35 -> 518998 | N35: 268448 | O35: 0 | P35: =L35+N35 -> 787446 | R35: 268448 | S35: 0 | T35: =P35+R35 -> 1055894 | V35: 268448 | W35: 0 | X35: =T35+V35 -> 1324342 | Z35: 268448 | AA35: 0 | AB35: =X35+Z35 -> 1592790 | AD35: 268448 | AE35: 0 | AF35: =AB35+AD35 -> 1861238
A36: 510539 | B36: Vacaciones | C36: 0 | D36: 0 | E36: =+C36 -> 0 | G36: 121282 | H36: 0 | I36: =E36+G36 -> 121282 | J36: 129946 | K36: 0 | L36: =I36+J36 -> 251228 | N36: 129946 | O36: 0 | P36: =L36+N36 -> 381174 | R36: 129946 | S36: 0 | T36: =P36+R36 -> 511120 | V36: 134384 | W36: 0 | X36: =T36+V36 -> 645504 | Z36: 134384 | AA36: 0 | AB36: =X36+Z36 -> 779888 | AD36: 134384 | AE36: 0 | AF36: =AB36+AD36 -> 914272
A37: 510545 | B37: Auxilios | C37: 0 | D37: 0 | E37: =+C37 -> 0 | G37: 350872 | H37: 0 | I37: =E37+G37 -> 350872 | J37: 350872 | K37: 0 | L37: =I37+J37 -> 701744 | N37: 350872 | O37: 0 | P37: =L37+N37 -> 1052616 | R37: 350872 | S37: 0 | T37: =P37+R37 -> 1403488 | V37: 350872 | W37: 0 | X37: =T37+V37 -> 1754360 | Z37: 350872 | AA37: 0 | AB37: =X37+Z37 -> 2105232 | AD37: 350872 | AE37: 0 | AF37: =AB37+AD37 -> 2456104
A38: 510551 | B38: Dotación y elementos seguridad trabajadores | C38: 30000 | D38: 0 | E38: =+C38 -> 30000 | G38: 391093 | H38: 0 | I38: =E38+G38 -> 421093 | J38: 0 | K38: 0 | L38: =I38+J38 -> 421093 | N38: 0 | O38: 0 | P38: =L38+N38 -> 421093 | R38: 73950 | S38: 0 | T38: =P38+R38 -> 495043 | V38: 17000 | W38: 0 | X38: =T38+V38 -> 512043 | Z38: 140504 | AA38: 0 | AB38: =X38+Z38 -> 652547 | AD38: 0 | AE38: 0 | AF38: =AB38+AD38 -> 652547
A39: 510568 | B39: Aportes a administradoras de riesgos profesionales arp | C39: 0 | D39: 0 | E39: =+C39 -> 0 | G39: 30400 | H39: 0 | I39: =E39+G39 -> 30400 | J39: 32408 | K39: 0 | L39: =I39+J39 -> 62808 | N39: 32700 | O39: 0 | P39: =L39+N39 -> 95508 | R39: 32678 | S39: 0 | T39: =P39+R39 -> 128186 | V39: 32532 | W39: 0 | X39: =T39+V39 -> 160718 | Z39: 32532 | AA39: 0 | AB39: =X39+Z39 -> 193250 | AD39: 32532 | AE39: 0 | AF39: =AB39+AD39 -> 225782
A40: 510569 | B40: Aportes a entidades promotoras de salud eps | C40: 0 | D40: 0 | E40: =+C40 -> 0 | G40: 0 | H40: 0 | I40: =E40+G40 -> 0 | J40: 0 | K40: 0 | L40: =I40+J40 -> 0 | N40: 0 | O40: 0 | P40: =L40+N40 -> 0 | R40: 0 | S40: 0 | T40: =P40+R40 -> 0 | V40: 0 | W40: 0 | X40: =T40+V40 -> 0 | Z40: 0 | AA40: 0 | AB40: =X40+Z40 -> 0 | AD40: 0 | AE40: 0 | AF40: =AB40+AD40 -> 0
A41: 510570 | B41: Aportes a fondos de pensiones y/o cesantías | C41: 0 | D41: 0 | E41: =+C41 -> 0 | G41: 349162 | H41: 0 | I41: =E41+G41 -> 349162 | J41: 373944 | K41: 0 | L41: =I41+J41 -> 723106 | N41: 374025 | O41: 0 | P41: =L41+N41 -> 1097131 | R41: 373944 | S41: 0 | T41: =P41+R41 -> 1471075 | V41: 341342 | W41: 0 | X41: =T41+V41 -> 1812417 | Z41: 341342 | AA41: 0 | AB41: =X41+Z41 -> 2153759 | AD41: 341342 | AE41: 0 | AF41: =AB41+AD41 -> 2495101
A42: 510572 | B42: Aportes cajas de compensación familiar | C42: 0 | D42: 0 | E42: =+C42 -> 0 | G42: 116400 | H42: 0 | I42: =E42+G42 -> 116400 | J42: 124648 | K42: 0 | L42: =I42+J42 -> 241048 | N42: =124700-52 -> 124648 | O42: 0 | P42: =L42+N42 -> 365696 | R42: 149712 | S42: 0 | T42: =P42+R42 -> 515408 | V42: 124648 | W42: 0 | X42: =T42+V42 -> 640056 | Z42: 124648 | AA42: 0 | AB42: =X42+Z42 -> 764704 | AD42: 124648 | AE42: 0 | AF42: =AB42+AD42 -> 889352
A43: 510584 | B43: Drogas y medicamentos | C43: 0 | E43: =+C43 -> 0
B44: GASTOS PERSONAL FISCAl y no fiscal | C44: =SUM(C29:C43)+C68 -> 2632000 | G44: =SUM(G29:G43)-391093+G68 -> 10921903 | J44: =SUM(J29:J43)+J68 -> 11612662 | N44: =SUM(N29:N43)+N68 -> 11582934 | R44: =SUM(R29:R43)+R68 -> 11461232 | V44: =SUM(V29:V43)+V68 -> 11418584 | Z44: =SUM(Z29:Z43)+Z68 -> 11664092 | AD44: =SUM(AD29:AD43)+AD68 -> 11600584
A45: 5110 | B45: Honorarios | C45: =C47 -> 300000 | D45: 0 | E45: =+C45 -> 300000 | G45: =G47 -> 300000 | H45: 0 | I45: =E45+G45 -> 600000 | J45: 300000 | K45: 0 | L45: =I45+J45 -> 900000 | N45: =N47 -> 300000 | O45: 0 | P45: =L45+N45 -> 1200000 | R45: =R47 -> 300000 | S45: 0 | T45: =P45+R45 -> 1500000 | V45: =V47 -> 300000 | W45: 0 | X45: =T45+V45 -> 1800000 | Z45: =Z47 -> 300000 | AA45: 0 | AB45: =X45+Z45 -> 2100000 | AD45: =AD47 -> 300000 | AE45: 0 | AF45: =AB45+AD45 -> 2400000
A46: 511025 | B46: Asesoria Juridica | C46: 0 | D46: 0 | E46: =+C46 -> 0 | G46: 0 | H46: 0 | I46: =E46+G46 -> 0 | J46: 0 | K46: 0 | L46: =I46+J46 -> 0 | N46: 0 | O46: 0 | P46: =L46+N46 -> 0 | R46: 0 | S46: 0 | T46: =P46+R46 -> 0 | V46: 0 | W46: 0 | X46: =T46+V46 -> 0 | Z46: 0 | AA46: 0 | AB46: =X46+Z46 -> 0 | AD46: 0 | AE46: 0 | AF46: =AB46+AD46 -> 0
A47: 511030 | B47: Asesoría financiera | C47: 300000 | D47: 0 | E47: =+C47 -> 300000 | G47: 300000 | H47: 0 | I47: =E47+G47 -> 600000 | J47: 300000 | K47: 0 | L47: =I47+J47 -> 900000 | N47: 300000 | O47: 0 | P47: =L47+N47 -> 1200000 | R47: 300000 | S47: 0 | T47: =P47+R47 -> 1500000 | V47: 300000 | W47: 0 | X47: =T47+V47 -> 1800000 | Z47: 300000 | AA47: 0 | AB47: =X47+Z47 -> 2100000 | AD47: 300000 | AE47: 0 | AF47: =AB47+AD47 -> 2400000
A48: 511095 | B48: EXOGENA
A50: 5115 | B50: Impuestos | C50: =+C51+C52+C53 -> 61900 | D50: 0 | E50: =+C50 -> 61900 | G50: =G53 -> 0 | H50: 0 | I50: =E50+G50 -> 61900 | J50: =+J52 -> 0 | K50: 0 | L50: =I50+J50 -> 61900 | N50: =+N54 -> 0 | O50: 0 | P50: =L50+N50 -> 61900 | R50: =+R54 -> 0 | S50: 0 | T50: =P50+R50 -> 61900 | V50: =+V54 -> 0 | W50: 0 | X50: =T50+V50 -> 61900 | Z50: =+Z54 -> 0 | AA50: 0 | AB50: =X50+Z50 -> 61900 | AD50: =+AD54 -> 0 | AE50: 0 | AF50: =AB50+AD50 -> 61900
A51: 511505 | B51: Insdustria y Comercio | C51: 0 | D51: 0 | E51: =+C51 -> 0 | G51: 0 | H51: 0 | I51: =E51+G51 -> 0 | J51: 0 | K51: 0 | L51: =I51+J51 -> 0 | N51: 0 | O51: 0 | P51: =L51+N51 -> 0 | R51: 0 | S51: 0 | T51: =P51+R51 -> 0 | V51: 0 | W51: 0 | X51: =T51+V51 -> 0 | Z51: 0 | AA51: 0 | AB51: =X51+Z51 -> 0 | AD51: 0 | AE51: 0 | AF51: =AB51+AD51 -> 0
A52: 511515 | B52: A la propiedad raiz | C52: 0 | D52: 0 | E52: =+C52 -> 0 | G52: 0 | H52: 0 | I52: =E52+G52 -> 0 | J52: 0 | K52: 0 | L52: =I52+J52 -> 0 | N52: 0 | O52: 0 | P52: =L52+N52 -> 0 | R52: 0 | S52: 0 | T52: =P52+R52 -> 0 | V52: 0 | W52: 0 | X52: =T52+V52 -> 0 | Z52: 0 | AA52: 0 | AB52: =X52+Z52 -> 0 | AD52: 0 | AE52: 0 | AF52: =AB52+AD52 -> 0
A53: 511540 | B53: De vehículos | C53: 61900 | D53: 0 | E53: =+C53 -> 61900 | G53: 0 | H53: 0 | I53: =E53+G53 -> 61900 | K53: 0 | L53: =I53+J53 -> 61900 | N53: 0 | O53: 0 | P53: =L53+N53 -> 61900 | R53: 0 | S53: 0 | T53: =P53+R53 -> 61900 | V53: 0 | W53: 0 | X53: =T53+V53 -> 61900 | Z53: 0 | AA53: 0 | AB53: =X53+Z53 -> 61900 | AD53: 0 | AE53: 0 | AF53: =AB53+AD53 -> 61900
A54: 511595 | B54: Otros | C54: 0 | E54: =+C54 -> 0 | I54: =E54+G54 -> 0 | L54: =I54+J54 -> 0 | N54: 0 | P54: =L54+N54 -> 0 | R54: 0 | T54: =P54+R54 -> 0 | V54: 0 | X54: =T54+V54 -> 0 | Z54: 0 | AB54: =X54+Z54 -> 0 | AD54: 0 | AF54: =AB54+AD54 -> 0
A56: 5120 | B56: Arrendamientos | C56: =+C57 -> 1000000 | D56: 0 | E56: =+C56 -> 1000000 | G56: =+G57+G58 -> 1017150 | H56: 0 | I56: =E56+G56 -> 2017150 | J56: =+J57+J61 -> 1000000 | K56: 0 | L56: =I56+J56 -> 3017150 | N56: =N57+N58 -> 1000000 | O56: 0 | P56: =L56+N56 -> 4017150 | R56: =R57+R58 -> 1000000 | S56: 0 | T56: =P56+R56 -> 5017150 | V56: =V57+V58 -> 1000000 | W56: 0 | X56: =T56+V56 -> 6017150 | Z56: =Z57+Z58 -> 1000000 | AA56: 0 | AB56: =X56+Z56 -> 7017150 | AD56: =AD57+AD58 -> 1000000 | AE56: 0 | AF56: =AB56+AD56 -> 8017150
A57: 512010 | B57: Construcciones y edificaciones | C57: 1000000 | D57: 0 | E57: =+C57 -> 1000000 | G57: 1000000 | H57: 0 | I57: =E57+G57 -> 2000000 | J57: 1000000 | K57: 0 | L57: =I57+J57 -> 3000000 | N57: 1000000 | O57: 0 | P57: =L57+N57 -> 4000000 | R57: 1000000 | S57: 0 | T57: =P57+R57 -> 5000000 | V57: 1000000 | W57: 0 | X57: =T57+V57 -> 6000000 | Z57: 1000000 | AA57: 0 | AB57: =X57+Z57 -> 7000000 | AD57: 1000000 | AE57: 0 | AF57: =AB57+AD57 -> 8000000
A58: 512015 | B58: Maquinaria y equipo | C58: 0 | D58: 0 | E58: =+C58 -> 0 | G58: 17150 | I58: =E58+G58 -> 17150 | J58: 0 | K58: 0 | L58: =I58+J58 -> 17150 | N58: 0 | P58: =L58+N58 -> 17150 | R58: 0 | T58: =P58+R58 -> 17150 | V58: 0 | X58: =T58+V58 -> 17150 | Z58: 0 | AB58: =X58+Z58 -> 17150 | AD58: 0 | AF58: =AB58+AD58 -> 17150
L59: =I59+J59 -> 0
A60: 5125 | B60: AFILIACIONES Y CONTRIBUCIONES | C60: =+C61 -> 130000 | E60: =+E61 -> 130000 | G60: 0 | I60: =E60+G60 -> 130000 | J60: =+J61 -> 0 | L60: =I60+J60 -> 130000 | N60: 0 | P60: =L60+N60 -> 130000 | R60: 0 | T60: =P60+R60 -> 130000 | V60: 0 | X60: =T60+V60 -> 130000 | Z60: 0 | AB60: =X60+Z60 -> 130000 | AD60: 0 | AF60: =AB60+AD60 -> 130000
A61: 512510 | B61: Afiliaciones | C61: 130000 | D61: 0 | E61: =+C61 -> 130000 | G61: 0 | I61: =E61+G61 -> 130000 | J61: 0 | L61: =I61+J61 -> 130000 | N61: 0 | P61: =L61+N61 -> 130000 | R61: 0 | T61: =P61+R61 -> 130000 | V61: 0 | X61: =T61+V61 -> 130000 | Z61: 0 | AB61: =X61+Z61 -> 130000 | AD61: 0 | AF61: =AB61+AD61 -> 130000
A63: 5130 | B63: Seguros | C63: =+C64 -> 652200 | D63: 0 | E63: =+C63 -> 652200 | G63: =G64 -> 0 | H63: 0 | I63: =E63+G63 -> 652200 | J63: =J64 -> 0 | K63: 0 | L63: =I63+J63 -> 652200 | N63: =N64 -> 0 | O63: 0 | P63: =L63+N63 -> 652200 | R63: =R64 -> 0 | S63: 0 | T63: =P63+R63 -> 652200 | V63: =V64 -> 0 | W63: 0 | X63: =T63+V63 -> 652200 | Z63: =Z64 -> 0 | AA63: 0 | AB63: =X63+Z63 -> 652200 | AD63: =AD64 -> 0 | AE63: 0 | AF63: =AB63+AD63 -> 652200
A64: 513095 | B64: Otros | C64: 652200 | D64: 0 | E64: =+C64 -> 652200 | G64: 0 | H64: 0 | I64: =E64+G64 -> 652200 | J64: 0 | K64: 0 | L64: =I64+J64 -> 652200 | N64: 0 | O64: 0 | P64: =L64+N64 -> 652200 | R64: 0 | S64: 0 | T64: =P64+R64 -> 652200 | V64: 0 | W64: 0 | X64: =T64+V64 -> 652200 | Z64: 0 | AA64: 0 | AB64: =X64+Z64 -> 652200 | AD64: 0 | AE64: 0 | AF64: =AB64+AD64 -> 652200
A66: 5135 | B66: Servicios | C66: =C67+C68+C70+C71+C72+C74+C73+C75 -> 2886130 | D66: 0 | E66: =+C66 -> 2886130 | G66: =G67+G68+G70+G71+G72+G75 -> 1861820 | H66: 0 | I66: =E66+G66 -> 4747950 | J66: =J67+J68+J70+J71+J72+J75 -> 2465725 | K66: 0 | L66: =I66+J66 -> 7213675 | N66: =SUM(N67:N75) -> 2381761 | O66: 0 | P66: =L66+N66 -> 9595436 | R66: =SUM(R67:R75) -> 2050581 | S66: 0 | T66: =P66+R66 -> 11646017 | V66: =SUM(V67:V75) -> 2277044 | W66: 0 | X66: =T66+V66 -> 13923061 | Z66: =SUM(Z67:Z75) -> 2357156 | AA66: 0 | AB66: =X66+Z66 -> 16280217 | AD66: =SUM(AD67:AD75) -> 2446634 | AE66: 0 | AF66: =AB66+AD66 -> 18726851
A67: 513505 | B67: Aseo y vigilancia | D67: 0 | E67: =+C67 -> 0 | G67: 30000 | H67: 0 | I67: =E67+G67 -> 30000 | J67: 0 | K67: 0 | L67: =I67+J67 -> 30000 | N67: 0 | O67: 0 | P67: =L67+N67 -> 30000 | R67: 0 | S67: 0 | T67: =P67+R67 -> 30000 | V67: 0 | W67: 0 | X67: =T67+V67 -> 30000 | Z67: 30000 | AA67: 0 | AB67: =X67+Z67 -> 60000 | AD67: 0 | AE67: 0 | AF67: =AB67+AD67 -> 60000
A68: 513510 | B68: Temporales | C68: 2572000 | D68: 0 | E68: =+C68 -> 2572000 | G68: 1535000 | H68: 0 | I68: =E68+G68 -> 4107000 | J68: 2005500 | K68: 0 | L68: =I68+J68 -> 6112500 | N68: 1975000 | O68: 0 | P68: =L68+N68 -> 8087500 | R68: 1655500 | S68: 0 | T68: =P68+R68 -> 9743000 | V68: 1833500 | W68: 0 | X68: =T68+V68 -> 11576500 | Z68: 1832000 | AA68: 0 | AB68: =X68+Z68 -> 13408500 | AD68: 1999500 | AE68: 0 | AF68: =AB68+AD68 -> 15408000
A69: 513520 | N69: 0 | R69: 0 | V69: 0 | Z69: 0 | AD69: 0
A70: 513525 | B70: Acueducto y alcantarillado | C70: 61030 | D70: 0 | E70: =+C70 -> 61030 | G70: 146724 | H70: 0 | I70: =E70+G70 -> 207754 | J70: 74320 | K70: 0 | L70: =I70+J70 -> 282074 | N70: 155552 | O70: 0 | P70: =L70+N70 -> 437626 | R70: 69830 | S70: 0 | T70: =P70+R70 -> 507456 | V70: 94890 | W70: 0 | X70: =T70+V70 -> 602346 | Z70: 94830 | AA70: 0 | AB70: =X70+Z70 -> 697176 | AD70: 63680 | AE70: 0 | AF70: =AB70+AD70 -> 760856
A71: 513530 | B71: Energía eléctrica | C71: 102021 | D71: 0 | E71: =+C71 -> 102021 | G71: 0 | H71: 0 | I71: =E71+G71 -> 102021 | J71: 92898 | K71: 0 | L71: =I71+J71 -> 194919 | N71: 100130 | O71: 0 | P71: =L71+N71 -> 295049 | R71: 109685 | S71: 0 | T71: =P71+R71 -> 404734 | V71: 88575 | W71: 0 | X71: =T71+V71 -> 493309 | Z71: 98168 | AA71: 0 | AB71: =X71+Z71 -> 591477 | AD71: 100276 | AE71: 0 | AF71: =AB71+AD71 -> 691753
A72: 513535 | B72: Teléfono fijo y moviles | C72: 151079 | D72: 0 | E72: =+C72 -> 151079 | G72: 150096 | H72: 0 | I72: =E72+G72 -> 301175 | J72: 293007 | K72: 0 | L72: =I72+J72 -> 594182 | N72: 151079 | O72: 0 | P72: =L72+N72 -> 745261 | R72: 215566 | S72: 0 | T72: =P72+R72 -> 960827 | V72: 210079 | W72: 0 | X72: =T72+V72 -> 1170906 | Z72: 302158 | AA72: 0 | AB72: =X72+Z72 -> 1473064 | AD72: 283178 | AE72: 0 | AF72: =AB72+AD72 -> 1756242
A73: 513540 | B73: Correo portes y telegrama | C73: 0 | D73: 0 | E73: =+C73 -> 0 | G73: 0 | H73: 0 | I73: =E73+G73 -> 0 | J73: 0 | K73: 0 | L73: =I73+J73 -> 0 | N73: 0 | O73: 0 | P73: =L73+N73 -> 0 | R73: 0 | S73: 0 | T73: =P73+R73 -> 0 | V73: 0 | W73: 0 | X73: =T73+V73 -> 0 | Z73: 0 | AA73: 0 | AB73: =X73+Z73 -> 0 | AD73: 0 | AE73: 0 | AF73: =AB73+AD73 -> 0
A74: 513595 | B74: Otros | C74: 0 | D74: 0 | E74: =+C74 -> 0 | G74: 0 | H74: 0 | I74: =E74+G74 -> 0 | J74: 0 | K74: 0 | L74: =I74+J74 -> 0 | N74: 0 | O74: 0 | P74: =L74+N74 -> 0 | R74: 0 | S74: 0 | T74: =P74+R74 -> 0 | V74: 0 | W74: 0 | X74: =T74+V74 -> 0 | Z74: 0 | AA74: 0 | AB74: =X74+Z74 -> 0 | AD74: 0 | AE74: 0 | AF74: =AB74+AD74 -> 0
A75: 513550 | B75: Transportes, fletes y acarreos | D75: 0 | E75: =+C75 -> 0 | G75: 0 | H75: 0 | I75: =E75+G75 -> 0 | J75: 0 | K75: 0 | L75: =I75+J75 -> 0 | N75: 0 | O75: 0 | P75: =L75+N75 -> 0 | R75: 0 | S75: 0 | T75: =P75+R75 -> 0 | V75: 50000 | W75: 0 | X75: =T75+V75 -> 50000 | Z75: 0 | AA75: 0 | AB75: =X75+Z75 -> 50000 | AD75: 0 | AE75: 0 | AF75: =AB75+AD75 -> 50000
E76: =+C76 -> 0 | P76: =L76+N76 -> 0 | T76: =P76+R76 -> 0 | X76: =T76+V76 -> 0 | AB76: =X76+Z76 -> 0 | AF76: =AB76+AD76 -> 0
A77: 5140 | B77: Gastos legales | C77: =+C80 -> 180000 | D77: 0 | E77: =+C77 -> 180000 | G77: =G79+G80 -> 0 | H77: 0 | I77: =E77+G77 -> 180000 | J77: =+J79 -> 5900 | K77: 0 | L77: =I77+J77 -> 185900 | N77: =N79+N80 -> 0 | O77: 0 | P77: =L77+N77 -> 185900 | R77: =R79+R80 -> 0 | S77: 0 | T77: =P77+R77 -> 185900 | V77: =V79+V80 -> 0 | W77: 0 | X77: =T77+V77 -> 185900 | Z77: =Z79+Z80 -> 5900 | AA77: 0 | AB77: =X77+Z77 -> 191800 | AD77: =AD79+AD80 -> 80000 | AE77: 0 | AF77: =AB77+AD77 -> 271800
A78: 514005 | B78: Notariales | C78: 0 | D78: 0 | E78: =+C78 -> 0 | G78: 0 | H78: 0 | I78: =E78+G78 -> 0 | J78: 0 | K78: 0 | L78: =I78+J78 -> 0 | N78: 0 | O78: 0 | P78: =L78+N78 -> 0 | R78: 0 | S78: 0 | T78: =P78+R78 -> 0 | V78: 0 | W78: 0 | X78: =T78+V78 -> 0 | Z78: 0 | AA78: 0 | AB78: =X78+Z78 -> 0 | AD78: 0 | AE78: 0 | AF78: =AB78+AD78 -> 0
A79: 514010 | B79: Registro mercantil | C79: 0 | D79: 0 | E79: =+C79 -> 0 | G79: 0 | H79: 0 | I79: =E79+G79 -> 0 | J79: 5900 | K79: 0 | L79: =I79+J79 -> 5900 | N79: 0 | O79: 0 | P79: =L79+N79 -> 5900 | R79: 0 | S79: 0 | T79: =P79+R79 -> 5900 | W79: 0 | X79: =T79+V79 -> 5900 | Z79: 5900 | AA79: 0 | AB79: =X79+Z79 -> 11800 | AD79: 0 | AE79: 0 | AF79: =AB79+AD79 -> 11800
A80: 514015 | B80: Trámites y licencias | C80: 180000 | D80: 0 | E80: =+C80 -> 180000 | G80: 0 | H80: 0 | I80: =E80+G80 -> 180000 | J80: 0 | K80: 0 | L80: =I80+J80 -> 180000 | N80: 0 | O80: 0 | P80: =L80+N80 -> 180000 | R80: 0 | S80: 0 | T80: =P80+R80 -> 180000 | V80: 0 | W80: 0 | X80: =T80+V80 -> 180000 | Z80: 0 | AA80: 0 | AB80: =X80+Z80 -> 180000 | AD80: 80000 | AE80: 0 | AF80: =AB80+AD80 -> 260000
A81: 514095 | B81: Otros | C81: 0 | D81: 0 | E81: =+C81 -> 0 | G81: 0 | H81: 0 | I81: =E81+G81 -> 0 | J81: 0 | K81: 0 | L81: =I81+J81 -> 0 | N81: 0 | O81: 0 | P81: =L81+N81 -> 0 | R81: 0 | S81: 0 | T81: =P81+R81 -> 0 | V81: 0 | W81: 0 | X81: =T81+V81 -> 0 | Z81: 0 | AA81: 0 | AB81: =X81+Z81 -> 0 | AD81: 0 | AE81: 0 | AF81: =AB81+AD81 -> 0
E82: =+C82 -> 0
A83: 5145 | B83: Mantenimiento y reparaciones | C83: =+C85+C86+C87+C88 -> 199000 | D83: 0 | E83: =+C83 -> 199000 | G83: =G85+G86+G88+G87 -> 566465 | H83: 0 | I83: =E83+G83 -> 765465 | J83: =+J85+J86+J87+J88 -> 1153513 | K83: 0 | L83: =I83+J83 -> 1918978 | N83: =+N85+N86+N87+N88+N84 -> 4011924 | O83: 0 | P83: =L83+N83 -> 5930902 | R83: =+R85+R86+R87+R88 -> 414071 | S83: 0 | T83: =P83+R83 -> 6344973 | V83: =+V85+V86+V87+V88 -> 2214231 | W83: 0 | X83: =T83+V83 -> 8559204 | Z83: =+Z85+Z86+Z87+Z88 -> 1515810 | AA83: 0 | AB83: =X83+Z83 -> 10075014 | AD83: =+AD85+AD86+AD87+AD88 -> 1454402 | AE83: 0 | AF83: =AB83+AD83 -> 11529416
A84: 514510 | B84: construcciones y edificaciones | N84: 12500 | P84: =L84+N84 -> 12500 | R84: 0 | V84: 0 | Z84: 12500 | AD84: 0
A85: 514515 | B85: Maquinaria y equipo | C85: 199000 | D85: 0 | E85: =+C85 -> 199000 | G85: 211465 | H85: 0 | I85: =E85+G85 -> 410465 | J85: 1071513 | K85: 0 | L85: =I85+J85 -> 1481978 | N85: 3999424 | O85: 0 | P85: =L85+N85 -> 5481402 | R85: 414071 | S85: 0 | T85: =P85+R85 -> 5895473 | V85: 2214231 | W85: 0 | X85: =T85+V85 -> 8109704 | Z85: 1035810 | AA85: 0 | AB85: =X85+Z85 -> 9145514 | AD85: 1452402 | AE85: 0 | AF85: =AB85+AD85 -> 10597916
A86: 514520 | B86: Equipo de oficina | C86: 0 | D86: 0 | E86: =+C86 -> 0 | G86: 0 | H86: 0 | I86: =E86+G86 -> 0 | J86: 0 | K86: 0 | L86: =I86+J86 -> 0 | N86: 0 | O86: 0 | P86: =L86+N86 -> 0 | R86: 0 | S86: 0 | T86: =P86+R86 -> 0 | V86: 0 | W86: 0 | X86: =T86+V86 -> 0 | Z86: 0 | AA86: 0 | AB86: =X86+Z86 -> 0 | AD86: 0 | AE86: 0 | AF86: =AB86+AD86 -> 0
A87: 514525 | B87: Equipo de computación y comunicación | C87: 0 | D87: 0 | E87: =+C87 -> 0 | G87: 15000 | H87: 0 | I87: =E87+G87 -> 15000 | J87: 0 | K87: 0 | L87: =I87+J87 -> 15000 | N87: 0 | O87: 0 | P87: =L87+N87 -> 15000 | R87: 0 | S87: 0 | T87: =P87+R87 -> 15000 | V87: 0 | W87: 0 | X87: =T87+V87 -> 15000 | Z87: 400000 | AA87: 0 | AB87: =X87+Z87 -> 415000 | AD87: 0 | AE87: 0 | AF87: =AB87+AD87 -> 415000
A88: 514540 | B88: Flota y equipo de transportes | D88: 0 | E88: =+C88 -> 0 | G88: 340000 | H88: 0 | I88: =E88+G88 -> 340000 | J88: 82000 | K88: 0 | L88: =I88+J88 -> 422000 | N88: 0 | O88: 0 | P88: =L88+N88 -> 422000 | R88: 0 | S88: 0 | T88: =P88+R88 -> 422000 | V88: 0 | W88: 0 | X88: =T88+V88 -> 422000 | Z88: 80000 | AA88: 0 | AB88: =X88+Z88 -> 502000 | AD88: 2000 | AE88: 0 | AF88: =AB88+AD88 -> 504000
E89: =+C89 -> 0
A90: 5150 | B90: Adecuación e instalación | C90: =+C91+C92+C93+C94 -> 10084 | D90: 0 | E90: =+C90 -> 10084 | G90: =+G91+G92+G93+G94 -> 535658 | H90: 0 | I90: =E90+G90 -> 545742 | J90: =+J91+J92+J93 -> 14500 | K90: 0 | L90: =I90+J90 -> 560242 | N90: =N94+N93 -> 38000 | O90: 0 | P90: =L90+N90 -> 598242 | R90: =R94+R93 -> 189050 | S90: 0 | T90: =P90+R90 -> 787292 | V90: =V94+V93 -> 45000 | W90: 0 | X90: =T90+V90 -> 832292 | Z90: =Z94+Z93 -> 0 | AA90: 0 | AB90: =X90+Z90 -> 832292 | AD90: =AD94+AD93 -> 0 | AE90: 0 | AF90: =AB90+AD90 -> 832292
A91: 515005 | B91: Instalaciones electricas | C91: 0 | D91: 0 | E91: =+C91 -> 0 | G91: 0 | H91: 0 | I91: =E91+G91 -> 0 | J91: 0 | K91: 0 | L91: =I91+J91 -> 0 | N91: 0 | O91: 0 | P91: =L91+N91 -> 0 | R91: 0 | S91: 0 | T91: =P91+R91 -> 0 | V91: 0 | W91: 0 | X91: =T91+V91 -> 0 | Z91: 0 | AA91: 0 | AB91: =X91+Z91 -> 0 | AD91: 0 | AE91: 0 | AF91: =AB91+AD91 -> 0
A92: 515010 | B92: Arreglos ornamentales | C92: 0 | D92: 0 | E92: =+C92 -> 0 | G92: 0 | H92: 0 | I92: =E92+G92 -> 0 | J92: 0 | K92: 0 | L92: =I92+J92 -> 0 | N92: 0 | O92: 0 | P92: =L92+N92 -> 0 | R92: 0 | S92: 0 | T92: =P92+R92 -> 0 | V92: 0 | W92: 0 | X92: =T92+V92 -> 0 | Z92: 0 | AA92: 0 | AB92: =X92+Z92 -> 0 | AD92: 0 | AE92: 0 | AF92: =AB92+AD92 -> 0
A93: 515015 | B93: Reparaciones locativas | C93: 10084 | D93: 0 | E93: =+C93 -> 10084 | G93: 535658 | H93: 0 | I93: =E93+G93 -> 545742 | J93: 14500 | K93: 0 | L93: =I93+J93 -> 560242 | N93: 38000 | O93: 0 | P93: =L93+N93 -> 598242 | R93: 189050 | S93: 0 | T93: =P93+R93 -> 787292 | V93: 45000 | W93: 0 | X93: =T93+V93 -> 832292 | Z93: 0 | AA93: 0 | AB93: =X93+Z93 -> 832292 | AD93: 0 | AE93: 0 | AF93: =AB93+AD93 -> 832292
A94: 515095 | B94: Otros | C94: 0 | D94: 0 | E94: =+C94 -> 0 | G94: 0 | H94: 0 | I94: =E94+G94 -> 0 | J94: 0 | K94: 0 | L94: =I94+J94 -> 0 | N94: 0 | O94: 0 | P94: =L94+N94 -> 0 | R94: 0 | S94: 0 | T94: =P94+R94 -> 0 | V94: 0 | W94: 0 | X94: =T94+V94 -> 0 | Z94: 0 | AA94: 0 | AB94: =X94+Z94 -> 0 | AD94: 0 | AE94: 0 | AF94: =AB94+AD94 -> 0
E95: =+C95 -> 0 | I95: =E95+G95 -> 0 | L95: =I95+J95 -> 0 | P95: =L95+N95 -> 0 | T95: =P95+R95 -> 0 | X95: =T95+V95 -> 0 | AB95: =X95+Z95 -> 0 | AF95: =AB95+AD95 -> 0
A96: 5160 | B96: Depreciacion | C96: =+C97+C98+C99+C100+C101 -> 2941584 | E96: =+C96 -> 2941584 | G96: =+G97+G98+G99+G100+G101 -> 2941584 | I96: =E96+G96 -> 5883168 | J96: =+J97+J98+J99+J100+J101 -> 2941584 | L96: =I96+J96 -> 8824752 | N96: =+N97+N98+N99+N100+N101 -> 2941584 | P96: =L96+N96 -> 11766336 | R96: =+Hoja1!E14 -> 1780051.6 | T96: =P96+R96 -> 13546388 | V96: 1780051 | X96: =T96+V96 -> 15326439 | Z96: 1780051 | AB96: =X96+Z96 -> 17106490 | AD96: 1780051 | AF96: =AB96+AD96 -> 18886541
A97: 516005 | B97: construcciones y edificaciones | C97: 1588943 | E97: =+C97 -> 1588943 | G97: 1588943 | I97: =E97+G97 -> 3177886 | J97: 1588943 | L97: =I97+J97 -> 4766829 | N97: 1588943 | P97: =L97+N97 -> 6355772 | R97: 1588943 | T97: =P97+R97 -> 7944715 | V97: 1588943 | X97: =T97+V97 -> 9533658 | Z97: 1588943 | AB97: =X97+Z97 -> 11122601 | AD97: 1588943 | AF97: =AB97+AD97 -> 12711544
A98: 516010 | B98: maquinaria y equipo | C98: 749658 | E98: =+C98 -> 749658 | G98: 749658 | I98: =E98+G98 -> 1499316 | J98: 749658 | L98: =I98+J98 -> 2248974 | N98: 749658 | P98: =L98+N98 -> 2998632 | R98: 749658 | T98: =P98+R98 -> 3748290 | V98: 749658 | X98: =T98+V98 -> 4497948 | Z98: 749658 | AB98: =X98+Z98 -> 5247606 | AD98: 749658 | AF98: =AB98+AD98 -> 5997264
A99: 516015 | B99: equipo de oficina | C99: 3733 | E99: =+C99 -> 3733 | G99: 3733 | I99: =E99+G99 -> 7466 | J99: 3733 | L99: =I99+J99 -> 11199 | N99: 3733 | P99: =L99+N99 -> 14932 | R99: 3733 | T99: =P99+R99 -> 18665 | V99: 3733 | X99: =T99+V99 -> 22398 | Z99: 3733 | AB99: =X99+Z99 -> 26131 | AD99: 3733 | AF99: =AB99+AD99 -> 29864
A100: 516020 | B100: equipo de computacion | C100: 22650 | E100: =+C100 -> 22650 | G100: 22650 | I100: =E100+G100 -> 45300 | J100: 22650 | L100: =I100+J100 -> 67950 | N100: 22650 | P100: =L100+N100 -> 90600 | R100: 22650 | T100: =P100+R100 -> 113250 | V100: 22650 | X100: =T100+V100 -> 135900 | Z100: 22650 | AB100: =X100+Z100 -> 158550 | AD100: 22650 | AF100: =AB100+AD100 -> 181200
A101: 516035 | B101: flota y equipo de transporte | C101: 576600 | E101: =+C101 -> 576600 | G101: 576600 | I101: =E101+G101 -> 1153200 | J101: 576600 | L101: =I101+J101 -> 1729800 | N101: 576600 | P101: =L101+N101 -> 2306400 | R101: 576600 | T101: =P101+R101 -> 2883000 | V101: 576600 | X101: =T101+V101 -> 3459600 | Z101: 576600 | AB101: =X101+Z101 -> 4036200 | AD101: 576600 | AF101: =AB101+AD101 -> 4612800
P102: =L102+N102 -> 0 | T102: =P102+R102 -> 0 | X102: =T102+V102 -> 0 | AB102: =X102+Z102 -> 0 | AF102: =AB102+AD102 -> 0
A104: 5195 | B104: Diversos | C104: =SUM(C105:C116) -> 555953 | D104: 0 | E104: =+C104 -> 555953 | G104: =G106+G107+G108+G109+G111+G112+G113+G114+G116+G110+G115 -> 218265 | H104: 0 | I104: =E104+G104 -> 774218 | J104: =SUM(J106:J116) -> 623155 | K104: 0 | L104: =I104+J104 -> 1397373 | N104: =SUM(N105:N116) -> 1500410 | O104: 0 | P104: =L104+N104 -> 2897783 | R104: =SUM(R105:R116) -> 1030154 | S104: 0 | T104: =P104+R104 -> 3927937 | V104: =SUM(V105:V116) -> 291111 | W104: 0 | X104: =T104+V104 -> 4219048 | Z104: =SUM(Z105:Z116) -> 1400254 | AA104: 0 | AB104: =X104+Z104 -> 5619302 | AD104: =SUM(AD105:AD116) -> 461191 | AE104: 0 | AF104: =AB104+AD104 -> 6080493
A105: 519505 | B105: Comisiones | C105: 0 | D105: 0 | E105: =+C105 -> 0 | G105: 0 | H105: 0 | I105: =E105+G105 -> 0 | J105: 0 | K105: 0 | L105: =I105+J105 -> 0 | N105: 0 | O105: 0 | P105: =L105+N105 -> 0 | R105: 0 | S105: 0 | T105: =P105+R105 -> 0 | V105: 0 | W105: 0 | X105: =T105+V105 -> 0 | Z105: 0 | AA105: 0 | AB105: =X105+Z105 -> 0 | AD105: 0 | AE105: 0 | AF105: =AB105+AD105 -> 0
A106: 519520 | B106: Gastos de representación y relaciones públicas | D106: 0 | E106: =+C106 -> 0 | G106: 0 | H106: 0 | I106: =E106+G106 -> 0 | J106: 0 | K106: 0 | L106: =I106+J106 -> 0 | N106: 0 | O106: 0 | P106: =L106+N106 -> 0 | R106: 0 | S106: 0 | T106: =P106+R106 -> 0 | V106: 0 | W106: 0 | X106: =T106+V106 -> 0 | Z106: 0 | AA106: 0 | AB106: =X106+Z106 -> 0 | AD106: 0 | AE106: 0 | AF106: =AB106+AD106 -> 0
A107: 519525 | B107: Elementos de aseo y cafetería | C107: 10500 | D107: 0 | E107: =+C107 -> 10500 | G107: 24000 | H107: 0 | I107: =E107+G107 -> 34500 | J107: 38000 | K107: 0 | L107: =I107+J107 -> 72500 | N107: 143029 | O107: 0 | P107: =L107+N107 -> 215529 | R107: 48600 | S107: 0 | T107: =P107+R107 -> 264129 | V107: 54000 | W107: 0 | X107: =T107+V107 -> 318129 | Z107: 107131 | AA107: 0 | AB107: =X107+Z107 -> 425260 | AD107: 9000 | AE107: 0 | AF107: =AB107+AD107 -> 434260
...

Sheet GRAFICAS PYG
B5: MES | C5: VENTAS FISCALES 2021 | D5: VENTAS FISCALES 2020 | E5: VENTAS FISCALES 2019 | F5: VENTAS FISCALES 2018 | G5: VENTAS FISCALES 2017 | H5: VENTAS SIN IVA 2021 | I5: VENTAS SIN IVA 2020 | J5: VENTAS SIN IVA 2019 | K5: VENTAS SIN IVA 2018 | L5: VENTAS SIN IVA 2017 | M5: GASTOS 2021 | N5: GASTOS 2020 | O5: GASTOS 2019 | P5: GASTOS 2018 | Q5: GASTOS 2017 | R5: UTILIDAD 2021 | S5: UTILIDAD 2020 | T5: UTILIDAD 2019 | U5: UTILIDAD 2018 | V5: UTILIDAD 2017
B6: ENERO | C6: 4088450 | D6: 9772741 | E6: 5232922 | F6: 20519674 | G6: 4068398 | H6: 5295548 | I6: 4656136 | J6: 7998115 | K6: 5489862 | L6: 3111549 | M6: =+'PYG '!C153 -> 9031235 | N6: 11183760 | O6: 8192569 | P6: 7055307 | Q6: 10452832 | R6: 352800 | S6: 3245117 | T6: 5038468 | U6: 18954229 | V6: -3272885
B7: FEBRERO | C7: 3444630 | D7: 8662267 | E7: 6735984 | F7: 347610 | G7: 3781685 | H7: 6881543 | I7: 7804429 | J7: 4974355 | K7: 7374328 | L7: 8157506 | M7: =+'PYG '!G153 -> 12420337 | N7: 13337610 | O7: 8084721 | P7: 8975623 | Q7: 8843670 | R7: =+C7+H7-M7 -> -2094164 | S7: 3129086 | T7: 3625618 | U7: -1253685 | V7: 3095521
B8: MARZO | C8: 4294490 | D8: 11213082 | E8: 4072345 | F8: 245528 | G8: 3264345 | H8: 7901560 | I8: 5900305 | J8: 7130437 | K8: 5439456 | L8: 5780617 | M8: =+'PYG '!J153 -> 13591375 | N8: 10865138 | O8: 8025783 | P8: 9788704 | Q8: 8621927 | R8: =+C8+H8-M8 -> -1395325 | S8: 6248249 | T8: 3176999 | U8: -4103720 | V8: 423035
B9: ABRIL | C9: 3094715 | D9: 109000 | E9: 8902568 | F9: 311788 | G9: 5714524 | H9: 10475785 | I9: 121014 | J9: 6001004 | K9: 7142915 | L9: 5636163 | M9: =+'PYG '!N153 -> 17060981 | N9: 8424882 | O9: 11161681 | P9: 9211395 | Q9: 6162384 | R9: =+C9+H9-M9 -> -3490481 | S9: -8194868 | T9: 3741891 | U9: -1756692 | V9: 5188303
B10: MAYO | C10: =+'PYG '!S9 -> 3036250 | E10: 4831245 | F10: 2070588 | G10: 1563099 | H10: 9475619 | I10: 1804105 | J10: 7419178 | K10: 5721041 | L10: 13796936 | M10: =+'PYG '!R153 -> 11744517 | N10: 10909925 | O10: 10164486 | P10: 8014528 | Q10: 10155182 | R10: =+C10+H10-M10 -> 767352.37 | S10: -9105820 | T10: 2085937 | U10: -222899 | V10: 5204853
B11: JUNIO | C11: =+'PYG '!W9 -> 3220640 | D11: 15088775 | E11: 2541098 | F11: 4186225 | G11: 2504537 | H11: 14072478 | I11: 5883300 | J11: 6384585 | K11: 4021740 | L11: 6565667 | M11: =+'PYG '!V154 -> 12797380 | N11: 12990071 | O11: 8433671 | P11: 7385244 | Q11: 14240736 | R11: =+C11+H11-M11 -> 4495738 | S11: 7982004 | T11: 492012 | U11: 822721 | V11: -5170532
B12: JULIO | C12: =+'PYG '!AA9 -> 2982171 | D12: 5107405 | E12: 2060928 | F12: 3502320 | G12: 14376812 | H12: 7847354 | I12: 9069381 | J12: 4374077 | K12: 1959742 | L12: 6138041 | M12: =+'PYG '!Z154 -> 13357892 | N12: 11530572 | O12: 8752682 | P12: 7676064 | Q12: 10531315 | R12: -2527014 | S12: 2646214 | T12: -2317677 | U12: -2214002 | V12: 9983538
B13: AGOSTO | C13: =+'PYG '!AE9 -> 2259634 | D13: 4348355 | E13: 722060 | F13: 13456626 | G13: 9843168 | H13: 10482068 | I13: 6862717 | J13: 8088583 | K13: 4820282 | L13: 5449400 | M13: =+'PYG '!AD154 -> 12441445 | N13: 11013798 | O13: 10250005 | P13: 9472439 | Q13: 10083753 | R13: =+C13+H13-M13 -> 300257 | S13: 197274 | T13: -1439362 | U13: 8804469 | V13: 5208815
B19: TOTAL | C19: =SUM(C6:C18) -> 26420980 | D19: =SUM(D6:D18) -> 54301625 | E19: =SUM(E6:E18) -> 35099150 | F19: =SUM(F6:F18) -> 44640359 | G19: =SUM(G6:G18) -> 45116568 | H19: =SUM(H6:H18) -> 72431955 | I19: =SUM(I6:I18) -> 42101387 | J19: =SUM(J6:J18) -> 52370334 | ... V19: =SUM(V6:V18) -> 20660648
B44: MES | C44: VENTAS FISCALES 2021 | D44: VENTAS FISCALES 2020 | E44: VENTAS FISCALES 2019 | F44: VENTAS FISCALES 2018 | G44: VENTAS FISCALES 2017
B45: ENERO | C45: 4088450 | D45: 9772741 | E45: 5232922 | F45: 20519674 | G45: =522963+299991+2769114+199640+276690 -> 4068398
B46: FEBRERO | C46: 3444630 | D46: 8662267 | E46: 6735984 | F46: 347610 | G46: =34155+356641+30000+185495+199640+2769114+52440+124200+30000 -> 3781685
B47: MARZO | C47: 4294490 | D47: 11213082 | E47: 4072345 | F47: =245268+260 -> 245528 | G47: =2501135+199640+393580+80730+29750+34510+25000 -> 3264345
B48: ABRIL | C48: 3094715 | D48: 109000 | E48: 8902568 | F48: =44268+102185+80587+29750+50000+4998 -> 311788 | G48: =2769114+199640+549053+161460+430560+90000+267950+437283+714714+17250+40000+37500 -> 5714524
B49: MAYO | C49: 3036250 | E49: 4831245 | F49: 2070588 | G49: 1563099
B50: JUNIO | C50: 3220640 | D50: 15088775 | E50: 2541098 | F50: 4186225 | G50: 2504537
B51: JULIO | C51: 2982171 | D51: 5107405 | E51: 2060928 | F51: 3502320 | G51: 14376812
B52: AGOSTO | C52: 2259634 | D52: 4348355 | E52: 722060 | F52: 13456626 | G52: 9843168
B53: SEPTIEMBRE | D53: 5343486 | E53: 1921510 | F53: 0 | G53: 6807513
B54: OCTUBRE | D54: 5206920 | E54: 1940050 | F54: =+'[1]PYG '!AP47 -> 11000000 | G54: 3921439
B55: NOVIEMBRE | D55: 4539945 | E55: 6096979 | F55: =+'[1]PYG '!AT47 -> 12000000 | G55: 2545390
B56: DICIEMBRE | D56: 5671900 | E56: 10802895 | F56: =+'[1]PYG '!AX47 -> 13000000 | G56: 68513641
B58: TOTAL | C58: =SUM(C45:C57) -> 26420980 | D58: =SUM(D45:D57) -> 75063876 | E58: =SUM(E45:E57) -> 55860584 | F58: =SUM(F45:F57) -> 80640359 | G58: =SUM(G45:G57) -> 126904551
C61: =SUM(C45:C48) -> 14922285 | F61: =SUM(F45:F48) -> 21424600
B70: MES | C70: VENTAS SIN IVA 2021 | D70: VENTAS SIN IVA 2020 | E70: VENTAS SIN IVA 2019 | F70: VENTAS SIN IVA 2018 | G70: VENTAS SIN IVA 2017
B71: ENERO | C71: 5295548 | D71: 4656136 | E71: 7998115 | F71: 5489862 | G71: 3111549
B72: FEBRERO | C72: 6881543 | D72: 7804429 | E72: 4974355 | F72: 7374328 | G72: 8157506
B73: MARZO | C73: 7901560 | D73: 5900305 | E73: 7130437 | F73: 5439456 | G73: 5780617
B74: ABRIL | C74: 10475785 | D74: 121014 | E74: 6001004 | F74: 7142915 | G74: 5636163
B75: MAYO | C75: 9475619 | D75: 1804105 | E75: 7419178 | F75: 5721041 | G75: 13796936
B76: JUNIO | C76: 14072478 | D76: 5883300 | E76: 6384585 | F76: 4021740 | G76: 6565667
B77: JULIO | C77: 7847354 | D77: 9069381 | E77: 4374077 | F77: 1959742 | G77: 6138041
B78: AGOSTO | C78: 10482068 | D78: 6862717 | E78: 8088583 | F78: 4820282 | G78: 5449400
B79: SEPTIEMBRE | D79: 9114471 | E79: 5761435 | F79: 6035931 | G79: 6941815
B80: OCTUBRE | D80: 11912110 | E80: 5903667 | F80: 10697305 | G80: 5541550
B81: NOVIEMBRE | D81: 9403633 | E81: 6953987 | F81: 7259988 | G81: 6901480
B82: DICIEMBRE | D82: 11129725 | E82: 3580427 | F82: 8230584 | G82: 7106144
B83: TOTAL | C83: =SUM(C71:C82) -> 72431955 | D83: =SUM(D71:D82) -> 83661326 | E83: =SUM(E71:E82) -> 74569850 | F83: =SUM(F71:F82) -> 74193174 | G83: =SUM(G71:G82) -> 81126868
C86: =SUM(C71:C74) -> 30554436 | F86: =SUM(F71:F74) -> 25446561
B102: MES | C102: GASTOS 2021 | D102: GASTOS 2020 | E102: GASTOS 2019 | F102: GASTOS 2018 | G102: GASTOS 2017
B103: ENERO | C103: 9031235 | D103: 11183760 | E103: 8192569 | F103: 7055307 | G103: 10452832
B104: FEBRERO | C104: 12420337 | D104: 13337610 | E104: 8084721 | F104: 8975623 | G104: 8843670
B105: MARZO | C105: 13591375 | D105: 10865138 | E105: 8025783 | F105: 9788704 | G105: 8621927
B106: ABRIL | C106: 17060981 | D106: 8424882 | E106: 11161681 | F106: 9211395 | G106: 6162384
B107: MAYO | C107: 11744517 | D107: 10909925 | E107: 10164486 | F107: 8014528 | G107: 10155182
B108: JUNIO | C108: 12797380 | D108: 12990071 | E108: 8433671 | F108: 7385244 | G108: 14240736
B109: JULIO | C109: 13357892 | D109: 11530572 | E109: 8752682 | F109: 7676064 | G109: 10531315
B110: AGOSTO | C110: 12441445 | D110: 11013798 | E110: 10250005 | F110: 9472439 | G110: 10083753
B111: SEPTIEMBRE | D111: 11098718 | E111: 12341541 | F111: 16476675 | G111: 13656658
B112: OCTUBRE | D112: 14559398 | E112: 13788361 | F112: 10699836 | G112: 12463405
B113: NOVIEMBRE | D113: 15548745 | E113: 12146151 | F113: 12696365 | G113: 13179987
B114: DICIEMBRE | D114: 12796951 | E114: 9554095.8 | F114: 8852048 | G114: 27294325
B116: TOTAL | C116: =SUM(C103:C115) -> 1.0244516e+08 | D116: =SUM(D103:D115) -> 144259568 | E116: =SUM(E103:E115) -> 120895746 | F116: =SUM(F103:F115) -> 116304228 | G116: =SUM(G103:G115) -> 145686174
B129: MES | C129: UTILIDAD 2021 | D129: UTILIDAD 2020 | E129: UTILIDAD 2019 | F129: UTILIDAD 2018 | G129: UTILIDAD 2017
B130: ENERO | C130: 352800 | D130: 3245117 | E130: 5038468 | F130: 18954229 | G130: -3272885
B131: FEBRERO | C131: -2094164 | D131: 3129086 | E131: 3625618 | F131: -1253685 | G131: 3095521
B132: MARZO | C132: -1395325 | D132: 6248249 | E132: 3176999 | F132: -4103720 | G132: 423035
B133: ABRIL | C133: -3490481 | D133: -8194868 | E133: 3741891 | F133: -1756692 | G133: 5188303
B134: MAYO | C134: 767352.37 | D134: -9105820 | E134: 2085937 | F134: -222899 | G134: 5204853
B135: JUNIO | C135: 4495738 | D135: 7982004 | E135: 492012 | F135: 822721 | G135: -5170532
B136: JULIO | C136: -2527014 | D136: 2646214 | E136: -2317677 | F136: -2214002 | G136: 9983538
B137: AGOSTO | C137: 300257 | D137: 197274 | E137: -1439362 | F137: 8804469 | G137: 5208815
B138: SEPTIEMBRE | D138: 3359239 | E138: -4658595.8 | F138: -10440744 | G138: 92670
B139: OCTUBRE | D139: 2559631.8 | E139: -5944643.8 | F139: 4755101 | G139: -3000416
B140: NOVIEMBRE | D140: -1605167 | E140: 904815.25 | F140: -380592 | G140: -3733117
B141: DICIEMBRE | D141: =+S17 -> 0 | E141: 4829226.2 | F141: 5224186 | G141: 48325460
B144: TOTAL | C144: =SUM(C130:C143) -> -3590836.6 | D144: =SUM(D130:D143) -> 10460960 | E144: =SUM(E130:E143) -> 9534688 | F144: =SUM(F130:F143) -> 18188372 | G144: =SUM(G130:G143) -> 62345245

Sheet INDICADORES
A1: Razones Financieras
A2: Liquidez
A4: Liquidez | B4: Activos Circulantes | C4: =+AGOSTO!E56 -> 576711378 | D4: =+C4/C5 -> 96.114991 | E4: La empresa cuenta con el 96,11% de respaldo de los activos
B5: Pasivos Circulantes | C5: =+AGOSTO!E93 -> 6000223
A7: Prueba Acida | B7: Activos Circulantes - Inventarios | C7: =+AGOSTO!E56-AGOSTO!E35 -> 410225482 | D7: =+C7/C8 -> 68.368373 | E7: con el activo que tenemos hay el 68,36% para pagar el pasivo
B8: Pasivos Circulantes | C8: =+C5 -> 6000223
A10: Administración de Activos
A12: Rotación Activos Fijos | B12: Ventas | C12: 136687592 | D12: =+C12/C13 -> 0.38563949 | E12: la empresa roto su activo el 0,38
B13: Activos Fijos Netos | C13: =+AGOSTO!E39 -> 354443971
A15: Rotación Activos Totales | B15: Ventas | C15: =+C12 -> 136687592 | D15: =+C15/C16 -> 0.23701213 | E15: la empresa roto su activo totales el 0,23
B16: Activos Totales | C16: =+C4 -> 576711378
A18: Administración de Deudas
A20: Razón de Endeudamiento | B20: Deudas Totales | C20: =+AGOSTO!E93 -> 6000223 | D20: =+C20/C21 -> 0.010404204 | E20: la empresa de los activos debe el 0,010
B21: Activos totales | C21: =+AGOSTO!E56 -> 576711378

Sheet Hoja1
D2: DEPRECIACION ANUAL
B3: Maquinaria y equipos en montaje | C3: =+C4 -> 10126196
B4: Equipo de oficina | C4: 10126196 | D4: =+C4/10 -> 1012619.6 | E4: =+D4/12 -> 84384.967
B5: Construcciones y edificaciones | C5: =+C6+C7 -> 381000000 | E5: =+D5/12 -> 0
B6: Apto sion | C6: 91000000 | D6: =+C6/30 -> 3033333.3 | E6: =+D6/12 -> 252777.78 | F6: =+E6+E7 -> 1058333.3
B7: Apto tamara | C7: 290000000 | D7: =+C7/30 -> 9666666.7 | E7: =+D7/12 -> 805555.56
B8: Equipo de oficina | C8: =+C9 -> 1070000 | E8: =+D8/12 -> 0
B9: Equipos | C9: 1070000 | D9: =+C9/10 -> 107000 | E9: =+D9/12 -> 8916.6667
B10: Equipo de computación y comunicación | C10: =+C11 -> 3109000 | E10: =+D10/12 -> 0
B11: Equipo de procesamiento de datos | C11: 3109000 | D11: =+C11/5 -> 621800 | E11: =+D11/12 -> 51816.667
B12: Flota y equipo de transporte | C12: 34596000 | E12: =+D12/12 -> 0
B13: Camiones, volquetas y furgones | C13: 34596000 | D13: =+C13/5 -> 6919200 | E13: =+D13/12 -> 576600
D14: =SUM(D3:D13) -> 21360620 | E14: =SUM(E3:E13) -> 1780051.6

Sheet TABLAS
B8: MES | C8: VENTAS FISCALES 2021 | D8: VENTAS FISCALES 2020 | E8: VENTAS FISCALES 2019 | F8: VENTAS FISCALES 2018 | G8: VENTAS FISCALES 2017
B9: MAYO | C9: =+'PYG '!S8 -> 3036250 | E9: 4831245 | F9: 2070588 | G9: 1563099
B10: JUNIO | C10: =+'PYG '!W8 -> 3220640 | D10: 15088775 | E10: 2541098 | F10: 4186225 | G10: 2504537
B11: JULIO | C11: =+'PYG '!AA8 -> 2982171 | D11: 5107405 | E11: 2060928 | F11: 3502320 | G11: 14376812
B12: AGOSTO | C12: =+'PYG '!AE8 -> 2259634 | D12: 4348355 | E12: 722060 | F12: 13456626 | G12: 9843168
B13: TOTAL | C13: =SUM(C9:C12) -> 11498695 | D13: =SUM(D9:D12) -> 24544535 | E13: =SUM(E9:E12) -> 10155331 | F13: =SUM(F9:F12) -> 23215759 | G13: =SUM(G9:G12) -> 28287616
B19: MES | C19: VENTAS SIN IVA 2021 | D19: VENTAS SIN IVA 2020 | E19: VENTAS SIN IVA 2019 | F19: VENTAS SIN IVA 2018 | G19: VENTAS SIN IVA 2017 | K19: MES | L19: VENTA ACUMULADA 2021 | M19: VENTA ACUMULADA 2020 | N19: VENTA ACUMULADA 2019 | O19: VENTA ACUMULADA 2018 | P19: VENTA ACUMULADA 2017
B20: MAYO | C20: 9475619 | D20: 1804105 | E20: 7419178 | F20: 5721041 | G20: 13796936 | K20: MAYO | L20: =+C9+C20 -> 12511869 | M20: =+D9+D20 -> 1804105 | N20: =+E9+E20 -> 12250423 | O20: =+F9+F20 -> 7791629 | P20: =+G9+G20 -> 15360035
B21: JUNIO | C21: 14072478 | D21: 5883300 | E21: 6384585 | F21: 4021740 | G21: 6565667 | K21: JUNIO | L21: =+C10+C21 -> 17293118 | M21: =+D10+D21 -> 20972075 | N21: =+E10+E21 -> 8925683 | O21: =+F10+F21 -> 8207965 | P21: =+G10+G21 -> 9070204
B22: JULIO | C22: 7847354 | D22: 9069381 | E22: 4374077 | F22: 1959742 | G22: 6138041 | K22: JULIO | L22: =+C11+C22 -> 10829525 | M22: =+D11+D22 -> 14176786 | N22: =+E11+E22 -> 6435005 | O22: =+F11+F22 -> 5462062 | P22: =+G11+G22 -> 20514853
B23: AGOSTO | C23: 10482068 | D23: 6862717 | E23: 8088583 | F23: 4820282 | G23: 5449400 | K23: AGOSTO | L23: =+C12+C23 -> 12741702 | M23: =+D12+D23 -> 11211072 | N23: =+E12+E23 -> 8810643 | O23: =+F12+F23 -> 18276908 | P23: =+G12+G23 -> 15292568
B24: TOTAL | C24: =SUM(C20:C23) -> 41877519 | D24: =SUM(D20:D23) -> 23619503 | E24: =SUM(E20:E23) -> 26266423 | F24: =SUM(F20:F23) -> 16522805 | G24: =SUM(G20:G23) -> 31950044 | K24: TOTAL | L24: =+C13+C24 -> 53376214 | M24: =SUM(M20:M23) -> 48164038 | N24: =SUM(N20:N23) -> 36421754 | O24: =SUM(O20:O23) -> 39738564 | P24: =SUM(P20:P23) -> 60237660
C25: =+C13+C24 -> 53376214 | D25: =+D13+D24 -> 48164038 | E25: =+E13+E24 -> 36421754 | F25: =+F13+F24 -> 39738564 | G25: =+G13+G24 -> 60237660
B27: MES | C27: GASTOS 2021 | D27: GASTOS 2020 | E27: GASTOS 2019 | F27: GASTOS 2018 | G27: GASTOS 2017
B28: MAYO | C28: 11744517 | D28: 10909925 | E28: 10164486 | F28: 8014528 | G28: 10155182
B29: JUNIO | C29: 12797380 | D29: 12990071 | E29: 8433671 | F29: 7385244 | G29: 14240736
B30: JULIO | C30: 13357892 | D30: 11530572 | E30: 8752682 | F30: 7676064 | G30: 10531315
B31: AGOSTO | C31: 12441445 | D31: 11013798 | E31: 10250005 | F31: 9472439 | G31: 10083753
B32: TOTAL | C32: =SUM(C28:C31) -> 50341234 | D32: =SUM(D28:D31) -> 46444366 | E32: =SUM(E28:E31) -> 37600844 | F32: =SUM(F28:F31) -> 32548275 | G32: =SUM(G28:G31) -> 45010986
C33: 0.08
B35: MES | C35: UTILIDAD 2021 | D35: UTILIDAD 2020 | E35: UTILIDAD 2019 | F35: UTILIDAD 2018 | G35: UTILIDAD 2017
B36: MAYO | C36: 767352.37 | D36: -9105820 | E36: 2085937 | F36: -222899 | G36: 5204853
B37: JUNIO | C37: 4495738 | D37: 7982004 | E37: 492012 | F37: 822721 | G37: -5170532
B38: JULIO | C38: -2527014 | D38: 2646214 | E38: -2317677 | F38: -2214002 | G38: 9983538
B39: AGOSTO | C39: 300257 | D39: 197274 | E39: -1439362 | F39: 8804469 | G39: 5208815
B40: TOTAL | C40: =SUM(C36:C39) -> 3036333.4 | D40: =SUM(D36:D39) -> 1719672 | E40: =SUM(E36:E39) -> -1179090 | F40: =SUM(F36:F39) -> 7190289 | G40: =SUM(G36:G39) -> 15226674
