Workbook

Sheet DICIEMBRE
A1: EQUIORIENTE LTDA
A2: SITUACION FINANCIERA
A3: A 31 DE DICIEMBRE DE 2020
A6: 1 | C6: ACTIVO
A8: 11 | C8: Efectivo y equivalentes al efectivo
A9: 1105 | C9: Caja | E9: =+D10 -> 18368749
A10: 110505 | C10: Caja general | D10: 18368749
A11: 1120 | C11: Cuentas de ahorro
A12: 112005 | C12: Bancos | E12: =+D13 -> 43071060
A13: 11200501 | C13: BBVA | D13: 43071060
A14: 11200502 | C14: Davivienda | D14: 1289007
A16: 13 | C16: Cuentas por cobrar (instrumentos financieros)
A17: 1305 | C17: Clientes | E17: =SUM(D19:D20) -> 6075013.7
A18: 130505 | C18: Nacionales
C19: Fenix Constructores | D19: 5655681.7
C20: Gonzalez Bohorques | D20: =193113+226219 -> 419332
C21: Ajc Inmobiliaria | D21: 1314587
A23: 130515 | C23: Deudores facturacion sin iva | E23: =+D24+D25 -> 12177061
C24: Miriam Serrano | D24: 6423723
C25: Clientes varios | D25: 5753338
A27: 1355 | C27: Anticipo de impuestos y contribuciones o saldos a favor | E27: =SUM(D28:D32) -> 4253045
A28: 135505 | C28: Anticipo de impuestos de renta y complementarios | D28: 413000
A29: 135518 | C29: Reteica | D29: 326615
A30: 135515 | C30: Retención en la fuente | D30: 3006385
A31: 135517 | C31: Impuesto a las ventas retenido | D31: 153045
A32: 13559006 | C32: Autorretencion de renta | D32: =43000+41000+121000+2000+69000+78000 -> 354000
A34: 14 | C34: Inventarios | E34: =+D35 -> 163235452
A35: 1435 | C35: Mercancías no fabricadas por la empresa | D35: =163654784-419332 -> 163235452
A38: 15 | C38: Propiedades planta y equipo | E38: =+D39+D41+D44+D46+D48+D50 -> 373330511
A39: 1512 | C39: Maquinaria y equipos en montaje | D39: =+D40 -> 10126196
A40: 151210 | C40: Equipo de oficina | D40: 10126196
A41: 1516 | C41: Construcciones y edificaciones | D41: =+D42+D43 -> 381000000
A42: 151605 | C42: Apto sion | D42: 91000000
A43: 151610 | C43: Apto tamara | D43: 290000000
A44: 1524 | C44: Equipo de oficina | D44: =+D45 -> 1070000
A45: 152410 | C45: Equipos | D45: 1070000
A46: 1528 | C46: Equipo de computación y comunicación | D46: =+D47 -> 3109000
A47: 152805 | C47: Equipo de procesamiento de datos | D47: 3109000
A48: 1540 | C48: Flota y equipo de transporte | D48: 34596000
A49: 154008 | C49: Camiones, volquetas y furgones | D49: 34596000
A50: 1592 | C50: Depreciación acumulada | D50: =SUM(D51:D55) -> -56570685
C51: MAQUINARIA Y EQUIPO | D51: -9040688
C52: EQUIPO DE CONSTRUCCION | D52: -36470801
C53: EQUIPO DE OFICINA | D53: -136796
C54: EQUIPO DE COMPUTO | D54: -543600
C55: Flota y equipo de transporte | D55: -10378800
A57: 16 | C57: Intangibles | E57: =+D58 -> 2548980
A58: 1635 | C58: Licencias | D58: 2548980
A60: TOTAL ACTIVO | E60: =SUM(E9:E58) -> 6.2305987e+08
A64: 2365 | C64: Retención en la fuente | E64: =+D65+D66 -> 400000
A65: 236525 | C65: Retención en la fuente | D65: 374000
A66: 236706 | C66: Autorretencion | D66: 26000
A68: 2370 | C68: Retenciones y aportes de nómina | E68: =+D69+D70+D71 -> 336200
A69: 237005 | C69: Aportes a entidades promotoras de salud EPS | D69: 107700
A70: 237006 | C70: Aportes a administradoras de riesgos profesionales arp | D70: 65600
A71: 237010 | C71: Aportes al i.c.b.f, sena y cajas compensación | D71: 162900
A72: 2380 | C72: Acreedores varios | E72: =+D73 -> 430500
A73: 238030 | C73: Fondos de cesantías y/o pensiones | D73: 430500
A76: 24 | C76: Impuestos, gravámenes y tasas | E76: =+D77+D78 -> 1073000
A77: 2408 | C77: Impuesto sobre las ventas por pagar | D77: 637000
A78: 2412 | C78: industria y comercio | D78: 436000
A82: 26 | C82: Provisión de pasivos
A83: 2610 | C83: Para obligaciones laborales | E83: =SUM(D84:D89) -> 0
A84: 261005 | C84: Cesantías | D84: 0
A85: 261010 | C85: Intereses sobre cesantías | D85: 0
A86: 261015 | C86: Vacaciones | D86: 0
A87: 261020 | C87: Prima | D87: 0
A91: 22 | C91: PROVEEDORES
A92: 2205 | C92: Nacionales | E92: =+D94+D95 -> 4052548
A93: 221005 | C93: Proveedores por debajo
C94: Olga gomez (metalmartinez) | D94: 4052548
A97: TOTAL PASIVO | E97: =SUM(E63:E96) -> 6292248
A100: 3 | C100: PATRIMONIO
A102: 31 | C102: Capital social | E102: =+D103 -> 574301990
A103: 3105 | C103: Capital suscrito y pagado | D103: 574301990
A104: 310505 | C104: Capital autorizado
A107: 36 | C107: Resultados del ejercicio | E107: =+D108 -> 14465634
A108: 3605 | C108: Utilidad del ejercicio | D108: =+D109 -> 14465634
A109: 360501 | C109: Utilidad del ejercicio | D109: =+'PYG '!AU154 -> 14465634
A111: 37 | C111: UTILIDAD DEL EJERCICIO ANTERIORES | E111: =+D112+D113 -> 28000000 | I111: =E111*19% -> 5320000
A112: 37 | C112: Utilidad de ejercicios anteriores | D112: 28000000
A115: TOTAL PATRIMONIO | E115: =+E102+E107+E111 -> 6.1676762e+08
A117: TOTAL PATRIMONIO Y PASIVO | E117: =+E115+E97 -> 6.2305987e+08
E119: 0
E120: =+E60-E97-E115 -> -0.085000038

Sheet PYG 
A1: EQUIORIENTE LTDA
A2: INFORMES AÑO 2020
C4: 43831 | G4: 43862 | J4: 43891 | N4: 43922 | R4: 43952 | V4: 43983 | Y4: 44013 | AC4: 44044 | AG4: 44075 | AK4: 44105 | AO4: 44136 | AS4: 44166
A5: Cuenta | C5: Mov. 02/01/2020 a 31/01/2020 | E5: Saldos a 31/01/2020 | G5: Mov. 01/02/2020 a 28/02/2020 | I5: Saldos a 28/02/2020 | J5: Mov. 01/03/2020 a 31/03/2020 | L5: Saldos a 31/03/2020 | N5: Mov. 01/04/2020 a 30/04/2020 | P5: Saldos a 30/04/2020 | R5: Mov. 02/05/2020 a 31/05/2020 | T5: Saldos a 31/01/2020 | V5: Mov. 01/06/2020 a 30/06/2020 | X5: Saldos a 28/06/2020 | Y5: Mov. 01/07/2020 a 31/07/2020 | AA5: Saldos a 31/07/2020 | AC5: Mov. 01/08/2020 a 30/08/2020 | AE5: Saldos a 30/08/2020 | AG5: Mov. 01/09/2020 a 31/09/2020 | AI5: Saldos a 31/09/2020 | AK5: Mov. 01/10/2020 a 31/10/2020 | AM5: Saldos a 31/10/2020 | AO5: Mov. 01/11/2020 a 30/11/2020 | AQ5: Saldos a 30/11/2020 | AS5: Mov. 01/12/2020 a 30/12/2020 | AU5: Saldos a 31/12/2020
A6: Cód. | B6: Nombre | C6: Débitos | D6: Créditos | E6: Saldo actual | G6: Débitos | H6: Créditos | I6: Saldo actual | J6: Débitos | K6: Créditos | L6: Saldo actual | N6: Débitos | O6: Créditos | P6: Saldo actual | R6: Débitos | S6: Créditos | T6: Saldo actual | V6: Débitos | W6: Créditos | X6: Saldo actual | Y6: Débitos | Z6: Créditos | AA6: Saldo actual | AC6: Débitos | AD6: Créditos | AE6: Saldo actual | AG6: Débitos | AH6: Créditos | AI6: Saldo actual | AK6: Débitos | AL6: Créditos | AM6: Saldo actual | AO6: Débitos | AP6: Créditos | AQ6: Saldo actual | AS6: Débitos | AT6: Créditos | AU6: Saldo actual
A7: 4 | B7: INGRESOS | C7: 0 | D7: =D8+D14 -> 16317677 | E7: =E8+E14 -> 16317677 | G7: 0 | H7: =H8+H14 -> 18355496 | I7: =E7+H7 -> 34673173 | J7: 0 | K7: =K8+K14 -> 19002187 | L7: =I7+K7 -> 53675360 | N7: 0 | O7: =O8+O14 -> 2118814 | P7: =L7+O7 -> 55794174 | R7: 0 | S7: =S8+S14 -> 3692905 | T7: =+P7+S7 -> 59487079 | V7: 0 | W7: =W8+W14 -> 22654975 | X7: =+T7+W7 -> 82142054 | Y7: 0 | Z7: =Z8+Z14 -> 15859686 | AA7: =+X7+Z7 -> 98001740 | AC7: 0 | AD7: =AD8+AD14 -> 13147172 | AE7: =AA7+AD7 -> 111148912 | AG7: 0 | AH7: =AH8+AH14 -> 16313657 | AI7: =AE7+AH7 -> 127462569 | AK7: 0 | AL7: =AL8+AL14 -> 19079630 | AM7: =AI7+AL7 -> 1.465422e+08 | AO7: 0 | AP7: =AP8+AP14 -> 15904178 | AQ7: =AM7+AP7 -> 1.6244638e+08 | AS7: 0 | AT7: =AT8+AT14 -> 18762225 | AU7: =AQ7+AT7 -> 1.812086e+08
A8: 41 | B8: Operacionales | C8: 0 | D8: =D9 -> 9772741 | E8: =E9 -> 9772741 | G8: 0 | H8: =H9 -> 8662267 | I8: =E8+H8 -> 18435008 | J8: 0 | K8: =K9 -> 11213082 | L8: =I8+K8 -> 29648090 | N8: 0 | O8: =O9 -> 109000 | P8: =L8+O8 -> 29757090 | R8: 0 | S8: =S9 -> 0 | T8: =+P8+S8 -> 29757090 | V8: 0 | W8: =W9 -> 15088775 | X8: =T8+W8 -> 44845865 | Y8: 0 | Z8: =Z9 -> 5107405 | AA8: =+X8+Z8 -> 49953270 | AC8: 0 | AD8: =AD9 -> 4348355 | AE8: =AA8+AD8 -> 54301625 | AG8: 0 | AH8: =AH9 -> 5343486 | AI8: =AE8+AH8 -> 59645111 | AK8: 0 | AL8: =AL9 -> 5206920 | AM8: =AI8+AL8 -> 64852031 | AO8: =AK8+AN8 -> 0 | AP8: =AP9 -> 4539945 | AQ8: =AM8+AP8 -> 69391976 | AS8: =AO8+AR8 -> 0 | AT8: =AT9 -> 5671900 | AU8: =AQ8+AT8 -> 75063876
A9: 4155 | B9: Actividades inmobiliarias, empresariales y de alquiler | C9: 0 | D9: =+D10+D11+D12 -> 9772741 | E9: =D9 -> 9772741 | G9: 0 | H9: =H10+H11+H12 -> 8662267 | I9: =E9+H9 -> 18435008 | J9: 0 | K9: =K10+K11+K12 -> 11213082 | L9: =I9+K9 -> 29648090 | N9: 0 | O9: =O10+O11+O12 -> 109000 | P9: =L9+O9 -> 29757090 | R9: 0 | S9: =+S10+S11+S12 -> 0 | T9: =+P9+S9 -> 29757090 | V9: 0 | W9: =+W10+W11+W12 -> 15088775 | X9: =T9+W9 -> 44845865 | Y9: 0 | Z9: =+Z10+Z12 -> 5107405 | AA9: =+AA10+AA11+AA12 -> 49953270 | AC9: 0 | AD9: =+AD10+AD11+AD12 -> 4348355 | AE9: =AA9+AD9 -> 54301625 | AG9: =AC9+AF9 -> 0 | AH9: =+AH10+AH11+AH12 -> 5343486 | AI9: =AE9+AH9 -> 59645111 | AK9: =AG9+AJ9 -> 0 | AL9: =+AL10+AL11+AL12 -> 5206920 | AM9: =AI9+AL9 -> 64852031 | AO9: =AK9+AN9 -> 0 | AP9: =+AP10+AP11+AP12 -> 4539945 | AQ9: =AM9+AP9 -> 69391976 | AS9: =AO9+AR9 -> 0 | AT9: =+AT10+AT11+AT12 -> 5671900 | AU9: =AQ9+AT9 -> 75063876
A10: 415520 | B10: Alquiler IVA | C10: 0 | D10: 9455741 | E10: =+D10 -> 9455741 | G10: 0 | H10: 8079667 | I10: =E10+H10 -> 17535408 | J10: 0 | K10: 10928082 | L10: =I10+K10 -> 28463490 | N10: 0 | O10: 84000 | P10: =L10+O10 -> 28547490 | R10: 0 | S10: 0 | T10: =+P10+S10 -> 28547490 | V10: 0 | W10: 13738340 | X10: =T10+W10 -> 42285830 | Y10: 0 | Z10: 4717405 | AA10: =+X10+Z10 -> 47003235 | AC10: 0 | AD10: 4228355 | AE10: =AA10+AD10 -> 51231590 | AG10: 0 | AH10: 5253486 | AI10: =AE10+AH10 -> 56485076 | AL10: 5206920 | AM10: =AI10+AL10 -> 61691996 | AO10: 0 | AP10: 4539945 | AQ10: =AM10+AP10 -> 66231941 | AS10: 0 | AT10: 5531900 | AU10: =AQ10+AT10 -> 71763841
A11: 415525 | B11: VENTA EQUIPO | D11: 0 | E11: =+D11 -> 0 | G11: 0 | H11: 0 | I11: =E11+H11 -> 0 | K11: 0 | L11: =I11+K11 -> 0 | O11: 0 | P11: =L11+O11 -> 0 | S11: 0 | T11: =+P11+S11 -> 0 | V11: 0 | W11: 0 | X11: =T11+W11 -> 0 | Y11: 0 | Z11: 0 | AA11: =+X11+Z11 -> 0 | AC11: 0 | AD11: 0 | AE11: =AA11+AD11 -> 0 | AG11: 0 | AI11: =AE11+AH11 -> 0 | AK11: 0 | AL11: 0 | AM11: =AI11+AL11 -> 0 | AO11: 0 | AP11: 0 | AQ11: =AM11+AP11 -> 0 | AS11: 0 | AT11: 0 | AU11: =AQ11+AT11 -> 0
A12: 415515 | B12: Transporte | C12: 0 | D12: 317000 | E12: =+D12 -> 317000 | G12: 0 | H12: 582600 | I12: =E12+H12 -> 899600 | J12: 0 | K12: 285000 | L12: =I12+K12 -> 1184600 | N12: 0 | O12: 25000 | P12: =L12+O12 -> 1209600 | R12: 0 | S12: 0 | T12: =+P12+S12 -> 1209600 | V12: 0 | W12: 1350435 | X12: =T12+W12 -> 2560035 | Y12: 0 | Z12: 390000 | AA12: =+X12+Z12 -> 2950035 | AC12: 0 | AD12: 120000 | AE12: =AA12+AD12 -> 3070035 | AG12: 0 | AH12: 90000 | AI12: =AE12+AH12 -> 3160035 | AK12: 0 | AL12: 0 | AM12: =AI12+AL12 -> 3160035 | AO12: 0 | AP12: 0 | AQ12: =AM12+AP12 -> 3160035 | AS12: 0 | AT12: 140000 | AU12: =AQ12+AT12 -> 3300035
L13: =I13+K13 -> 0 | AA13: =+X13+Z13 -> 0
A14: 42 | B14: No operacionales | C14: 0 | D14: =D15+D19+D22+D24 -> 6544936 | E14: =+D14 -> 6544936 | G14: 0 | H14: =H15+H19+H22+H24 -> 9693229 | I14: =E14+H14 -> 16238165 | J14: 0 | K14: =K15+K19+K22+K24 -> 7789105 | L14: =I14+K14 -> 24027270 | N14: 0 | O14: =O15+O19+O22+O24 -> 2009814 | P14: =L14+O14 -> 26037084 | R14: 0 | S14: =S15+S19+S22+S24 -> 3692905 | T14: =+P14+S14 -> 29729989 | V14: 0 | W14: =W15+W19+W22+W24 -> 7566200 | X14: =+T14+W14 -> 37296189 | Y14: 0 | Z14: =Z15+Z19+Z22+Z24 -> 10752281 | AA14: =X14+Z14 -> 48048470 | AC14: 0 | AD14: =AD15+AD19+AD22+AD24 -> 8798817 | AE14: =AA14+AD14 -> 56847287 | AG14: 0 | AH14: =AH15+AH19+AH22+AH24 -> 10970171 | AI14: =AE14+AH14 -> 67817458 | AK14: 0 | AL14: =AL15+AL19+AL22+AL24 -> 13872710 | AM14: =AI14+AL14 -> 81690168 | AO14: 0 | AP14: =AP15+AP19+AP22+AP24 -> 11364233 | AQ14: =AM14+AP14 -> 93054401 | AS14: 0 | AT14: =AT15+AT19+AT22+AT24 -> 13090325 | AU14: =AQ14+AT14 -> 1.0614473e+08
A15: 4210 | B15: Financieros | C15: 0 | D15: =+D16+D17 -> 98461 | E15: =+D15 -> 98461 | G15: 0 | H15: =+H16+H17 -> 119593 | I15: =E15+H15 -> 218054 | J15: 0 | K15: =+K16+K17 -> 116227 | L15: =I15+K15 -> 334281 | N15: 0 | O15: =+O16+O17 -> 120723 | P15: =L15+O15 -> 455004 | R15: 0 | S15: =+S16 -> 7961 | T15: =+P15+S15 -> 462965 | V15: 0 | W15: =+W16+W17 -> 9258 | X15: =+T15+W15 -> 472223 | Y15: 0 | Z15: =+Z16+Z17 -> 5860 | AA15: =+X15+Z15 -> 478083 | AC15: 0 | AD15: =+AD16+AD17 -> 6465 | AE15: =AA15+AD15 -> 484548 | AG15: 0 | AH15: =+AH16+AH17 -> 6863 | AI15: =AE15+AH15 -> 491411 | AK15: 0 | AL15: =+AL16+AL17 -> 7468 | AM15: =AI15+AL15 -> 498879 | AO15: 0 | AP15: =+AP16+AP17 -> 3771 | AQ15: =AM15+AP15 -> 502650 | AS15: 0 | AT15: =+AT16+AT17 -> 3436 | AU15: =AQ15+AT15 -> 506086
A16: 421005 | B16: Intereses | C16: 0 | D16: 389 | E16: =+D16 -> 389 | G16: 0 | H16: 8163 | I16: =E16+H16 -> 8552 | J16: 0 | K16: 4797 | L16: =I16+K16 -> 13349 | N16: 0 | O16: 9293 | P16: =L16+O16 -> 22642 | R16: 0 | S16: 7961 | T16: =+P16+S16 -> 30603 | V16: 0 | W16: 9258 | X16: =+T16+W16 -> 39861 | Y16: 0 | Z16: 5860 | AA16: =+X16+Z16 -> 45721 | AC16: 0 | AD16: 6465 | AE16: =AA16+AD16 -> 52186 | AG16: 0 | AH16: 6863 | AI16: =AE16+AH16 -> 59049 | AK16: 0 | AL16: 7468 | AM16: =AI16+AL16 -> 66517 | AO16: 0 | AP16: 3771 | AQ16: =AM16+AP16 -> 70288 | AS16: 0 | AT16: 3436 | AU16: =AQ16+AT16 -> 73724
A17: 421095 | B17: intereses prestamos socios | D17: 98072 | E17: =+D17 -> 98072 | H17: 111430 | I17: =E17+H17 -> 209502 | K17: 111430 | L17: =I17+K17 -> 320932 | O17: 111430 | P17: =L17+O17 -> 432362 | X17: =+T17+W17 -> 0 | Z17: 0 | AA17: =+X17+Z17 -> 0 | AD17: 0 | AE17: =AA17+AD17 -> 0 | AI17: =AE17+AH17 -> 0 | AL17: 0 | AM17: =AI17+AL17 -> 0 | AQ17: =AM17+AP17 -> 0 | AU17: =AQ17+AT17 -> 0
L18: =I18+K18 -> 0 | T18: =+P18+S18 -> 0 | X18: =+T18+W18 -> 0 | AA18: =+X18+Z18 -> 0 | AE18: =AA18+AD18 -> 0 | AI18: =AE18+AH18 -> 0 | AM18: =AI18+AL18 -> 0 | AQ18: =AM18+AP18 -> 0 | AU18: =AQ18+AT18 -> 0
A19: 4220 | B19: ARRENDAMIENTOS APARTAMENTOS | C19: 0 | D19: =D20 -> 1888800 | E19: =+D19 -> 1888800 | G19: 0 | H19: =+H20 -> 1888800 | I19: =E19+H19 -> 3777600 | J19: 0 | K19: 1888800 | L19: =I19+K19 -> 5666400 | N19: 0 | O19: =O20 -> 1888800 | P19: =L19+O19 -> 7555200 | R19: 0 | S19: =+S20 -> 1888800 | T19: =+P19+S19 -> 9444000 | V19: 0 | W19: =+W20 -> 1682900 | X19: =+T19+W19 -> 11126900 | Y19: 0 | Z19: =+Z20 -> 1682900 | AA19: =+X19+Z19 -> 12809800 | AC19: 0 | AD19: =+AD20 -> 1936100 | AE19: =AA19+AD19 -> 14745900 | AG19: 0 | AH19: =+AH20 -> 1855700 | AI19: =AE19+AH19 -> 16601600 | AK19: 0 | AL19: =+AL20 -> 1960600 | AM19: =AI19+AL19 -> 18562200 | AO19: 0 | AP19: =+AP20 -> 1960600 | AQ19: =AM19+AP19 -> 20522800 | AS19: 0 | AT19: =+AT20 -> 1960600 | AU19: =AQ19+AT19 -> 22483400
A20: 422010 | B20: Apartamentos Arrendados | C20: 0 | D20: 1888800 | E20: =+D20 -> 1888800 | G20: 0 | H20: =+K20 -> 1888800 | I20: =E20+H20 -> 3777600 | J20: 0 | K20: =+K19 -> 1888800 | L20: =I20+K20 -> 5666400 | N20: 0 | O20: 1888800 | P20: =L20+O20 -> 7555200 | R20: 0 | S20: 1888800 | T20: =+P20+S20 -> 9444000 | V20: 0 | W20: 1682900 | X20: =+T20+W20 -> 11126900 | Y20: 0 | Z20: 1682900 | AA20: =+X20+Z20 -> 12809800 | AC20: 0 | AD20: 1936100 | AE20: =AA20+AD20 -> 14745900 | AG20: 0 | AH20: 1855700 | AI20: =AE20+AH20 -> 16601600 | AK20: 0 | AL20: 1960600 | AM20: =AI20+AL20 -> 18562200 | AO20: 0 | AP20: 1960600 | AQ20: =AM20+AP20 -> 20522800 | AS20: 0 | AT20: 1960600 | AU20: =AQ20+AT20 -> 22483400
L21: =I21+K21 -> 0 | T21: =+P21+S21 -> 0 | X21: =+T21+W21 -> 0 | AA21: =+X21+Z21 -> 0
A22: 4235 | B22: Servicios | C22: 0 | D22: =D23 -> 4555634 | E22: =+D22 -> 4555634 | G22: 0 | H22: =H23 -> 7684835 | I22: =E22+H22 -> 12240469 | J22: 0 | K22: =K23 -> 5784014 | L22: =I22+K22 -> 18024483 | N22: 0 | O22: =O23 -> 0 | P22: =L22+O22 -> 18024483 | R22: 0 | S22: =S23 -> 1735600 | T22: =+P22+S22 -> 19760083 | V22: 0 | W22: =+W23 -> 5171840 | X22: =+T22+W22 -> 24931923 | Y22: 0 | Z22: =+Z23 -> 8361192 | AA22: =+X22+Z22 -> 33293115 | AC22: 0 | AD22: =AD23 -> 6855832 | AE22: =AA22+AD22 -> 40148947 | AG22: 0 | AH22: =AH23 -> 9106991 | AI22: =AE22+AH22 -> 49255938 | AK22: 0 | AL22: =AL23 -> 11904424 | AM22: =AI22+AL22 -> 61160362 | AO22: 0 | AP22: =AP23 -> 9399435 | AQ22: =AM22+AP22 -> 70559797 | AS22: 0 | AT22: =AT23 -> 11126088 | AU22: =AQ22+AT22 -> 81685885
A23: 423510 | B23: VENTAS SIN IVA | C23: 0 | D23: 4555634 | E23: =+D23 -> 4555634 | G23: 0 | H23: 7684835 | I23: =E23+H23 -> 12240469 | J23: 0 | K23: 5784014 | L23: =I23+K23 -> 18024483 | N23: 0 | O23: 0 | P23: =L23+O23 -> 18024483 | R23: 0 | S23: 1735600 | T23: =+P23+S23 -> 19760083 | V23: 0 | W23: 5171840 | X23: =+T23+W23 -> 24931923 | Y23: 0 | Z23: 8361192 | AA23: =+X23+Z23 -> 33293115 | AC23: 0 | AD23: 6855832 | AE23: =AA23+AD23 -> 40148947 | AG23: 0 | AH23: 9106991 | AI23: =AE23+AH23 -> 49255938 | AK23: 0 | AL23: 11904424 | AM23: =AI23+AL23 -> 61160362 | AO23: 0 | AP23: 9399435 | AQ23: =AM23+AP23 -> 70559797 | AS23: 0 | AT23: 11126088 | AU23: =AQ23+AT23 -> 81685885
A24: 4295 | B24: DIVERSOS | C24: 0 | D24: =+D25 -> 2041 | E24: =+D24 -> 2041 | G24: 0 | H24: =+H25 -> 1 | I24: =E24+H24 -> 2042 | J24: 0 | K24: =+K25 -> 64 | L24: =I24+K24 -> 2106 | N24: 0 | O24: =+O25 -> 291 | P24: =L24+O24 -> 2397 | R24: 0 | S24: =+S25 -> 60544 | T24: =+P24+S24 -> 62941 | V24: 0 | W24: =+W25 -> 702202 | X24: =+T24+W24 -> 765143 | Y24: 0 | Z24: =+Z25 -> 702329 | AA24: =+X24+Z24 -> 1467472 | AC24: 0 | AD24: =+AD25 -> 420 | AE24: =AA24+AD24 -> 1467892 | AG24: 0 | AH24: =+AH25 -> 617 | AI24: =AE24+AH24 -> 1468509 | AK24: 0 | AL24: =+AL25 -> 217.83 | AM24: =AI24+AL24 -> 1468726.8 | AO24: 0 | AP24: =+AP25 -> 427 | AQ24: =AM24+AP24 -> 1469153.8 | AS24: 0 | AT24: 201 | AU24: =AQ24+AT24 -> 1469354.8
A25: 429581 | B25: Ajuste al peso | C25: 0 | D25: 2041 | E25: =+D25 -> 2041 | G25: 0 | H25: 1 | I25: =E25+H25 -> 2042 | J25: 0 | K25: 64 | L25: =I25+K25 -> 2106 | N25: 0 | O25: 291 | P25: =L25+O25 -> 2397 | R25: 0 | S25: 60544 | T25: =+P25+S25 -> 62941 | V25: 0 | W25: 702202 | X25: =+T25+W25 -> 765143 | Y25: 0 | Z25: 702329 | AA25: =+X25+Z25 -> 1467472 | AC25: 0 | AD25: 420 | AE25: =AA25+AD25 -> 1467892 | AG25: 0 | AH25: 617 | AI25: =AE25+AH25 -> 1468509 | AK25: 0 | AL25: 217.83 | AM25: =AI25+AL25 -> 1468726.8 | AO25: 0 | AP25: 427 | AQ25: =AM25+AP25 -> 1469153.8 | AS25: 0 | AT25: 201 | AU25: =AQ25+AT25 -> 1469354.8
A27: 5 | B27: GASTOS | C27: =C28+C140+C118 -> 11744572 | D27: 0 | E27: =+C27 -> 11744572 | G27: =G28+G140+G118 -> 13567384 | H27: 0 | I27: =E27+G27 -> 25311956 | J27: =J28+J140+J118 -> 11094912 | K27: 0 | L27: =I27+J27 -> 36406868 | N27: =N28+N140+N118 -> 8654656 | O27: 0 | P27: =L27+N27 -> 45061524 | R27: =R28+R140+R118 -> 11139699 | S27: 0 | T27: =+P27+R27 -> 56201223 | V27: =V28+V140+V118 -> 13198472 | W27: 0 | X27: =T27+V27 -> 69399695 | Y27: =Y28+Y140+Y118 -> 11738973 | Z27: 0 | AA27: =X27+Y27 -> 81138668 | AC27: =AC28+AC140+AC118 -> 11240136 | AD27: 0 | AE27: =AA27+AC27 -> 92378804 | AG27: =AG28+AG140+AG118 -> 11325056 | AH27: 0 | AI27: =AE27+AG27 -> 103703860 | AK27: =AK28+AK140+AK118 -> 14796625 | AL27: 0 | AM27: =AI27+AK27 -> 118500485 | AO27: =AO28+AO140+AO118 -> 15785972 | AP27: 0 | AQ27: =AM27+AO27 -> 134286457 | AS27: =AS28+AS140+AS118 -> 13034178 | AT27: 0 | AU27: =AQ27+AS27 -> 147320635
A28: 51 | B28: Operacionales de administración | C28: =C29+C45+C56+C50+C63+C66+C77+C83+C90+C104+C60+C96 -> 11085668 | D28: 0 | E28: =+C28 -> 11085668 | G28: =G29+G45+G56+G50+G63+G66+G77+G83+G90+G104+G60+G96 -> 13257332 | H28: 0 | I28: =E28+G28 -> 24343000 | J28: =J29+J45+J56+J50+J63+J66+J77+J83+J90+J104+J60+J96 -> 10689110 | K28: 0 | L28: =I28+J28 -> 35032110 | N28: =N29+N45+N56+N50+N63+N66+N77+N83+N90+N104+N60+N96 -> 8333942 | O28: 0 | P28: =L28+N28 -> 43366052 | R28: =R29+R45+R56+R50+R63+R66+R77+R83+R90+R104+R60+R96 -> 10779740 | S28: 0 | T28: =+P28+R28 -> 54145792 | V28: =V29+V45+V50+V56+V63+V66+V77+V83+V90+V104+V96 -> 12830518 | W28: 0 | X28: =T28+V28 -> 66976310 | Y28: =Y29+Y45+Y50+Y56+Y63+Y66+Y77+Y83+Y90+Y104+Y96 -> 11399718 | Z28: 0 | AA28: =X28+Y28 -> 78376028 | AC28: =AC29+AC45+AC50+AC56+AC63+AC66+AC77+AC83+AC90+AC104+AC96 -> 10811171 | AD28: 0 | AE28: =AA28+AC28 -> 89187199 | AG28: =AG29+AG45+AG50+AG56+AG63+AG66+AG77+AG83+AG90+AG104+AG96 -> 11022465 | AH28: 0 | AI28: =AE28+AG28 -> 100209664 | AK28: =AK29+AK45+AK50+AK56+AK63+AK66+AK77+AK83+AK90+AK104+AK96 -> 14479282 | AL28: 0 | AM28: =AI28+AK28 -> 114688946 | AO28: =AO29+AO45+AO50+AO56+AO63+AO66+AO77+AO83+AO90+AO104+AO96 -> 15438511 | AP28: 0 | AQ28: =AM28+AO28 -> 130127457 | AS28: =AS29+AS45+AS50+AS56+AS63+AS66+AS77+AS83+AS90+AS104+AS96 -> 12665615 | AT28: 0 | AU28: =AQ28+AS28 -> 142793072
A29: 5105 | B29: Gastos de personal | C29: =C30+C32+C33+C34+C35+C36+C37+C38+C39+C40+C41+C42 -> 2240070 | D29: 0 | E29: =+C29 -> 2240070 | G29: =SUM(G30:G42) -> 4589258 | H29: 0 | I29: =E29+G29 -> 6829328 | J29: =SUM(J30:J42) -> 3812340 | K29: 0 | L29: =I29+J29 -> 10641668 | N29: =N30+N32+N33+N34+N35+N36+N37+N38+N39+N40+N41+N42 -> 2438298 | O29: 0 | P29: =L29+N29 -> 13079966 | R29: =SUM(R30:R42) -> 4265577 | S29: 0 | T29: =+P29+R29 -> 17345543 | V29: =SUM(V30:V42) -> 4726603 | W29: 0 | X29: =T29+V29 -> 22072146 | Y29: =SUM(Y30:Y42) -> 4759971 | Z29: 0 | AA29: =X29+Y29 -> 26832117 | AC29: =AC30+AC32+AC33+AC34+AC35+AC36+AC37+AC38+AC39+AC40+AC41+AC42 -> 4463934 | AD29: 0 | AE29: =AA29+AC29 -> 31296051 | AG29: =AG30+AG32+AG33+AG34+AG35+AG36+AG37+AG38+AG39+AG40+AG41+AG42 -> 4682010 | AH29: 0 | AI29: =AE29+AG29 -> 35978061 | AK29: =AK30+AK32+AK33+AK34+AK35+AK36+AK37+AK38+AK39+AK40+AK41+AK42+AK43 -> 4764290 | AL29: 0 | AM29: =AI29+AK29 -> 40742351 | AO29: =AO30+AO32+AO33+AO34+AO35+AO36+AO37+AO38+AO39+AO40+AO41+AO42 -> 4766659 | AP29: 0 | AQ29: =AM29+AO29 -> 45509010 | AS29: =AS30+AS32+AS33+AS34+AS35+AS36+AS37+AS38+AS39+AS40+AS41+AS42 -> 4185647 | AT29: 0 | AU29: =AQ29+AS29 -> 49694657
A30: 510506 | B30: Sueldos | C30: 1266596 | D30: 0 | E30: =+C30 -> 1266596 | G30: 2860993 | H30: 0 | I30: =E30+G30 -> 4127589 | J30: 2308429 | K30: 0 | L30: =I30+J30 -> 6436018 | N30: 1806596 | O30: 0 | P30: =L30+N30 -> 8242614 | R30: 2890994 | S30: 0 | T30: =+P30+R30 -> 11133608 | V30: 2980994 | W30: 0 | X30: =T30+V30 -> 14114602 | Y30: 3010994 | Z30: 0 | AA30: =X30+Y30 -> 17125596 | AC30: 2810261 | AD30: 0 | AE30: =AA30+AC30 -> 19935857 | AG30: 3010994 | AH30: 0 | AI30: =AE30+AG30 -> 22946851 | AK30: 3010994 | AL30: 0 | AM30: =AI30+AK30 -> 25957845 | AO30: 3010994 | AP30: 0 | AQ30: =AM30+AO30 -> 28968839 | AS30: 2690261 | AT30: 0 | AU30: =AQ30+AS30 -> 31659100
A31: 5105 | B31: Horas extras | C31: 0 | D31: 0 | E31: 0 | G31: 0 | H31: 0 | I31: 0 | J31: 0 | K31: 0 | L31: 0 | N31: 0 | O31: 0 | P31: 0 | T31: =+P31+R31 -> 0 | V31: 0 | AU31: =AQ31+AS31 -> 0
A32: 510527 | B32: Auxilio de transporte | C32: 0 | D32: 0 | E32: =+C32 -> 0 | G32: 85712 | H32: 0 | I32: =E32+G32 -> 85712 | J32: 78855 | K32: 0 | L32: =I32+J32 -> 164567 | N32: 0 | O32: 0 | P32: =L32+N32 -> 164567 | R32: 89140 | S32: 0 | T32: =+P32+R32 -> 253707 | V32: 99426 | W32: 0 | X32: =T32+V32 -> 353133 | Y32: 102854 | Z32: 0 | AA32: =X32+Y32 -> 455987 | AC32: 95997 | AD32: 0 | AE32: =AA32+AC32 -> 551984 | AG32: 102854 | AH32: 0 | AI32: =AE32+AG32 -> 654838 | AK32: 102854 | AL32: 0 | AM32: =AI32+AK32 -> 757692 | AO32: 102854 | AP32: 0 | AQ32: =AM32+AO32 -> 860546 | AS32: 82283 | AT32: 0 | AU32: =AQ32+AS32 -> 942829
A33: 510530 | B33: Cesantías | C33: 105507 | D33: 0 | E33: =+C33 -> 105507 | G33: 298275 | H33: 0 | I33: =E33+G33 -> 403782 | J33: 298275 | K33: 0 | L33: =I33+J33 -> 702057 | N33: =150489-13022 -> 137467 | O33: 0 | P33: =L33+N33 -> 839524 | R33: 298275 | S33: 0 | T33: =+P33+R33 -> 1137799 | V33: 298275 | W33: 0 | X33: =T33+V33 -> 1436074 | Y33: 298275 | Z33: 0 | AA33: =X33+Y33 -> 1734349 | AC33: 259384 | AD33: 0 | AE33: =AA33+AC33 -> 1993733 | AG33: 259384 | AH33: 0 | AI33: =AE33+AG33 -> 2253117 | AK33: 259384 | AL33: 0 | AM33: =AI33+AK33 -> 2512501 | AO33: 259384 | AP33: 0 | AQ33: =AM33+AO33 -> 2771885 | AS33: 50063 | AT33: 0 | AU33: =AQ33+AS33 -> 2821948
A34: 510533 | B34: Intereses sobre cesantías | C34: 12666 | D34: 0 | E34: =+C34 -> 12666 | G34: 29467 | H34: 0 | I34: =E34+G34 -> 42133 | J34: 23872 | K34: 0 | L34: =I34+J34 -> 66005 | N34: 28218 | O34: 0 | P34: =L34+N34 -> 94223 | R34: 37981 | S34: 0 | T34: =+P34+R34 -> 132204 | V34: 28217 | W34: 0 | X34: =T34+V34 -> 160421 | Y34: 28217 | Z34: 0 | AA34: =X34+Y34 -> 188638 | AC34: 20823 | AD34: 0 | AE34: =AA34+AC34 -> 209461 | AG34: 28218 | AH34: 0 | AI34: =AE34+AG34 -> 237679 | AK34: 28218 | AL34: 0 | AM34: =AI34+AK34 -> 265897 | AO34: 28218 | AP34: 0 | AQ34: =AM34+AO34 -> 294115 | AS34: 14475 | AT34: 0 | AU34: =AQ34+AS34 -> 308590
A35: 510536 | B35: Prima de servicios | C35: 105507 | D35: 0 | E35: =+C35 -> 105507 | G35: 298275 | H35: 0 | I35: =E35+G35 -> 403782 | J35: 298275 | K35: 0 | L35: =I35+J35 -> 702057 | N35: =+N33 -> 137467 | O35: 0 | P35: =L35+N35 -> 839524 | R35: 298275 | S35: 0 | T35: =+P35+R35 -> 1137799 | V35: 298275 | W35: 0 | X35: =T35+V35 -> 1436074 | Y35: 298275 | Z35: 0 | AA35: =X35+Y35 -> 1734349 | AC35: =+AC33 -> 259384 | AD35: 0 | AE35: =AA35+AC35 -> 1993733 | AG35: =+AG33 -> 259384 | AH35: 0 | AI35: =AE35+AG35 -> 2253117 | AK35: 259384 | AL35: 0 | AM35: =AI35+AK35 -> 2512501 | AO35: 259384 | AP35: 0 | AQ35: =AM35+AO35 -> 2771885 | AS35: =+AS33 -> 50063 | AT35: 0 | AU35: =AQ35+AS35 -> 2821948
A36: 510539 | B36: Vacaciones | C36: 52817 | D36: 0 | E36: =+C36 -> 52817 | G36: 126868 | H36: 0 | I36: =E36+G36 -> 179685 | J36: 126868 | K36: 0 | L36: =I36+J36 -> 306553 | N36: 75335 | O36: 0 | P36: =L36+N36 -> 381888 | R36: 126868 | S36: 0 | T36: =+P36+R36 -> 508756 | V36: 126868 | W36: 0 | X36: =T36+V36 -> 635624 | Y36: 126868 | Z36: 0 | AA36: =X36+Y36 -> 762492 | AC36: 126868 | AD36: 0 | AE36: =AA36+AC36 -> 889360 | AG36: 126868 | AH36: 0 | AI36: =AE36+AG36 -> 1016228 | AK36: 126868 | AL36: 0 | AM36: =AI36+AK36 -> 1143096 | AO36: 126868 | AP36: 0 | AQ36: =AM36+AO36 -> 1269964 | AS36: 141010 | AT36: 0 | AU36: =AQ36+AS36 -> 1410974
A37: 510545 | B37: Auxilios | C37: 203405 | D37: 0 | E37: =+C37 -> 203405 | G37: 339008 | H37: 0 | I37: =E37+G37 -> 542413 | J37: 259906 | K37: 0 | L37: =I37+J37 -> 802319 | N37: 0 | O37: 0 | P37: =L37+N37 -> 802319 | R37: 169504 | S37: 0 | T37: =+P37+R37 -> 971823 | V37: 339008 | W37: 0 | X37: =T37+V37 -> 1310831 | Y37: 339008 | Z37: 0 | AA37: =X37+Y37 -> 1649839 | AC37: 327708 | AD37: 0 | AE37: =AA37+AC37 -> 1977547 | AG37: 339008 | AH37: 0 | AI37: =AE37+AG37 -> 2316555 | AK37: 339008 | AL37: 0 | AM37: =AI37+AK37 -> 2655563 | AO37: 339008 | AP37: 0 | AQ37: =AM37+AO37 -> 2994571 | AS37: 316407 | AT37: 0 | AU37: =AQ37+AS37 -> 3310978
A38: 510551 | B38: Dotación y elementos seguridad trabajadores | C38: 103000 | D38: 0 | E38: =+C38 -> 103000 | H38: 0 | I38: =E38+G38 -> 103000 | J38: 0 | K38: 0 | L38: =I38+J38 -> 103000 | N38: 22269 | O38: 0 | P38: =L38+N38 -> 125269 | R38: 0 | S38: 0 | T38: =+P38+R38 -> 125269 | V38: 0 | W38: 0 | X38: =T38+V38 -> 125269 | Y38: 0 | Z38: 0 | AA38: =X38+Y38 -> 125269 | AC38: 0 | AD38: 0 | AE38: =AA38+AC38 -> 125269 | AG38: 0 | AH38: 0 | AI38: =AE38+AG38 -> 125269 | AK38: 24000 | AL38: 0 | AM38: =AI38+AK38 -> 149269 | AO38: 8403 | AP38: 0 | AQ38: =AM38+AO38 -> 157672 | AT38: 0 | AU38: =AQ38+AS38 -> 157672
A39: 510568 | B39: Aportes a administradoras de riesgos profesionales arp | C39: 29400 | D39: 0 | E39: =+C39 -> 29400 | G39: 71900 | H39: 0 | I39: =E39+G39 -> 101300 | J39: 56400 | K39: 0 | L39: =I39+J39 -> 157700 | N39: 44100 | O39: 0 | P39: =L39+N39 -> 201800 | R39: 73500 | S39: 0 | T39: =+P39+R39 -> 275300 | V39: 73500 | W39: 0 | X39: =T39+V39 -> 348800 | Y39: 73500 | Z39: 0 | AA39: =X39+Y39 -> 422300 | AC39: 73500 | AD39: 0 | AE39: =AA39+AC39 -> 495800 | AG39: 73500 | AH39: 0 | AI39: =AE39+AG39 -> 569300 | AK39: 73500 | AL39: 0 | AM39: =AI39+AK39 -> 642800 | AO39: 73500 | AP39: 0 | AQ39: =AM39+AO39 -> 716300 | AS39: 63300 | AT39: 0 | AU39: =AQ39+AS39 -> 779600
A40: 510569 | B40: Aportes a entidades promotoras de salud eps | C40: 32336 | D40: 0 | E40: =+C40 -> 32336 | G40: 3600 | H40: 0 | I40: =E40+G40 -> 35936 | J40: 0 | K40: 0 | L40: =I40+J40 -> 35936 | N40: 48206 | O40: 0 | P40: =L40+N40 -> 84142 | R40: 5060 | S40: 0 | T40: =+P40+R40 -> 89202 | V40: 0 | W40: 0 | X40: =T40+V40 -> 89202 | Y40: 0 | Z40: 0 | AA40: =X40+Y40 -> 89202 | AC40: 0 | AD40: 0 | AE40: =AA40+AC40 -> 89202 | AG40: 0 | AH40: 0 | AI40: =AE40+AG40 -> 89202 | AL40: 0 | AM40: =AI40+AK40 -> 89202 | AP40: 0 | AQ40: =AM40+AO40 -> 89202 | AT40: 0 | AU40: =AQ40+AS40 -> 89202
A41: 510570 | B41: Aportes a fondos de pensiones y/o cesantías | C41: 280636 | D41: 0 | E41: =+C41 -> 280636 | G41: 357160 | H41: 0 | I41: =E41+G41 -> 637796 | J41: 361460 | K41: 0 | L41: =I41+J41 -> 999256 | N41: 18140 | O41: 0 | P41: =L41+N41 -> 1017396 | R41: 34980 | S41: 0 | T41: =+P41+R41 -> 1052376 | V41: 361540 | W41: 0 | X41: =T41+V41 -> 1413916 | Y41: 361540 | Z41: 0 | AA41: =X41+Y41 -> 1775456 | AC41: 369569 | AD41: 0 | AE41: =AA41+AC41 -> 2145025 | AG41: 361360 | AH41: 0 | AI41: =AE41+AG41 -> 2506385 | AK41: 361360 | AL41: 0 | AM41: =AI41+AK41 -> 2867745 | AO41: 437606 | AP41: 0 | AQ41: =AM41+AO41 -> 3305351 | AS41: 618285 | AT41: 0 | AU41: =AQ41+AS41 -> 3923636
A42: 510572 | B42: Aportes cajas de compensación familiar | C42: 48200 | D42: 0 | E42: =+C42 -> 48200 | G42: 118000 | H42: 0 | I42: =E42+G42 -> 166200 | K42: 0 | L42: =I42+J42 -> 166200 | N42: 120500 | O42: 0 | P42: =L42+N42 -> 286700 | R42: 241000 | S42: 0 | T42: =+P42+R42 -> 527700 | V42: 120500 | W42: 0 | X42: =T42+V42 -> 648200 | Y42: 120440 | Z42: 0 | AA42: =X42+Y42 -> 768640 | AC42: 120440 | AD42: 0 | AE42: =AA42+AC42 -> 889080 | AG42: 120440 | AH42: 0 | AI42: =AE42+AG42 -> 1009520 | AK42: 120440 | AL42: 0 | AM42: =AI42+AK42 -> 1129960 | AO42: 120440 | AP42: 0 | AQ42: =AM42+AO42 -> 1250400 | AS42: 159500 | AT42: 0 | AU42: =AQ42+AS42 -> 1409900
A43: 510584 | B43: Drogas y medicamentos | AK43: 58280 | AU43: =AQ43+AS43 -> 0
AU44: =AQ44+AS44 -> 0
A45: 5110 | B45: Honorarios | C45: =C47 -> 300000 | D45: 0 | E45: =+C45 -> 300000 | G45: =G47 -> 300000 | H45: 0 | I45: =E45+G45 -> 600000 | J45: 300000 | K45: 0 | L45: =I45+J45 -> 900000 | N45: =N47 -> 300000 | O45: 0 | P45: =L45+N45 -> 1200000 | R45: =+R47+R48 -> 300000 | S45: 0 | T45: =+T47+T48 -> 1500000 | V45: =V47 -> 300000 | W45: 0 | X45: =T45+V45 -> 1800000 | Y45: 300000 | Z45: 0 | AA45: =X45+Y45 -> 2100000 | AC45: =AC47 -> 300000 | AD45: 0 | AE45: =AA45+AC45 -> 2400000 | AG45: =AG47 -> 300000 | AH45: 0 | AI45: =AE45+AG45 -> 2700000 | AK45: =AK47 -> 300000 | AL45: 0 | AM45: =AI45+AK45 -> 3000000 | AO45: =AO47 -> 300000 | AP45: 0 | AQ45: =AM45+AO45 -> 3300000 | AS45: 300000 | AT45: 0 | AU45: =AQ45+AS45 -> 3600000
A46: 511025 | B46: Asesoria Juridica | C46: 0 | D46: 0 | E46: =+C46 -> 0 | G46: 0 | H46: 0 | I46: =E46+G46 -> 0 | J46: 0 | K46: 0 | L46: =I46+J46 -> 0 | N46: 0 | O46: 0 | P46: =L46+N46 -> 0 | R46: 0 | S46: 0 | T46: =+P46+R46 -> 0 | V46: 0 | W46: 0 | X46: =T46+V46 -> 0 | Y46: 0 | Z46: 0 | AA46: =X46+Y46 -> 0 | AC46: 0 | AD46: 0 | AE46: =AA46+AC46 -> 0 | AG46: 0 | AH46: 0 | AI46: =AE46+AG46 -> 0 | AK46: 0 | AL46: 0 | AM46: =AI46+AK46 -> 0 | AO46: 0 | AP46: 0 | AQ46: =AM46+AO46 -> 0 | AS46: 0 | AT46: 0 | AU46: =AQ46+AS46 -> 0
A47: 511030 | B47: Asesoría financiera | C47: 300000 | D47: 0 | E47: =+C47 -> 300000 | G47: 300000 | H47: 0 | I47: =E47+G47 -> 600000 | J47: 300000 | K47: 0 | L47: =I47+J47 -> 900000 | N47: 300000 | O47: 0 | P47: =L47+N47 -> 1200000 | R47: 300000 | S47: 0 | T47: =+P47+R47 -> 1500000 | V47: 300000 | W47: 0 | X47: =T47+V47 -> 1800000 | Y47: 300000 | Z47: 0 | AA47: =X47+Y47 -> 2100000 | AC47: 300000 | AD47: 0 | AE47: =AA47+AC47 -> 2400000 | AG47: 300000 | AH47: 0 | AI47: =AE47+AG47 -> 2700000 | AK47: 300000 | AL47: 0 | AM47: =AI47+AK47 -> 3000000 | AO47: 300000 | AP47: 0 | AQ47: =AM47+AO47 -> 3300000 | AS47: 300000 | AT47: 0 | AU47: =AQ47+AS47 -> 3600000
A48: 511095 | B48: EXOGENA | R48: 0 | T48: =+P48+R48 -> 0 | X48: =T48+V48 -> 0 | AA48: =X48+Y48 -> 0 | AE48: =AA48+AC48 -> 0 | AI48: =AE48+AG48 -> 0 | AM48: =AI48+AK48 -> 0 | AQ48: =AM48+AO48 -> 0 | AU48: =AQ48+AS48 -> 0
AU49: =AQ49+AS49 -> 0
A50: 5115 | B50: Impuestos | C50: =+C51+C52+C53 -> 0 | D50: 0 | E50: =+C50 -> 0 | G50: =G53 -> 0 | H50: 0 | I50: =E50+G50 -> 0 | J50: =+J52 -> 0 | K50: 0 | L50: =I50+J50 -> 0 | N50: =+N54 -> 0 | O50: 0 | P50: =L50+N50 -> 0 | R50: =+R51+R52+R53+R54 -> 0 | S50: 0 | T50: =+P50+R50 -> 0 | V50: =V53 -> 0 | W50: 0 | X50: =T50+V50 -> 0 | Y50: 0 | Z50: 0 | AA50: =X50+Y50 -> 0 | AC50: =+AC54 -> 0 | AD50: 0 | AE50: =AA50+AC50 -> 0 | AG50: =+AG51+AG52+AG53+AG54 -> 59100 | AH50: 0 | AI50: =AE50+AG50 -> 59100 | AK50: =+AK54 -> 0 | AL50: 0 | AM50: =AI50+AK50 -> 59100 | AO50: =+AO54 -> 0 | AP50: 0 | AQ50: =AM50+AO50 -> 59100 | AS50: =+AS51 -> 436000 | AT50: 0 | AU50: =AQ50+AS50 -> 495100
A51: 511505 | B51: Insdustria y Comercio | C51: 0 | D51: 0 | E51: =+C51 -> 0 | G51: 0 | H51: 0 | I51: =E51+G51 -> 0 | J51: 0 | K51: 0 | L51: =I51+J51 -> 0 | N51: 0 | O51: 0 | P51: =L51+N51 -> 0 | R51: 0 | S51: 0 | T51: =+P51+R51 -> 0 | V51: 0 | W51: 0 | X51: =T51+V51 -> 0 | Y51: 0 | Z51: 0 | AA51: =X51+Y51 -> 0 | AC51: 0 | AD51: 0 | AE51: =AA51+AC51 -> 0 | AG51: 0 | AH51: 0 | AI51: =AE51+AG51 -> 0 | AK51: 0 | AL51: 0 | AM51: =AI51+AK51 -> 0 | AO51: 0 | AP51: 0 | AQ51: =AM51+AO51 -> 0 | AS51: 436000 | AT51: 0 | AU51: =AQ51+AS51 -> 436000
A52: 511515 | B52: A la propiedad raiz | C52: 0 | D52: 0 | E52: =+C52 -> 0 | G52: 0 | H52: 0 | I52: =E52+G52 -> 0 | J52: 0 | K52: 0 | L52: =I52+J52 -> 0 | N52: 0 | O52: 0 | P52: =L52+N52 -> 0 | R52: 0 | S52: 0 | T52: =+P52+R52 -> 0 | V52: 0 | W52: 0 | X52: =T52+V52 -> 0 | Y52: 0 | Z52: 0 | AA52: =X52+Y52 -> 0 | AC52: 0 | AD52: 0 | AE52: =AA52+AC52 -> 0 | AG52: 0 | AH52: 0 | AI52: =AE52+AG52 -> 0 | AK52: 0 | AL52: 0 | AM52: =AI52+AK52 -> 0 | AO52: 0 | AP52: 0 | AQ52: =AM52+AO52 -> 0 | AS52: 0 | AT52: 0 | AU52: =AQ52+AS52 -> 0
A53: 511540 | B53: De vehículos | C53: 0 | D53: 0 | E53: =+C53 -> 0 | G53: 0 | H53: 0 | I53: =E53+G53 -> 0 | K53: 0 | L53: =I53+J53 -> 0 | N53: 0 | O53: 0 | P53: =L53+N53 -> 0 | R53: 0 | S53: 0 | T53: =+P53+R53 -> 0 | V53: 0 | W53: 0 | X53: =T53+V53 -> 0 | Y53: 0 | Z53: 0 | AA53: =X53+Y53 -> 0 | AC53: 0 | AD53: 0 | AE53: =AA53+AC53 -> 0 | AG53: 59100 | AH53: 0 | AI53: =AE53+AG53 -> 59100 | AK53: 0 | AL53: 0 | AM53: =AI53+AK53 -> 59100 | AO53: 0 | AP53: 0 | AQ53: =AM53+AO53 -> 59100 | AS53: 0 | AT53: 0 | AU53: =AQ53+AS53 -> 59100
A54: 511595 | B54: Otros | C54: 0 | E54: =+C54 -> 0 | I54: =E54+G54 -> 0 | L54: =I54+J54 -> 0 | N54: 0 | P54: =L54+N54 -> 0 | R54: 0 | T54: =+P54+R54 -> 0 | X54: =T54+V54 -> 0 | AA54: =X54+Y54 -> 0 | AC54: 0 | AE54: =AA54+AC54 -> 0 | AG54: 0 | AI54: =AE54+AG54 -> 0 | AK54: 0 | AM54: =AI54+AK54 -> 0 | AO54: 0 | AQ54: =AM54+AO54 -> 0 | AS54: 0 | AU54: =AQ54+AS54 -> 0
AU55: =AQ55+AS55 -> 0
A56: 5120 | B56: Arrendamientos | C56: =+C57 -> 1000000 | D56: 0 | E56: =+C56 -> 1000000 | G56: =+G57+G58 -> 1000000 | H56: 0 | I56: =E56+G56 -> 2000000 | J56: =+J57+J61 -> 1000000 | K56: 0 | L56: =I56+J56 -> 3000000 | N56: =N57+N58 -> 1000000 | O56: 0 | P56: =L56+N56 -> 4000000 | R56: =+R57+R58 -> 1000000 | S56: 0 | T56: =+P56+R56 -> 5000000 | V56: =V57 -> 1000000 | W56: 0 | X56: =T56+V56 -> 6000000 | Y56: =+Y57+Y58 -> 1000000 | Z56: 0 | AA56: =X56+Y56 -> 7000000 | AC56: =AC57+AC58 -> 1000000 | AD56: 0 | AE56: =AA56+AC56 -> 8000000 | AG56: =AG57+AG58 -> 1000000 | AH56: 0 | AI56: =AE56+AG56 -> 9000000 | AK56: =AK57+AK58 -> 2116500 | AL56: 0 | AM56: =AI56+AK56 -> 11116500 | AO56: =AO57+AO58 -> 1033300 | AP56: 0 | AQ56: =AM56+AO56 -> 12149800 | AS56: =AS57+AS58 -> 1134520 | AT56: 0 | AU56: =AQ56+AS56 -> 13284320
A57: 512010 | B57: Construcciones y edificaciones | C57: 1000000 | D57: 0 | E57: =+C57 -> 1000000 | G57: 1000000 | H57: 0 | I57: =E57+G57 -> 2000000 | J57: 1000000 | K57: 0 | L57: =I57+J57 -> 3000000 | N57: 1000000 | O57: 0 | P57: =L57+N57 -> 4000000 | R57: 1000000 | S57: 0 | T57: =+P57+R57 -> 5000000 | V57: 1000000 | W57: 0 | X57: =T57+V57 -> 6000000 | Y57: 1000000 | Z57: 0 | AA57: =X57+Y57 -> 7000000 | AC57: 1000000 | AD57: 0 | AE57: =AA57+AC57 -> 8000000 | AG57: 1000000 | AH57: 0 | AI57: =AE57+AG57 -> 9000000 | AK57: 1000000 | AL57: 0 | AM57: =AI57+AK57 -> 10000000 | AO57: 1000000 | AP57: 0 | AQ57: =AM57+AO57 -> 11000000 | AS57: 1000000 | AT57: 0 | AU57: =AQ57+AS57 -> 12000000
A58: 512015 | B58: Maquinaria y equipo | C58: 0 | D58: 0 | E58: =+C58 -> 0 | G58: 0 | I58: =E58+G58 -> 0 | J58: 0 | K58: 0 | L58: =I58+J58 -> 0 | N58: 0 | P58: =L58+N58 -> 0 | S58: 0 | T58: =+P58+R58 -> 0 | V58: 0 | X58: =T58+V58 -> 0 | Y58: 0 | Z58: 0 | AA58: =X58+Y58 -> 0 | AC58: 0 | AE58: =AA58+AC58 -> 0 | AG58: 0 | AI58: =AE58+AG58 -> 0 | AK58: 1116500 | AM58: =AI58+AK58 -> 1116500 | AO58: 33300 | AQ58: =AM58+AO58 -> 1149800 | AS58: 134520 | AU58: =AQ58+AS58 -> 1284320
L59: =I59+J59 -> 0 | AA59: =X59+Y59 -> 0 | AU59: =AQ59+AS59 -> 0
A60: 5125 | B60: AFILIACIONES Y CONTRIBUCIONES | C60: =+C61 -> 130000 | E60: =+E61 -> 130000 | G60: 0 | I60: =E60+G60 -> 130000 | J60: =+J61 -> 0 | L60: =I60+J60 -> 130000 | N60: 0 | P60: =L60+N60 -> 130000 | R60: =+R61 -> 0 | T60: =+P60+R60 -> 130000 | X60: =T60+V60 -> 130000 | Y60: =+Y61 -> 0 | AA60: =X60+Y60 -> 130000 | AC60: 0 | AE60: =AA60+AC60 -> 130000 | AG60: 0 | AI60: =AE60+AG60 -> 130000 | AK60: 0 | AM60: =AI60+AK60 -> 130000 | AO60: 0 | AQ60: =AM60+AO60 -> 130000 | AS60: 0 | AU60: =AQ60+AS60 -> 130000
A61: 512510 | B61: Afiliaciones | C61: 130000 | D61: 0 | E61: =+C61 -> 130000 | G61: 0 | I61: =E61+G61 -> 130000 | J61: 0 | L61: =I61+J61 -> 130000 | N61: 0 | P61: =L61+N61 -> 130000 | R61: 0 | S61: 0 | T61: =+P61+R61 -> 130000 | X61: =T61+V61 -> 130000 | Y61: 0 | AA61: =X61+Y61 -> 130000 | AC61: 0 | AE61: =AA61+AC61 -> 130000 | AG61: 0 | AI61: =AE61+AG61 -> 130000 | AK61: 0 | AM61: =AI61+AK61 -> 130000 | AO61: 0 | AQ61: =AM61+AO61 -> 130000 | AS61: 0 | AU61: =AQ61+AS61 -> 130000
AU62: =AQ62+AS62 -> 0
A63: 5130 | B63: Seguros | C63: =+C64 -> 636650 | D63: 0 | E63: =+C63 -> 636650 | G63: =G64 -> 0 | H63: 0 | I63: =E63+G63 -> 636650 | J63: =J64 -> 0 | K63: 0 | L63: =I63+J63 -> 636650 | N63: =N64 -> 0 | O63: 0 | P63: =L63+N63 -> 636650 | R63: =+R64 -> 0 | S63: 0 | T63: =+P63+R63 -> 636650 | V63: =V64 -> 0 | W63: 0 | X63: =T63+V63 -> 636650 | Y63: =Y64 -> 0 | Z63: 0 | AA63: =X63+Y63 -> 636650 | AC63: =AC64 -> 0 | AD63: 0 | AE63: =AA63+AC63 -> 636650 | AG63: =AG64 -> 0 | AH63: 0 | AI63: =AE63+AG63 -> 636650 | AK63: =AK64 -> 0 | AL63: 0 | AM63: =AI63+AK63 -> 636650 | AO63: =AO64 -> 0 | AP63: 0 | AQ63: =AM63+AO63 -> 636650 | AS63: =AS64 -> 0 | AT63: 0 | AU63: =AQ63+AS63 -> 636650
A64: 513095 | B64: Otros | C64: 636650 | D64: 0 | E64: =+C64 -> 636650 | G64: 0 | H64: 0 | I64: =E64+G64 -> 636650 | J64: 0 | K64: 0 | L64: =I64+J64 -> 636650 | N64: 0 | O64: 0 | P64: =L64+N64 -> 636650 | R64: 0 | S64: 0 | T64: =+P64+R64 -> 636650 | V64: 0 | W64: 0 | X64: =T64+V64 -> 636650 | Y64: 0 | Z64: 0 | AA64: =X64+Y64 -> 636650 | AC64: 0 | AD64: 0 | AE64: =AA64+AC64 -> 636650 | AG64: 0 | AH64: 0 | AI64: =AE64+AG64 -> 636650 | AK64: 0 | AL64: 0 | AM64: =AI64+AK64 -> 636650 | AO64: 0 | AP64: 0 | AQ64: =AM64+AO64 -> 636650 | AS64: 0 | AT64: 0 | AU64: =AQ64+AS64 -> 636650
AU65: =AQ65+AS65 -> 0
A66: 5135 | B66: Servicios | C66: =C67+C68+C70+C71+C72+C74+C73+C75 -> 2295686 | D66: 0 | E66: =+C66 -> 2295686 | G66: =G67+G68+G70+G71+G72+G75 -> 2052254 | H66: 0 | I66: =E66+G66 -> 4347940 | J66: =J67+J68+J70+J71+J72+J75 -> 1581294 | K66: 0 | L66: =I66+J66 -> 5929234 | N66: =SUM(N67:N75) -> 536847 | O66: 0 | P66: =L66+N66 -> 6466081 | R66: =R67+R68+R70+R71+R72+R74+R73+R75 -> 920025 | S66: 0 | T66: =+P66+R66 -> 7386106 | V66: =V67+V68+V70+V71+V72+V75 -> 1266455 | W66: 0 | X66: =T66+V66 -> 8652561 | Y66: =SUM(Y67:Y75) -> 1458360 | Z66: 0 | AA66: =X66+Y66 -> 10110921 | AC66: =SUM(AC67:AC75) -> 1063327 | AD66: 0 | AE66: =AA66+AC66 -> 11174248 | AG66: =SUM(AG67:AG75) -> 1148861 | AH66: 0 | AI66: =AE66+AG66 -> 12323109 | AK66: =SUM(AK67:AK75) -> 3382709 | AL66: 0 | AM66: =AI66+AK66 -> 15705818 | AO66: =SUM(AO67:AO75) -> 1713768 | AP66: 0 | AQ66: =AM66+AO66 -> 17419586 | AS66: =SUM(AS67:AS75) -> 1969094 | AT66: 0 | AU66: =AQ66+AS66 -> 19388680
A67: 513505 | B67: Aseo y vigilancia | C67: 30000 | D67: 0 | E67: =+C67 -> 30000 | G67: 90000 | H67: 0 | I67: =E67+G67 -> 120000 | J67: 0 | K67: 0 | L67: =I67+J67 -> 120000 | N67: 0 | O67: 0 | P67: =L67+N67 -> 120000 | R67: 0 | S67: 0 | T67: =+P67+R67 -> 120000 | V67: 0 | W67: 0 | X67: =T67+V67 -> 120000 | Y67: 0 | Z67: 0 | AA67: =X67+Y67 -> 120000 | AC67: 0 | AD67: 0 | AE67: =AA67+AC67 -> 120000 | AG67: 25000 | AH67: 0 | AI67: =AE67+AG67 -> 145000 | AK67: 0 | AL67: 0 | AM67: =AI67+AK67 -> 145000 | AO67: 0 | AP67: 0 | AQ67: =AM67+AO67 -> 145000 | AT67: 0 | AU67: =AQ67+AS67 -> 145000
A68: 513510 | B68: Temporales | C68: 1455000 | D68: 0 | E68: =+C68 -> 1455000 | G68: 1820000 | H68: 0 | I68: =E68+G68 -> 3275000 | J68: 1210000 | K68: 0 | L68: =I68+J68 -> 4485000 | N68: 0 | O68: 0 | P68: =L68+N68 -> 4485000 | R68: 578000 | S68: 0 | T68: =+P68+R68 -> 5063000 | V68: 665000 | W68: 0 | X68: =T68+V68 -> 5728000 | Y68: 885000 | Z68: 0 | AA68: =X68+Y68 -> 6613000 | AC68: 529000 | AD68: 0 | AE68: =AA68+AC68 -> 7142000 | AG68: 662500 | AH68: 0 | AI68: =AE68+AG68 -> 7804500 | AK68: 2080000 | AL68: 0 | AM68: =AI68+AK68 -> 9884500 | AO68: 1284000 | AP68: 0 | AQ68: =AM68+AO68 -> 11168500 | AS68: 1567000 | AT68: 0 | AU68: =AQ68+AS68 -> 12735500
A69: 513520 | N69: 0 | AC69: 50000 | AE69: =AA69+AC69 -> 50000 | AI69: =AE69+AG69 -> 50000 | AM69: =AI69+AK69 -> 50000 | AQ69: =AM69+AO69 -> 50000 | AU69: =AQ69+AS69 -> 50000
A70: 513525 | B70: Acueducto y alcantarillado | C70: 60930 | D70: 0 | E70: =+C70 -> 60930 | G70: 54760 | H70: 0 | I70: =E70+G70 -> 115690 | J70: 0 | K70: 0 | L70: =I70+J70 -> 115690 | N70: 116430 | O70: 0 | P70: =L70+N70 -> 232120 | R70: 60710 | S70: 0 | T70: =+P70+R70 -> 292830 | V70: 72750 | W70: 0 | X70: =T70+V70 -> 365580 | Y70: 72740 | Z70: 0 | AA70: =X70+Y70 -> 438320 | AC70: 96770 | AD70: 0 | AE70: =AA70+AC70 -> 535090 | AG70: 95720 | AH70: 0 | AI70: =AE70+AG70 -> 630810 | AK70: 71670 | AL70: 0 | AM70: =AI70+AK70 -> 702480 | AO70: 71670 | AP70: 0 | AQ70: =AM70+AO70 -> 774150 | AS70: 59630 | AT70: 0 | AU70: =AQ70+AS70 -> 833780
A71: 513530 | B71: Energía eléctrica | C71: 95209 | D71: 0 | E71: =+C71 -> 95209 | G71: 0 | H71: 0 | I71: =E71+G71 -> 95209 | J71: 213096 | K71: 0 | L71: =I71+J71 -> 308305 | N71: 100070 | O71: 0 | P71: =L71+N71 -> 408375 | R71: 48190 | S71: 0 | T71: =+P71+R71 -> 456565 | V71: 113030 | W71: 0 | X71: =T71+V71 -> 569595 | Y71: 152664 | Z71: 0 | AA71: =X71+Y71 -> 722259 | AC71: 132848 | AD71: 0 | AE71: =AA71+AC71 -> 855107 | AG71: 96883 | AH71: 0 | AI71: =AE71+AG71 -> 951990 | AK71: 102755 | AL71: 0 | AM71: =AI71+AK71 -> 1054745 | AO71: 106425 | AP71: 0 | AQ71: =AM71+AO71 -> 1161170 | AS71: 111563 | AT71: 0 | AU71: =AQ71+AS71 -> 1272733
A72: 513535 | B72: Teléfono fijo y moviles | C72: 539247 | D72: 0 | E72: =+C72 -> 539247 | G72: 87494 | H72: 0 | I72: =E72+G72 -> 626741 | J72: 132698 | K72: 0 | L72: =I72+J72 -> 759439 | N72: 320347 | O72: 0 | P72: =L72+N72 -> 1079786 | R72: 225125 | S72: 0 | T72: =+P72+R72 -> 1304911 | V72: 415675 | W72: 0 | X72: =T72+V72 -> 1720586 | Y72: 347956 | Z72: 0 | AA72: =X72+Y72 -> 2068542 | AC72: 254709 | AD72: 0 | AE72: =AA72+AC72 -> 2323251 | AG72: 163758 | AH72: 0 | AI72: =AE72+AG72 -> 2487009 | AK72: 363284 | AL72: 0 | AM72: =AI72+AK72 -> 2850293 | AO72: 251673 | AP72: 0 | AQ72: =AM72+AO72 -> 3101966 | AS72: 230901 | AT72: 0 | AU72: =AQ72+AS72 -> 3332867
A73: 513540 | B73: Correo portes y telegrama | C73: 0 | D73: 0 | E73: =+C73 -> 0 | G73: 0 | H73: 0 | I73: =E73+G73 -> 0 | J73: 0 | K73: 0 | L73: =I73+J73 -> 0 | N73: 0 | O73: 0 | P73: =L73+N73 -> 0 | R73: 0 | S73: 0 | T73: =+P73+R73 -> 0 | V73: 0 | W73: 0 | X73: =T73+V73 -> 0 | Y73: 0 | Z73: 0 | AA73: =X73+Y73 -> 0 | AC73: 0 | AD73: 0 | AE73: =AA73+AC73 -> 0 | AH73: 0 | AI73: =AE73+AG73 -> 0 | AK73: 0 | AL73: 0 | AM73: =AI73+AK73 -> 0 | AO73: 0 | AP73: 0 | AQ73: =AM73+AO73 -> 0 | AS73: 0 | AT73: 0 | AU73: =AQ73+AS73 -> 0
A74: 513595 | B74: Otros | C74: 0 | D74: 0 | E74: =+C74 -> 0 | G74: 0 | H74: 0 | I74: =E74+G74 -> 0 | J74: 0 | K74: 0 | L74: =I74+J74 -> 0 | N74: 0 | O74: 0 | P74: =L74+N74 -> 0 | R74: 0 | S74: 0 | T74: =+P74+R74 -> 0 | V74: 0 | W74: 0 | X74: =T74+V74 -> 0 | Y74: 0 | Z74: 0 | AA74: =X74+Y74 -> 0 | AC74: 0 | AD74: 0 | AE74: =AA74+AC74 -> 0 | AG74: 90000 | AH74: 0 | AI74: =AE74+AG74 -> 90000 | AL74: 0 | AM74: =AI74+AK74 -> 90000 | AO74: 0 | AP74: 0 | AQ74: =AM74+AO74 -> 90000 | AS74: 0 | AT74: 0 | AU74: =AQ74+AS74 -> 90000
A75: 513550 | B75: Transportes, fletes y acarreos | C75: 115300 | D75: 0 | E75: =+C75 -> 115300 | G75: 0 | H75: 0 | I75: =E75+G75 -> 115300 | J75: 25500 | K75: 0 | L75: =I75+J75 -> 140800 | N75: 0 | O75: 0 | P75: =L75+N75 -> 140800 | R75: 8000 | S75: 0 | T75: =+P75+R75 -> 148800 | V75: 0 | W75: 0 | X75: =T75+V75 -> 148800 | Y75: 0 | Z75: 0 | AA75: =X75+Y75 -> 148800 | AC75: 0 | AD75: 0 | AE75: =AA75+AC75 -> 148800 | AG75: 15000 | AH75: 0 | AI75: =AE75+AG75 -> 163800 | AK75: 765000 | AL75: 0 | AM75: =AI75+AK75 -> 928800 | AP75: 0 | AQ75: =AM75+AO75 -> 928800 | AS75: 0 | AT75: 0 | AU75: =AQ75+AS75 -> 928800
E76: =+C76 -> 0 | P76: =L76+N76 -> 0 | AE76: =AA76+AC76 -> 0 | AI76: =AE76+AG76 -> 0 | AM76: =AI76+AK76 -> 0 | AQ76: =AM76+AO76 -> 0 | AU76: =AQ76+AS76 -> 0
A77: 5140 | B77: Gastos legales | C77: =+C80 -> 10100 | D77: 0 | E77: =+C77 -> 10100 | G77: =G79+G80 -> 0 | H77: 0 | I77: =E77+G77 -> 10100 | J77: 0 | K77: 0 | L77: =I77+J77 -> 10100 | N77: =N79+N80 -> 0 | O77: 0 | P77: =L77+N77 -> 10100 | R77: =+R79 -> 6100 | S77: 0 | T77: =+P77+R77 -> 16200 | V77: =V79+V80 -> 0 | W77: 0 | X77: =T77+V77 -> 16200 | Y77: =+Y79 -> 99400 | Z77: 0 | AA77: =X77+Y77 -> 115600 | AC77: =AC79+AC80 -> 6100 | AD77: 0 | AE77: =AA77+AC77 -> 121700 | AG77: =AG79+AG80 -> 6100 | AH77: 0 | AI77: =AE77+AG77 -> 127800 | AK77: =+AK79+AK81 -> 0 | AL77: 0 | AM77: =AI77+AK77 -> 127800 | AO77: =AO79+AO80 -> 1580100 | AP77: 0 | AQ77: =AM77+AO77 -> 1707900 | AS77: =AS79+AS80 -> 12200 | AT77: 0 | AU77: =AQ77+AS77 -> 1720100
A78: 514005 | B78: Notariales | C78: 0 | D78: 0 | E78: =+C78 -> 0 | G78: 0 | H78: 0 | I78: =E78+G78 -> 0 | J78: 0 | K78: 0 | L78: =I78+J78 -> 0 | N78: 0 | O78: 0 | P78: =L78+N78 -> 0 | S78: 0 | T78: =+P78+R78 -> 0 | V78: 0 | W78: 0 | X78: =T78+V78 -> 0 | Y78: 0 | Z78: 0 | AA78: =X78+Y78 -> 0 | AC78: 0 | AD78: 0 | AE78: =AA78+AC78 -> 0 | AG78: 0 | AH78: 0 | AI78: =AE78+AG78 -> 0 | AK78: 0 | AL78: 0 | AM78: =AI78+AK78 -> 0 | AO78: 0 | AP78: 0 | AQ78: =AM78+AO78 -> 0 | AS78: 0 | AT78: 0 | AU78: =AQ78+AS78 -> 0
A79: 514010 | B79: Registro mercantil | C79: 0 | D79: 0 | E79: =+C79 -> 0 | G79: 0 | H79: 0 | I79: =E79+G79 -> 0 | J79: 0 | K79: 0 | L79: =I79+J79 -> 0 | N79: 0 | O79: 0 | P79: =L79+N79 -> 0 | R79: 6100 | S79: 0 | T79: =+P79+R79 -> 6100 | V79: 0 | W79: 0 | X79: =T79+V79 -> 6100 | Y79: 99400 | Z79: 0 | AA79: =X79+Y79 -> 105500 | AC79: 6100 | AD79: 0 | AE79: =AA79+AC79 -> 111600 | AG79: 6100 | AH79: 0 | AI79: =AE79+AG79 -> 117700 | AK79: 0 | AL79: 0 | AM79: =AI79+AK79 -> 117700 | AO79: 1580100 | AP79: 0 | AQ79: =AM79+AO79 -> 1697800 | AS79: 12200 | AT79: 0 | AU79: =AQ79+AS79 -> 1710000
A80: 514015 | B80: Trámites y licencias | C80: 10100 | D80: 0 | E80: =+C80 -> 10100 | G80: 0 | H80: 0 | I80: =E80+G80 -> 10100 | J80: 0 | K80: 0 | L80: =I80+J80 -> 10100 | N80: 0 | O80: 0 | P80: =L80+N80 -> 10100 | R80: 0 | S80: 0 | T80: =+P80+R80 -> 10100 | V80: 0 | W80: 0 | X80: =T80+V80 -> 10100 | Y80: 0 | Z80: 0 | AA80: =X80+Y80 -> 10100 | AC80: 0 | AD80: 0 | AE80: =AA80+AC80 -> 10100 | AG80: 0 | AH80: 0 | AI80: =AE80+AG80 -> 10100 | AK80: 0 | AL80: 0 | AM80: =AI80+AK80 -> 10100 | AO80: 0 | AP80: 0 | AQ80: =AM80+AO80 -> 10100 | AS80: 0 | AT80: 0 | AU80: =AQ80+AS80 -> 10100
A81: 514095 | B81: Otros | C81: 0 | D81: 0 | E81: =+C81 -> 0 | G81: 0 | H81: 0 | I81: =E81+G81 -> 0 | J81: 0 | K81: 0 | L81: =I81+J81 -> 0 | N81: 0 | O81: 0 | P81: =L81+N81 -> 0 | R81: 0 | S81: 0 | T81: =+P81+R81 -> 0 | V81: 0 | W81: 0 | X81: =T81+V81 -> 0 | Y81: 0 | Z81: 0 | AA81: =X81+Y81 -> 0 | AC81: 0 | AD81: 0 | AE81: =AA81+AC81 -> 0 | AG81: 0 | AH81: 0 | AI81: =AE81+AG81 -> 0 | AL81: 0 | AM81: =AI81+AK81 -> 0 | AO81: 0 | AP81: 0 | AQ81: =AM81+AO81 -> 0 | AS81: 0 | AT81: 0 | AU81: =AQ81+AS81 -> 0
E82: =+C82 -> 0 | T82: =+P82+R82 -> 0 | AU82: =AQ82+AS82 -> 0
A83: 5145 | B83: Mantenimiento y reparaciones | C83: =+C85+C86+C87+C88 -> 860692 | D83: 0 | E83: =+C83 -> 860692 | G83: =G85+G86+G88+G87 -> 1323528 | H83: 0 | I83: =E83+G83 -> 2184220 | J83: =+J85+J86+J87+J88 -> 387424 | K83: 0 | L83: =I83+J83 -> 2571644 | N83: =+N85+N86+N87+N88 -> 0 | O83: 0 | P83: =L83+N83 -> 2571644 | R83: =+R85+R86+R87+R88 -> 130709 | S83: 0 | T83: =+P83+R83 -> 2702353 | V83: =V85+V86+V88 -> 2136926 | W83: 0 | X83: =T83+V83 -> 4839279 | Y83: =+Y85+Y86+Y87+Y88 -> 185600 | Z83: 0 | AA83: =X83+Y83 -> 5024879 | AC83: =+AC85+AC86+AC87+AC88 -> 35000 | AD83: 0 | AE83: =AA83+AC83 -> 5059879 | AG83: =+AG85+AG86+AG87+AG88+AG84 -> 329820 | AH83: 0 | AI83: =AE83+AG83 -> 5389699 | AK83: =+AK85+AK86+AK87+AK88 -> 82850 | AL83: 0 | AM83: =AI83+AK83 -> 5472549 | AO83: =+AO85+AO86+AO87+AO88 -> 2241508 | AP83: 0 | AQ83: =AM83+AO83 -> 7714057 | AS83: =+AS85+AS86+AS87+AS88 -> 634124 | AT83: 0 | AU83: =AQ83+AS83 -> 8348181
A84: 514510 | B84: construcciones y edificaciones | AG84: 79920 | AI84: =AE84+AG84 -> 79920 | AM84: =AI84+AK84 -> 79920 | AQ84: =AM84+AO84 -> 79920 | AU84: =AQ84+AS84 -> 79920
A85: 514515 | B85: Maquinaria y equipo | C85: 529654 | D85: 0 | E85: =+C85 -> 529654 | G85: 543028 | H85: 0 | I85: =E85+G85 -> 1072682 | J85: 330021 | K85: 0 | L85: =I85+J85 -> 1402703 | N85: 0 | O85: 0 | P85: =L85+N85 -> 1402703 | R85: 109709 | S85: 0 | T85: =+P85+R85 -> 1512412 | V85: 989168 | W85: 0 | X85: =T85+V85 -> 2501580 | Y85: 88000 | Z85: 0 | AA85: =X85+Y85 -> 2589580 | AC85: 0 | AD85: 0 | AE85: =AA85+AC85 -> 2589580 | AG85: 0 | AH85: 0 | AI85: =AE85+AG85 -> 2589580 | AK85: 67850 | AL85: 0 | AM85: =AI85+AK85 -> 2657430 | AO85: 2116100 | AP85: 0 | AQ85: =AM85+AO85 -> 4773530 | AS85: 296124 | AT85: 0 | AU85: =AQ85+AS85 -> 5069654
A86: 514520 | B86: Equipo de oficina | C86: 0 | D86: 0 | E86: =+C86 -> 0 | G86: 400000 | H86: 0 | I86: =E86+G86 -> 400000 | J86: 0 | K86: 0 | L86: =I86+J86 -> 400000 | N86: 0 | O86: 0 | P86: =L86+N86 -> 400000 | R86: 0 | S86: 0 | T86: =+P86+R86 -> 400000 | V86: 0 | W86: 0 | X86: =T86+V86 -> 400000 | Y86: 13000 | Z86: 0 | AA86: =X86+Y86 -> 413000 | AC86: 0 | AD86: 0 | AE86: =AA86+AC86 -> 413000 | AG86: 0 | AH86: 0 | AI86: =AE86+AG86 -> 413000 | AL86: 0 | AM86: =AI86+AK86 -> 413000 | AO86: 0 | AP86: 0 | AQ86: =AM86+AO86 -> 413000 | AS86: 0 | AT86: 0 | AU86: =AQ86+AS86 -> 413000
A87: 514525 | B87: Equipo de computación y comunicación | C87: 0 | D87: 0 | E87: =+C87 -> 0 | G87: 70000 | H87: 0 | I87: =E87+G87 -> 70000 | J87: 57403 | K87: 0 | L87: =I87+J87 -> 127403 | N87: 0 | O87: 0 | P87: =L87+N87 -> 127403 | R87: 0 | S87: 0 | T87: =+P87+R87 -> 127403 | V87: 0 | W87: 0 | X87: =T87+V87 -> 127403 | Y87: 0 | Z87: 0 | AA87: =X87+Y87 -> 127403 | AC87: 35000 | AD87: 0 | AE87: =AA87+AC87 -> 162403 | AH87: 0 | AI87: =AE87+AG87 -> 162403 | AK87: 15000 | AL87: 0 | AM87: =AI87+AK87 -> 177403 | AO87: 0 | AP87: 0 | AQ87: =AM87+AO87 -> 177403 | AS87: 140000 | AT87: 0 | AU87: =AQ87+AS87 -> 317403
A88: 514540 | B88: Flota y equipo de transportes | C88: 331038 | D88: 0 | E88: =+C88 -> 331038 | G88: 310500 | H88: 0 | I88: =E88+G88 -> 641538 | J88: 0 | K88: 0 | L88: =I88+J88 -> 641538 | N88: 0 | O88: 0 | P88: =L88+N88 -> 641538 | R88: 21000 | S88: 0 | T88: =+P88+R88 -> 662538 | V88: 1147758 | W88: 0 | X88: =T88+V88 -> 1810296 | Y88: 84600 | Z88: 0 | AA88: =X88+Y88 -> 1894896 | AC88: 0 | AD88: 0 | AE88: =AA88+AC88 -> 1894896 | AG88: 249900 | AH88: 0 | AI88: =AE88+AG88 -> 2144796 | AK88: 0 | AL88: 0 | AM88: =AI88+AK88 -> 2144796 | AO88: 125408 | AP88: 0 | AQ88: =AM88+AO88 -> 2270204 | AS88: 198000 | AT88: 0 | AU88: =AQ88+AS88 -> 2468204
E89: =+C89 -> 0 | T89: =+P89+R89 -> 0 | AU89: =AQ89+AS89 -> 0
A90: 5150 | B90: Adecuación e instalación | C90: =+C91+C92+C93+C94 -> 0 | D90: 0 | E90: =+C90 -> 0 | G90: =+G91+G92+G93+G94 -> 185798 | H90: 0 | I90: =E90+G90 -> 185798 | J90: =+J91+J92+J93 -> 251815 | K90: 0 | L90: =I90+J90 -> 437613 | N90: =N94+N93 -> 1079764 | O90: 0 | P90: =L90+N90 -> 1517377 | R90: 0 | S90: 0 | T90: =+P90+R90 -> 1517377 | V90: =+V91+V92+V93+V94 -> 0 | W90: 0 | X90: =T90+V90 -> 1517377 | Y90: =+Y91+Y92+Y93 -> 11177 | Z90: 0 | AA90: =X90+Y90 -> 1528554 | AC90: =+AC91+AC92+AC93+AC94 -> 65589 | AD90: 0 | AE90: =AA90+AC90 -> 1594143 | AG90: =+AG91+AG92+AG93+AG94 -> 0 | AH90: 0 | AI90: =AE90+AG90 -> 1594143 | AK90: =+AK91+AK92+AK93+AK94 -> 562294 | AL90: 0 | AM90: =AI90+AK90 -> 2156437 | AO90: =+AO91+AO92+AO93+AO94 -> 273728 | AP90: 0 | AQ90: =AM90+AO90 -> 2430165 | AS90: =+AS91+AS92+AS93+AS94 -> 0 | AT90: 0 | AU90: =AQ90+AS90 -> 2430165
A91: 515005 | B91: Instalaciones electricas | C91: 0 | D91: 0 | E91: =+C91 -> 0 | G91: 0 | H91: 0 | I91: =E91+G91 -> 0 | J91: 0 | K91: 0 | L91: =I91+J91 -> 0 | N91: 0 | O91: 0 | P91: =L91+N91 -> 0 | R91: 0 | S91: 0 | T91: =+P91+R91 -> 0 | V91: 0 | W91: 0 | X91: =T91+V91 -> 0 | Y91: 11177 | Z91: 0 | AA91: =X91+Y91 -> 11177 | AC91: 0 | AD91: 0 | AE91: =AA91+AC91 -> 11177 | AG91: 0 | AH91: 0 | AI91: =AE91+AG91 -> 11177 | AK91: 0 | AL91: 0 | AM91: =AI91+AK91 -> 11177 | AO91: 0 | AP91: 0 | AQ91: =AM91+AO91 -> 11177 | AS91: 0 | AT91: 0 | AU91: =AQ91+AS91 -> 11177
A92: 515010 | B92: Arreglos ornamentales | C92: 0 | D92: 0 | E92: =+C92 -> 0 | G92: 0 | H92: 0 | I92: =E92+G92 -> 0 | J92: 0 | K92: 0 | L92: =I92+J92 -> 0 | N92: 0 | O92: 0 | P92: =L92+N92 -> 0 | R92: 0 | S92: 0 | T92: =+P92+R92 -> 0 | V92: 0 | W92: 0 | X92: =T92+V92 -> 0 | Y92: 0 | Z92: 0 | AA92: =X92+Y92 -> 0 | AC92: 0 | AD92: 0 | AE92: =AA92+AC92 -> 0 | AG92: 0 | AH92: 0 | AI92: =AE92+AG92 -> 0 | AK92: 0 | AL92: 0 | AM92: =AI92+AK92 -> 0 | AO92: 0 | AP92: 0 | AQ92: =AM92+AO92 -> 0 | AS92: 0 | AT92: 0 | AU92: =AQ92+AS92 -> 0
A93: 515015 | B93: Reparaciones locativas | C93: 0 | D93: 0 | E93: =+C93 -> 0 | G93: 185798 | H93: 0 | I93: =E93+G93 -> 185798 | J93: 251815 | K93: 0 | L93: =I93+J93 -> 437613 | N93: 1055954 | O93: 0 | P93: =L93+N93 -> 1493567 | R93: 0 | S93: 0 | T93: =+P93+R93 -> 1493567 | V93: 0 | W93: 0 | X93: =T93+V93 -> 1493567 | Y93: 0 | Z93: 0 | AA93: =X93+Y93 -> 1493567 | AC93: 65589 | AD93: 0 | AE93: =AA93+AC93 -> 1559156 | AG93: 0 | AH93: 0 | AI93: =AE93+AG93 -> 1559156 | AK93: 562294 | AL93: 0 | AM93: =AI93+AK93 -> 2121450 | AO93: 273728 | AP93: 0 | AQ93: =AM93+AO93 -> 2395178 | AT93: 0 | AU93: =AQ93+AS93 -> 2395178
A94: 515095 | B94: Otros | C94: 0 | D94: 0 | E94: =+C94 -> 0 | G94: 0 | H94: 0 | I94: =E94+G94 -> 0 | J94: 0 | K94: 0 | L94: =I94+J94 -> 0 | N94: 23810 | O94: 0 | P94: =L94+N94 -> 23810 | R94: 0 | S94: 0 | T94: =+P94+R94 -> 23810 | V94: 0 | W94: 0 | X94: =T94+V94 -> 23810 | Y94: 0 | Z94: 0 | AA94: =X94+Y94 -> 23810 | AC94: 0 | AD94: 0 | AE94: =AA94+AC94 -> 23810 | AG94: 0 | AH94: 0 | AI94: =AE94+AG94 -> 23810 | AK94: 0 | AL94: 0 | AM94: =AI94+AK94 -> 23810 | AO94: 0 | AP94: 0 | AQ94: =AM94+AO94 -> 23810 | AS94: 0 | AT94: 0 | AU94: =AQ94+AS94 -> 23810
E95: =+C95 -> 0 | I95: =E95+G95 -> 0 | L95: =I95+J95 -> 0 | P95: =L95+N95 -> 0 | T95: =+P95+R95 -> 0 | X95: =T95+V95 -> 0 | AA95: =X95+Y95 -> 0 | AE95: =AA95+AC95 -> 0 | AI95: =AE95+AG95 -> 0 | AM95: =AI95+AK95 -> 0 | AQ95: =AM95+AO95 -> 0 | AU95: =AQ95+AS95 -> 0
A96: 5160 | B96: Depreciacion | C96: =+C97+C98+C99+C100+C101 -> 2941584 | E96: =+C96 -> 2941584 | G96: =+G97+G98+G99+G100+G101 -> 2941584 | I96: =E96+G96 -> 5883168 | J96: =+J97+J98+J99+J100+J101 -> 2941584 | L96: =I96+J96 -> 8824752 | N96: =+N97+N98+N99+N100+N101 -> 2941584 | P96: =L96+N96 -> 11766336 | R96: =+R97+R98+R99+R100+R101 -> 2941584 | T96: =+P96+R96 -> 14707920 | V96: =+V97+V98+V99+V100+V101 -> 2941584 | X96: =T96+V96 -> 17649504 | Y96: =+Y97+Y98+Y99+Y100+Y101 -> 2941584 | AA96: =X96+Y96 -> 20591088 | AC96: =SUM(AC97:AC101) -> 2941584 | AE96: =AA96+AC96 -> 23532672 | AG96: =SUM(AG97:AG101) -> 2941584 | AI96: =AE96+AG96 -> 26474256 | AK96: =SUM(AK97:AK101) -> 2941584 | AM96: =AI96+AK96 -> 29415840 | AO96: =SUM(AO97:AO101) -> 2941584 | AQ96: =AM96+AO96 -> 32357424 | AS96: =SUM(AS97:AS101) -> 2941584 | AU96: =AQ96+AS96 -> 35299008
A97: 516005 | B97: construcciones y edificaciones | C97: 1588943 | E97: =+C97 -> 1588943 | G97: 1588943 | I97: =E97+G97 -> 3177886 | J97: 1588943 | L97: =I97+J97 -> 4766829 | N97: 1588943 | P97: =L97+N97 -> 6355772 | R97: 1588943 | T97: =+P97+R97 -> 7944715 | V97: 1588943 | X97: =T97+V97 -> 9533658 | Y97: 1588943 | AA97: =X97+Y97 -> 11122601 | AC97: 1588943 | AE97: =AA97+AC97 -> 12711544 | AG97: 1588943 | AI97: =AE97+AG97 -> 14300487 | AK97: 1588943 | AM97: =AI97+AK97 -> 15889430 | AO97: 1588943 | AQ97: =AM97+AO97 -> 17478373 | AS97: 1588943 | AU97: =AQ97+AS97 -> 19067316
A98: 516010 | B98: maquinaria y equipo | C98: 749658 | E98: =+C98 -> 749658 | G98: 749658 | I98: =E98+G98 -> 1499316 | J98: 749658 | L98: =I98+J98 -> 2248974 | N98: 749658 | P98: =L98+N98 -> 2998632 | R98: 749658 | T98: =+P98+R98 -> 3748290 | V98: 749658 | X98: =T98+V98 -> 4497948 | Y98: 749658 | AA98: =X98+Y98 -> 5247606 | AC98: 749658 | AE98: =AA98+AC98 -> 5997264 | AG98: 749658 | AI98: =AE98+AG98 -> 6746922 | AK98: 749658 | AM98: =AI98+AK98 -> 7496580 | AO98: 749658 | AQ98: =AM98+AO98 -> 8246238 | AS98: 749658 | AU98: =AQ98+AS98 -> 8995896
A99: 516015 | B99: equipo de oficina | C99: 3733 | E99: =+C99 -> 3733 | G99: 3733 | I99: =E99+G99 -> 7466 | J99: 3733 | L99: =I99+J99 -> 11199 | N99: 3733 | P99: =L99+N99 -> 14932 | R99: 3733 | T99: =+P99+R99 -> 18665 | V99: 3733 | X99: =T99+V99 -> 22398 | Y99: 3733 | AA99: =X99+Y99 -> 26131 | AC99: 3733 | AE99: =AA99+AC99 -> 29864 | AG99: 3733 | AI99: =AE99+AG99 -> 33597 | AK99: 3733 | AM99: =AI99+AK99 -> 37330 | AO99: 3733 | AQ99: =AM99+AO99 -> 41063 | AS99: 3733 | AU99: =AQ99+AS99 -> 44796
A100: 516020 | B100: equipo de computacion | C100: 22650 | E100: =+C100 -> 22650 | G100: 22650 | I100: =E100+G100 -> 45300 | J100: 22650 | L100: =I100+J100 -> 67950 | N100: 22650 | P100: =L100+N100 -> 90600 | R100: 22650 | T100: =+P100+R100 -> 113250 | V100: 22650 | X100: =T100+V100 -> 135900 | Y100: 22650 | AA100: =X100+Y100 -> 158550 | AC100: 22650 | AE100: =AA100+AC100 -> 181200 | AG100: 22650 | AI100: =AE100+AG100 -> 203850 | AK100: 22650 | AM100: =AI100+AK100 -> 226500 | AO100: 22650 | AQ100: =AM100+AO100 -> 249150 | AS100: 22650 | AU100: =AQ100+AS100 -> 271800
A101: 516035 | B101: flota y equipo de transporte | C101: 576600 | E101: =+C101 -> 576600 | G101: 576600 | I101: =E101+G101 -> 1153200 | J101: 576600 | L101: =I101+J101 -> 1729800 | N101: 576600 | P101: =L101+N101 -> 2306400 | R101: 576600 | T101: =+P101+R101 -> 2883000 | V101: 576600 | X101: =T101+V101 -> 3459600 | Y101: 576600 | AA101: =X101+Y101 -> 4036200 | AC101: 576600 | AE101: =AA101+AC101 -> 4612800 | AG101: 576600 | AI101: =AE101+AG101 -> 5189400 | AK101: 576600 | AM101: =AI101+AK101 -> 5766000 | AO101: 576600 | AQ101: =AM101+AO101 -> 6342600 | AS101: 576600 | AU101: =AQ101+AS101 -> 6919200
P102: =L102+N102 -> 0 | T102: =+P102+R102 -> 0 | X102: =T102+V102 -> 0 | AI102: =AE102+AG102 -> 0 | AM102: =AI102+AK102 -> 0 | AQ102: =AM102+AO102 -> 0 | AU102: =AQ102+AS102 -> 0
...

Sheet GRAFICAS PYG
B5: MES | C5: VENTAS FISCALES 2020 | D5: VENTAS FISCALES 2019 | E5: VENTAS FISCALES 2018 | F5: VENTAS FISCALES 2017 | G5: VENTAS SIN IVA 2020 | H5: VENTAS SIN IVA 2019 | I5: VENTAS SIN IVA 2018 | J5: VENTAS SIN IVA 2017 | K5: GASTOS 2020 | L5: GASTOS 2019 | M5: GASTOS 2018 | N5: GASTOS 2017 | O5: UTILIDAD 2020 | P5: UTILIDAD 2019 | Q5: UTILIDAD 2018 | R5: UTILIDAD 2017
B6: ENERO | C6: 9772741 | D6: 5232922 | E6: 20519674 | F6: =522963+299991+2769114+199640+276690 -> 4068398 | G6: =+'PYG '!D14-'PYG '!D19 -> 4656136 | H6: =7998115 -> 7998115 | I6: 5489862 | J6: 3111549 | K6: =+'PYG '!C153 -> 11183760 | L6: 8192569 | M6: 7055307 | N6: 10452832 | O6: =+C6+G6-K6 -> 3245117 | P6: =+D6+H6-L6 -> 5038468 | Q6: 18954229 | R6: -3272885
B7: FEBRERO | C7: 8662267 | D7: 6735984 | E7: 347610 | F7: =34155+356641+30000+185495+199640+2769114+52440+124200+30000 -> 3781685 | G7: =+'PYG '!H14-'PYG '!H19 -> 7804429 | H7: =4974356-1 -> 4974355 | I7: 7374328 | J7: 8157506 | K7: =+'PYG '!G153 -> 13337610 | L7: 8084721 | M7: 8975623 | N7: 8843670 | O7: =+C7+G7-K7 -> 3129086 | P7: =+D7+H7-L7 -> 3625618 | Q7: -1253685 | R7: 3095521
B8: MARZO | C8: 11213082 | D8: 4072345 | E8: =245268+260 -> 245528 | F8: =2501135+199640+393580+80730+29750+34510+25000 -> 3264345 | G8: =+'PYG '!K14-'PYG '!K19 -> 5900305 | H8: =7130394+43 -> 7130437 | I8: 5439456 | J8: 5780617 | K8: =+'PYG '!J153 -> 10865138 | L8: 8025783 | M8: 9788704 | N8: 8621927 | O8: =+C8+G8-K8 -> 6248249 | P8: =+D8+H8-L8 -> 3176999 | Q8: -4103720 | R8: 423035
B9: ABRIL | C9: 109000 | D9: 8902568 | E9: =44268+102185+80587+29750+50000+4998 -> 311788 | F9: =2769114+199640+549053+161460+430560+90000+267950+437283+714714+17250+40000+37500 -> 5714524 | G9: =+'PYG '!O14-'PYG '!O19 -> 121014 | H9: =6000929+75 -> 6001004 | I9: 7142915 | J9: 5636163 | K9: =+'PYG '!N154 -> 8424882 | L9: 11161681 | M9: 9211395 | N9: 6162384 | O9: =+C9+G9-K9 -> -8194868 | P9: =+D9+H9-L9 -> 3741891 | Q9: -1756692 | R9: 5188303
B10: MAYO | D10: 4831245 | E10: 2070588 | F10: 1563099 | G10: =+'PYG '!S14-'PYG '!S19 -> 1804105 | H10: 7419178 | I10: 5721041 | J10: 13796936 | K10: =+'PYG '!R154 -> 10909925 | L10: 10164486 | M10: 8014528 | N10: 10155182 | O10: =+C10+G10-K10 -> -9105820 | P10: =+D10+H10-L10 -> 2085937 | Q10: -222899 | R10: 5204853
B11: JUNIO | C11: 15088775 | D11: 2541098 | E11: 4186225 | F11: 2504537 | G11: =+'PYG '!W14-'PYG '!W19 -> 5883300 | H11: =6384494+91 -> 6384585 | I11: 4021740 | J11: 6565667 | K11: =+'PYG '!V154 -> 12990071 | L11: 8433671 | M11: 7385244 | N11: 14240736 | O11: =+C11+G11-K11 -> 7982004 | P11: =+D11+H11-L11 -> 492012 | Q11: 822721 | R11: -5170532
B12: JULIO | C12: 5107405 | D12: 2060928 | E12: 3502320 | F12: 14376812 | G12: =+'PYG '!Z14-'PYG '!Z19 -> 9069381 | H12: 4374077 | I12: 1959742 | J12: 6138041 | K12: =+'PYG '!Y154 -> 11530572 | L12: 8752682 | M12: 7676064 | N12: 10531315 | O12: =+C12+G12-K12 -> 2646214 | P12: =+D12+H12-L12 -> -2317677 | Q12: -2214002 | R12: 9983538
B13: AGOSTO | C13: 4348355 | D13: 722060 | E13: 13456626 | F13: 9843168 | G13: =+'PYG '!AD14-'PYG '!AD19 -> 6862717 | H13: =8088407+176 -> 8088583 | I13: 4820282 | J13: 5449400 | K13: =+'PYG '!AC154 -> 11013798 | L13: 10250005 | M13: 9472439 | N13: 10083753 | O13: =+C13+G13-K13 -> 197274 | P13: =+D13+H13-L13 -> -1439362 | Q13: 8804469 | R13: 5208815
B14: SEPTIEMBRE | C14: 5343486 | D14: 1921510 | E14: 0 | F14: 6807513 | G14: =+'PYG '!AH14-'PYG '!AH19 -> 9114471 | H14: 5761435 | I14: 6035931 | J14: 6941815 | K14: =+'PYG '!AG154 -> 11098718 | L14: 12341541 | M14: 16476675 | N14: 13656658 | O14: =+C14+G14-K14 -> 3359239 | P14: =+D14+H14-L14 -> -4658595.8 | Q14: -10440744 | R14: 92670
B15: OCTUBRE | C15: 5206920 | D15: 1940050 | E15: =+'[1]PYG '!AP8 -> 53036592 | F15: 3921439 | G15: =+'PYG '!AL14-'PYG '!AL19 -> 11912110 | H15: 5903667 | I15: 10697305 | J15: 5541550 | K15: =+'PYG '!AK154 -> 14559398 | L15: 13788361 | M15: 10699836 | N15: 12463405 | O15: =+C15+G15-K15 -> 2559631.8 | P15: =+D15+H15-L15 -> -5944643.8 | Q15: 4755101 | R15: -3000416
B16: NOVIEMBRE | C16: 4539945 | D16: 6096979 | E16: =+'[1]PYG '!AT8 -> 58092377 | F16: 2545390 | G16: =+'PYG '!AP22+'PYG '!AP24+'PYG '!AP15 -> 9403633 | H16: 6953987 | I16: 7259988 | J16: 6901480 | K16: =+'PYG '!AO154 -> 15548745 | L16: 12146151 | M16: 12696365 | N16: 13179987 | O16: =+C16+G16-K16 -> -1605167 | P16: =+D16+H16-L16 -> 904815.25 | Q16: -380592 | R16: -3733117
B17: DICIEMBRE | C17: 5671900 | D17: 10802895 | E17: =+'[1]PYG '!AX8 -> 63938027 | F17: 68513641 | G17: =+'PYG '!AT22+'PYG '!AT15+'PYG '!AT24 -> 11129725 | H17: 3580427 | I17: 8230584 | J17: 7106144 | K17: =+'PYG '!AS154 -> 12796951 | L17: 9554095.8 | M17: 8852048 | N17: 27294325 | O17: =+C17+G17-K17 -> 4004674 | P17: =+D17+H17-L17 -> 4829226.2 | Q17: 5224186 | R17: 48325460
B19: TOTAL | C19: =SUM(C6:C18) -> 75063876 | D19: =SUM(D6:D18) -> 55860584 | E19: =SUM(E6:E18) -> 219707355 | F19: =SUM(F6:F18) -> 126904551 | G19: =SUM(G6:G18) -> 83661326 | H19: =SUM(H6:H18) -> 74569850 | I19: =SUM(I6:I18) -> 74193174 | J19: =SUM(J6:J18) -> 81126868 | ... R19: =SUM(R6:R18) -> 62345245
B44: MES | C44: VENTAS FISCALES 2020 | D44: VENTAS FISCALES 2019 | E44: VENTAS FISCALES 2018 | F44: VENTAS FISCALES 2017
B45: ENERO | C45: 9772741 | D45: 5232922 | E45: 20519674 | F45: =522963+299991+2769114+199640+276690 -> 4068398
B46: FEBRERO | C46: 8662267 | D46: 6735984 | E46: 347610 | F46: =34155+356641+30000+185495+199640+2769114+52440+124200+30000 -> 3781685
B47: MARZO | C47: 11213082 | D47: 4072345 | E47: =245268+260 -> 245528 | F47: =2501135+199640+393580+80730+29750+34510+25000 -> 3264345
B48: ABRIL | C48: 109000 | D48: 8902568 | E48: =44268+102185+80587+29750+50000+4998 -> 311788 | F48: =2769114+199640+549053+161460+430560+90000+267950+437283+714714+17250+40000+37500 -> 5714524
B49: MAYO | D49: 4831245 | E49: 2070588 | F49: 1563099
B50: JUNIO | C50: 15088775 | D50: 2541098 | E50: 4186225 | F50: 2504537
B51: JULIO | C51: 5107405 | D51: 2060928 | E51: 3502320 | F51: 14376812
B52: AGOSTO | C52: 4348355 | D52: 722060 | E52: 13456626 | F52: 9843168
B53: SEPTIEMBRE | C53: 5343486 | D53: 1921510 | E53: 0 | F53: 6807513
B54: OCTUBRE | C54: 5206920 | D54: 1940050 | E54: =+'[1]PYG '!AP47 -> 11000000 | F54: 3921439
B55: NOVIEMBRE | C55: 4539945 | D55: 6096979 | E55: =+'[1]PYG '!AT47 -> 12000000 | F55: 2545390
B56: DICIEMBRE | C56: 5671900 | D56: 10802895 | E56: =+'[1]PYG '!AX47 -> 13000000 | F56: 68513641
B58: TOTAL | C58: =SUM(C45:C57) -> 75063876 | D58: =SUM(D45:D57) -> 55860584 | E58: =SUM(E45:E57) -> 80640359 | F58: =SUM(F45:F57) -> 126904551
B70: MES | C70: VENTAS SIN IVA 2020 | D70: VENTAS SIN IVA 2019 | E70: VENTAS SIN IVA 2018 | F70: VENTAS SIN IVA 2017
B71: ENERO | C71: 4656136 | D71: 7998115 | E71: 5489862 | F71: 3111549
B72: FEBRERO | C72: 7804429 | D72: 4974355 | E72: 7374328 | F72: 8157506
B73: MARZO | C73: 5900305 | D73: 7130437 | E73: 5439456 | F73: 5780617
B74: ABRIL | C74: 121014 | D74: 6001004 | E74: 7142915 | F74: 5636163
B75: MAYO | C75: 1804105 | D75: 7419178 | E75: 5721041 | F75: 13796936
B76: JUNIO | C76: 5883300 | D76: 6384585 | E76: 4021740 | F76: 6565667
B77: JULIO | C77: 9069381 | D77: 4374077 | E77: 1959742 | F77: 6138041
B78: AGOSTO | C78: 6862717 | D78: 8088583 | E78: 4820282 | F78: 5449400
B79: SEPTIEMBRE | C79: 9114471 | D79: 5761435 | E79: 6035931 | F79: 6941815
B80: OCTUBRE | C80: 11912110 | D80: 5903667 | E80: 10697305 | F80: 5541550
B81: NOVIEMBRE | C81: 9403633 | D81: 6953987 | E81: 7259988 | F81: 6901480
B82: DICIEMBRE | C82: 11129725 | D82: 3580427 | E82: 8230584 | F82: 7106144
B83: TOTAL | C83: =SUM(C71:C82) -> 83661326 | D83: =SUM(D71:D82) -> 74569850 | E83: =SUM(E71:E82) -> 74193174 | F83: =SUM(F71:F82) -> 81126868
B102: MES | C102: GASTOS 2020 | D102: GASTOS 2019 | E102: GASTOS 2018 | F102: GASTOS 2017
B103: ENERO | C103: 11183760 | D103: 8192569 | E103: 7055307 | F103: 10452832
B104: FEBRERO | C104: 13337610 | D104: 8084721 | E104: 8975623 | F104: 8843670
B105: MARZO | C105: 10865138 | D105: 8025783 | E105: 9788704 | F105: 8621927
B106: ABRIL | C106: 8424882 | D106: 11161681 | E106: 9211395 | F106: 6162384
B107: MAYO | C107: 10909925 | D107: 10164486 | E107: 8014528 | F107: 10155182
B108: JUNIO | C108: 12990071 | D108: 8433671 | E108: 7385244 | F108: 14240736
B109: JULIO | C109: 11530572 | D109: 8752682 | E109: 7676064 | F109: 10531315
B110: AGOSTO | C110: 11013798 | D110: 10250005 | E110: 9472439 | F110: 10083753
B111: SEPTIEMBRE | C111: 11098718 | D111: 12341541 | E111: 16476675 | F111: 13656658
B112: OCTUBRE | C112: 14559398 | D112: 13788361 | E112: 10699836 | F112: 12463405
B113: NOVIEMBRE | C113: 15548745 | D113: 12146151 | E113: 12696365 | F113: 13179987
B114: DICIEMBRE | C114: =+'PYG '!AS154 -> 12796951 | D114: 9554095.8 | E114: 8852048 | F114: 27294325
B116: TOTAL | C116: =SUM(C103:C115) -> 144259568 | D116: =SUM(D103:D115) -> 120895746 | E116: =SUM(E103:E115) -> 116304228 | F116: =SUM(F103:F115) -> 145686174
B129: MES | C129: UTILIDAD 2020 | D129: UTILIDAD 2019 | E129: UTILIDAD 2018 | F129: UTILIDAD 2017
B130: ENERO | C130: 3245117 | D130: 5038468 | E130: 18954229 | F130: -3272885
B131: FEBRERO | C131: 3129086 | D131: 3625618 | E131: -1253685 | F131: 3095521
B132: MARZO | C132: 6248249 | D132: 3176999 | E132: -4103720 | F132: 423035
B133: ABRIL | C133: -8194868 | D133: 3741891 | E133: -1756692 | F133: 5188303
B134: MAYO | C134: -9105820 | D134: 2085937 | E134: -222899 | F134: 5204853
B135: JUNIO | C135: 7982004 | D135: 492012 | E135: 822721 | F135: -5170532
B136: JULIO | C136: 2646214 | D136: -2317677 | E136: -2214002 | F136: 9983538
B137: AGOSTO | C137: 197274 | D137: -1439362 | E137: 8804469 | F137: 5208815
B138: SEPTIEMBRE | C138: 3359239 | D138: -4658595.8 | E138: -10440744 | F138: 92670
B139: OCTUBRE | C139: 2559631.8 | D139: -5944643.8 | E139: 4755101 | F139: -3000416
B140: NOVIEMBRE | C140: -1605167 | D140: 904815.25 | E140: -380592 | F140: -3733117
B141: DICIEMBRE | C141: =+'PYG '!AU155 -> 4004674 | D141: 4829226.2 | E141: 5224186 | F141: 48325460
B144: TOTAL | C144: =SUM(C130:C143) -> 14465634 | D144: =SUM(D130:D143) -> 9534688 | E144: =SUM(E130:E143) -> 18188372 | F144: =SUM(F130:F143) -> 62345245

Sheet INDICADORES
A1: Razones Financieras
A2: Liquidez
A4: Liquidez | B4: Activos Circulantes | C4: =+DICIEMBRE!E60 -> 6.2305987e+08 | D4: =+C4/C5 -> 99.020234 | E4: La empresa cuenta con el 99% de respaldo de los activos
B5: Pasivos Circulantes | C5: =+DICIEMBRE!E97 -> 6292248
A7: Prueba Acida | B7: Activos Circulantes - Inventarios | C7: =+DICIEMBRE!E60-DICIEMBRE!E34 -> 4.5982442e+08 | D7: =+C7/C8 -> 73.077924 | E7: con el activo que tenemos hay el 73,07% para pagar el pasivo
B8: Pasivos Circulantes | C8: =+C5 -> 6292248
A10: Administración de Activos
A12: Rotación Activos Fijos | B12: Ventas | C12: 136687592 | D12: =+C12/C13 -> 0.36613025 | E12: la empresa roto su activo el 0,36
B13: Activos Fijos Netos | C13: =+DICIEMBRE!E38 -> 373330511
A15: Rotación Activos Totales | B15: Ventas | C15: =+C12 -> 136687592 | D15: =+C15/C16 -> 0.21938115 | E15: la empresa roto su activo totales el 0,21
B16: Activos Totales | C16: =+C4 -> 6.2305987e+08
A18: Administración de Deudas
A20: Razón de Endeudamiento | B20: Deudas Totales | C20: =+DICIEMBRE!E97 -> 6292248 | D20: =+C20/C21 -> 0.010098946 | E20: la empresa de los activos debe el 0,010
B21: Activos totales | C21: =+DICIEMBRE!E60 -> 6.2305987e+08
A23: Rentabilidad
A25: Margen de utilidad | B25: Utilidad Neta | C25: =+'PYG '!AU154 -> 14465634 | D25: =+C25/C26*100 -> 9.1987892 | E25: el margen de utilidad es del 9,19%
B26: Ventas | C26: =+'PYG '!AU8+'PYG '!AU15+'PYG '!AU22 -> 157255847
A28: Rendimiento sobre los activos totales (RAT) | B28: Utilidad Neta | C28: =+C25 -> 14465634 | D28: =+C28/C29*100 -> 2.3217085 | E28: la empresa puede utilizarr el 2,32% de sus activos para generar ventas
B29: Activos totales | C29: =+C16 -> 6.2305987e+08
