Workbook

Sheet PYG 
A1: EQUIORIENTE LTDA
A2: INFORMES FINAL AÑO 2019
C4: ENERO 2019 | G4: FEBRERO 2019 | J4: MARZO 2019 | N4: ABRIL 2019 | R4: MAYO 2019 | V4: JUNIO 2019 | Y4: JULIO 2019 | AC4: AGOSTO 2019 | AG4: SEPTIEMBRE 2019 | AK4: OCTUBRE 2019 | AO4: NOVIEMBRE 2019 | AS4: DICIEMBRE 2019
A5: Cuenta | C5: Mov. 02/01/2019 a 31/01/2019 | E5: Saldos a 31/01/2019 | G5: Mov. 01/02/2019 a 28/02/2019 | I5: Saldos a 28/02/2019 | J5: Mov. 01/03/2019 a 31/03/2019 | L5: Saldos a 31/03/2019 | N5: Mov. 01/04/2019 a 30/04/2019 | P5: Saldos a 30/04/2019 | R5: Mov. 02/05/2019 a 31/05/2019 | T5: Saldos a 31/01/2019 | V5: Mov. 01/06/2019 a 30/06/2019 | X5: Saldos a 28/06/2019 | Y5: Mov. 01/07/2019 a 31/07/2019 | AA5: Saldos a 31/07/2019 | AC5: Mov. 01/08/2019 a 30/08/2019 | AE5: Saldos a 30/08/2019 | AG5: Mov. 01/09/2019 a 31/09/2019 | AI5: Saldos a 31/09/2019 | AK5: Mov. 01/10/2019 a 31/10/2019 | AM5: Saldos a 31/10/2019 | AO5: Mov. 01/11/2019 a 30/11/2019 | AQ5: Saldos a 30/11/2019 | AS5: Mov. 01/12/2019 a 30/12/2019 | AU5: Saldos a 31/12/2019
A6: Cód. | B6: Nombre | C6: Débitos | D6: Créditos | E6: Saldo actual | G6: Débitos | H6: Créditos | I6: Saldo actual | J6: Débitos | K6: Créditos | L6: Saldo actual | N6: Débitos | O6: Créditos | P6: Saldo actual | R6: Débitos | S6: Créditos | T6: Saldo actual | V6: Débitos | W6: Créditos | X6: Saldo actual | Y6: Débitos | Z6: Créditos | AA6: Saldo actual | AC6: Débitos | AD6: Créditos | AE6: Saldo actual | AG6: Débitos | AH6: Créditos | AI6: Saldo actual | AK6: Débitos | AL6: Créditos | AM6: Saldo actual | AO6: Débitos | AP6: Créditos | AQ6: Saldo actual | AS6: Débitos | AT6: Créditos | AU6: Saldo actual
A7: 4 | B7: INGRESOS | C7: 0 | D7: =D8+D14 -> 15080037 | E7: =E8+E14 -> 15080037 | G7: 0 | H7: =H8+H14 -> 13559340 | I7: =E7+H7 -> 28639377 | J7: 0 | K7: =K8+K14 -> 12451739 | L7: =I7+K7 -> 41091116 | N7: 0 | O7: =O8+O14 -> 16172397 | P7: =L7+O7 -> 57263513 | R7: 0 | S7: =S8+S14 -> 13539222 | T7: =+P7+S7 -> 70802735 | V7: 0 | W7: =W8+W14 -> 10214483 | X7: =+T7+W7 -> 81017218 | Y7: 0 | Z7: =Z8+Z14 -> 7723804 | AA7: =+X7+Z7 -> 88741022 | AC7: 0 | AD7: =AD8+AD14 -> 10099562 | AE7: =AA7+AD7 -> 98840584 | AG7: 0 | AH7: =AH8+AH14 -> 8971745 | AI7: =AE7+AH7 -> 107812329 | AK7: 0 | AL7: =AL8+AL14 -> 9132517 | AM7: =AI7+AL7 -> 116944846 | AO7: 0 | AP7: =AP8+AP14 -> 14339766 | AQ7: =AM7+AP7 -> 131284612 | AS7: 0 | AT7: =AT8+AT14 -> 15672122 | AU7: =AQ7+AT7 -> 146956734
A8: 41 | B8: Operacionales | C8: 0 | D8: =D9 -> 5232922 | E8: =E9 -> 5232922 | G8: 0 | H8: =H9 -> 6735984 | I8: =E8+H8 -> 11968906 | J8: 0 | K8: =K9 -> 4072345 | L8: =I8+K8 -> 16041251 | N8: 0 | O8: =O9 -> 8902568 | P8: =L8+O8 -> 24943819 | R8: 0 | S8: =S9 -> 4831245 | T8: =+P8+S8 -> 29775064 | V8: 0 | W8: =W9 -> 2541098 | X8: =T8+W8 -> 32316162 | Y8: 0 | Z8: =Z9 -> 2060928 | AA8: =+X8+Z8 -> 34377090 | AC8: 0 | AD8: =AD9 -> 722060 | AE8: =AA8+AD8 -> 35099150 | AG8: 0 | AH8: =AH9 -> 1921510 | AI8: =AE8+AH8 -> 37020660 | AK8: 0 | AL8: =AL9 -> 1940050 | AM8: =AI8+AL8 -> 38960710 | AO8: =AK8+AN8 -> 0 | AP8: =AP9 -> 6096979 | AQ8: =AM8+AP8 -> 45057689 | AS8: =AO8+AR8 -> 0 | AT8: =AT9 -> 10802895 | AU8: =AQ8+AT8 -> 55860584
A9: 4155 | B9: Actividades inmobiliarias, empresariales y de alquiler | C9: 0 | D9: =+D10+D11+D12 -> 5232922 | E9: =D9 -> 5232922 | G9: 0 | H9: =+H10+H11+H12 -> 6735984 | I9: =E9+H9 -> 11968906 | J9: 0 | K9: =K10+K11+K12 -> 4072345 | L9: =I9+K9 -> 16041251 | N9: 0 | O9: =O10+O11+O12 -> 8902568 | P9: =L9+O9 -> 24943819 | R9: 0 | S9: =+S10+S11+S12 -> 4831245 | T9: =+P9+S9 -> 29775064 | V9: 0 | W9: =+W10+W11+W12 -> 2541098 | X9: =T9+W9 -> 32316162 | Y9: 0 | Z9: =+Z10+Z12 -> 2060928 | AA9: =+AA10+AA11+AA12 -> 34377090 | AC9: 0 | AD9: =+AD10+AD11+AD12 -> 722060 | AE9: =AA9+AD9 -> 35099150 | AG9: =AC9+AF9 -> 0 | AH9: =+AH10+AH11+AH12 -> 1921510 | AI9: =AE9+AH9 -> 37020660 | AK9: =AG9+AJ9 -> 0 | AL9: =+AL10+AL11+AL12 -> 1940050 | AM9: =AI9+AL9 -> 38960710 | AO9: =AK9+AN9 -> 0 | AP9: =+AP10+AP11+AP12 -> 6096979 | AQ9: =AM9+AP9 -> 45057689 | AS9: =AO9+AR9 -> 0 | AT9: =+AT10+AT11+AT12 -> 10802895 | AU9: =AQ9+AT9 -> 55860584
A10: 415520 | B10: Alquiler IVA | C10: 0 | D10: 4907922 | E10: =+D10 -> 4907922 | G10: 0 | H10: 6635984 | I10: =E10+H10 -> 11543906 | J10: 0 | K10: 4072345 | L10: =I10+K10 -> 15616251 | N10: 0 | O10: 8155068 | P10: =L10+O10 -> 23771319 | R10: 0 | S10: 4596245 | T10: =+P10+S10 -> 28367564 | V10: 0 | W10: 2343598 | X10: =T10+W10 -> 30711162 | Y10: 0 | Z10: 1900928 | AA10: =+X10+Z10 -> 32612090 | AC10: 0 | AD10: 497060 | AE10: =AA10+AD10 -> 33109150 | AG10: 0 | AH10: 1771510 | AI10: =AE10+AH10 -> 34880660 | AK10: 0 | AL10: 1735050 | AM10: =AI10+AL10 -> 36615710 | AO10: 0 | AP10: 5463429 | AQ10: =AM10+AP10 -> 42079139 | AS10: 0 | AT10: 10412895 | AU10: =AQ10+AT10 -> 52492034
A11: 415525 | B11: VENTA EQUIPO | D11: 0 | E11: =+D11 -> 0 | G11: 0 | H11: 0 | I11: =E11+H11 -> 0 | K11: =+K12 -> 0 | L11: =I11+K11 -> 0 | O11: 0 | P11: =L11+O11 -> 0 | S11: 0 | T11: =+P11+S11 -> 0 | V11: 0 | W11: 0 | X11: =T11+W11 -> 0 | Y11: 0 | Z11: 0 | AA11: =+X11+Z11 -> 0 | AC11: 0 | AD11: 0 | AE11: =AA11+AD11 -> 0 | AG11: 0 | AH11: 0 | AI11: =AE11+AH11 -> 0 | AK11: 0 | AL11: 0 | AM11: =AI11+AL11 -> 0 | AO11: 0 | AP11: 168550 | AQ11: =AM11+AP11 -> 168550 | AS11: 0 | AT11: 0 | AU11: =AQ11+AT11 -> 168550
A12: 415515 | B12: Transporte | C12: 0 | D12: 325000 | E12: =+D12 -> 325000 | G12: 0 | H12: 100000 | I12: =E12+H12 -> 425000 | J12: 0 | K12: 0 | L12: =I12+K12 -> 425000 | N12: 0 | O12: 747500 | P12: =L12+O12 -> 1172500 | R12: 0 | S12: 235000 | T12: =+P12+S12 -> 1407500 | V12: 0 | W12: 197500 | X12: =T12+W12 -> 1605000 | Y12: 0 | Z12: 160000 | AA12: =+X12+Z12 -> 1765000 | AC12: 0 | AD12: 225000 | AE12: =AA12+AD12 -> 1990000 | AG12: 0 | AH12: 150000 | AI12: =AE12+AH12 -> 2140000 | AK12: 0 | AL12: 205000 | AM12: =AI12+AL12 -> 2345000 | AO12: 0 | AP12: 465000 | AQ12: =AM12+AP12 -> 2810000 | AS12: 0 | AT12: 390000 | AU12: =AQ12+AT12 -> 3200000
L13: =I13+K13 -> 0 | AA13: =+X13+Z13 -> 0
A14: 42 | B14: No operacionales | C14: 0 | D14: =D15+D19+D22 -> 9847115 | E14: =+D14 -> 9847115 | G14: 0 | H14: =H15+H19+H22+H24 -> 6823356 | I14: =E14+H14 -> 16670471 | J14: 0 | K14: =K15+K19+K22 -> 8379394 | L14: =I14+K14 -> 25049865 | N14: 0 | O14: =O15+O19+O22 -> 7269829 | P14: =L14+O14 -> 32319694 | R14: 0 | S14: =S15+S19+S22+S24 -> 8707977 | T14: =+P14+S14 -> 41027671 | V14: 0 | W14: =+W15+W19+W22+W24 -> 7673385 | X14: =+T14+W14 -> 48701056 | Y14: 0 | Z14: =+Z15+Z19+Z22+Z24 -> 5662876 | AA14: =X14+Z14 -> 54363932 | AC14: 0 | AD14: =AD15+AD19+AD22+AD24 -> 9377502 | AE14: =AA14+AD14 -> 63741434 | AG14: 0 | AH14: =AH15+AH19+AH22+AH24 -> 7050235 | AI14: =AE14+AH14 -> 70791669 | AK14: 0 | AL14: =AL15+AL19+AL22+AL24 -> 7192467 | AM14: =AI14+AL14 -> 77984136 | AO14: 0 | AP14: =AP15+AP19+AP22+AP24 -> 8242787 | AQ14: =AM14+AP14 -> 86226923 | AS14: 0 | AT14: =AT15+AT19+AT22+AT24 -> 4869227 | AU14: =AQ14+AT14 -> 91096150
A15: 4210 | B15: Financieros | C15: 0 | D15: 8491 | E15: =+D15 -> 8491 | G15: 0 | H15: =+H16 -> 11670 | I15: =E15+H15 -> 20161 | J15: 0 | K15: 14542 | L15: =I15+K15 -> 34703 | N15: 0 | O15: =O16 -> 16079 | P15: =L15+O15 -> 50782 | R15: 0 | S15: 12936 | T15: =+P15+S15 -> 63718 | V15: 0 | W15: =+W16+W17 -> 171494 | X15: =+T15+W15 -> 235212 | Y15: 0 | Z15: =+Z16+Z17 -> 76252 | AA15: =+X15+Z15 -> 311464 | AC15: 0 | AD15: =+AD16+AD17 -> 73730 | AE15: =AA15+AD15 -> 385194 | AG15: 0 | AH15: =+AH16+AH17 -> 69406 | AI15: =AE15+AH15 -> 454600 | AK15: 0 | AL15: =+AL16+AL17 -> 64152 | AM15: =AI15+AL15 -> 518752 | AO15: 0 | AP15: =+AP16+AP17 -> 56845 | AQ15: =AM15+AP15 -> 575597 | AS15: 0 | AT15: =+AT16+AT17 -> 103419 | AU15: =AQ15+AT15 -> 679016
A16: 421005 | B16: Intereses | C16: 0 | D16: =+D15 -> 8491 | E16: =+D16 -> 8491 | G16: 0 | H16: 11670 | I16: =E16+H16 -> 20161 | J16: 0 | K16: =+K15 -> 14542 | L16: =I16+K16 -> 34703 | N16: 0 | O16: 16079 | P16: =L16+O16 -> 50782 | R16: 0 | S16: =+S15 -> 12936 | T16: =+P16+S16 -> 63718 | V16: 0 | W16: 104053 | X16: =+T16+W16 -> 167771 | Y16: 0 | Z16: 11408 | AA16: =+X16+Z16 -> 179179 | AC16: 0 | AD16: 11503 | AE16: =AA16+AD16 -> 190682 | AG16: 0 | AH16: 9812 | AI16: =AE16+AH16 -> 200494 | AK16: 0 | AL16: 7209 | AM16: =AI16+AL16 -> 207703 | AO16: 0 | AP16: 2571 | AQ16: =AM16+AP16 -> 210274 | AS16: 0 | AT16: 245 | AU16: =AQ16+AT16 -> 210519
A17: 421095 | B17: intereses prestamos socios | W17: 67441 | X17: =+T17+W17 -> 67441 | Z17: 64844 | AA17: =+X17+Z17 -> 132285 | AD17: 62227 | AE17: =AA17+AD17 -> 194512 | AH17: 59594 | AI17: =AE17+AH17 -> 254106 | AL17: 56943 | AM17: =AI17+AL17 -> 311049 | AP17: 54274 | AQ17: =AM17+AP17 -> 365323 | AT17: 103174 | AU17: =AQ17+AT17 -> 468497
L18: =I18+K18 -> 0 | T18: =+P18+S18 -> 0 | X18: =+T18+W18 -> 0 | AA18: =+X18+Z18 -> 0 | AE18: =AA18+AD18 -> 0 | AI18: =AE18+AH18 -> 0 | AM18: =AI18+AL18 -> 0 | AQ18: =AM18+AP18 -> 0 | AU18: =AQ18+AT18 -> 0
A19: 4220 | B19: ARRENDAMIENTOS APARTAMENTOS | C19: 0 | D19: =D20 -> 1849000 | E19: =+D19 -> 1849000 | G19: 0 | H19: =H20 -> 1849000 | I19: =E19+H19 -> 3698000 | J19: 0 | K19: 1249000 | L19: =I19+K19 -> 4947000 | N19: 0 | O19: =O20 -> 1268900 | P19: =L19+O19 -> 6215900 | R19: 0 | S19: 1288800 | T19: =+P19+S19 -> 7504700 | V19: 0 | W19: 1288800 | X19: =+T19+W19 -> 8793500 | Y19: 0 | Z19: 1288800 | AA19: =+X19+Z19 -> 10082300 | AC19: 0 | AD19: 1288800 | AE19: =AA19+AD19 -> 11371100 | AG19: 0 | AH19: 1288800 | AI19: =AE19+AH19 -> 12659900 | AK19: 0 | AL19: 1288800 | AM19: =AI19+AL19 -> 13948700 | AO19: 0 | AP19: 1288800 | AQ19: =AM19+AP19 -> 15237500 | AS19: 0 | AT19: 1288800 | AU19: =AQ19+AT19 -> 16526300
A20: 422010 | B20: Apartamentos Arrendados | C20: 0 | D20: 1849000 | E20: =+D20 -> 1849000 | G20: 0 | H20: 1849000 | I20: =E20+H20 -> 3698000 | J20: 0 | K20: =+K19 -> 1249000 | L20: =I20+K20 -> 4947000 | N20: 0 | O20: 1268900 | P20: =L20+O20 -> 6215900 | R20: 0 | S20: =+S19 -> 1288800 | T20: =+P20+S20 -> 7504700 | V20: 0 | W20: =+W19 -> 1288800 | X20: =+T20+W20 -> 8793500 | Y20: 0 | Z20: =+Z19 -> 1288800 | AA20: =+X20+Z20 -> 10082300 | AC20: 0 | AD20: =+AD19 -> 1288800 | AE20: =AA20+AD20 -> 11371100 | AG20: 0 | AH20: =+AH19 -> 1288800 | AI20: =AE20+AH20 -> 12659900 | AK20: 0 | AL20: =+AL19 -> 1288800 | AM20: =AI20+AL20 -> 13948700 | AO20: 0 | AP20: =+AP19 -> 1288800 | AQ20: =AM20+AP20 -> 15237500 | AS20: 0 | AT20: =+AT19 -> 1288800 | AU20: =AQ20+AT20 -> 16526300
L21: =I21+K21 -> 0 | T21: =+P21+S21 -> 0 | X21: =+T21+W21 -> 0 | AA21: =+X21+Z21 -> 0
A22: 4235 | B22: Servicios | C22: 0 | D22: =D23 -> 7989624 | E22: =+D22 -> 7989624 | G22: 0 | H22: =H23 -> 4962680 | I22: =E22+H22 -> 12952304 | J22: 0 | K22: =K23 -> 7115852 | L22: =I22+K22 -> 20068156 | N22: 0 | O22: =O23 -> 5984850 | P22: =L22+O22 -> 26053006 | R22: 0 | S22: =S23 -> 7406240 | T22: =+P22+S22 -> 33459246 | V22: 0 | W22: =+W23 -> 6213000 | X22: =+T22+W22 -> 39672246 | Y22: 0 | Z22: 4295391 | AA22: =+X22+Z22 -> 43967637 | AC22: 0 | AD22: =AD23 -> 8014677 | AE22: =AA22+AD22 -> 51982314 | AG22: 0 | AH22: =AH23 -> 5691827 | AI22: =AE22+AH22 -> 57674141 | AK22: 0 | AL22: =AL23 -> 5839339 | AM22: =AI22+AL22 -> 63513480 | AO22: 0 | AP22: =AP23 -> 6896946 | AQ22: =AM22+AP22 -> 70410426 | AS22: 0 | AT22: =AT23 -> 3471702 | AU22: =AQ22+AT22 -> 73882128
A23: 423510 | B23: VENTAS SIN IVA | C23: 0 | D23: 7989624 | E23: =+D23 -> 7989624 | G23: 0 | H23: 4962680 | I23: =E23+H23 -> 12952304 | J23: 0 | K23: 7115852 | L23: =I23+K23 -> 20068156 | N23: 0 | O23: 5984850 | P23: =L23+O23 -> 26053006 | R23: 0 | S23: 7406240 | T23: =+P23+S23 -> 33459246 | V23: 0 | W23: 6213000 | X23: =+T23+W23 -> 39672246 | Y23: 0 | Z23: =+Z22 -> 4295391 | AA23: =+X23+Z23 -> 43967637 | AC23: 0 | AD23: 8014677 | AE23: =AA23+AD23 -> 51982314 | AG23: 0 | AH23: 5691827 | AI23: =AE23+AH23 -> 57674141 | AK23: 0 | AL23: 5839339 | AM23: =AI23+AL23 -> 63513480 | AO23: 0 | AP23: 6896946 | AQ23: =AM23+AP23 -> 70410426 | AS23: 0 | AT23: 3471702 | AU23: =AQ23+AT23 -> 73882128
A24: 4295 | B24: DIVERSOS | C24: 0 | D24: 0 | E24: =+D24 -> 0 | G24: 0 | H24: =+H25 -> 6 | I24: =E24+H24 -> 6 | J24: 0 | K24: =+K25 -> 43 | L24: =I24+K24 -> 49 | N24: 0 | O24: =+O25 -> 75 | P24: =L24+O24 -> 124 | R24: 0 | S24: 1 | T24: =+P24+S24 -> 125 | V24: 0 | W24: 91 | X24: =+T24+W24 -> 216 | Y24: 0 | Z24: 2433 | AA24: =+X24+Z24 -> 2649 | AC24: 0 | AD24: =175+120 -> 295 | AE24: =AA24+AD24 -> 2944 | AG24: 0 | AH24: =+AH25 -> 202 | AI24: =AE24+AH24 -> 3146 | AK24: 0 | AL24: =+AL25 -> 176 | AM24: =AI24+AL24 -> 3322 | AO24: 0 | AP24: =+AP25 -> 196 | AQ24: =AM24+AP24 -> 3518 | AS24: 0 | AT24: =+AT25 -> 5306 | AU24: =AQ24+AT24 -> 8824
A25: 429581 | B25: Ajuste al peso | C25: 0 | D25: 0 | E25: =+D25 -> 0 | G25: 0 | H25: 6 | I25: =E25+H25 -> 6 | J25: 0 | K25: 43 | L25: =I25+K25 -> 49 | N25: 0 | O25: 75 | P25: =L25+O25 -> 124 | R25: 0 | S25: 1 | T25: =+P25+S25 -> 125 | V25: 0 | W25: 91 | X25: =+T25+W25 -> 216 | Y25: 0 | Z25: =+Z24 -> 2433 | AA25: =+X25+Z25 -> 2649 | AC25: 0 | AD25: =+AD24 -> 295 | AE25: =AA25+AD25 -> 2944 | AG25: 0 | AH25: 202 | AI25: =AE25+AH25 -> 3146 | AK25: 0 | AL25: 176 | AM25: =AI25+AL25 -> 3322 | AO25: 0 | AP25: 196 | AQ25: =AM25+AP25 -> 3518 | AS25: 0 | AT25: 5306 | AU25: =AQ25+AT25 -> 8824
A27: 5 | B27: GASTOS | C27: =C28+C136+C114 -> 8400620 | D27: 0 | E27: =+C27 -> 8400620 | G27: =G28+G136+G114 -> 9693071 | H27: 0 | I27: =E27+G27 -> 18093691 | J27: =J28+J136+J114 -> 8371715 | K27: 0 | L27: =I27+J27 -> 26465406 | N27: =N28+N136+N114 -> 12711829 | O27: 0 | P27: =L27+N27 -> 39177235 | R27: =R28+R136+R114 -> 10565555 | S27: 0 | T27: =+P27+R27 -> 49742790 | V27: =V28+V136+V114 -> 8819295 | W27: 0 | X27: =T27+V27 -> 58562085 | Y27: =Y28+Y136+Y114 -> 9153751 | Z27: 0 | AA27: =X27+Y27 -> 67715836 | AC27: =AC28+AC136+AC114 -> 13697507 | AD27: 0 | AE27: =AA27+AC27 -> 81413343 | AG27: =AG28+AG136+AG114 -> 12742610 | AH27: 0 | AI27: =AE27+AG27 -> 94155953 | AK27: =AK28+AK136+AK114 -> 14189430 | AL27: 0 | AM27: =AI27+AK27 -> 1.0834538e+08 | AO27: =AO28+AO136+AO114 -> 12547220 | AP27: 0 | AQ27: =AM27+AO27 -> 1.208926e+08 | AS27: =AS28+AS136+AS114 -> 9955164.8 | AT27: 0 | AU27: =AQ27+AS27 -> 130847767
A28: 51 | B28: Operacionales de administración | C28: =C29+C44+C55+C49+C62+C65+C75+C81+C87+C101+C59 -> 8116046 | D28: 0 | E28: =+C28 -> 8116046 | G28: =G29+G44+G49+G55+G62+G65+G75+G81+G87+G101 -> 7966455 | H28: 0 | I28: =E28+G28 -> 16082501 | J28: =J29+J44+J49+J55+J62+J65+J75+J81+J87+J101 -> 7903971 | K28: 0 | L28: =I28+J28 -> 23986472 | N28: =N29+N44+N49+N55+N62+N65+N75+N81+N87+N101 -> 11049135 | O28: 0 | P28: =L28+N28 -> 35035607 | R28: =R29+R44+R55+R49+R62+R65+R75+R81+R87+R101+R59 -> 9890052 | S28: 0 | T28: =+P28+R28 -> 44925659 | V28: =V29+V44+V49+V55+V62+V65+V75+V81+V87+V101 -> 8345602 | W28: 0 | X28: =T28+V28 -> 53271261 | Y28: =Y29+Y44+Y49+Y55+Y62+Y65+Y75+Y81+Y87+Y101 -> 8661808 | Z28: 0 | AA28: =X28+Y28 -> 61933069 | AC28: =AC29+AC44+AC49+AC55+AC62+AC65+AC75+AC81+AC87+AC101 -> 10142788 | AD28: 0 | AE28: =AA28+AC28 -> 72075857 | AG28: =AG29+AG44+AG49+AG55+AG62+AG65+AG75+AG81+AG87+AG101+AG93 -> 12198219 | AH28: 0 | AI28: =AE28+AG28 -> 84274076 | AK28: =AK29+AK44+AK49+AK55+AK62+AK65+AK75+AK81+AK87+AK101+AK93 -> 13649169 | AL28: 0 | AM28: =AI28+AK28 -> 97923244 | AO28: =AO29+AO44+AO49+AO55+AO62+AO65+AO75+AO81+AO87+AO101+AO93 -> 12035857 | AP28: 0 | AQ28: =AM28+AO28 -> 1.099591e+08 | AS28: =AS29+AS44+AS49+AS55+AS62+AS65+AS75+AS81+AS87+AS101+AS93 -> 9451620.8 | AT28: 0 | AU28: =AQ28+AS28 -> 119410722
A29: 5105 | B29: Gastos de personal | C29: =C30+C32+C33+C34+C35+C36+C37+C38+C39+C40+C41+C42 -> 1600392 | D29: 0 | E29: =+C29 -> 1600392 | G29: =SUM(G30:G42) -> 4130279 | H29: 0 | I29: =E29+G29 -> 5730671 | J29: =SUM(J30:J42) -> 4439790 | K29: 0 | L29: =I29+J29 -> 10170461 | N29: =N30+N32+N33+N34+N35+N36+N37+N38+N39+N40+N41+N42 -> 4419929 | O29: 0 | P29: =L29+N29 -> 14590390 | R29: =SUM(R30:R42) -> 4484929 | S29: 0 | T29: =+P29+R29 -> 19075319 | V29: =SUM(V30:V42) -> 4419929 | W29: 0 | X29: =T29+V29 -> 23495248 | Y29: =SUM(Y30:Y42) -> 4836778 | Z29: 0 | AA29: =X29+Y29 -> 28332026 | AC29: =AC30+AC32+AC33+AC34+AC35+AC36+AC37+AC38+AC39+AC40+AC41+AC42 -> 4599929 | AD29: 0 | AE29: =AA29+AC29 -> 32931955 | AG29: =AG30+AG32+AG33+AG34+AG35+AG36+AG37+AG38+AG39+AG40+AG41+AG42 -> 4419929 | AH29: 0 | AI29: =AE29+AG29 -> 37351884 | AK29: =AK30+AK32+AK33+AK34+AK35+AK36+AK37+AK38+AK39+AK40+AK41+AK42 -> 4419929 | AL29: 0 | AM29: =AI29+AK29 -> 41771813 | AO29: =AO30+AO32+AO33+AO34+AO35+AO36+AO37+AO38+AO39+AO40+AO41+AO42 -> 4469929 | AP29: 0 | AQ29: =AM29+AO29 -> 46241742 | AS29: =AS30+AS32+AS33+AS34+AS35+AS36+AS37+AS38+AS39+AS40+AS41+AS42 -> 3285180 | AT29: 0 | AU29: =AQ29+AS29 -> 49526922
A30: 510506 | B30: Sueldos | C30: 929368 | D30: 0 | E30: =+C30 -> 929368 | G30: 2643170 | H30: 0 | I30: =E30+G30 -> 3572538 | J30: 2841503 | K30: 0 | L30: =I30+J30 -> 6414041 | N30: 2841503 | O30: 0 | P30: =L30+N30 -> 9255544 | R30: 2841503 | S30: 0 | T30: =+P30+R30 -> 12097047 | V30: 2841503 | W30: 0 | X30: =T30+V30 -> 14938550 | Y30: 2841503 | Z30: 0 | AA30: =X30+Y30 -> 17780053 | AC30: 2841503 | AD30: 0 | AE30: =AA30+AC30 -> 20621556 | AG30: 2841503 | AH30: 0 | AI30: =AE30+AG30 -> 23463059 | AK30: 2841503 | AL30: 0 | AM30: =AI30+AK30 -> 26304562 | AO30: 2841503 | AP30: 0 | AQ30: =AM30+AO30 -> 29146065 | AS30: 1989052 | AT30: 0 | AU30: =AQ30+AS30 -> 31135117
A31: 5105 | B31: Horas extras | C31: 0 | D31: 0 | E31: 0 | G31: 0 | H31: 0 | I31: 0 | J31: 0 | K31: 0 | L31: 0 | N31: 0 | O31: 0 | P31: 0 | R31: 5000 | T31: =+P31+R31 -> 5000 | V31: 0
A32: 510527 | B32: Auxilio de transporte | C32: 0 | D32: 0 | E32: =+C32 -> 0 | G32: 74391 | H32: 0 | I32: =E32+G32 -> 74391 | J32: 97032 | K32: 0 | L32: =I32+J32 -> 171423 | N32: 97032 | O32: 0 | P32: =L32+N32 -> 268455 | R32: 97032 | S32: 0 | T32: =+P32+R32 -> 365487 | V32: 97032 | W32: 0 | X32: =T32+V32 -> 462519 | Y32: 97032 | Z32: 0 | AA32: =X32+Y32 -> 559551 | AC32: 97032 | AD32: 0 | AE32: =AA32+AC32 -> 656583 | AG32: 97032 | AH32: 0 | AI32: =AE32+AG32 -> 753615 | AK32: 97032 | AL32: 0 | AM32: =AI32+AK32 -> 850647 | AO32: 97032 | AP32: 0 | AQ32: =AM32+AO32 -> 947679 | AS32: 67922 | AT32: 0 | AU32: =AQ32+AS32 -> 1015601
A33: 510530 | B33: Cesantías | C33: 77416 | D33: 0 | E33: =+C33 -> 77416 | G33: 226373 | H33: 0 | I33: =E33+G33 -> 303789 | J33: 244780 | K33: 0 | L33: =I33+J33 -> 548569 | N33: 244780 | O33: 0 | P33: =L33+N33 -> 793349 | R33: 244780 | S33: 0 | T33: =+P33+R33 -> 1038129 | V33: 244780 | W33: 0 | X33: =T33+V33 -> 1282909 | Y33: 244780 | Z33: 0 | AA33: =X33+Y33 -> 1527689 | AC33: 244780 | AD33: 0 | AE33: =AA33+AC33 -> 1772469 | AG33: 244780 | AH33: 0 | AI33: =AE33+AG33 -> 2017249 | AK33: 244780 | AL33: 0 | AM33: =AI33+AK33 -> 2262029 | AO33: 244780 | AP33: 0 | AQ33: =AM33+AO33 -> 2506809 | AS33: 244780 | AT33: 0 | AU33: =AQ33+AS33 -> 2751589
A34: 510533 | B34: Intereses sobre cesantías | C34: 9289 | D34: 0 | E34: =+C34 -> 9289 | G34: 27176 | H34: 0 | I34: =E34+G34 -> 36465 | J34: 29385 | K34: 0 | L34: =I34+J34 -> 65850 | N34: 29385 | O34: 0 | P34: =L34+N34 -> 95235 | R34: 29385 | S34: 0 | T34: =+P34+R34 -> 124620 | V34: 29385 | W34: 0 | X34: =T34+V34 -> 154005 | Y34: 29385 | Z34: 0 | AA34: =X34+Y34 -> 183390 | AC34: 29385 | AD34: 0 | AE34: =AA34+AC34 -> 212775 | AG34: 29385 | AH34: 0 | AI34: =AE34+AG34 -> 242160 | AK34: 29385 | AL34: 0 | AM34: =AI34+AK34 -> 271545 | AO34: 29385 | AP34: 0 | AQ34: =AM34+AO34 -> 300930 | AS34: 29385 | AT34: 0 | AU34: =AQ34+AS34 -> 330315
A35: 510536 | B35: Prima de servicios | C35: 77416 | D35: 0 | E35: =+C35 -> 77416 | G35: 110220 | H35: 0 | I35: =E35+G35 -> 187636 | J35: 118491 | K35: 0 | L35: =I35+J35 -> 306127 | N35: 118491 | O35: 0 | P35: =L35+N35 -> 424618 | R35: 118491 | S35: 0 | T35: =+P35+R35 -> 543109 | V35: 118491 | W35: 0 | X35: =T35+V35 -> 661600 | Y35: 118491 | Z35: 0 | AA35: =X35+Y35 -> 780091 | AC35: 118491 | AD35: 0 | AE35: =AA35+AC35 -> 898582 | AG35: 118491 | AH35: 0 | AI35: =AE35+AG35 -> 1017073 | AK35: 118491 | AL35: 0 | AM35: =AI35+AK35 -> 1135564 | AO35: 118491 | AP35: 0 | AQ35: =AM35+AO35 -> 1254055 | AS35: 118491 | AT35: 0 | AU35: =AQ35+AS35 -> 1372546
A36: 510539 | B36: Vacaciones | C36: 38755 | D36: 0 | E36: =+C36 -> 38755 | G36: 226373 | H36: 0 | I36: =E36+G36 -> 265128 | J36: 244780 | K36: 0 | L36: =I36+J36 -> 509908 | N36: 244780 | O36: 0 | P36: =L36+N36 -> 754688 | R36: 244780 | S36: 0 | T36: =+P36+R36 -> 999468 | V36: 244780 | W36: 0 | X36: =T36+V36 -> 1244248 | Y36: 244780 | Z36: 0 | AA36: =X36+Y36 -> 1489028 | AC36: 244780 | AD36: 0 | AE36: =AA36+AC36 -> 1733808 | AG36: 244780 | AH36: 0 | AI36: =AE36+AG36 -> 1978588 | AK36: 244780 | AL36: 0 | AM36: =AI36+AK36 -> 2223368 | AO36: 244780 | AP36: 0 | AQ36: =AM36+AO36 -> 2468148 | AS36: 244780 | AT36: 0 | AU36: =AQ36+AS36 -> 2712928
A37: 510545 | B37: Auxilios | C37: 149248 | D37: 0 | E37: =+C37 -> 149248 | G37: 319818 | H37: 0 | I37: =E37+G37 -> 469066 | J37: 319818 | K37: 0 | L37: =I37+J37 -> 788884 | N37: 319818 | O37: 0 | P37: =L37+N37 -> 1108702 | R37: 319818 | S37: 0 | T37: =+P37+R37 -> 1428520 | V37: 319818 | W37: 0 | X37: =T37+V37 -> 1748338 | Y37: 319818 | Z37: 0 | AA37: =X37+Y37 -> 2068156 | AC37: 319818 | AD37: 0 | AE37: =AA37+AC37 -> 2387974 | AG37: 319818 | AH37: 0 | AI37: =AE37+AG37 -> 2707792 | AK37: 319818 | AL37: 0 | AM37: =AI37+AK37 -> 3027610 | AO37: 319818 | AP37: 0 | AQ37: =AM37+AO37 -> 3347428 | AS37: 223873 | AT37: 0 | AU37: =AQ37+AS37 -> 3571301
A38: 510551 | B38: Dotación y elementos seguridad trabajadores | C38: 0 | D38: 0 | E38: =+C38 -> 0 | H38: 0 | I38: =E38+G38 -> 0 | J38: 19861 | K38: 0 | L38: =I38+J38 -> 19861 | N38: 0 | O38: 0 | P38: =L38+N38 -> 19861 | R38: 60000 | S38: 0 | T38: =+P38+R38 -> 79861 | V38: 0 | W38: 0 | X38: =T38+V38 -> 79861 | Y38: 416849 | Z38: 0 | AA38: =X38+Y38 -> 496710 | AC38: 180000 | AD38: 0 | AE38: =AA38+AC38 -> 676710 | AH38: 0 | AI38: =AE38+AG38 -> 676710 | AK38: 0 | AL38: 0 | AM38: =AI38+AK38 -> 676710 | AO38: 50000 | AP38: 0 | AQ38: =AM38+AO38 -> 726710 | AS38: 0 | AT38: 0 | AU38: =AQ38+AS38 -> 726710
A39: 510568 | B39: Aportes a administradoras de riesgos profesionales arp | C39: 9500 | D39: 0 | E39: =+C39 -> 9500 | G39: 64500 | H39: 0 | I39: =E39+G39 -> 74000 | J39: 69400 | K39: 0 | L39: =I39+J39 -> 143400 | N39: 69400 | O39: 0 | P39: =L39+N39 -> 212800 | R39: 69400 | S39: 0 | T39: =+P39+R39 -> 282200 | V39: 69400 | W39: 0 | X39: =T39+V39 -> 351600 | Y39: 69400 | Z39: 0 | AA39: =X39+Y39 -> 421000 | AC39: 69400 | AD39: 0 | AE39: =AA39+AC39 -> 490400 | AG39: 69400 | AH39: 0 | AI39: =AE39+AG39 -> 559800 | AK39: 69400 | AL39: 0 | AM39: =AI39+AK39 -> 629200 | AO39: 69400 | AP39: 0 | AQ39: =AM39+AO39 -> 698600 | AS39: 48579 | AT39: 0 | AU39: =AQ39+AS39 -> 747179
A40: 510569 | B40: Aportes a entidades promotoras de salud eps | C40: 0 | D40: 0 | E40: =+C40 -> 0 | G40: 0 | H40: 0 | I40: =E40+G40 -> 0 | J40: 0 | K40: 0 | L40: =I40+J40 -> 0 | N40: 0 | O40: 0 | P40: =L40+N40 -> 0 | R40: 0 | S40: 0 | T40: =+P40+R40 -> 0 | V40: 0 | W40: 0 | X40: =T40+V40 -> 0 | Y40: 0 | Z40: 0 | AA40: =X40+Y40 -> 0 | AC40: 0 | AD40: 0 | AE40: =AA40+AC40 -> 0 | AG40: 0 | AH40: 0 | AI40: =AE40+AG40 -> 0 | AK40: 0 | AL40: 0 | AM40: =AI40+AK40 -> 0 | AO40: 0 | AP40: 0 | AQ40: =AM40+AO40 -> 0 | AS40: 0 | AT40: 0 | AU40: =AQ40+AS40 -> 0
A41: 510570 | B41: Aportes a fondos de pensiones y/o cesantías | C41: 232000 | D41: 0 | E41: =+C41 -> 232000 | G41: 332458 | H41: 0 | I41: =E41+G41 -> 564458 | J41: 341040 | K41: 0 | L41: =I41+J41 -> 905498 | N41: 341040 | O41: 0 | P41: =L41+N41 -> 1246538 | R41: 341040 | S41: 0 | T41: =+P41+R41 -> 1587578 | V41: 341040 | W41: 0 | X41: =T41+V41 -> 1928618 | Y41: 341040 | Z41: 0 | AA41: =X41+Y41 -> 2269658 | AC41: 341040 | AD41: 0 | AE41: =AA41+AC41 -> 2610698 | AG41: 341040 | AH41: 0 | AI41: =AE41+AG41 -> 2951738 | AK41: 341040 | AL41: 0 | AM41: =AI41+AK41 -> 3292778 | AO41: 341040 | AP41: 0 | AQ41: =AM41+AO41 -> 3633818 | AS41: 238728 | AT41: 0 | AU41: =AQ41+AS41 -> 3872546
A42: 510572 | B42: Aportes cajas de compensación familiar | C42: 77400 | D42: 0 | E42: =+C42 -> 77400 | G42: 105800 | H42: 0 | I42: =E42+G42 -> 183200 | J42: 113700 | K42: 0 | L42: =I42+J42 -> 296900 | N42: 113700 | O42: 0 | P42: =L42+N42 -> 410600 | R42: 113700 | S42: 0 | T42: =+P42+R42 -> 524300 | V42: 113700 | W42: 0 | X42: =T42+V42 -> 638000 | Y42: 113700 | Z42: 0 | AA42: =X42+Y42 -> 751700 | AC42: 113700 | AD42: 0 | AE42: =AA42+AC42 -> 865400 | AG42: 113700 | AH42: 0 | AI42: =AE42+AG42 -> 979100 | AK42: 113700 | AL42: 0 | AM42: =AI42+AK42 -> 1092800 | AO42: 113700 | AP42: 0 | AQ42: =AM42+AO42 -> 1206500 | AS42: 79590 | AT42: 0 | AU42: =AQ42+AS42 -> 1286090
A44: 5110 | B44: Honorarios | C44: =C46 -> 300000 | D44: 0 | E44: =+C44 -> 300000 | G44: =G46 -> 300000 | H44: 0 | I44: =E44+G44 -> 600000 | J44: 300000 | K44: 0 | L44: =I44+J44 -> 900000 | N44: =N46 -> 300000 | O44: 0 | P44: =L44+N44 -> 1200000 | R44: =+R46+R47 -> 500000 | S44: 0 | T44: =+T46+T47 -> 1700000 | V44: =V46 -> 300000 | W44: 0 | X44: =T44+V44 -> 2000000 | Y44: 300000 | Z44: 0 | AA44: =X44+Y44 -> 2300000 | AC44: =AC46 -> 300000 | AD44: 0 | AE44: =AA44+AC44 -> 2600000 | AG44: =AG46 -> 300000 | AH44: 0 | AI44: =AE44+AG44 -> 2900000 | AK44: =AK46 -> 300000 | AL44: 0 | AM44: =AI44+AK44 -> 3200000 | AO44: =AO46 -> 300000 | AP44: 0 | AQ44: =AM44+AO44 -> 3500000 | AS44: =AS46 -> 300000 | AT44: 0 | AU44: =AQ44+AS44 -> 3800000
A45: 511025 | B45: Asesoria Juridica | C45: 0 | D45: 0 | E45: =+C45 -> 0 | G45: 0 | H45: 0 | I45: =E45+G45 -> 0 | J45: 0 | K45: 0 | L45: =I45+J45 -> 0 | N45: 0 | O45: 0 | P45: =L45+N45 -> 0 | R45: 0 | S45: 0 | T45: =+P45+R45 -> 0 | V45: 0 | W45: 0 | X45: =T45+V45 -> 0 | Y45: 0 | Z45: 0 | AA45: =X45+Y45 -> 0 | AC45: 0 | AD45: 0 | AE45: =AA45+AC45 -> 0 | AG45: 0 | AH45: 0 | AI45: =AE45+AG45 -> 0 | AK45: 0 | AL45: 0 | AM45: =AI45+AK45 -> 0 | AO45: 0 | AP45: 0 | AQ45: =AM45+AO45 -> 0 | AS45: 0 | AT45: 0 | AU45: =AQ45+AS45 -> 0
A46: 511030 | B46: Asesoría financiera | C46: 300000 | D46: 0 | E46: =+C46 -> 300000 | G46: 300000 | H46: 0 | I46: =E46+G46 -> 600000 | J46: 300000 | K46: 0 | L46: =I46+J46 -> 900000 | N46: 300000 | O46: 0 | P46: =L46+N46 -> 1200000 | R46: 300000 | S46: 0 | T46: =+P46+R46 -> 1500000 | V46: 300000 | W46: 0 | X46: =T46+V46 -> 1800000 | Y46: 300000 | Z46: 0 | AA46: =X46+Y46 -> 2100000 | AC46: 300000 | AD46: 0 | AE46: =AA46+AC46 -> 2400000 | AG46: 300000 | AH46: 0 | AI46: =AE46+AG46 -> 2700000 | AK46: 300000 | AL46: 0 | AM46: =AI46+AK46 -> 3000000 | AO46: 300000 | AP46: 0 | AQ46: =AM46+AO46 -> 3300000 | AS46: 300000 | AT46: 0 | AU46: =AQ46+AS46 -> 3600000
A47: 511095 | B47: EXOGENA | R47: 200000 | T47: =+P47+R47 -> 200000 | X47: =T47+V47 -> 200000 | AA47: =X47+Y47 -> 200000 | AE47: =AA47+AC47 -> 200000 | AI47: =AE47+AG47 -> 200000 | AM47: =AI47+AK47 -> 200000 | AQ47: =AM47+AO47 -> 200000 | AU47: =AQ47+AS47 -> 200000
A49: 5115 | B49: Impuestos | C49: =+C50+C51+C52 -> 2464000 | D49: 0 | E49: =+C49 -> 2464000 | G49: =G52 -> 0 | H49: 0 | I49: =E49+G49 -> 2464000 | J49: =+J52 -> 50580 | K49: 0 | L49: =I49+J49 -> 2514580 | N49: =+N53 -> 2000 | O49: 0 | P49: =L49+N49 -> 2516580 | R49: =+R50+R51+R52+R53 -> 136030 | S49: 0 | T49: =+P49+R49 -> 2652610 | V49: =V52 -> 0 | W49: 0 | X49: =T49+V49 -> 2652610 | Y49: 0 | Z49: 0 | AA49: =X49+Y49 -> 2652610 | AC49: =+AC53 -> 0 | AD49: 0 | AE49: =AA49+AC49 -> 2652610 | AG49: =+AG53 -> 0 | AH49: 0 | AI49: =AE49+AG49 -> 2652610 | AK49: =+AK53 -> 0 | AL49: 0 | AM49: =AI49+AK49 -> 2652610 | AO49: =+AO53 -> 0 | AP49: 0 | AQ49: =AM49+AO49 -> 2652610 | AS49: =+AS50 -> 315000 | AT49: 0 | AU49: =AQ49+AS49 -> 2967610
A50: 511505 | B50: Insdustria y Comercio | C50: 0 | D50: 0 | E50: =+C50 -> 0 | G50: 0 | H50: 0 | I50: =E50+G50 -> 0 | J50: 0 | K50: 0 | L50: =I50+J50 -> 0 | N50: 0 | O50: 0 | P50: =L50+N50 -> 0 | R50: 136000 | S50: 0 | T50: =+P50+R50 -> 136000 | V50: 0 | W50: 0 | X50: =T50+V50 -> 136000 | Y50: 0 | Z50: 0 | AA50: =X50+Y50 -> 136000 | AC50: 0 | AD50: 0 | AE50: =AA50+AC50 -> 136000 | AG50: 0 | AH50: 0 | AI50: =AE50+AG50 -> 136000 | AK50: 0 | AL50: 0 | AM50: =AI50+AK50 -> 136000 | AO50: 0 | AP50: 0 | AQ50: =AM50+AO50 -> 136000 | AS50: 315000 | AT50: 0 | AU50: =AQ50+AS50 -> 451000
A51: 511515 | B51: A la propiedad raiz | C51: 1832000 | D51: 0 | E51: =+C51 -> 1832000 | G51: 0 | H51: 0 | I51: =E51+G51 -> 1832000 | J51: 0 | K51: 0 | L51: =I51+J51 -> 1832000 | N51: 0 | O51: 0 | P51: =L51+N51 -> 1832000 | R51: 0 | S51: 0 | T51: =+P51+R51 -> 1832000 | V51: 0 | W51: 0 | X51: =T51+V51 -> 1832000 | Y51: 0 | Z51: 0 | AA51: =X51+Y51 -> 1832000 | AC51: 0 | AD51: 0 | AE51: =AA51+AC51 -> 1832000 | AG51: 0 | AH51: 0 | AI51: =AE51+AG51 -> 1832000 | AK51: 0 | AL51: 0 | AM51: =AI51+AK51 -> 1832000 | AO51: 0 | AP51: 0 | AQ51: =AM51+AO51 -> 1832000 | AS51: 0 | AT51: 0 | AU51: =AQ51+AS51 -> 1832000
A52: 511540 | B52: De vehículos | C52: 632000 | D52: 0 | E52: =+C52 -> 632000 | G52: 0 | H52: 0 | I52: =E52+G52 -> 632000 | J52: 50580 | K52: 0 | L52: =I52+J52 -> 682580 | N52: 0 | O52: 0 | P52: =L52+N52 -> 682580 | R52: 0 | S52: 0 | T52: =+P52+R52 -> 682580 | V52: 0 | W52: 0 | X52: =T52+V52 -> 682580 | Y52: 0 | Z52: 0 | AA52: =X52+Y52 -> 682580 | AC52: 0 | AD52: 0 | AE52: =AA52+AC52 -> 682580 | AG52: 0 | AH52: 0 | AI52: =AE52+AG52 -> 682580 | AK52: 0 | AL52: 0 | AM52: =AI52+AK52 -> 682580 | AO52: 0 | AP52: 0 | AQ52: =AM52+AO52 -> 682580 | AS52: 0 | AT52: 0 | AU52: =AQ52+AS52 -> 682580
A53: 511595 | B53: Otros | C53: 0 | E53: =+C53 -> 0 | I53: =E53+G53 -> 0 | L53: =I53+J53 -> 0 | N53: 2000 | P53: =L53+N53 -> 2000 | R53: 30 | T53: =+P53+R53 -> 2030 | X53: =T53+V53 -> 2030 | AA53: =X53+Y53 -> 2030 | AC53: 0 | AE53: =AA53+AC53 -> 2030 | AG53: 0 | AI53: =AE53+AG53 -> 2030 | AK53: 0 | AM53: =AI53+AK53 -> 2030 | AO53: 0 | AQ53: =AM53+AO53 -> 2030 | AS53: 0 | AU53: =AQ53+AS53 -> 2030
A55: 5120 | B55: Arrendamientos | C55: =+C56 -> 1000000 | D55: 0 | E55: =+C55 -> 1000000 | G55: =+G56+G57 -> 1021000 | H55: 0 | I55: =E55+G55 -> 2021000 | J55: =+J56+J60 -> 1000000 | K55: 0 | L55: =I55+J55 -> 3021000 | N55: =N56+N57 -> 1806723 | O55: 0 | P55: =L55+N55 -> 4827723 | R55: =+R56+R57 -> 2080000 | S55: 0 | T55: =+P55+R55 -> 6907723 | V55: =V56 -> 1000000 | W55: 0 | X55: =T55+V55 -> 7907723 | Y55: =+Y56+Y57 -> 1046100 | Z55: 0 | AA55: =X55+Y55 -> 8953823 | AC55: =AC56+AC57 -> 1000000 | AD55: 0 | AE55: =AA55+AC55 -> 9953823 | AG55: =AG56+AG57 -> 1000000 | AH55: 0 | AI55: =AE55+AG55 -> 10953823 | AK55: =AK56+AK57 -> 1000000 | AL55: 0 | AM55: =AI55+AK55 -> 11953823 | AO55: =AO56+AO57 -> 1000000 | AP55: 0 | AQ55: =AM55+AO55 -> 12953823 | AS55: =AS56+AS57 -> 1000000 | AT55: 0 | AU55: =AQ55+AS55 -> 13953823
A56: 512010 | B56: Construcciones y edificaciones | C56: 1000000 | D56: 0 | E56: =+C56 -> 1000000 | G56: 1000000 | H56: 0 | I56: =E56+G56 -> 2000000 | J56: 1000000 | K56: 0 | L56: =I56+J56 -> 3000000 | N56: 1000000 | O56: 0 | P56: =L56+N56 -> 4000000 | R56: 1000000 | S56: 0 | T56: =+P56+R56 -> 5000000 | V56: 1000000 | W56: 0 | X56: =T56+V56 -> 6000000 | Y56: 1000000 | Z56: 0 | AA56: =X56+Y56 -> 7000000 | AC56: 1000000 | AD56: 0 | AE56: =AA56+AC56 -> 8000000 | AG56: 1000000 | AH56: 0 | AI56: =AE56+AG56 -> 9000000 | AK56: 1000000 | AL56: 0 | AM56: =AI56+AK56 -> 10000000 | AO56: 1000000 | AP56: 0 | AQ56: =AM56+AO56 -> 11000000 | AS56: 1000000 | AT56: 0 | AU56: =AQ56+AS56 -> 12000000
A57: 512015 | B57: Maquinaria y equipo | C57: 0 | D57: 0 | E57: =+C57 -> 0 | G57: 21000 | I57: =E57+G57 -> 21000 | J57: 0 | K57: 0 | L57: =I57+J57 -> 21000 | N57: 806723 | P57: =L57+N57 -> 827723 | R57: 1080000 | S57: 0 | T57: =+P57+R57 -> 1907723 | V57: 0 | X57: =T57+V57 -> 1907723 | Y57: 46100 | Z57: 0 | AA57: =X57+Y57 -> 1953823 | AC57: 0 | AE57: =AA57+AC57 -> 1953823 | AG57: 0 | AI57: =AE57+AG57 -> 1953823 | AK57: 0 | AM57: =AI57+AK57 -> 1953823 | AO57: 0 | AQ57: =AM57+AO57 -> 1953823 | AS57: 0 | AU57: =AQ57+AS57 -> 1953823
L58: =I58+J58 -> 0 | AA58: =X58+Y58 -> 0
A59: 5125 | B59: AFILIACIONES Y CONTRIBUCIONES | C59: =+C60 -> 130000 | E59: =+E60 -> 130000 | I59: =E59+G59 -> 130000 | J59: =+J60 -> 0 | L59: =I59+J59 -> 130000 | N59: 0 | P59: =L59+N59 -> 130000 | R59: =+R60 -> 0 | T59: =+P59+R59 -> 130000 | X59: =T59+V59 -> 130000 | Y59: =+Y60 -> 0 | AA59: =X59+Y59 -> 130000 | AC59: 0 | AE59: =AA59+AC59 -> 130000 | AG59: 0 | AI59: =AE59+AG59 -> 130000 | AK59: 0 | AM59: =AI59+AK59 -> 130000 | AO59: 0 | AQ59: =AM59+AO59 -> 130000 | AS59: 0 | AU59: =AQ59+AS59 -> 130000
A60: 512510 | B60: Afiliaciones | C60: 130000 | D60: 0 | E60: =+C60 -> 130000 | I60: =E60+G60 -> 130000 | J60: 0 | L60: =I60+J60 -> 130000 | N60: 0 | P60: =L60+N60 -> 130000 | R60: 0 | S60: 0 | T60: =+P60+R60 -> 130000 | X60: =T60+V60 -> 130000 | Y60: 0 | AA60: =X60+Y60 -> 130000 | AC60: 0 | AE60: =AA60+AC60 -> 130000 | AG60: 0 | AI60: =AE60+AG60 -> 130000 | AK60: 0 | AM60: =AI60+AK60 -> 130000 | AO60: 0 | AQ60: =AM60+AO60 -> 130000 | AS60: 0 | AU60: =AQ60+AS60 -> 130000
A62: 5130 | B62: Seguros | C62: =+C63 -> 0 | D62: 0 | E62: =+C62 -> 0 | G62: =G63 -> 0 | H62: 0 | I62: =E62+G62 -> 0 | J62: =J63 -> 0 | K62: 0 | L62: =I62+J62 -> 0 | N62: =N63 -> 0 | O62: 0 | P62: =L62+N62 -> 0 | R62: =+R63 -> 0 | S62: 0 | T62: =+R62 -> 0 | V62: =V63 -> 0 | W62: 0 | X62: =T62+V62 -> 0 | Y62: =Y63 -> 0 | Z62: 0 | AA62: =X62+Y62 -> 0 | AC62: =AC63 -> 0 | AD62: 0 | AE62: =AA62+AC62 -> 0 | AG62: =AG63 -> 0 | AH62: 0 | AI62: =AE62+AG62 -> 0 | AK62: =AK63 -> 0 | AL62: 0 | AM62: =AI62+AK62 -> 0 | AO62: =AO63 -> 0 | AP62: 0 | AQ62: =AM62+AO62 -> 0 | AS62: =AS63 -> 0 | AT62: 0 | AU62: =AQ62+AS62 -> 0
A63: 513095 | B63: Otros | C63: 0 | D63: 0 | E63: =+C63 -> 0 | G63: 0 | H63: 0 | I63: =E63+G63 -> 0 | J63: 0 | K63: 0 | L63: =I63+J63 -> 0 | N63: 0 | O63: 0 | P63: =L63+N63 -> 0 | R63: 0 | S63: 0 | T63: =+R63 -> 0 | V63: 0 | W63: 0 | X63: =T63+V63 -> 0 | Y63: 0 | Z63: 0 | AA63: =X63+Y63 -> 0 | AC63: 0 | AD63: 0 | AE63: =AA63+AC63 -> 0 | AG63: 0 | AH63: 0 | AI63: =AE63+AG63 -> 0 | AK63: 0 | AL63: 0 | AM63: =AI63+AK63 -> 0 | AO63: 0 | AP63: 0 | AQ63: =AM63+AO63 -> 0 | AS63: 0 | AT63: 0 | AU63: =AQ63+AS63 -> 0
A65: 5135 | B65: Servicios | C65: =C66+C67+C68+C69+C70+C72+C71 -> 1729670 | D65: 0 | E65: =+C65 -> 1729670 | G65: =G66+G67+G68+G69+G70+G73 -> 1574494 | H65: 0 | I65: =E65+G65 -> 3304164 | J65: =J66+J67+J68+J69+J70 -> 1593698 | K65: 0 | L65: =I65+J65 -> 4897862 | N65: =SUM(N66:N73) -> 1221247 | O65: 0 | P65: =L65+N65 -> 6119109 | R65: =R66+R67+R68+R69+R70+R72+R71 -> 1986125 | S65: 0 | T65: =+P65+R65 -> 8105234 | V65: =V66+V67+V68+V69+V70+V73 -> 1898251 | W65: 0 | X65: =T65+V65 -> 10003485 | Y65: =SUM(Y66:Y73) -> 1813459 | Z65: 0 | AA65: =X65+Y65 -> 11816944 | AC65: =SUM(AC66:AC73) -> 1730830 | AD65: 0 | AE65: =AA65+AC65 -> 13547774 | AG65: =SUM(AG66:AG73) -> 1661657 | AH65: 0 | AI65: =AE65+AG65 -> 15209431 | AK65: =SUM(AK66:AK73) -> 2747607 | AL65: 0 | AM65: =AI65+AK65 -> 17957038 | AO65: =SUM(AO66:AO73) -> 2532985 | AP65: 0 | AQ65: =AM65+AO65 -> 20490023 | AS65: =SUM(AS66:AS73) -> 863540 | AT65: 0 | AU65: =AQ65+AS65 -> 21353563
A66: 513505 | B66: Aseo y vigilancia | C66: 30000 | D66: 0 | E66: =+C66 -> 30000 | G66: 30000 | H66: 0 | I66: =E66+G66 -> 60000 | J66: 0 | K66: 0 | L66: =I66+J66 -> 60000 | N66: 30000 | O66: 0 | P66: =L66+N66 -> 90000 | R66: 0 | S66: 0 | T66: =+P66+R66 -> 90000 | V66: 35000 | W66: 0 | X66: =T66+V66 -> 125000 | Y66: 30000 | Z66: 0 | AA66: =X66+Y66 -> 155000 | AC66: 30000 | AD66: 0 | AE66: =AA66+AC66 -> 185000 | AG66: 50000 | AH66: 0 | AI66: =AE66+AG66 -> 235000 | AK66: 30000 | AL66: 0 | AM66: =AI66+AK66 -> 265000 | AO66: 0 | AP66: 0 | AQ66: =AM66+AO66 -> 265000 | AS66: 30000 | AT66: 0 | AU66: =AQ66+AS66 -> 295000
A67: 513510 | B67: Temporales | C67: 1307000 | D67: 0 | E67: =+C67 -> 1307000 | G67: 705000 | H67: 0 | I67: =E67+G67 -> 2012000 | J67: 925000 | K67: 0 | L67: =I67+J67 -> 2937000 | N67: 537000 | O67: 0 | P67: =L67+N67 -> 3474000 | R67: 1520000 | S67: 0 | T67: =+P67+R67 -> 4994000 | V67: 1312000 | W67: 0 | X67: =T67+V67 -> 6306000 | Y67: 1150000 | Z67: 0 | AA67: =X67+Y67 -> 7456000 | AC67: 1235000 | AD67: 0 | AE67: =AA67+AC67 -> 8691000 | AG67: 1155000 | AH67: 0 | AI67: =AE67+AG67 -> 9846000 | AK67: 1827500 | AL67: 0 | AM67: =AI67+AK67 -> 11673500 | AO67: 1635000 | AP67: 0 | AQ67: =AM67+AO67 -> 13308500 | AS67: 655000 | AT67: 0 | AU67: =AQ67+AS67 -> 13963500
A68: 513525 | B68: Acueducto y alcantarillado | C68: 47820 | D68: 0 | E68: =+C68 -> 47820 | G68: 51390 | H68: 0 | I68: =E68+G68 -> 99210 | J68: 51770 | K68: 0 | L68: =I68+J68 -> 150980 | N68: 46090 | O68: 0 | P68: =L68+N68 -> 197070 | R68: 46070 | S68: 0 | T68: =+P68+R68 -> 243140 | V68: 57670 | W68: 0 | X68: =T68+V68 -> 300810 | Y68: 58770 | Z68: 0 | AA68: =X68+Y68 -> 359580 | AC68: 58840 | AD68: 0 | AE68: =AA68+AC68 -> 418420 | AG68: 59020 | AH68: 0 | AI68: =AE68+AG68 -> 477440 | AK68: 60570 | AL68: 0 | AM68: =AI68+AK68 -> 538010 | AO68: 61320 | AP68: 0 | AQ68: =AM68+AO68 -> 599330 | AS68: 61850 | AT68: 0 | AU68: =AQ68+AS68 -> 661180
A69: 513530 | B69: Energía eléctrica | C69: 66500 | D69: 0 | E69: =+C69 -> 66500 | G69: 68500 | H69: 0 | I69: =E69+G69 -> 135000 | J69: 89091 | K69: 0 | L69: =I69+J69 -> 224091 | N69: 68513 | O69: 0 | P69: =L69+N69 -> 292604 | R69: 70858 | S69: 0 | T69: =+P69+R69 -> 363462 | V69: 86600 | W69: 0 | X69: =T69+V69 -> 450062 | Y69: 82806 | Z69: 0 | AA69: =X69+Y69 -> 532868 | AC69: 93107 | AD69: 0 | AE69: =AA69+AC69 -> 625975 | AG69: 90374 | AH69: 0 | AI69: =AE69+AG69 -> 716349 | AK69: 90918 | AL69: 0 | AM69: =AI69+AK69 -> 807267 | AO69: 104676 | AP69: 0 | AQ69: =AM69+AO69 -> 911943 | AS69: 116690 | AT69: 0 | AU69: =AQ69+AS69 -> 1028633
A70: 513535 | B70: Teléfono fijo y moviles | C70: 268350 | D70: 0 | E70: =+C70 -> 268350 | G70: 719604 | H70: 0 | I70: =E70+G70 -> 987954 | J70: 527837 | K70: 0 | L70: =I70+J70 -> 1515791 | N70: 317644 | O70: 0 | P70: =L70+N70 -> 1833435 | R70: 349197 | S70: 0 | T70: =+P70+R70 -> 2182632 | V70: 326981 | W70: 0 | X70: =T70+V70 -> 2509613 | Y70: 311883 | Z70: 0 | AA70: =X70+Y70 -> 2821496 | AC70: 313883 | AD70: 0 | AE70: =AA70+AC70 -> 3135379 | AG70: 307263 | AH70: 0 | AI70: =AE70+AG70 -> 3442642 | AK70: 338619 | AL70: 0 | AM70: =AI70+AK70 -> 3781261 | AO70: 415989 | AP70: 0 | AQ70: =AM70+AO70 -> 4197250 | AS70: 0 | AT70: 0 | AU70: =AQ70+AS70 -> 4197250
A71: 513540 | B71: Correo portes y telegrama | C71: 10000 | D71: 0 | E71: =+C71 -> 10000 | G71: 0 | H71: 0 | I71: =E71+G71 -> 10000 | J71: 0 | K71: 0 | L71: =I71+J71 -> 10000 | N71: 0 | O71: 0 | P71: =L71+N71 -> 10000 | R71: 0 | S71: 0 | T71: =+P71+R71 -> 10000 | V71: 0 | W71: 0 | X71: =T71+V71 -> 10000 | Y71: 0 | Z71: 0 | AA71: =X71+Y71 -> 10000 | AC71: 0 | AD71: 0 | AE71: =AA71+AC71 -> 10000 | AG71: 0 | AH71: 0 | AI71: =AE71+AG71 -> 10000 | AK71: 0 | AL71: 0 | AM71: =AI71+AK71 -> 10000 | AO71: 0 | AP71: 0 | AQ71: =AM71+AO71 -> 10000 | AS71: 0 | AT71: 0 | AU71: =AQ71+AS71 -> 10000
A72: 513595 | B72: Otros | C72: 0 | D72: 0 | E72: =+C72 -> 0 | G72: 0 | H72: 0 | I72: =E72+G72 -> 0 | J72: 0 | K72: 0 | L72: =I72+J72 -> 0 | N72: 0 | O72: 0 | P72: =L72+N72 -> 0 | R72: 0 | S72: 0 | T72: =+P72+R72 -> 0 | V72: 0 | W72: 0 | X72: =T72+V72 -> 0 | Y72: 0 | Z72: 0 | AA72: =X72+Y72 -> 0 | AC72: 0 | AD72: 0 | AE72: =AA72+AC72 -> 0 | AG72: 0 | AH72: 0 | AI72: =AE72+AG72 -> 0 | AK72: 0 | AL72: 0 | AM72: =AI72+AK72 -> 0 | AO72: 0 | AP72: 0 | AQ72: =AM72+AO72 -> 0 | AS72: 0 | AT72: 0 | AU72: =AQ72+AS72 -> 0
A73: 513550 | B73: Transportes, fletes y acarreos | C73: 0 | D73: 0 | E73: =+C73 -> 0 | G73: 0 | H73: 0 | I73: =E73+G73 -> 0 | J73: 0 | K73: 0 | L73: =I73+J73 -> 0 | N73: 222000 | O73: 0 | P73: =L73+N73 -> 222000 | R73: 0 | S73: 0 | T73: =+P73+R73 -> 222000 | V73: 80000 | W73: 0 | X73: =T73+V73 -> 302000 | Y73: 180000 | Z73: 0 | AA73: =X73+Y73 -> 482000 | AC73: 0 | AD73: 0 | AE73: =AA73+AC73 -> 482000 | AG73: 0 | AH73: 0 | AI73: =AE73+AG73 -> 482000 | AK73: 400000 | AL73: 0 | AM73: =AI73+AK73 -> 882000 | AO73: 316000 | AP73: 0 | AQ73: =AM73+AO73 -> 1198000 | AS73: 0 | AT73: 0 | AU73: =AQ73+AS73 -> 1198000
E74: =+C74 -> 0 | P74: =L74+N74 -> 0 | AE74: =AA74+AC74 -> 0 | AI74: =AE74+AG74 -> 0 | AM74: =AI74+AK74 -> 0 | AQ74: =AM74+AO74 -> 0 | AU74: =AQ74+AS74 -> 0
A75: 5140 | B75: Gastos legales | C75: 0 | D75: 0 | E75: =+C75 -> 0 | G75: =G77+G78 -> 5800 | H75: 0 | I75: =E75+G75 -> 5800 | J75: 0 | K75: 0 | L75: =I75+J75 -> 5800 | N75: =N77+N78 -> 1600136 | O75: 0 | P75: =L75+N75 -> 1605936 | R75: =+R77 -> 5800 | S75: 0 | T75: =+P75+R75 -> 1611736 | V75: =V77+V78 -> 0 | W75: 0 | X75: =T75+V75 -> 1611736 | Y75: =+Y77 -> 5800 | Z75: 0 | AA75: =X75+Y75 -> 1617536 | AC75: =AC77+AC78 -> 5800 | AD75: 0 | AE75: =AA75+AC75 -> 1623336 | AG75: =AG77+AG78 -> 5800 | AH75: 0 | AI75: =AE75+AG75 -> 1629136 | AK75: =+AK77+AK79 -> 22600 | AL75: 0 | AM75: =AI75+AK75 -> 1651736 | AO75: =AO77+AO78 -> 0 | AP75: 0 | AQ75: =AM75+AO75 -> 1651736 | AS75: =AS77+AS78 -> 0 | AT75: 0 | AU75: =AQ75+AS75 -> 1651736
A76: 514005 | B76: Notariales | C76: 0 | D76: 0 | E76: =+C76 -> 0 | G76: 0 | H76: 0 | I76: =E76+G76 -> 0 | J76: 0 | K76: 0 | L76: =I76+J76 -> 0 | N76: 0 | O76: 0 | P76: =L76+N76 -> 0 | S76: 0 | T76: =+P76+R76 -> 0 | V76: 0 | W76: 0 | X76: =T76+V76 -> 0 | Y76: 0 | Z76: 0 | AA76: =X76+Y76 -> 0 | AC76: 0 | AD76: 0 | AE76: =AA76+AC76 -> 0 | AG76: 0 | AH76: 0 | AI76: =AE76+AG76 -> 0 | AK76: 0 | AL76: 0 | AM76: =AI76+AK76 -> 0 | AO76: 0 | AP76: 0 | AQ76: =AM76+AO76 -> 0 | AS76: 0 | AT76: 0 | AU76: =AQ76+AS76 -> 0
A77: 514010 | B77: Registro mercantil | C77: 0 | D77: 0 | E77: =+C77 -> 0 | G77: 5800 | H77: 0 | I77: =E77+G77 -> 5800 | J77: 0 | K77: 0 | L77: =I77+J77 -> 5800 | N77: 1600136 | O77: 0 | P77: =L77+N77 -> 1605936 | R77: 5800 | S77: 0 | T77: =+P77+R77 -> 1611736 | V77: 0 | W77: 0 | X77: =T77+V77 -> 1611736 | Y77: 5800 | Z77: 0 | AA77: =X77+Y77 -> 1617536 | AC77: 5800 | AD77: 0 | AE77: =AA77+AC77 -> 1623336 | AG77: 5800 | AH77: 0 | AI77: =AE77+AG77 -> 1629136 | AK77: 5800 | AL77: 0 | AM77: =AI77+AK77 -> 1634936 | AO77: 0 | AP77: 0 | AQ77: =AM77+AO77 -> 1634936 | AS77: 0 | AT77: 0 | AU77: =AQ77+AS77 -> 1634936
A78: 514015 | B78: Trámites y licencias | C78: 0 | D78: 0 | E78: =+C78 -> 0 | G78: 0 | H78: 0 | I78: =E78+G78 -> 0 | J78: 0 | K78: 0 | L78: =I78+J78 -> 0 | N78: 0 | O78: 0 | P78: =L78+N78 -> 0 | R78: 0 | S78: 0 | T78: =+P78+R78 -> 0 | V78: 0 | W78: 0 | X78: =T78+V78 -> 0 | Y78: 0 | Z78: 0 | AA78: =X78+Y78 -> 0 | AC78: 0 | AD78: 0 | AE78: =AA78+AC78 -> 0 | AG78: 0 | AH78: 0 | AI78: =AE78+AG78 -> 0 | AK78: 0 | AL78: 0 | AM78: =AI78+AK78 -> 0 | AO78: 0 | AP78: 0 | AQ78: =AM78+AO78 -> 0 | AS78: 0 | AT78: 0 | AU78: =AQ78+AS78 -> 0
A79: 514095 | B79: Otros | C79: 0 | D79: 0 | E79: =+C79 -> 0 | G79: 0 | H79: 0 | I79: =E79+G79 -> 0 | J79: 0 | K79: 0 | L79: =I79+J79 -> 0 | N79: 0 | O79: 0 | P79: =L79+N79 -> 0 | R79: 0 | S79: 0 | T79: =+P79+R79 -> 0 | V79: 0 | W79: 0 | X79: =T79+V79 -> 0 | Y79: 0 | Z79: 0 | AA79: =X79+Y79 -> 0 | AC79: 0 | AD79: 0 | AE79: =AA79+AC79 -> 0 | AG79: 0 | AH79: 0 | AI79: =AE79+AG79 -> 0 | AK79: 16800 | AL79: 0 | AM79: =AI79+AK79 -> 16800 | AO79: 0 | AP79: 0 | AQ79: =AM79+AO79 -> 16800 | AS79: 0 | AT79: 0 | AU79: =AQ79+AS79 -> 16800
E80: =+C80 -> 0 | T80: =+P80+R80 -> 0
A81: 5145 | B81: Mantenimiento y reparaciones | C81: =+C82+C83+C84+C85 -> 283680 | D81: 0 | E81: =+C81 -> 283680 | G81: =G82+G83+G85 -> 506400 | H81: 0 | I81: =E81+G81 -> 790080 | J81: =+J82+J83+J84+J85 -> 160403 | K81: 0 | L81: =I81+J81 -> 950483 | N81: =+N82+N83+N84+N85 -> 929362 | O81: 0 | P81: =L81+N81 -> 1879845 | R81: =+R82+R83+R84+R85 -> 244500 | S81: 0 | T81: =+P81+R81 -> 2124345 | V81: =V82+V83+V85 -> 120000 | W81: 0 | X81: =T81+V81 -> 2244345 | Y81: =+Y82+Y83+Y84+Y85 -> 263626 | Z81: 0 | AA81: =X81+Y81 -> 2507971 | AC81: =+AC82+AC83+AC84+AC85 -> 1332622 | AD81: 0 | AE81: =AA81+AC81 -> 3840593 | AG81: =+AG82+AG83+AG84+AG85 -> 1005135 | AH81: 0 | AI81: =AE81+AG81 -> 4845728 | AK81: =+AK82+AK83+AK84+AK85 -> 1377272 | AL81: 0 | AM81: =AI81+AK81 -> 6223000 | AO81: =+AO82+AO83+AO84+AO85 -> 198886 | AP81: 0 | AQ81: =AM81+AO81 -> 6421886 | AS81: =+AS82+AS83+AS84+AS85 -> 82142 | AT81: 0 | AU81: =AQ81+AS81 -> 6504028
A82: 514515 | B82: Maquinaria y equipo | C82: 208680 | D82: 0 | E82: =+C82 -> 208680 | G82: 506400 | H82: 0 | I82: =E82+G82 -> 715080 | J82: 1600 | K82: 0 | L82: =I82+J82 -> 716680 | N82: 214118 | O82: 0 | P82: =L82+N82 -> 930798 | R82: 184500 | S82: 0 | T82: =+P82+R82 -> 1115298 | V82: 120000 | W82: 0 | X82: =T82+V82 -> 1235298 | Y82: 263626 | Z82: 0 | AA82: =X82+Y82 -> 1498924 | AC82: 1124622 | AD82: 0 | AE82: =AA82+AC82 -> 2623546 | AG82: 3500 | AH82: 0 | AI82: =AE82+AG82 -> 2627046 | AK82: 1113491 | AL82: 0 | AM82: =AI82+AK82 -> 3740537 | AO82: 183886 | AP82: 0 | AQ82: =AM82+AO82 -> 3924423 | AS82: 82142 | AT82: 0 | AU82: =AQ82+AS82 -> 4006565
A83: 514520 | B83: Equipo de oficina | C83: 0 | D83: 0 | E83: =+C83 -> 0 | G83: 0 | H83: 0 | I83: =E83+G83 -> 0 | J83: 120190 | K83: 0 | L83: =I83+J83 -> 120190 | N83: 0 | O83: 0 | P83: =L83+N83 -> 120190 | R83: 0 | S83: 0 | T83: =+P83+R83 -> 120190 | V83: 0 | W83: 0 | X83: =T83+V83 -> 120190 | Y83: 0 | Z83: 0 | AA83: 120180 | AC83: 0 | AD83: 0 | AE83: =AA83+AC83 -> 120180 | AG83: 0 | AH83: 0 | AI83: =AE83+AG83 -> 120180 | AK83: 35714 | AL83: 0 | AM83: =AI83+AK83 -> 155894 | AO83: 0 | AP83: 0 | AQ83: =AM83+AO83 -> 155894 | AS83: 0 | AT83: 0 | AU83: =AQ83+AS83 -> 155894
A84: 514525 | B84: Equipo de computación y comunicación | C84: 0 | D84: 0 | E84: =+C84 -> 0 | G84: 0 | H84: 0 | I84: =E84+G84 -> 0 | J84: 0 | K84: 0 | L84: =I84+J84 -> 0 | N84: 0 | O84: 0 | P84: =L84+N84 -> 0 | R84: 60000 | S84: 0 | T84: =+P84+R84 -> 60000 | V84: 0 | W84: 0 | X84: =T84+V84 -> 60000 | Y84: 0 | Z84: 0 | AA84: =X84+Y84 -> 60000 | AC84: 0 | AD84: 0 | AE84: =AA84+AC84 -> 60000 | AG84: 332521 | AH84: 0 | AI84: =AE84+AG84 -> 392521 | AK84: 50000 | AL84: 0 | AM84: =AI84+AK84 -> 442521 | AO84: 0 | AP84: 0 | AQ84: =AM84+AO84 -> 442521 | AS84: 0 | AT84: 0 | AU84: =AQ84+AS84 -> 442521
A85: 514540 | B85: Flota y equipo de transportes | C85: 75000 | D85: 0 | E85: =+C85 -> 75000 | G85: 0 | H85: 0 | I85: =E85+G85 -> 75000 | J85: 38613 | K85: 0 | L85: =I85+J85 -> 113613 | N85: 715244 | O85: 0 | P85: =L85+N85 -> 828857 | R85: 0 | S85: 0 | T85: =+P85+R85 -> 828857 | V85: 0 | W85: 0 | X85: =T85+V85 -> 828857 | Y85: 0 | Z85: 0 | AA85: =X85+Y85 -> 828857 | AC85: 208000 | AD85: 0 | AE85: =AA85+AC85 -> 1036857 | AG85: 669114 | AH85: 0 | AI85: =AE85+AG85 -> 1705971 | AK85: 178067 | AL85: 0 | AM85: =AI85+AK85 -> 1884038 | AO85: 15000 | AP85: 0 | AQ85: =AM85+AO85 -> 1899038 | AS85: 0 | AT85: 0 | AU85: =AQ85+AS85 -> 1899038
E86: =+C86 -> 0 | T86: =+P86+R86 -> 0
A87: 5150 | B87: Adecuación e instalación | C87: =+C88+C89+C90+C91 -> 12000 | D87: 0 | E87: =+C87 -> 12000 | G87: =+G88+G89+G90+G91 -> 9600 | H87: 0 | I87: =E87+G87 -> 21600 | J87: =+J88+J89+J90 -> 12400 | K87: 0 | L87: =I87+J87 -> 34000 | N87: =N91 -> 0 | O87: 0 | P87: =L87+N87 -> 34000 | R87: 0 | S87: 0 | T87: =+P87+R87 -> 34000 | V87: =+V88+V89+V90+V91 -> 62200 | W87: 0 | X87: =T87+V87 -> 96200 | Y87: =+Y88+Y89+Y90 -> 0 | Z87: 0 | AA87: =X87+Y87 -> 96200 | AC87: =+AC88+AC89+AC90+AC91 -> 25000 | AD87: 0 | AE87: =AA87+AC87 -> 121200 | AG87: =+AG88+AG89+AG90+AG91 -> 241765 | AH87: 0 | AI87: =AE87+AG87 -> 362965 | AK87: =+AK88+AK89+AK90+AK91 -> 0 | AL87: 0 | AM87: =AI87+AK87 -> 362965 | AO87: =+AO88+AO89+AO90+AO91 -> 71009 | AP87: 0 | AQ87: =AM87+AO87 -> 433974 | AS87: =+AS88+AS89+AS90+AS91 -> 176143 | AT87: 0 | AU87: =AQ87+AS87 -> 610117
A88: 515005 | B88: Instalaciones electricas | C88: 0 | D88: 0 | E88: =+C88 -> 0 | G88: 0 | H88: 0 | I88: =E88+G88 -> 0 | J88: 0 | K88: 0 | L88: =I88+J88 -> 0 | N88: 0 | O88: 0 | P88: =L88+N88 -> 0 | R88: 0 | S88: 0 | T88: =+P88+R88 -> 0 | V88: 0 | W88: 0 | X88: =T88+V88 -> 0 | Y88: 0 | Z88: 0 | AA88: =X88+Y88 -> 0 | AC88: 0 | AD88: 0 | AE88: =AA88+AC88 -> 0 | AG88: 0 | AH88: 0 | AI88: =AE88+AG88 -> 0 | AK88: 0 | AL88: 0 | AM88: =AI88+AK88 -> 0 | AO88: 0 | AP88: 0 | AQ88: =AM88+AO88 -> 0 | AS88: 0 | AT88: 0 | AU88: =AQ88+AS88 -> 0
A89: 515010 | B89: Arreglos ornamentales | C89: 0 | D89: 0 | E89: =+C89 -> 0 | G89: 0 | H89: 0 | I89: =E89+G89 -> 0 | J89: 0 | K89: 0 | L89: =I89+J89 -> 0 | N89: 0 | O89: 0 | P89: =L89+N89 -> 0 | R89: 0 | S89: 0 | T89: =+P89+R89 -> 0 | V89: 0 | W89: 0 | X89: =T89+V89 -> 0 | Y89: 0 | Z89: 0 | AA89: =X89+Y89 -> 0 | AC89: 0 | AD89: 0 | AE89: =AA89+AC89 -> 0 | AG89: 0 | AH89: 0 | AI89: =AE89+AG89 -> 0 | AK89: 0 | AL89: 0 | AM89: =AI89+AK89 -> 0 | AO89: 0 | AP89: 0 | AQ89: =AM89+AO89 -> 0 | AS89: 0 | AT89: 0 | AU89: =AQ89+AS89 -> 0
A90: 515015 | B90: Reparaciones locativas | C90: 12000 | D90: 0 | E90: =+C90 -> 12000 | G90: 9600 | H90: 0 | I90: =E90+G90 -> 21600 | J90: 12400 | K90: 0 | L90: =I90+J90 -> 34000 | N90: 0 | O90: 0 | P90: =L90+N90 -> 34000 | R90: 0 | S90: 0 | T90: =+P90+R90 -> 34000 | V90: 62200 | W90: 0 | X90: =T90+V90 -> 96200 | Y90: 0 | Z90: 0 | AA90: =X90+Y90 -> 96200 | AC90: 25000 | AD90: 0 | AE90: =AA90+AC90 -> 121200 | AG90: 241765 | AH90: 0 | AI90: =AE90+AG90 -> 362965 | AK90: 0 | AL90: 0 | AM90: =AI90+AK90 -> 362965 | AO90: 71009 | AP90: 0 | AQ90: =AM90+AO90 -> 433974 | AS90: 176143 | AT90: 0 | AU90: =AQ90+AS90 -> 610117
A91: 515095 | B91: Otros | C91: 0 | D91: 0 | E91: =+C91 -> 0 | G91: 0 | H91: 0 | I91: =E91+G91 -> 0 | J91: 0 | K91: 0 | L91: =I91+J91 -> 0 | N91: 0 | O91: 0 | P91: =L91+N91 -> 0 | R91: 0 | S91: 0 | T91: =+P91+R91 -> 0 | V91: 0 | W91: 0 | X91: =T91+V91 -> 0 | Y91: 0 | Z91: 0 | AA91: =X91+Y91 -> 0 | AC91: 0 | AD91: 0 | AE91: =AA91+AC91 -> 0 | AG91: 0 | AH91: 0 | AI91: =AE91+AG91 -> 0 | AK91: 0 | AL91: 0 | AM91: =AI91+AK91 -> 0 | AO91: 0 | AP91: 0 | AQ91: =AM91+AO91 -> 0 | AS91: 0 | AT91: 0 | AU91: =AQ91+AS91 -> 0
E92: =+C92 -> 0 | T92: =+P92+R92 -> 0 | AI92: =AE92+AG92 -> 0 | AM92: =AI92+AK92 -> 0 | AQ92: =AM92+AO92 -> 0
A93: 5160 | B93: Depreciacion | AG93: =SUM(AG94:AG98) -> 3083714.8 | AI93: =AE93+AG93 -> 3083714.8 | AK93: =SUM(AK94:AK98) -> 3083714.8 | AM93: =AI93+AK93 -> 6167429.5 | AO93: =SUM(AO94:AO98) -> 3083714.8 | AQ93: =AM93+AO93 -> 9251144.2 | AS93: =SUM(AS94:AS98) -> 3083714.8 | AU93: =SUM(AU94:AU98) -> 12334859
A94: 516005 | B94: construcciones y edificaciones | AG94: 2116666.8 | AI94: =AE94+AG94 -> 2116666.8 | AK94: 2116666.8 | AM94: =AI94+AK94 -> 4233333.5 | AO94: 2116666.8 | AQ94: =AM94+AO94 -> 6350000.2 | AS94: 2116666.8 | AU94: 8466667
A95: 516010 | B95: maquinaria y equipo | AG95: 11198 | AI95: =AE95+AG95 -> 11198 | AK95: 11198 | AM95: =AI95+AK95 -> 22396 | AO95: 11198 | AQ95: =AM95+AO95 -> 33594 | AS95: 11198 | AU95: 44792
A96: 516015 | B96: equipo de oficina | AG96: 23000 | AI96: =AE96+AG96 -> 23000 | AK96: 23000 | AM96: =AI96+AK96 -> 46000 | AO96: 23000 | AQ96: =AM96+AO96 -> 69000 | AS96: 23000 | AU96: 92000
A97: 516020 | B97: equipo de computacion | AG97: 67950 | AI97: =AE97+AG97 -> 67950 | AK97: 67950 | AM97: =AI97+AK97 -> 135900 | AO97: 67950 | AQ97: =AM97+AO97 -> 203850 | AS97: 67950 | AU97: 271800
A98: 516035 | B98: flota y equipo de transporte | AG98: 864900 | AI98: =AE98+AG98 -> 864900 | AK98: 864900 | AM98: =AI98+AK98 -> 1729800 | AO98: 864900 | AQ98: =AM98+AO98 -> 2594700 | AS98: 864900 | AU98: 3459600
AI99: =AE99+AG99 -> 0 | AM99: =AI99+AK99 -> 0 | AQ99: =AM99+AO99 -> 0
AI100: =AE100+AG100 -> 0 | AM100: =AI100+AK100 -> 0 | AQ100: =AM100+AO100 -> 0
A101: 5195 | B101: Diversos | C101: =SUM(C103:C112) -> 596304 | D101: 0 | E101: =+C101 -> 596304 | G101: =G103+G104+G105+G106+G108+G109+G110+G111+G112+G107 -> 418882 | H101: 0 | I101: =E101+G101 -> 1015186 | J101: =SUM(J103:J112) -> 347100 | K101: 0 | L101: =I101+J101 -> 1362286 | N101: =SUM(N102:N112) -> 769738 | O101: 0 | P101: =L101+N101 -> 2132024 | R101: =SUM(R103:R112) -> 452668 | S101: 0 | T101: =+P101+R101 -> 2584692 | V101: =V103+V104+V105+V106+V108+V109+V110+V111+V112+V107 -> 545222 | W101: 0 | X101: =T101+V101 -> 3129914 | Y101: =SUM(Y103:Y112) -> 396045 | Z101: 0 | AA101: =X101+Y101 -> 3525959 | AC101: =SUM(AC102:AC112) -> 1148607 | AD101: 0 | AE101: =AA101+AC101 -> 4674566 | AG101: =SUM(AG102:AG112) -> 480218 | AH101: 0 | AI101: =AE101+AG101 -> 5154784 | AK101: =SUM(AK102:AK112) -> 698046 | AL101: 0 | AM101: =AI101+AK101 -> 5852830 | AO101: =SUM(AO102:AO112) -> 379333 | AP101: 0 | AQ101: =AM101+AO101 -> 6232163 | AS101: =SUM(AS102:AS112) -> 345901 | AT101: 0 | AU101: =AQ101+AS101 -> 6578064
A102: 519505 | B102: Comisiones | C102: 0 | D102: 0 | E102: =+C102 -> 0 | G102: 0 | H102: 0 | I102: =E102+G102 -> 0 | J102: 0 | K102: 0 | L102: =I102+J102 -> 0 | N102: 0 | O102: 0 | P102: =L102+N102 -> 0 | R102: 0 | S102: 0 | T102: =+P102+R102 -> 0 | V102: 0 | W102: 0 | X102: =T102+V102 -> 0 | Y102: 0 | Z102: 0 | AA102: =X102+Y102 -> 0 | AC102: 0 | AD102: 0 | AE102: =AA102+AC102 -> 0 | AG102: 0 | AH102: 0 | AI102: =AE102+AG102 -> 0 | AK102: 0 | AL102: 0 | AM102: =AI102+AK102 -> 0 | AO102: 0 | AP102: 0 | AQ102: =AM102+AO102 -> 0 | AS102: 0 | AT102: 0 | AU102: =AQ102+AS102 -> 0
A103: 519520 | B103: Gastos de representación y relaciones públicas | C103: 0 | D103: 0 | E103: =+C103 -> 0 | G103: 0 | H103: 0 | I103: =E103+G103 -> 0 | J103: 0 | K103: 0 | L103: =I103+J103 -> 0 | N103: 0 | O103: 0 | P103: =L103+N103 -> 0 | R103: 0 | S103: 0 | T103: =+P103+R103 -> 0 | V103: 0 | W103: 0 | X103: =T103+V103 -> 0 | Y103: 0 | Z103: 0 | AA103: =X103+Y103 -> 0 | AC103: 0 | AD103: 0 | AE103: =AA103+AC103 -> 0 | AG103: 0 | AH103: 0 | AI103: =AE103+AG103 -> 0 | AK103: 0 | AL103: 0 | AM103: =AI103+AK103 -> 0 | AO103: 0 | AP103: 0 | AQ103: =AM103+AO103 -> 0 | AS103: 117941 | AT103: 0 | AU103: =AQ103+AS103 -> 117941
A104: 519525 | B104: Elementos de aseo y cafetería | C104: 18400 | D104: 0 | E104: =+C104 -> 18400 | G104: 63400 | H104: 0 | I104: =E104+G104 -> 81800 | J104: 28400 | K104: 0 | L104: =I104+J104 -> 110200 | N104: 23900 | O104: 0 | P104: =L104+N104 -> 134100 | R104: 36800 | S104: 0 | T104: =+P104+R104 -> 170900 | V104: 4600 | W104: 0 | X104: =T104+V104 -> 175500 | Y104: 36800 | Z104: 0 | AA104: =X104+Y104 -> 212300 | AC104: 0 | AD104: 0 | AE104: =AA104+AC104 -> 212300 | AG104: 55496 | AH104: 0 | AI104: =AE104+AG104 -> 267796 | AK104: 89665 | AL104: 0 | AM104: =AI104+AK104 -> 357461 | AO104: 94033 | AP104: 0 | AQ104: =AM104+AO104 -> 451494 | AS104: 0 | AT104: 0 | AU104: =AQ104+AS104 -> 451494
A105: 519530 | B105: Utiles, papelería y fotocopias | C105: 32400 | D105: 0 | E105: =+C105 -> 32400 | G105: 0 | H105: 0 | I105: =E105+G105 -> 32400 | J105: 15000 | K105: 0 | L105: =I105+J105 -> 47400 | N105: 0 | O105: 0 | P105: =L105+N105 -> 47400 | R105: 47173 | S105: 0 | T105: =+P105+R105 -> 94573 | V105: 0 | W105: 0 | X105: =T105+V105 -> 94573 | Y105: 33445 | Z105: 0 | AA105: =X105+Y105 -> 128018 | AC105: 158151 | AD105: 0 | AE105: =AA105+AC105 -> 286169 | AG105: 171974 | AH105: 0 | AI105: =AE105+AG105 -> 458143 | AK105: 75335 | AL105: 0 | AM105: =AI105+AK105 -> 533478 | AO105: 14500 | AP105: 0 | AQ105: =AM105+AO105 -> 547978 | AS105: 1260 | AT105: 0 | AU105: =AQ105+AS105 -> 549238
A106: 519535 | B106: Combustibles Turbo | C106: 5000 | D106: 0 | E106: =+C106 -> 5000 | G106: 194282 | H106: 0 | I106: =E106+G106 -> 199282 | J106: 100000 | K106: 0 | L106: =I106+J106 -> 299282 | N106: 200000 | O106: 0 | P106: =L106+N106 -> 499282 | R106: 300000 | S106: 0 | T106: =+P106+R106 -> 799282 | V106: 357968 | W106: 0 | X106: =T106+V106 -> 1157250 | Y106: 300000 | Z106: 0 | AA106: =X106+Y106 -> 1457250 | AC106: 466229 | AD106: 0 | AE106: =AA106+AC106 -> 1923479 | AG106: 246948 | AH106: 0 | AI106: =AE106+AG106 -> 2170427 | AK106: 492725 | AL106: 0 | AM106: =AI106+AK106 -> 2663152 | AO106: 0 | AP106: 0 | AQ106: =AM106+AO106 -> 2663152 | AS106: 100000 | AT106: 0 | AU106: =AQ106+AS106 -> 2763152
A107: 519540 | B107: Combustible Mantenimiento | C107: 295000 | D107: 0 | E107: =+C107 -> 295000 | G107: 120000 | H107: 0 | I107: =E107+G107 -> 415000 | J107: 100000 | K107: 0 | L107: =I107+J107 -> 515000 | N107: 106500 | O107: 0 | P107: =L107+N107 -> 621500 | R107: 60000 | S107: 0 | T107: =+P107+R107 -> 681500 | V107: 40000 | W107: 0 | X107: =T107+V107 -> 721500 | Y107: 0 | Z107: 0 | AA107: =X107+Y107 -> 721500 | AC107: 160000 | AD107: 0 | AE107: =AA107+AC107 -> 881500 | AG107: 0 | AH107: 0 | AI107: =AE107+AG107 -> 881500 | AK107: 0 | AL107: 0 | AM107: =AI107+AK107 -> 881500 | AO107: 250000 | AP107: 0 | AQ107: =AM107+AO107 -> 1131500 | AS107: 0 | AT107: 0 | AU107: =AQ107+AS107 -> 1131500
...

Sheet GRAFICAS PYG
B5: MES | C5: VENTAS FISCALES 2019 | D5: VENTAS FISCALES 2018 | E5: VENTAS FISCALES 2017 | F5: VENTAS SIN IVA 2019 | G5: VENTAS SIN IVA 2018 | H5: VENTAS SIN IVA 2017 | I5: GASTOS 2019 | J5: GASTOS 2018 | K5: GASTOS 2017 | L5: UTILIDAD 2019 | M5: UTILIDAD 2018 | N5: UTILIDAD 2017
B6: ENERO | C6: 5232922 | D6: 20519674 | E6: =522963+299991+2769114+199640+276690 -> 4068398 | F6: =7998115 -> 7998115 | G6: 5489862 | H6: 3111549 | I6: =+'PYG '!C149 -> 8192569 | J6: 7055307 | K6: 10452832 | L6: =+C6+F6-I6 -> 5038468 | M6: 18954229 | N6: -3272885
B7: FEBRERO | C7: 6735984 | D7: 347610 | E7: =34155+356641+30000+185495+199640+2769114+52440+124200+30000 -> 3781685 | F7: =4974356-1 -> 4974355 | G7: 7374328 | H7: 8157506 | I7: =+'PYG '!G149 -> 8084721 | J7: 8975623 | K7: 8843670 | L7: =+C7+F7-I7 -> 3625618 | M7: -1253685 | N7: 3095521
B8: MARZO | C8: 4072345 | D8: =245268+260 -> 245528 | E8: =2501135+199640+393580+80730+29750+34510+25000 -> 3264345 | F8: =7130394+43 -> 7130437 | G8: 5439456 | H8: 5780617 | I8: =+'PYG '!J149 -> 8025783 | J8: 9788704 | K8: 8621927 | L8: =+C8+F8-I8 -> 3176999 | M8: -4103720 | N8: 423035
B9: ABRIL | C9: 8902568 | D9: =44268+102185+80587+29750+50000+4998 -> 311788 | E9: =2769114+199640+549053+161460+430560+90000+267950+437283+714714+17250+40000+37500 -> 5714524 | F9: =6000929+75 -> 6001004 | G9: 7142915 | H9: 5636163 | I9: =+'PYG '!N149 -> 11161681 | J9: 9211395 | K9: 6162384 | L9: =+C9+F9-I9 -> 3741891 | M9: -1756692 | N9: 5188303
B10: MAYO | C10: 4831245 | D10: 2070588 | E10: 1563099 | F10: 7419178 | G10: 5721041 | H10: 13796936 | I10: =+'PYG '!R149 -> 10164486 | J10: 8014528 | K10: 10155182 | L10: =+C10+F10-I10 -> 2085937 | M10: -222899 | N10: 5204853
B11: JUNIO | C11: 2541098 | D11: 4186225 | E11: 2504537 | F11: =6384494+91 -> 6384585 | G11: 4021740 | H11: 6565667 | I11: =+'PYG '!V149 -> 8433671 | J11: 7385244 | K11: 14240736 | L11: =+C11+F11-I11 -> 492012 | M11: 822721 | N11: -5170532
B12: JULIO | C12: 2060928 | D12: 3502320 | E12: 14376812 | F12: 4374077 | G12: 1959742 | H12: 6138041 | I12: =+'PYG '!Y149 -> 8752682 | J12: 7676064 | K12: 10531315 | L12: =+C12+F12-I12 -> -2317677 | M12: -2214002 | N12: 9983538
B13: AGOSTO | C13: 722060 | D13: 13456626 | E13: 9843168 | F13: =8088407+176 -> 8088583 | G13: 4820282 | H13: 5449400 | I13: =+'PYG '!AC149 -> 10250005 | J13: 9472439 | K13: 10083753 | L13: =+C13+F13-I13 -> -1439362 | M13: 8804469 | N13: 5208815
B14: SEPTIEMBRE | C14: =+'PYG '!AH8 -> 1921510 | D14: 0 | E14: 6807513 | F14: 5761435 | G14: 6035931 | H14: 6941815 | I14: =+'PYG '!AG149 -> 12341541 | J14: 16476675 | K14: 13656658 | L14: =+C14+F14-I14 -> -4658595.8 | M14: -10440744 | N14: 92670
B15: OCTUBRE | C15: =+'PYG '!AL8 -> 1940050 | D15: =+'[1]PYG '!AP8 -> 53036592 | E15: 3921439 | F15: 5903667 | G15: 10697305 | H15: 5541550 | I15: =+'PYG '!AK149 -> 13788361 | J15: 10699836 | K15: 12463405 | L15: =+C15+F15-I15 -> -5944643.8 | M15: 4755101 | N15: -3000416
B16: NOVIEMBRE | C16: =+'PYG '!AP8 -> 6096979 | D16: =+'[1]PYG '!AT8 -> 58092377 | E16: 2545390 | F16: 6953987 | G16: 7259988 | H16: 6901480 | I16: =+'PYG '!AO149 -> 12146151 | J16: 12696365 | K16: 13179987 | L16: =+C16+F16-I16 -> 904815.25 | M16: -380592 | N16: -3733117
B17: DICIEMBRE | C17: =+'PYG '!AT8 -> 10802895 | D17: =+'[1]PYG '!AX8 -> 63938027 | E17: 68513641 | F17: 3580427 | G17: 8230584 | H17: 7106144 | I17: =+'PYG '!AS149 -> 9554095.8 | J17: 8852048 | K17: 27294325 | L17: =+C17+F17-I17 -> 4829226.2 | M17: 5224186 | N17: 48325460
B19: TOTAL | C19: =SUM(C6:C18) -> 55860584 | D19: =SUM(D6:D18) -> 219707355 | E19: =SUM(E6:E18) -> 126904551 | F19: =SUM(F6:F18) -> 74569850 | G19: =SUM(G6:G18) -> 74193174 | H19: =SUM(H6:H18) -> 81126868 | I19: =SUM(I6:I18) -> 120895746 | J19: =SUM(J6:J18) -> 116304228 | ... N19: =SUM(N6:N18) -> 62345245
B44: MES | C44: VENTAS FISCALES 2019 | D44: VENTAS FISCALES 2018 | E44: VENTAS FISCALES 2017
B45: ENERO | C45: 5232922 | D45: 20519674 | E45: =522963+299991+2769114+199640+276690 -> 4068398
B46: FEBRERO | C46: 6735984 | D46: 347610 | E46: =34155+356641+30000+185495+199640+2769114+52440+124200+30000 -> 3781685
B47: MARZO | C47: 4072345 | D47: =245268+260 -> 245528 | E47: =2501135+199640+393580+80730+29750+34510+25000 -> 3264345
B48: ABRIL | C48: 8902568 | D48: =44268+102185+80587+29750+50000+4998 -> 311788 | E48: =2769114+199640+549053+161460+430560+90000+267950+437283+714714+17250+40000+37500 -> 5714524
B49: MAYO | C49: 4831245 | D49: 2070588 | E49: 1563099
B50: JUNIO | C50: 2541098 | D50: 4186225 | E50: 2504537
B51: JULIO | C51: 2060928 | D51: 3502320 | E51: 14376812
B52: AGOSTO | C52: 722060 | D52: 13456626 | E52: 9843168
B53: SEPTIEMBRE | C53: 1921510 | D53: 0 | E53: 6807513
B54: OCTUBRE | C54: 1940050 | D54: =+'[1]PYG '!AP47 -> 11000000 | E54: 3921439
B55: NOVIEMBRE | C55: 6096979 | D55: =+'[1]PYG '!AT47 -> 12000000 | E55: 2545390
B56: DICIEMBRE | C56: 10802895 | D56: =+'[1]PYG '!AX47 -> 13000000 | E56: 68513641
B58: TOTAL | C58: =SUM(C45:C57) -> 55860584 | D58: =SUM(D45:D57) -> 80640359 | E58: =SUM(E45:E57) -> 126904551
B70: MES | C70: VENTAS SIN IVA 2019 | D70: VENTAS SIN IVA 2018 | E70: VENTAS SIN IVA 2017
B71: ENERO | C71: 7998115 | D71: 5489862 | E71: 3111549
B72: FEBRERO | C72: 4974355 | D72: 7374328 | E72: 8157506
B73: MARZO | C73: 7130437 | D73: 5439456 | E73: 5780617
B74: ABRIL | C74: 6001004 | D74: 7142915 | E74: 5636163
B75: MAYO | C75: 7419178 | D75: 5721041 | E75: 13796936
B76: JUNIO | C76: 6384585 | D76: 4021740 | E76: 6565667
B77: JULIO | C77: 4374077 | D77: 1959742 | E77: 6138041
B78: AGOSTO | C78: 8088583 | D78: 4820282 | E78: 5449400
B79: SEPTIEMBRE | C79: 5761435 | D79: 6035931 | E79: 6941815
B80: OCTUBRE | C80: 5903667 | D80: 10697305 | E80: 5541550
B81: NOVIEMBRE | C81: 6953987 | D81: 7259988 | E81: 6901480
B82: DICIEMBRE | C82: 3580427 | D82: 8230584 | E82: 7106144
B83: TOTAL | C83: =SUM(C71:C82) -> 74569850 | D83: =SUM(D71:D82) -> 74193174 | E83: =SUM(E71:E82) -> 81126868
B102: MES | C102: GASTOS 2019 | D102: GASTOS 2018 | E102: GASTOS 2017
B103: ENERO | C103: 8192569 | D103: 7055307 | E103: 10452832
B104: FEBRERO | C104: 8084721 | D104: 8975623 | E104: 8843670
B105: MARZO | C105: 8025783 | D105: 9788704 | E105: 8621927
B106: ABRIL | C106: 11161681 | D106: 9211395 | E106: 6162384
B107: MAYO | C107: 10164486 | D107: 8014528 | E107: 10155182
B108: JUNIO | C108: 8433671 | D108: 7385244 | E108: 14240736
B109: JULIO | C109: 8752682 | D109: 7676064 | E109: 10531315
B110: AGOSTO | C110: 10250005 | D110: 9472439 | E110: 10083753
B111: SEPTIEMBRE | C111: 12341541 | D111: 16476675 | E111: 13656658
B112: OCTUBRE | C112: 13788361 | D112: 10699836 | E112: 12463405
B113: NOVIEMBRE | C113: 12146151 | D113: 12696365 | E113: 13179987
B114: DICIEMBRE | C114: 9554095.8 | D114: 8852048 | E114: 27294325
B116: TOTAL | C116: =SUM(C103:C115) -> 120895746 | D116: =SUM(D103:D115) -> 116304228 | E116: =SUM(E103:E115) -> 145686174
B129: MES | C129: UTILIDAD 2019 | D129: UTILIDAD 2018 | E129: UTILIDAD 2017
B130: ENERO | C130: 5038468 | D130: 18954229 | E130: -3272885
B131: FEBRERO | C131: 3625618 | D131: -1253685 | E131: 3095521
B132: MARZO | C132: 3176999 | D132: -4103720 | E132: 423035
B133: ABRIL | C133: 3741891 | D133: -1756692 | E133: 5188303
B134: MAYO | C134: 2085937 | D134: -222899 | E134: 5204853
B135: JUNIO | C135: 492012 | D135: 822721 | E135: -5170532
B136: JULIO | C136: -2317677 | D136: -2214002 | E136: 9983538
B137: AGOSTO | C137: -1439362 | D137: 8804469 | E137: 5208815
B138: SEPTIEMBRE | C138: -4658595.8 | D138: -10440744 | E138: 92670
B139: OCTUBRE | C139: -5944643.8 | D139: 4755101 | E139: -3000416
B140: NOVIEMBRE | C140: 904815.25 | D140: -380592 | E140: -3733117
B141: DICIEMBRE | C141: 4829226.2 | D141: 5224186 | E141: 48325460
B144: TOTAL | C144: =SUM(C130:C143) -> 9534688 | D144: =SUM(D130:D143) -> 18188372 | E144: =SUM(E130:E143) -> 62345245

Sheet DICIEMBRE
A1: EQUIORIENTE LTDA
A2: SITUACION FINANCIERA
A3: A 31 DE DICIEMBRE DE 2019
A6: 1 | C6: ACTIVO
A8: 11 | C8: Efectivo y equivalentes al efectivo
A9: 1105 | C9: Caja | E9: =+D10 -> 2895707
A10: 110505 | C10: Caja general | D10: 2895707
A11: 1120 | C11: Cuentas de ahorro
A12: 112005 | C12: Bancos | E12: =+D13+D14 -> 9512760
A13: 11200501 | C13: BBVA | D13: 5639481
A14: 11200502 | C14: Davivienda | D14: 3873279
A16: 1120 | C16: CDT | E16: =+D17 -> 15000652
A17: 112005 | C17: Cdt | D17: 15000652
A21: 13 | C21: Cuentas por cobrar (instrumentos financieros)
A22: 1305 | C22: Clientes | E22: =SUM(D24:D29) -> 24838151
A23: 130505 | C23: Nacionales
C24: Aurbana | D24: =+'[2] AURBANA'!$E$24 -> 646807
C25: Dinoxcol | D25: 1076700
C26: Fenix Constructores | D26: 9176470
C27: Gonzales Bohoruqez | D27: 565344
C28: CONSTRUCASA | D28: =+[2]CONSTRUCASA!$E$12 -> 11054406
C29: Consorcio san Ignacio | D29: 2318424
A31: 130515 | C31: Deudores facturacion sin iva | E31: =+D32+D33 -> 6829806
C32: Miriam Serrano | D32: 6743406
C33: leidy carolina saavedra | D33: 86400
A36: 1310 | C36: CUENTAS POR COBRAR A SOCIOS | E36: 6968498
A37: 112005 | C37: John Jaimes | D37: =+E36 -> 6968498
A39: 1395 | C39: Cuentas por cobrar | E39: =+D40 -> 1314587
C40: Inmboliaria ajc | D40: 1314587
A42: 1355 | C42: Anticipo de impuestos y contribuciones o saldos a favor | E42: =SUM(D43:D46) -> 3094161
A43: 135505 | C43: Anticipo de impuestos de renta y complementarios | D43: 1080000
A44: 135515 | C44: Retención en la fuente vtas | D44: 1548161
A45: 135517 | C45: Impuesto a las ventas retenido | D45: 185000
A46: 13559006 | C46: Autorretencion de renta | D46: 281000
A48: 14 | C48: Inventarios | E48: =+D49 -> 149182534
A49: 1435 | C49: Mercancías no fabricadas por la empresa | D49: 149182534
A52: 15 | C52: Propiedades planta y equipo | E52: =+D53+D55+D58+D60+D62+D64 -> 397051240
A53: 1512 | C53: Maquinaria y equipos en montaje | D53: 447920
A54: 151210 | C54: Equipo de oficina | D54: 447920
A55: 1516 | C55: Construcciones y edificaciones | D55: =+D56+D57 -> 381000000
A56: 151605 | C56: Apto sion | D56: 91000000
A57: 151610 | C57: Apto tamara | D57: 290000000
A58: 1524 | C58: Equipo de oficina | D58: 920000
A59: 152410 | C59: Equipos | D59: 920000
A60: 1528 | C60: Equipo de computación y comunicación | D60: 1359000
A61: 152805 | C61: Equipo de procesamiento de datos | D61: 1359000
A62: 1540 | C62: Flota y equipo de transporte | D62: 34596000
A63: 154008 | C63: Camiones, volquetas y furgones | D63: 34596000
A64: 1592 | C64: Depreciación acumulada | D64: =SUM(D65:D69) -> -21271680
C65: DEPRECIACION VEHICULO | D65: -7495800
C66: MAQUINARIA Y EQUIPO | D66: -44792
C67: EQUIPO DE CONSTRUCCION | D67: -12265522
C68: EQUIPO DE OFICINA | D68: -536666
C69: EQUIPO DE COMPUTO | D69: -928900
A71: 16 | C71: Intangibles | E71: =+D72 -> 2548980
A72: 1635 | C72: Licencias | D72: 2548980
A74: TOTAL ACTIVO | E74: =SUM(E9:E72) -> 6.1923708e+08
A78: 2335 | C78: Costos y gastos por pagar | E78: =+D79+D80 -> 300000
A79: 233525 | C79: Honorarios | D79: 300000
A82: 2365 | C82: Retención en la fuente | E82: =+D83+D84 -> 206000
A83: 236525 | C83: Retención en la fuente | D83: 120000
A84: 236706 | C84: Autorretencion | D84: 86000
A86: 2370 | C86: Retenciones y aportes de nómina | E86: =+D87+D88+D89 -> 275500
A87: 237005 | C87: Aportes a entidades promotoras de salud EPS | D87: 105100
A88: 237006 | C88: Aportes a administradoras de riesgos profesionales arp | D88: 50900
A89: 237010 | C89: Aportes al i.c.b.f, sena y cajas compensación | D89: 119500
A90: 2380 | C90: Acreedores varios | E90: =+D91 -> 419200
A91: 238030 | C91: Fondos de cesantías y/o pensiones | D91: 419200
A94: 24 | C94: Impuestos, gravámenes y tasas | E94: =+D95+D96 -> 1594000
A95: 2408 | C95: Impuesto sobre las ventas por pagar | D95: 1301000
A96: 2412 | C96: industria y comercio | D96: 293000
A100: 26 | C100: Provisión de pasivos
A101: 2610 | C101: Para obligaciones laborales | E101: =SUM(D102:D105) -> 2230483.4
A102: 261005 | C102: Cesantías | D102: 1991503
A103: 261010 | C103: Intereses sobre cesantías | D103: =+D102*12% -> 238980.36
A107: 22 | C107: PROVEEDORES
A108: 2205 | C108: Nacionales | E108: =+D110+D111 -> 2375215
A109: 221005 | C109: Proveedores por debajo
C110: Olga gomez (metalmartinez) | D110: 2375215
A113: TOTAL PASIVO | E113: =SUM(E77:E112) -> 7400398.4
A116: 3 | C116: PATRIMONIO
A118: 31 | C118: Capital social | E118: =+D119 -> 574301990
A119: 3105 | C119: Capital suscrito y pagado | D119: 574301990
A120: 310505 | C120: Capital autorizado
A123: 36 | C123: Resultados del ejercicio | E123: =+D124 -> 9534688
A124: 3605 | C124: Utilidad del ejercicio | D124: =+D125 -> 9534688
A125: 360501 | C125: Utilidad del ejercicio | D125: =+'PYG '!AU150 -> 9534688
A127: 37 | C127: UTILIDAD DEL EJERCICIO ANTERIORES | E127: =+D128 -> 28000000
A128: 37 | C128: Utilidad de ejercicios anteriores | D128: 28000000
A130: TOTAL PATRIMONIO | E130: =+E118+E123+E127 -> 611836678
A132: TOTAL PATRIMONIO Y PASIVO | E132: =+E130+E113 -> 6.1923708e+08
E134: =+E74-E113-E130 -> -0.40999997

Sheet INDICADORES
A1: Razones Financieras
A2: Liquidez
A4: Liquidez | B4: Activos Circulantes | C4: =+DICIEMBRE!E74 -> 6.1923708e+08 | D4: =+C4/C5 -> 83.676181 | E4: La empresa cuenta con el 84% de respaldo de los activos
B5: Pasivos Circulantes | C5: =+DICIEMBRE!E113 -> 7400398.4
A7: Prueba Acida | B7: Activos Circulantes - Inventarios | C7: =+DICIEMBRE!E74-DICIEMBRE!E48 -> 4.7005454e+08 | D7: =+C7/C8 -> 63.517465 | E7: con el activo que tenemos hay el 62,59% para pagar el pasivo
B8: Pasivos Circulantes | C8: =+C5 -> 7400398.4
A10: Administración de Activos
A12: Rotación Activos Fijos | B12: Ventas | C12: 136687592 | D12: =+C12/C13 -> 0.34425681 | E12: la empresa roto su activo el 0,34
B13: Activos Fijos Netos | C13: =+DICIEMBRE!E52 -> 397051240
A15: Rotación Activos Totales | B15: Ventas | C15: =+C12 -> 136687592 | D15: =+C15/C16 -> 0.22073548 | E15: la empresa roto su activo totales el 0,21
B16: Activos Totales | C16: =+C4 -> 6.1923708e+08
A18: Administración de Deudas
A20: Razón de Endeudamiento | B20: Deudas Totales | C20: =+DICIEMBRE!E113 -> 7400398.4 | D20: =+C20/C21 -> 0.011950832 | E20: la empresa de los activos debe el 0,01
B21: Activos totales | C21: =+DICIEMBRE!E74 -> 6.1923708e+08
A23: Rentabilidad
A25: Margen de utilidad | B25: Utilidad Neta | C25: =+'PYG '!AU150 -> 9534688 | D25: =+C25/C26*100 -> 7.3106592 | E25: el margen de utilidad es del 11,7%
B26: Ventas | C26: =+'PYG '!AU8+'PYG '!AU15+'PYG '!AU22 -> 130421728
A28: Rendimiento sobre los activos totales (RAT) | B28: Utilidad Neta | C28: =+C25 -> 9534688 | D28: =+C28/C29*100 -> 1.5397476 | E28: la empresa puede utilizarr el 2,57% de sus activos para generar ventas
B29: Activos totales | C29: =+C16 -> 6.1923708e+08

Sheet PRESUPUESTO
A1: EQUIORIENTE PRESUPUESTO
A4: INGRESOS | B4: INGRESO MENSUAL | C4: INGRESO ANUAL
A5: VENTAS CON IVA
A7: VENTAS SIN IVA
A9: total ingresos | B9: =+B66 -> 9294206.1 | C9: =+C66 -> 53487580
A11: GASTOS | B11: GASTO MENSUAL | C11: GASTO ANUAL
A13: Sueldos | B13: =2110993+900000 -> 3010993 | C13: =+B13*12 -> 36131916
A14: Auxilio de transporte | B14: 102854 | C14: =+B14*12 -> 1234248
A15: Bono de alimentacion | B15: 339007 | C15: =+B15*12 -> 4068084
A16: Dotacion | B16: =480000/12 -> 40000 | C16: =+B16*12 -> 480000
A17: Prestaciones Sociales | B17: =+(B13+B14)*21.83% -> 679752.8 | C17: =+B17*12 -> 8157033.6
A18: Parafiscales | B18: =+B13*18.43% -> 554926.01 | C18: =+B18*12 -> 6659112.1
A20: HONORARIOS CONTADOR | B20: 320000 | C20: =+B20*12 -> 3840000
A21: EXOGENA | B21: 20000 | C21: =+B21*12 -> 240000
A23: IMPUESTOS
A24: Vehiculos | B24: 61000 | C24: =+B24*12 -> 732000
A26: ARRENDAMIENTOS | B26: 1060000 | C26: =+B26*12 -> 12720000
A27: Bodega
A29: SEGURO
A30: Vehiculo | B30: 55340 | C30: =+B30*12 -> 664080
A31: Tecnicomecanica | B31: 17000 | C31: =+B31*12 -> 204000
A33: SERVICIO GENERAL DE ASEO | B33: 30000 | C33: =+B33*12 -> 360000
A34: TEMPORALES | B34: 1200000 | C34: =+B34*12 -> 14400000
A35: ACUEDUCTO | B35: 60000 | C35: =+B35*12 -> 720000
A36: ELECTRIFICADORA DE SANTANDER | B36: 90000 | C36: =+B36*12 -> 1080000
A37: TELEFONIA FIJA | B37: 87000 | C37: =+B37*12 -> 1044000
A38: CELULAR | B38: 173000 | C38: =+B38*12 -> 2076000
A39: TRANSPORTES Y FLETES | B39: 100000 | C39: 300000
A40: AFILIACION A SERVICIO PUBLICO | B40: =130000/12 -> 10833.333 | C40: =+B40*12 -> 130000
A42: GASTOS LEGALES
A43: Registro mercantil | B43: =1000000/12 -> 83333.333 | C43: =+B43*12 -> 1000000
A44: Impuesto de industria y comercio | B44: 25000 | C44: =+B44*12 -> 300000
A46: MANTENIMIENTO | B46: =+C46/12 -> 0
A47: Maquinaria y equipo | B47: =680000/12 -> 56666.667 | C47: =+B47*12 -> 680000
A48: Equipo de oficina | B48: =150000/12 -> 12500 | C48: =+B48 -> 12500
A49: Equipo de computación y comunicación | B49: =300000/12 -> 25000 | C49: =+B49 -> 25000
A50: Flota y equipo de transportes | B50: 100000 | C50: =+B50*12 -> 1200000
A52: Reparaciones locativas | B52: 40000 | C52: =+B52*12 -> 480000
B54: =+C54/12 -> 0
A55: PAPELERIA Y FOTOCOPIAS | B55: 60000 | C55: =+B55*12 -> 720000
A56: ELEMENTOS DE ASEO | B56: 50000 | C56: =+B56*12 -> 600000
A57: FLETES ENCOMIENDAS Y DEMAS | B57: 5000 | C57: =+B57*12 -> 60000
A58: COMBUSTIBLE | B58: 200000 | C58: =+B58*12 -> 2400000
A59: TAXIS BUSES Y DOMICILIOS | B59: 25000 | C59: =+B59*12 -> 300000
A60: COMBUSTIBLE MANTENIMIENTO | B60: 50000 | C60: =+B60*12 -> 600000
A61: ARRENDAMIENTO MAQUINARIA | B61: 265000 | C61: =+B61*12 -> 3180000
A63: GASTOS FINANCIEROS | B63: 285000 | C63: =+B63*12 -> 3420000
B64: =+C64/12 -> 0
A66: TOTAL | B66: =SUM(B12:B65) -> 9294206.1 | C66: =SUM(C20:C64) -> 53487580
