Workbook

Sheet Calculo
B4: DESCRIPCION | C4: VALOR | D4: ONSERVACIONES
B5: BODEGA (AVALUO COMERCIAL) | C5: 722820000 | D5: Avaluo realizado por arquitecto.
B6: CAMION (AVALUO COMERCIAL) | C6: 30000000 | D6: Valor calculado de mercadolibre.
B7: EQUIPO DE CONSTRUCCION (AVALUO REAL) | C7: 152131800 | D7: Valor aportado por Jimmy, luego del inventario.
B8: ANTICIPOS APTO PUERTA ORO | C8: 50879394 | F8: CDT 1 - COMULTRASAN - 20/02/2025 | G8: 7474000
B9: HEIDY ZION | C9: 24447900 | D9: Pagado Septiembre 2025 | F9: CDT 1 - Utilidades al 20/08/2025 | G9: 336240 | H9: Utilidad a Agosto
B10: JHON ZION | C10: 24447900 | D10: Pagado Septiembre 2025 | F10: CDT 1 - Utilidades a diciembre | G10: 197870 | H10: Utilidad a diciembre
B11: JIMMY ZION | C11: 24447900 | D11: Pagado Septiembre 2025 | F11: CDT 2 - COOMULTRASAN 18/07/2025 | G11: 22337500
B12: CDT 1 - COMULTRASAN - 20/02/2025 | C12: 7474000 | F12: CDT 2 - Utilidades a 18/10/2025 | G12: 426707 | H12: Utilidad a octubre
B13: CDT 1 - Utilidades al 20/08/2025 | C13: 336240 | D13: Utilidad a Agosto | F13: CDT 2 - Utilidades a diciembre | G13: 281086 | H13: Utilidad a diciembre
B14: CDT 1 - Utilidades a diciembre | C14: 197870 | D14: Utilidad a diciembre | F14: CDT 3 - BBVA 19/12/2025 | G14: 92994996 | H14: Valor del CDT incluyendo lo pendiente de Zion
B15: CDT 2 - COOMULTRASAN 18/07/2025 | C15: 22337500 | F15: TOTAL | G15: =+SUM(G8:G14) -> 124048399
B16: CDT 2 - Utilidades a 18/10/2025 | C16: 426707 | D16: Utilidad a octubre
B17: CDT 2 - Utilidades a diciembre | C17: 281086 | D17: Utilidad a diciembre
B18: CDT 3 - BBVA 19/12/2025 | C18: 92994996 | D18: Valor del CDT incluyendo lo pendiente de Zion
B19: CAJA | C19: 9204613
B20: BANCO | C20: =6165540.43-4857700 -> 1307840.4 | D20: Se resta el valor pendiente que debe incluirse en el CDT del BBVA
B21: CLIENTES | C21: 5456823
C22: =SUM(C5:C21) -> 1.1691926e+09
B23: PASIVOS | C23: 6891940
C24: =+C22-C23 -> 1.1623006e+09
B26: Repartición entre los socios segun su porcentaje.
B27: Flor Alba Carrilo de Jaimes | C27: =C24*D27 -> 6.3926535e+08 | D27: 0.55
B28: Heidy Milena Jaimes Carrillo | C28: =+(C24*D28) -> 1.7434509e+08 | D28: 0.15
B29: Jhon Alexander Jaimes Carrillo | C29: =(C24*D29) -> 1.7434509e+08 | D29: 0.15
B30: Jhon Alexander Jaimes Carrillo | C30: =+(C24*D30) -> 1.7434509e+08 | D30: 0.15
C31: =SUM(C27:C30) -> 1.1623006e+09
B33: Repartición entre lo socios descontando el efectivo pagado en Septiembre 2025
B34: Flor Alba Carrilo de Jaimes | C34: =C24*D34 -> 6.3926535e+08 | D34: 0.55
B35: Heidy Milena Jaimes Carrillo | C35: =+(C24*D35)-C9 -> 1.4989719e+08 | D35: 0.15
B36: Jhon Alexander Jaimes Carrillo | C36: =(C24*D36)-C10 -> 1.4989719e+08 | D36: 0.15
B37: Jhon Alexander Jaimes Carrillo | C37: =+(C24*D37)-C11 -> 1.4989719e+08 | D37: 0.15
C38: =SUM(C34:C37) -> 1.0889569e+09
B40: Saldo Pendiente Apto Puerta de Oro | C40: 118718586 | D40: =C40*D42/C42 -> 0.7
B41: Pagado | C41: =C8 -> 50879394 | D41: =C41*D42/C42 -> 0.3
B42: Valor total | C42: =C40+C41 -> 169597980 | D42: 1
B45: CDTs | C45: =SUM(C12:C18) -> 124048399

Sheet Propuesta 1
B2: Propuesta | D2: Total | E2: Heidy | F2: Jhon | G2: Jimmy | H2: Flor Alba
D3: =Calculo!C31 -> 1.1623006e+09 | E3: =+Calculo!$C$28 -> 1.7434509e+08 | F3: =+Calculo!$C$28 -> 1.7434509e+08 | G3: =+Calculo!$C$28 -> 1.7434509e+08 | H3: =Calculo!C27 -> 6.3926535e+08
D4: =D7+D11+D15+D19+D23+D27 -> 1.1623006e+09 | E4: =E7+E11+E15+E19 -> 1.7434509e+08 | F4: =F7+F11+F15+F19 -> 1.7434509e+08 | G4: =G7+G11+G15+G19+G23+G27 -> 1.7434509e+08 | H4: =+H7+H11+H15+H19+H23+H27 -> 6.3926535e+08
C5: Dinero Repartido Venta de Zion | D5: 1 | E5: Heidy | F5: Jhon | G5: Jimmy | H5: Flor Alba
E6: 0.333333 | F6: 0.333333 | G6: 0.333333 | H6: 0
D7: =Calculo!C9+Calculo!C9+Calculo!C10 -> 73343700 | E7: 24447900 | F7: 24447900 | G7: 24447900 | H7: 0
C9: Puerta de Oro - Pagado | D9: 1 | E9: Heidy | F9: Jhon | G9: Jimmy | H9: Flor Alba
E10: 0.5 | F10: 0.5 | G10: 0 | H10: 0
D11: =Calculo!C41 -> 50879394 | E11: =+D11*E10 -> 25439697 | F11: =+D11*F10 -> 25439697 | G11: =+D11*G10 -> 0 | H11: =+D11*H10 -> 0
C13: CDTs a Diciembre | D13: 1 | E13: Heidy | F13: Jhon | G13: Jimmy | H13: Flor Alba | J13: Arriendo Actual | M13: Arriendo Futuro
E14: 0.5 | F14: 0.5 | G14: 0 | H14: 0 | J14: Socio | K14: Porcentaje | L14: 2266666.7 | N14: 3500000
D15: =Calculo!C45 -> 124048399 | E15: =+$D$15*E14 -> 62024200 | F15: =+$D$15*F14 -> 62024200 | G15: =+$D$15*G14 -> 0 | H15: =+$D$15*H14 -> 0 | J15: Heidy | K15: 0.15 | L15: 340000 | M15: =$E$18 -> 0.086374613 | N15: =$N$14*M15 -> 302311.15
J16: Jhon | K16: 0.15 | L16: 340000 | M16: =$F$18 -> 0.086374613 | N16: =$N$14*M16 -> 302311.15
C17: Bodega | D17: 1 | E17: Heidy | F17: Jhon | G17: Jimmy | H17: Flor Alba | J17: Jimmy | K17: 0.15 | L17: 340000 | M17: =$G$18 -> 0.12801867 | N17: =$N$14*M17 -> 448065.34
E18: =E19/D19 -> 0.086374613 | F18: =F19*1/D19 -> 0.086374613 | G18: =G19/D19 -> 0.12801867 | H18: =H19/D19 -> 0.69923211 | J18: Flor | K18: 0.55 | L18: =L14*K18 -> 1246666.7 | M18: =$H$18 -> 0.69923211 | N18: =$N$14*M18 -> 2447312.4
D19: 722820000 | E19: =E3-E7-E11-E15 -> 62433298 | F19: =F3-F7-F11-F15 -> 62433298 | G19: =G3-G7-G23-G27 -> 92534453 | H19: =H3-H23-H27 -> 5.0541895e+08
C21: Equioriente | D21: 1 | E21: Heidy | F21: Jhon | G21: Jimmy | H21: Flor Alba
E22: 0 | F22: 0 | G22: 0.3 | H22: =D21-E22-F22-G22 -> 0.7
D23: =Calculo!C6+Calculo!C7 -> 182131800 | E23: 0 | F23: 0 | G23: =+D23*G22 -> 54639540 | H23: =+D23*H22 -> 1.2749226e+08
C25: CAJA, BANCO, CLIENTES - PASIVOS | D25: 1 | E25: Heidy | F25: Jhon | G25: Jimmy | H25: Flor Alba
E26: 0 | F26: 0 | G26: 0.3 | H26: 0.7
D27: =Calculo!C19+Calculo!C20+Calculo!C21-Calculo!C23 -> 9077336.4 | E27: 0 | F27: 0 | G27: =+D27*G26 -> 2723200.9 | H27: =+D27*H26 -> 6354135.5
B30: Porcentajes | C30: Puerta de Oro | D30: 1 | E30: Heidy | F30: Jhon | G30: Jimmy | H30: Flor Alba
E31: 0.5 | F31: 0.5 | G31: - | H31: -
C33: Bodega | D33: 1 | E33: Heidy | F33: Jhon | G33: Jimmy | H33: Madre
E34: 0.0864 | F34: 0.0864 | G34: 0.1270106 | H34: 0.7002
C36: Equioriente | D36: 1 | E36: Heidy | F36: Jhon | G36: Jimmy | H36: Madre
E37: - | F37: - | G37: 0.3 | H37: 0.7
B40: 1 | C40: La utilidades del dinero de los CDT para la compra del apto se va repartir entre los 4 socios en partes iguales a partir del 1 de enero del 2026.
B41: 2 | C41: Acordamos que seguiremos recibiendo el arriendo de $340.000 equivalente al 15% de cada socio, hasta definir lo del apto, luego miramos el aumento del arriendo de la bodega.
B42: 3 | C42: Se hara un derecho de peticion para solicitar la devolucion del dinero aporta por el apto.
B43: 4 | C43: Al momento de definir lo del apto, se realizará la ejecución de la propuesta.

Sheet Propuesta J1
B2: Propuesta | D2: Total | E2: Heidy | F2: Jhon | G2: Jimmy | H2: Flor Alba
D3: =Calculo!C31 -> 1.1623006e+09 | E3: =+Calculo!$C$28 -> 1.7434509e+08 | F3: =+Calculo!$C$28 -> 1.7434509e+08 | G3: =+Calculo!$C$28 -> 1.7434509e+08 | H3: =Calculo!C27 -> 6.3926535e+08
D4: =D7+D11+D15+D19+D23+D27 -> 1.1623006e+09 | E4: =E7+E11+E15+E19 -> 1.7434509e+08 | F4: =F7+F11+F15+F19 -> 1.7434509e+08 | G4: =G7+G11+G15+G19+G23+G27 -> 1.7434509e+08 | H4: =+H7+H11+H15+H19+H23+H27 -> 6.3926535e+08
C5: Dinero Repartido Venta de Zion | D5: 1 | E5: Heidy | F5: Jhon | G5: Jimmy | H5: Flor Alba
E6: 0.333333 | F6: 0.333333 | G6: 0.333333 | H6: 0
D7: =Calculo!C9+Calculo!C9+Calculo!C10 -> 73343700 | E7: 24447900 | F7: 24447900 | G7: 24447900 | H7: 0
C9: Puerta de Oro - Pagado | D9: 1 | E9: Heidy | F9: Jhon | G9: Jimmy | H9: Flor Alba
E10: 0.5 | F10: 0.5 | G10: 0 | H10: 0
D11: =Calculo!C41 -> 50879394 | E11: =+D11*E10 -> 25439697 | F11: =+D11*F10 -> 25439697 | G11: =+D11*G10 -> 0 | H11: =+D11*H10 -> 0
C13: CDTs a Diciembre | D13: 1 | E13: Heidy | F13: Jhon | G13: Jimmy | H13: Flor Alba | J13: Arriendo Futuro
E14: 0.5 | F14: 0.5 | G14: 0 | H14: 0 | K14: 3473250
D15: =Calculo!C45 -> 124048399 | E15: =+$D$15*E14 -> 62024200 | F15: =+$D$15*F14 -> 62024200 | G15: =+$D$15*G14 -> 0 | H15: =+$D$15*H14 -> 0 | J15: =$E$18 -> 0.086374613 | K15: =$K$14*J15 -> 300000.63
J16: =$F$18 -> 0.086374613 | K16: =$K$14*J16 -> 300000.63
C17: Bodega | D17: 1 | E17: Heidy | F17: Jhon | G17: Jimmy | H17: Flor Alba | J17: =$G$18 -> 0.11922791 | K17: =$K$14*J17 -> 414108.34
E18: =E19/D19 -> 0.086374613 | F18: =F19*1/D19 -> 0.086374613 | G18: =G19/D19 -> 0.11922791 | H18: =H19/D19 -> 0.70802286 | J18: =$H$18 -> 0.70802286 | K18: =$K$14*J18 -> 2459140.4
D19: 722820000 | E19: =E3-E7-E11-E15 -> 62433298 | F19: =F3-F7-F11-F15 -> 62433298 | G19: =G3-G7-G23-G27 -> 86180318 | H19: =H3-H23-H27 -> 5.1177309e+08
C21: Equioriente | D21: 1 | E21: Heidy | F21: Jhon | G21: Jimmy | H21: Flor Alba
E22: 0 | F22: 0 | G22: 0.3 | H22: =D21-E22-F22-G22 -> 0.7
D23: =Calculo!C6+Calculo!C7 -> 182131800 | E23: 0 | F23: 0 | G23: =+D23*G22 -> 54639540 | H23: =+D23*H22 -> 1.2749226e+08
C25: CAJA, BANCO, CLIENTES - PASIVOS | D25: 1 | E25: Heidy | F25: Jhon | G25: Jimmy | H25: Flor Alba
E26: 0 | F26: 0 | G26: 1 | H26: 0
D27: =Calculo!C19+Calculo!C20+Calculo!C21-Calculo!C23 -> 9077336.4 | E27: 0 | F27: 0 | G27: 9077336 | H27: =+D27*H26 -> 0
B30: Porcentajes | C30: Puerta de Oro | D30: 1 | E30: Heidy | F30: Jhon | G30: Jimmy | H30: Flor Alba
E31: 0.5 | F31: 0.5 | G31: - | H31: -
C33: Bodega | D33: 1 | E33: Heidy | F33: Jhon | G33: Jimmy | H33: Madre
E34: 0.087998038 | F34: 0.087998038 | G34: 0.11853216 | H34: 0.70547177
C36: Equioriente | D36: 1 | E36: Heidy | F36: Jhon | G36: Jimmy | H36: Madre
E37: - | F37: - | G37: 0.3 | H37: 0.7
B40: 1 | C40: La utilidades del dinero de los CDT para la compra del apto se va repartir entre los 3 socios en partes iguales a partir del 1 de enero hasta el 31 de marzo del 2026.
B41: 2 | C41: Acordamos que seguiremos recibiendo el arriendo de $340.000 equivalente al 15% de cada socio, hasta pasar lla propiedad del apto, luego el aumento del arriendo de la bodega queda este año en $3,473,250.
B42: 3 | C42: Se solicitara el traspaso de la propiedad del Apto puerta de Oro de Equioriente a Heidy y Jhon.
B43: 4 | C43: Al momento de definir lo del apto, se realizará la ejecución de la propuesta.

Sheet CALCULO PROPUESTA2
B1: DESCRIPCION | C1: VALOR | D1: ONSERVACIONES
B2: CAMION (AVALUO COMERCIAL) | C2: 30000000 | D2: Valor calculado de mercadolibre.
B3: EQUIPO DE CONSTRUCCION (AVALUO REAL) | C3: 152131800 | D3: Valor aportado por Jimmy, luego del inventario.
B4: HEIDY ZION | C4: 24447900 | D4: Pagado Septiembre 2025
B5: JHON ZION | C5: 24447900 | D5: Pagado Septiembre 2025
B6: JIMMY ZION | C6: 24447900 | D6: Pagado Septiembre 2025
B7: CDT 1 - COMULTRASAN - 20/02/2025 | C7: 7474000
B8: CDT 1 - Utilidades al 20/08/2025 | C8: 336240 | D8: Utilidad a Agosto
B9: CDT 1 - Utilidades a diciembre | C9: 197870 | D9: Utilidad a diciembre
B10: CDT 2 - COOMULTRASAN 18/07/2025 | C10: 22337500
B11: CDT 2 - Utilidades a 18/10/2025 | C11: 426707 | D11: Utilidad a octubre
B12: CDT 2 - Utilidades a diciembre | C12: 281086 | D12: Utilidad a diciembre
B13: CDT 3 - BBVA 19/12/2025 | C13: 92994996 | D13: Valor del CDT incluyendo lo pendiente de Zion
B14: CAJA | C14: 9204613
B15: BANCO | C15: =6165540.43-4857700 -> 1307840.4 | D15: Se resta el valor pendiente que debe incluirse en el CDT del BBVA
B16: CLIENTES | C16: 5456823
C17: =SUM(C2:C16) -> 3.9549318e+08
B18: PASIVOS | C18: 6891940
C19: =+C17-C18 -> 3.8860124e+08
B21: Repartición entre los socios segun su porcentaje.
B22: Flor Alba Carrilo de Jaimes | C22: =C19*D22 -> 2.1373068e+08 | D22: 0.55
B23: Heidy Milena Jaimes Carrillo | C23: =+(C19*D23) -> 58290185 | D23: 0.15
B24: Jhon Alexander Jaimes Carrillo | C24: =(C19*D24) -> 58290185 | D24: 0.15
B25: Jimmy Alfredo Jaimes Carrillo | C25: =+(C19*D25) -> 58290185 | D25: 0.15
C26: =C19 -> 3.8860124e+08
B28: Repartición entre lo socios descontando el efectivo pagado en Septiembre 2025
B29: Flor Alba Carrilo de Jaimes | C29: =$C33*D29 -> 1.7339164e+08 | D29: 0.55
B30: Heidy Milena Jaimes Carrillo | C30: =$C33*D30 -> 47288630 | D30: 0.15
B31: Jhon Alexander Jaimes Carrillo | C31: =$C33*D31 -> 47288630 | D31: 0.15
B32: Jimmy Alfredo Jaimes Carrillo | C32: =$C33*D32 -> 47288630 | D32: 0.15
C33: =C26-(C4+C5+C6) -> 3.1525754e+08
B35: Saldo Pendiente Apto Puerta de Oro | C35: 118718586 | D35: =C35*#REF!/#REF! -> #REF!
B38: CDTs | C38: =SUM(C7:C13) -> 124048399

Sheet PROPUESTA JIMMY 2
C1: Total | D1: Heidy | E1: Jhon | F1: Jimmy | G1: Flor Alba
D2: =D3/C3 -> 0.15 | E2: =E3/C3 -> 0.15 | F2: =F3/C3 -> 0.15 | G2: =G3/C3 -> 0.55
C3: ='CALCULO PROPUESTA2'!C26 -> 3.8860124e+08 | D3: ='CALCULO PROPUESTA2'!C23 -> 58290185 | E3: ='CALCULO PROPUESTA2'!C24 -> 58290185 | F3: ='CALCULO PROPUESTA2'!C25 -> 58290185 | G3: ='CALCULO PROPUESTA2'!C22 -> 2.1373068e+08
I4: =C3*0.15 -> 58290185
B5: Dinero Repartido Venta de Zion | C5: 1 | D5: Heidy | E5: Jhon | F5: Jimmy | G5: Flor Alba
D6: 0.333333 | E6: 0.333333 | F6: 0.333333 | G6: 0
C7: ='PROPUESTA JIMMY 2'!D7+'PROPUESTA JIMMY 2'!E7+'PROPUESTA JIMMY 2'!F7 -> 73343700 | D7: 24447900 | E7: 24447900 | F7: 24447900 | G7: 0
B10: CDTs a Diciembre | C10: 1 | D10: Heidy | E10: Jhon | F10: Jimmy | G10: Flor Alba
D11: =D12/C12 -> 0.28039345 | E11: =E12/C12 -> 0.28039345 | F11: 0 | G11: =G12/C12 -> 0.00044753872
C12: 120695703 | D12: 33842285 | E12: 33842285 | F12: =+$D$13*F11 -> 0 | G12: 54016 | J12: Arriendo Futuro
K13: 3000000
J14: 0.15 | K14: =K13*J14 -> 450000
B15: Equioriente | C15: 1 | D15: Heidy | E15: Jhon | F15: Jimmy | G15: Flor Alba | J15: 0.15 | K15: =K13*J15 -> 450000
D16: 0 | E16: 0 | F16: =F17/C17 -> 0.13598915 | G16: =C15-D16-E16-F16 -> 0.86401085 | J16: 0.15 | K16: =K13*J16 -> 450000
C17: ='CALCULO PROPUESTA2'!C2+'CALCULO PROPUESTA2'!C3 -> 182131800 | D17: 0 | E17: 0 | F17: 24767949 | G17: 157869766 | J17: 0.55 | K17: =K13*J17 -> 1650000
B19: CAJA, BANCO, CLIENTES - PASIVOS | C19: 1 | D19: Heidy | E19: Jhon | F19: Jimmy | G19: Flor Alba
D20: 0 | E20: 0 | F20: =F21/C21 -> 0.99999995 | G20: =G21/C21 -> 0
C21: ='CALCULO PROPUESTA2'!C14+'CALCULO PROPUESTA2'!C15+'CALCULO PROPUESTA2'!C16-'CALCULO PROPUESTA2'!C18 -> 9077336.4 | D21: 0 | E21: 0 | F21: 9077336
C24: =C7+C12+C17+C21 -> 3.8524854e+08 | D24: =D7+D12 -> 58290185 | E24: =E7+E12 -> 58290185 | F24: =F7+F21+F17 -> 58293185 | G24: =G12+G17+G21 -> 157923782
