Workbook

Sheet ENERO
B1: INGRESOS
B2: ENERO 1 AL 31 2026
B3: SALDO EN CAJA: | C3: 0
A4: FECHA | B4: DETALLE | C4: VALOR
A5: 46029 | B5: ADRIAN BRAVO | C5: 400000
B6: RONALD COLORADOS COLORADOS | C6: 208000
B7: TABLON | C7: 5000
B8: HERNAN TORRADO CANCELADO A ENERO 18 2025 | C8: 111500
B9: ABONO ALQUILER COLUMNAS YURANIS PABLON | C9: 400000 | D9: nequi
A10: 46036 | B10: ABONO ALQUILER ENERO 2026 CLAUDIA JEREZ | C10: 104250
B11: ABONOI MAESTRO GREGORIO ALQUILER ANDAMIOS 20 DIAS ENERO 14 A FEBRERO 3 | C11: 200000
B12: DEPOSITO PLACA RONALD | C12: 400000 | D12: NEQUI
A13: 46037 | B13: MAESTRO ROGELIO A ENERO 8 2025 | C13: 957000
B14: RETIRO NEQUI | C14: 300000 | D14: NEQUI
A15: 46039 | B15: SOPORTE ALQUILER POLEAS A PARTIR 20 ENERO 2026 | C15: 800000 | D15: BANCOLOMBIA
A16: 46041 | B16: PAGO YURANIS ALQUILER PLACA ENERO 20 A FEBRERO 3 | C16: 2745000 | D16: BBVA
B17: DEPOSITO JOSE HERNAN PARADA | C17: 72000 | D17: BANCOLOMBIA | E17: CUADRADO HASTA AQUÍ | F17: 200000
A18: 46042 | B18: DEPOSITOKETHERIN PALACIOS | C18: 200000 | D18: NEQUI
A19: 46043 | B19: ALQUILER DIEGO GUTIERREZ SALIDA 13282 A PARTIR 17 ENERO | C19: 300000
B20: MARICEL ABONO | C20: 50000
B21: ESCALERA CECILIA INFANTE | C21: 30000
A22: 46044 | B22: ADBONO YURANIS MATERIAL ADICICONAL | C22: 264500 | D22: BBVA
B23: HERNAN TORRADO ENERO 19 AL 25 | C23: 77000
A24: 46048 | B24: ALQUILER 26 ENERO A FEBRERO 6 DIEGO GUTIERREZ | C24: 330000
A25: 46049 | B25: ANDREA PAOLA ABONO A PLACA PRIMER PISO | C25: 1500000 | D25: BBVA JIMMY
A26: 46050 | B26: JUAN CARLOS BAUTISTA | C26: 84000
B27: ERNESTO ´PICOSN | C27: 36000
B28: DIEGO GUTIERREZ ENERO 27 AL 31 | C28: 6000
B29: ALQUILER ESCALERA GLASCOL POR 1 DIA | C29: 30000
B30: DIEGO GUTIERREZ ENERO 27 AL 31 | C30: 25760 | D30: NEQUI
A31: 46052 | B31: JORGE MANTILLA PAGO DE ALQUILER ENERO | C31: 170000 | D31: NEQUI
B32: POLIMYS ALQUILER DICIEMBRE | C32: 30240 | D32: BBVA JIMMY | E32: =1000000-630080 -> 369920 | F32: PENDIENTE FACTURAS
A33: 46053 | B33: PAGO ALQUILER LIBARDO REY A 2 FEBRERO 2026 | C33: 1000000
B34: PAGO ALQUILER FORMALETA MAESTRO ROGELIO A ENERO 23 2026 | C34: 909000
B35: CESAR AUGUSTO CACERES ABONO A ALQUILER | C35: 200000 | D35: NEQUI
C36: =SUM(C5:C35) -> 11945250
A38: EGRESOS
A39: FECHA | B39: ENERO 1 AL 31 2026
B40: DETALLE | C40: VALOR
A41: 46031 | B41: DIEGO ROJAS ENERO 7 AL 9 2026 | C41: 217500
B42: HORAS EXTRAS ENERO 7 AL 9 | C42: 25000
B43: EIDER DE JESUS CAICEDO ENERO 7 AL 9 2026 | C43: 202500
B44: YANETH LUNA CAICEDO ENERO 7 AL 9 2026 | C44: 202500
B45: DROGUERIA FAMICARE NORTE # 18167 ( YODO Y AGUA OXIGENADA} | C45: 13000 | G45: SE DEB A JIMMY
A46: 46036 | B46: PAPELERIA DONDE JAIRO ( AZ; | C46: 106100
B47: PINTASMAS FVE PQSF -20679 ( 1 GALON ESMALTHE AZUL Y 2 GALONE STHINER | C47: 83000
B48: ABONO EN EFCTIVO CLAUDIA GIL | D48: 104245
A49: 46037 | B49: PAGO LUZ 29 NOVIEMBRE A DICIEMBRE 16 /2025 | C49: 124567
B50: PAGO FACTURA WOM | C50: 79485
B51: SERGIO ANTONIO JIMENES 1 SPITER VGA 1X2 | C51: 60000 | D51: iva
A52: 45674 | B52: SEMANA 13 AL 17 ENERO 2026 EIDER DE JESUS | C52: 350000
B53: SEMANA 13 AL 17 ENERO 2026DIEGO ROJAS | C53: 390000
B54: SEMANA 13 AL 17 ENERO 2026 YANETH LUNA | C54: 338000 | D54: NEQUI
A55: 46041 | B55: TECNIRACORES Y MANGUERAS CHIMITA FVEP 14583 | C55: 145000
B56: MANO OBRA CAMBIO MANGUERA VEHICULO Y CAMBIO CORREA TRANSMISION | C56: 40000 | D56: NEQUI
B57: ARREGLO IMPRESORA EPSON | C57: 40000 | D57: NEQUI | E57: FACTURA CON IVA
B58: TKEO JAC | C58: 100000 | D58: DIEGO
A59: 46042 | B59: MANEJAR GASTOS ADMINISTRATIVOS ST0117305 | C59: 30000 | D59: NEQUI
B60: MANEJAR SOAT AÑO 2026 CAMION JAC | C60: 888400 | D60: NEQUI
B61: ABONO HECHURA POLOS | C61: 50000
B62: ACARREO A ADRIAN BRAVO JAVIER CARMONA | C62: 30000
B63: RECIBO DEL AGUA NOVIEMBRE 2025 | C63: 129380
B64: CARGADOR SPARTAN V8 | C64: 20000
A65: 46043 | B65: COMPRA MONITOR VGA CAMARAS OFICINA | C65: 130000
A66: 46043 | B66: TUREBOMAX ( REPARACION TURBO Jak hp 55 ( empaquetadyra , alineacion, bujes y rueda compresora | C66: 750000 | D66: NEQUI
B67: MIB MECANIZADIOS INDUCTRIALES RECOBO 1479 ( RELLENAR POLEA DISTRIBUCION) | C67: 70000
B68: TECNIRACORES Y MANGUERAS CHIMITA FVEP 14656 | C68: 22000
B69: TECNIRACORES Y MANGUERAS CHIMITA FVEP 14658 | C69: 28000
B70: PAGO ALQUILER LUNA NOVIEMBRE ( 56498); DICIEMBRRE ( 46000) Y ABONO A ENERO 2026 $10,000 | C70: 113000 | D70: NEQUI
B71: FERRETERIA FIXXY 25204 ( 1 LB PUNTILLAS 3 " | C71: 5500
B72: PAGO ENERO 20 Y ENERO 21 2026 JOSE | C72: 120000
A73: 46044 | B73: DESMONTAJE Y MONTAJE DE TURBO, CAMBIO RODILLO PATIN TENSOR Y MANTENIMIENTO INTERCOOLER | C73: 270000 | D73: NEQUI
B74: ALMACEN REYCOL SAS ( TECNIMANGUERA FILTRO atre 9007 | C74: 135000
B75: CUENTA DE COBRO JORGE ENRIQUE HERRERA ( INSYTALACION PUNTO RED, INSTALACION BASE MONITOR, RECONFIGURACION DVR | C75: 150000
B76: TUREBOMAX ( REPARACION TURBO Jak hp 55 ( empaquetadyra , alineacion, bujes y rueda compresora | C76: 750000
B77: MIB MECANIZADIOS INDUCTRIALES RECOBO 1479 ( RELLENAR POLEA DISTRIBUCION | C77: 70000
B78: TECNIRACORES Y MANGUERAS CHIMITA FVEP 14656 | C78: 22000
B79: TECNIRACORES Y MANGUERAS CHIMITA FVEP 14658 | C79: 28000
B80: TECNIRACORES Y MANGUERAS CHIMITA FVEP 14583 | C80: 145000
B81: MANO OBRA CAMBIO MANGUERA VEHICULO Y CAMBIO CORREA TRANSMISION | C81: 40000
B82: AUTOSANDOVAL SAS ( CAMBIO ACEITE DEL MOTOR ; FILTRO AVCEITE, FILTRO AIRE Y FILTRO COMBUSTIBLE) | C82: 262000
B83: SUMINISTRRO BASE MONITOR Y FUENTE 12 V- 2 AMOR | C83: 50000
A84: 46045 | B84: TRANSFERIDOS BBVA A CUENTA EMPRESA PAGO FACTURAS | C84: 302411 | D84: BBVA EMPRESA
A85: 46046 | B85: FVE 22202 ARYLIZ ( 1 PAR DE BOTAS ) | C85: 75500 | D85: NEQUI
B86: SEMANA 19 AL 24ENERO 2026 YANETH LUNA | C86: 410000 | D86: NEQUI
B87: SEMANA 19 AL 24 ENERO 2026 EIDER DE JESUS | C87: 425000
B88: SEMANA 19 AL 24 ENERO 2026DIEGO ROJAS | C88: 475000
B89: HORAS EXTRAS DIEGO GUITIERREZ ENERO13 AL 24 ENERO 2026 | C89: 32000 | D89: =C86+C54 -> 748000
B90: HORAS EXTRAS EIDER DE JESUS ENERO 13 AL 24 2026 | C90: 15000
B91: ABONADO HECHURA TABLONES MADERAS MIRANDA | C91: 290000 | D91: NEQUI
A92: 46048 | B92: EDS CHAPINERO TKEO JAC 379405 | C92: 100000
A93: 46049 | B93: FERRETERIA FIXXY 25236 ( 1 TOMA BIFASICO;1 CINTA NEGRA 1 PROBADA CORRIENTE) | C93: 19500
B94: FERRETERIA FIXXY 25237( 9 CHAZOS; 1 CAJA SM Y 70 MTS DE CABLE) | C94: 7500
B95: JOSE CANTILLO PAGO DIA DE TRABAJO | C95: 60000
A96: 46050 | B96: PAGO MOVISTAR | C96: 118000
B97: PAGO INTERESES DE CESANTIAS JIMMY JAIMES | C97: 384840
B98: FERRETERIA FIXXY 25242 ( 2 AEROSOLES) | C98: 20000
B99: FERRETERIA FIXXY 25241( 1 KG SOLDADURA; VIDRIO CARETA) | C99: 23300
A100: 46052 | B100: PAGO IMPUESTO PREDIAL BODEGA EQUIORIENTE | C100: 3388000 | D100: BBVA JIMMY
B101: ABONO ARILYZ 4 PANTALONES | C101: 100000
...

Sheet FEBRERO
B1: INGRESOS
B2: FEBRERO 1 AL 28/ 2026
B3: SALDO EN CAJA: | C3: =ENERO!C112 -> -2874733
A4: FECHA | B4: DETALLE | C4: VALOR
A5: 46055 | B5: ANIBAL MEZA ALQUILERT AL 2 DEFBRERO | C5: 133000
B6: ABONO ENERO CLAUDIA GIL | C6: 300000 | D6: NEQUI
A7: 46057 | B7: ABONO ANTONIO GUTIERREZ | C7: 300000
B8: MARICEL | C8: 100000
A9: 46059 | B9: HERNAN TORRADO A FEBRERO 8 | C9: 196000
B10: ALQUILER ENERO ADRIAN BRAVO A FEBRERO 3 2026 | C10: 487840 | D10: NEQUI
B11: ABONO FEBRERO YURANIS PLACA | C11: 3403450 | D11: BBVA JIMMY
B12: OSWALDO GALVIS BOTERO ALQUIER 10 PARALES POR 8 DIAS FEBRERO | C12: 90000
A13: 46062 | B13: MARICEL | C13: 90000
B14: ALQUILER ANDAMIOS JORG E DIAZ FEBRERO | C14: 65000
B15: ABONO CUENTA ENERO25 A FEBRERO 9 2026 YURANIS | C15: 1500000
A16: 46065 | B16: ABONO ANDREA paola | C16: 1000000 | D16: BBVA JIMMY
B17: ENERO 2026 ALQUIOBRADS | C17: 253600 | D17: nequi
B18: ABONO ALQUILER JORGE | C18: 1000000
A19: 46066 | B19: SEMANA FEBRERO 9 AL 15 HERNAN TORRADO | C19: 91000
B20: Sacados de nequi | C20: 148000
B21: Diego Gutierrez abono ssalidas hasta FEBRERO 15 | C21: 402000
B22: ABONODIEGO GUTIERREZ SALIDA 13337 A PARTIR DEL 11 FEBRERO | C22: 100000
A23: 46067 | B23: ABONO ANDRREA CONKASA | C23: 500000 | D23: BBVA JIMMY
A24: 46069 | B24: ALQUILER SILVIA GOMEZ ENERO 31 A FEBRERO 15 | C24: 1500000
B25: ESCALERA ERACLITO 1 DIA | C25: 30000
B26: FEBRERO 6 AL 13 ANTONIO GUTIERREZ | C26: 200000
B27: CESAR CACERES FEBRERO 6 AL 14 | C27: 353000
A28: 46070 | B28: PAGO DIEGO GUTIERREZ SALDO SALIDA 133732 A PARTIR FEBRERO 11 | C28: 250000 | D28: NEQUI
A29: 46074 | B29: ABONO ALBA GARCIA | C29: 500000 | D29: NEQUI
A30: 46078 | B30: ALQUILER EDUARDO ARIZAFEBRERO SECCIONES ANDAMIO Y TABLONES | C30: 280000
B31: TRANSPORTE EDUARDO ARIZAFEBRERO SECCIONES ANDAMIO Y TABLONES | C31: 20000
B32: ALQUILER COLUMNAS A PARTIR DEL 26 LUIS SANCHEZ Cabecera | C32: 114500 | D32: NEQUI
B33: JUAN PABLO SARMIENTO ALQUYILER ANDAMIOS FEBRERO 2026 | C33: 300000
A34: 46080 | B34: ABONO ENERO CLAUDIA GIL | C34: 700000 | D34: NEQUI
B35: ABONO JORGE ALEXANDER | C35: 1200000
B36: HERNAN TORRADO FEBRERO 23 A MARZO 1 | C36: 100000
B37: PAGO ALQUILER 5 COLUMNAS DUBAN ORTEGA A PARTIR 2 DE MARZO | C37: 263200 | D37: NEQUI
B38: NELSON BERNAL ALQUILER | C38: 81500
A39: 46081 | B39: CESAR CACERES | C39: 12000
B40: SALDO YURANIS FEBRERO | C40: 101000 | D40: BBVA JIMMY
B41: ABONO OBRA JORGE ALEXANDER PLACA KENEDDY | C41: 420000
C42: =SUM(C5:C41) -> 16585090
A44: EGRESOS
A45: FECHA | B45: FEBRERO 1 AL 28/ 2026
B46: DETALLE | C46: VALOR
A47: 46054 | B47: PAPELERIA (LIGAS, SOBRES, RECIBO CAJA MENOR) | C47: 8600
A48: 46055 | B48: LLEVADOS PARA ALQUILER 20 ALINEADORES 6 MTS EL OPERADOR 1 MES | C48: 300000
B49: SALDO MADERAS MIRANDA FVE 1703 | C49: 300000
A50: 46056 | B50: PAGO DIA DE TRABAJO JOSE | C50: 60000
A51: 46057 | B51: P AGO ACARREO KATHERINE TRANSICION | C51: 100000
B52: PAGO ACAREO KHATERIN JAVIER | C52: 25000
A53: 46059 | B53: LLEVO PARA FABRICACION DE DISTANCIADORES CONSORCIO LA VICTORIA | C53: 200000 | D53: COBRAR $4,000
B54: PAGO ALQUILERENERO 31 A FEBRERO 14 1331 DIEGO | C54: 207300
B55: FERRETYERIA FIXXY 25295 ( 2 LBS PUNTILLAS 3 " | C55: 11000
B56: FACTURA 22354 ARYKIZ( 4 JEANS ) | C56: 204000 | D56: NEQUI | E56: 104000
A57: 46060 | B57: EIDE DE JESUS 2 AL 7 FEBRERO /2026 | C57: 350000
B58: DIEGO ROJAS 2 AL 7 FEBRERRO | C58: 475000
B59: JANETH LUNA FEBRERO 2 AL 7 /2026 | C59: 410000
B60: JOSE CANTILLO 4 AL 7 FEBRERO /2026 | C60: 215000
B61: HORAS EXTRAS JOSE CA NTILLO FEBRERO 2 AL 7 | C61: 5000
B62: DIEGO ROJAS HORAS EXTRAS FEBRERO 2 AL 7 | C62: 45000
B63: EIDER DE JESUS HORAS EXTRAS FEBRERO 2 AL 7 | C63: 12500
A64: 46062 | B64: CUENTA DE COBRO 116 ( 4 PARES PROTECTORES AUDITIVOS)TAPAOIDOS 4 PARES | C64: 100000
B65: PINTASMAS FVE 15485 ( 2 GALONES DE ESMALTE Y 2 GALONES DE THINER) | C65: 158000
B66: COMPRA 600 CHAPETAS A JAVIER PARRA | C66: 1450000
A67: 46063 | B67: ACPM JAC DADOS A DIEGO | C67: 100000
B68: RECIBO LUZ FEBRERO 2026 | C68: 85300
A69: 46065 | B69: COMPRA 320 PINES JAVIER PARRA | C69: 256000
B70: PAGO 271 CORBATAS PARA EL CONSORCIO LA VICTORIA A JAVIER PARRA | C70: 763323 | D70: PENDIENTE FACTURA
A71: 46066 | B71: SERVICIO AUTOMOTRIZ FV 0184 (ARREGLO DE CREMALLERA CAMION JAC) | C71: 130000
B72: PAGO 11, 12 Y 13 FEBRERO 2026 JOSE | C72: 180000
B73: PAGO SEMANA 9 AL 14 FEBRERO 2026 YANETH LUNA | C73: 410000
B74: PAGO SEMANA 9 AL 14 FEBRERO 2026 DIEGO ROJAS | C74: 475000
B75: PAGO HORA EXTRA SEMANA 9 AL 14 FEBRERO 2026 DIEGO ROJAS | C75: 10000
B76: PAGO SEMANA 9 AL 14 FEBRERO 2026 EIDER DE JESUS | C76: 425000 | D76: VALOR SEMANA | E76: =SUM(C72:C76) -> 1500000
A77: 46069 | B77: SALDODOTACION PERSONAL | C77: 166000
B78: pago recogida katherin a JAVIER CARMONA | C78: 25000
B79: PAGO FACTURA WOM FEBRERO | C79: 79500
A80: 46070 | B80: FVE 27128INDURRUEDAS CAJA PUNTILLAS 2 "( CAJA PUNTILLAS Caballo 2" x 12 x 500 GMS | C80: 191679 | D80: NEQUI | E80: CON IVA
B81: CERTIFICADO DE TRTADICION Y LIBERTAD | C81: 24300
B82: PARQUEADERO 3 PALACIOS | C82: 2000
B83: 2 PANTALONES JEAN ABONO | C83: 46000
B84: IMPUESTO MUNICIPAL JAC2026 | C84: 98110
B85: COMPTA ACEITE DE MOTO LIMPIEZA LATAS JOSE MESA | C85: 25000
B86: COMPRA DE 6 PARES DE GUANTES | C86: 51000
B87: COMPRA DROGA | C87: 15000
A88: 46072 | B88: VUELTOS DEPOSITO JAVIER FRANCISCO | C88: 109500
B89: ANDAMIOS MAESTRO BERNAL | C89: 10000
B90: LLEVAda 8 parales 3 mts norma | C90: 30000
B91: FERRETERIA FIXXY 25353 ( 1 LB PUNTILLA) | C91: 5550
A92: 46073 | B92: 1 bola de licra negra FERRETERIA FIXXY 25383 | C92: 7000
B93: PAGO SEMANA JOSE 16 AL 21 FEBRERO 2026 | C93: 280000
B94: PAGO SEMANA 16 AL 21 DIEGO ROJAS | C94: 475000
B95: PAGO SEMANA 16 AL 21 EIDER DE JESUS | C95: 375000
B96: PAGO SEMANA 16 AL 21 YANETH LUNA | C96: 410000
B97: TKEO JAC COOPERATIVA MULTIACTIVA EDS LA GACELA | C97: 100000
B98: AUTOSERVICIO ANGELFVE 6976 ( 1 LIQUIDO FRENO) | C98: 30000
B99: PAGO RECOGIDA YURANIS AL SEÑOR RAFAEL TELLEZ | C99: 300000
B100: LLEVADA AL SEÑOR BERNABE PAGADOS A JAVIER | C100: 30000
A101: 46078 | B101: linea fija movistar febrero | C101: 129555
...

Sheet MARZO
B1: INGRESOS
B2: MARZO 1 AL 31/ 2026
C3: =FEBRERO!C117 -> 64040
C4: VALOR
A5: 46085 | B5: PAGO DE POLIMYS A AEO CUENTA ENERO 2026 | C5: 190350
B6: PAGO POLIMYS A AEO CUENTA FEBRERO | C6: 60180
B7: ABONO ALQUILER HERNAN TORRADO A MARZO 3 | C7: 1300000
B8: ALQUILER COLUMNAS MARZO 4 AL 8 LUDWING | C8: 600000 | D8: NEQUI
B9: PAGO ANDRERA CONKASA A MARZO 1 | C9: 1926830 | D9: BBVA
B10: PAGO HERNAN TORRADO MARZO 2026 | C10: 600000
B11: ALQUILER ESCALERA 4M A 8M | C11: 80000
B12: BERNABE ALQUILER PARALES 24 FEBRERO A MARZO 6 2026 | C12: 65000
B13: RETIRO BBVA | C13: 500000 | D13: RETIRO BBVA
B14: PEDRO ROSAS MARZO 2 AL 10 | C14: 1206000
B15: FELIZ CARRILLO | C15: 28000
A16: 46088 | B16: ALQUILER EMILIANO OLIVEROS | C16: 50000 | D16: nequi
B17: ABONO ALQUILER LUIS SANCHEZ MARZO 2026 | C17: 339000 | D17: NEQUI
B18: LUIS ANTONIO CACERES | C18: 647400 | D18: BBVA JIMMY
A19: 46092 | B19: FEBRERO 27 A MARZO 11 YEISON BARBA ANDAMIO | C19: 221000
B20: YORGUIN JAIMES ALQUILER MARZO | C20: 125000
A21: 46094 | B21: ELIAS RIOS ALQUILER MARZO 2026 | C21: 57600
B22: ALQUILER ALBA FEBRERO 27 A MARZO 12 | C22: 530000 | D22: 533350
B23: DIEGO GUTIERREZ ALQUILER 55 PARALES 6 MTS 14 AL 28 MARZO | C23: 250000 | D23: NEQUI
A24: 46095 | B24: RETIRO NEQUI | C24: 1000000 | D24: NEQUI
B25: LUIS SANCHEZ ALQUILER A 31 MARZO 2026 | C25: 727500
A26: 46097 | B26: PEDRO ROSAS SECCION DE ANDAMIOS MARZO 13 AL 17 | C26: 55000
B27: MAESTRO VIDAL COLUMNAS MARZO 12 AL 16 | C27: 250000
B28: RETIRO NEQUI | C28: 410620 | D28: NEQUI
A29: 46098 | B29: HERNAN TORRADO SALDO PLACA A 18 MARZO | C29: 247000
B30: ANDAMIOS DEL 2 AL 15 MARZO HERNAN TORRADO | C30: 200000
A31: 46100 | B31: CRUCE CUENTAS AFEBRERO CLAUDIA GIL | C31: 342135 | D31: NEQUI
B32: MAESTRO VIDAL ALQUILER 20 DE MARZO AL 3 DE ABRIL 2026 | C32: 1320000
A33: 46101 | B33: ABONO DIEGO GUTIERREZ | C33: 300000
A34: 46104 | B34: ABONO DIEGO GUTIERREZ | C34: 300000 | D34: NEQUI
A35: 46107 | B35: DANIEL CORREDOR MARZO | C35: 72000
B36: PEDRO JULIO MARZO | C36: 26350
B37: ELIBARDO GARCIA | C37: 96000
B38: BRAYAN MARZO | C38: 88000
B39: HERNAN TORRADO ALQUILER ANDAMIO 16 AL 22 MARZO | C39: 100000
B40: ALQUILER ESCALERA YORGUIN JAIMES | C40: 20000
B41: ANTONIO GUTIERREZ | C41: 383550
B42: ALQUILER RUEDAS DEL 27 AL 31 DE MARZO 2026 | C42: 20000
B43: RETIRO PAGO DE NOMINA | C43: 1000000 | D43: BBVA JIMMY
A44: 46111 | B44: ALQUILER ANDAMIOS MARTIN ESTUPIÑAN | C44: 107000
A45: 46112 | B45: ALFONSO GARCIA 31 MARZO 2026 | C45: 785450
B46: ALQUILER JORGE ALEXANDER A 31 MARZO | C46: 800000
C47: =SUM(C5:C46) -> 17426965
A49: EGRESOS
B50: MARZO 1 AL 31/ 2026
A51: 46084 | B51: PAGO A POLIMYS CUENTA DE ENERO | C51: 441120
B52: ABONO A POLIMYS CUENTA FEBRERO | C52: 558880
B53: SALDO A POLIMYS CUENTA FEBRERO 2026 | C53: 435400
B54: ESTACION SERVICIO SANTA MARTHA EMANUEL 1166048 | C54: 100000
A55: 46085 | B55: RECARGA EXTINTOR 2500 GMS SOLKAFLAN | C55: 70000
B56: CAJAS FUERTES VIVIAN SECURITY 4008(1 CAJA MENOR AZUL) | C56: 50000
A57: 46087 | B57: PAGO LINEA 3005678367 | C57: 24950 | D57: NEQUI
B58: PAGO LINEA 3016032896 | C58: 24950 | D58: NEQUI
A59: 46088 | B59: DIEGO ROJAS SEMANA DEL 2 AL 7 | C59: 550000
B60: JANETH LUNA SEMANA DEL 2 AL 7 | C60: 410000
B61: EIDER JESUS SEMALA DEL 2 AL 7 | C61: 425000
B62: ESTRA 1,25 DIEGO ROJAS | C62: 12000
A63: 46091 | B63: ESTACION DE SERVICIO SANTA MARTHA TKEO JAC | C63: 100000
B64: PAGO DIA TRABAJO YEIDER | C64: 70000
A65: 46092 | B65: ABONO A HECHURA TALONARIO | C65: 50000 | D65: SALDO
B66: DESCARGA CAMION JAVIER | C66: 40000 | E66: 60000
B67: COMPRA 20 PARES DE GUANTES | C67: 100000
B68: FERRETERIA FIXXY 25458 (AEROSOL BERMELLON Y 1 CJA DE PUNTILLA 3´) | C68: 15800
B69: PAGO DE TRANSPORTE JAVIER EMILIANO | C69: 10000
B70: FERRETERIA CAPITALIZ 32876 ( 2 KILOS SOLDADURA 6013 1/8¨´) | C70: 32000
B71: FERRETERIA FIXXY 25489 (2 DISCOS DE PULIR 1 AEROSOL BERMELLON) | C71: 21600
B72: PAGO EL OPERADOR ALQUILER MARZO ALINEADORES 7 DE MARZO AL 5 DE ABRIL2026 | C72: 300000
A73: 46094 | B73: MADERAS MIRANDA FV 1710 ( 6 TABLASDE 2,1X0,35X0,018) | C73: 147000
B74: ARRIENDO MES DE MARZO JHON | C74: 340000 | D74: NEQUI
A75: 46095 | B75: DIEGO ROJAS SEMANA DE MARZO 9 AL 14 | C75: 550000
B76: JANETH LUNA SEMANA DE MARZO 9 AL 14 | C76: 410000
B77: EIDER DE JESUS SEMANA DEL 9 AL 14 | C77: 425000
B78: PRESTAMO A EIDER DE JESUS | C78: 100000
B79: HORAS EXTRAS EIDER DE JESUS | C79: 20000
B80: HORAS EXTRAS DIEGO ROJAS | C80: 20000
A81: 46097 | B81: PAGO DE RECIBO DE LUZ | C81: 120621
B82: ALMACEN EL TORNILLO (84 TORNILLO GRADO 3/8´x3/4)) | C82: 27720
B83: ALMACEN REYCOL SAS TUBERIA 3/18 | C83: 13360
B84: ARRIENDO HEIDY MARZO 2026 | C84: 340000 | D84: NEQUI
B85: ARRIENDO JIMMY MARZO 2026 | C85: 340000 | D85: EFCTIVO
B86: ARRIENDO FLORALBA MARZO 2026 | C86: 1246000 | D86: BBVA
B87: PAGO ACARREO NORMA JAVIER | C87: 30000
A88: 46098 | B88: LUNA SANCHEZ FEBRERO 2026 | C88: 125750
B89: ACARREO ADRIAN BRAVO JAVIER | C89: 35000
A90: 46099 | B90: FERRETERIA FIXXY 25509 ( 1 LIBRA DE PUNTILLA 1´CORRIENTE) | C90: 6000
B91: LLEVO TALONARIOS RABAC | C91: 60000
B92: PAGO ALQUILER TRONZADORA | C92: 40000
A93: 20-/03/2026 | B93: RETIRADOS EN EFECTIVO PAGO FVE 631, FVE 632, FVE 635,FVE636 | C93: 160000 | D93: SACAR DE NEQUI Y REPONER
B94: MULTIACTIVA TAXIS Y TRANSPORTES | C94: 100000
A95: 46102 | B95: HORA EXTRA EIDER | C95: 10000
B96: HORA EXTRA DIEGO | C96: 10000
B97: EIDER DE SEMANA DEL 16 AL 21 DE MARZO | C97: 425000
B98: DIEGO ROJAS SEMANA DEL 16 AL 21 DE MARZO | C98: 550000
B99: JANETH LUNA SEMANA DEL 16 AL 21 DE MARZO | C99: 410000
B100: FERRETERIA FIXXY FV202F-41907 ( DETERGENTE PAPEL HIGIENICO LIMPIADOR) | C100: 51750
A101: 46106 | B101: PAGO DIA JOSE CANTILLO | C101: 60000
...

Sheet ABRIL
B1: INGRESOS
B2: ABRIL 1 AL 30/ 2026
C3: =MARZO!C123 -> 4581555
A5: 46119 | B5: MARIA RUTH SAAVEDRA | C5: 900000 | D5: NEQUI
A6: 46120 | B6: DUBAN ORTEGA | C6: 500000 | D6: NEQUI
B7: JORGE ALEXANDER | C7: 800000 | D7: NEQUI
B8: RAUL DELGADO CARREÑO | C8: 300000 | D8: NEQUI
A9: 46127 | B9: RAUL QUINTERO | C9: 112000
A10: 46128 | B10: TILCIA URIBE DURAN | C10: 200000 | D10: NEQUI
B11: YINA MARCELA RAMOS | C11: 333683 | D11: NEQUI
B12: ALQUILER ANDAMIOS NARYAM BLANDON | C12: 25000
B13: ABONO PLACA 20 ABRIL DIEGO | C13: 300000 | D13: NEQUI
A14: 46131 | B14: ABRIL 11 AL 19 ANTONIO GUTIERREZ | C14: 314000
B15: ALQUILER MAESTRO RIGO ABRIL 21 A MAYO 5 | C15: 1500000
B16: EDUARDO CORREDOR ANDAMIOS | C16: 20000
B17: WILSON PARRA ANDAMIOS 21 AL 25 ABRIL | C17: 55000
B18: PARALES HERNANDO GARCIA | C18: 22000
A19: 46132 | B19: RETIRO POR NEQUI | C19: 2000000 | D19: NEQUI
A20: 46134 | B20: BRYAN GARZON ALQUILER ABRIL MARZO | C20: 30000
B21: NELSON PADILLA PAGO HASTA EL 21 ABRIL | C21: 722340
B22: HOLGUER ALQUILER PLACA | C22: 1300000
B23: LUIS CACERES A ABRIL 22 PARALES Y FORMALETA | C23: 79300
B24: GRERORIO HERNAN DEZ A ABRIL 21 | C24: 183700
A25: 46136 | B25: CESAR AUGUSTO HERNANDEZ | C25: 602500 | D25: NEQUI
A26: 46139 | B26: LUIS SANCHEZ ALQUILER ABRIL 1 AL 24 | C26: 966000
B27: EDUARDO TOLOZA ALQUILER FORMALETA 21 AL 24 ABRIL | C27: 210350
B28: ANDREI ALQUILER COLUMNAS PRIMER PISO ANDREI | C28: 917450 | D28: DAVIPLATA
A29: 46141 | B29: DUBAN ORTEGA 42 CHAPETAS | C29: 126000
B30: DUBAN ORTEGA SALDOALQUILE | C30: 91600
B31: PARALES DUBAN | C31: 56000
B32: HERNAN TORRADO ABRIL 1 AL 30 | C32: 687000
B33: JOSE LUIS SILVA 1 ANDAMIO | C33: 7500
B34: ELIAS RIOS | C34: 46400
B35: LAURA ROCHA | C35: 30000
C36: =SUM(C5:C35) -> 13437823
B38: EGRESOS
B39: ABRIL 1 AL 30/ 2026
A40: 46119 | B40: PAGO LINEA EMPRESA TIGO | C40: 26950 | D40: NEQUI
B41: PAGO LINEA EMPRESA TIGO | C41: 26950 | D41: NEQUI
A42: 46123 | B42: YANETH LUNA ABRIL 6 AL 11 ABRIL | C42: 400000
B43: DIEGO ROJAS ABRIL 6 AL 11 | C43: 450000
B44: EIDER DE JESUS ABRIL 6 AL 11 | C44: 425000
B45: RETIRO POR NEQUI | C45: 127000 | D45: NEQUI
A46: 46125 | B46: JAVIER CARMONA TRANSPORTE ADRIAN BRAVO | C46: 35000
B47: TRANSPORTE DISQUINAL | C47: 20000
B48: PAGO ALQUILER MARSZO 2026 POLIMYS | C48: 556630
B49: ABONOALQUILER ABRIL 2026 POLIMYS | C49: 6820
A50: 46129 | B50: FERRETERIA FVE 25689 ( 1 AEROSOL AZUL) | C50: 10000
A51: 46129 | B51: YANETH LUNA ABRIL 13 AL 18 | C51: 400000
A52: 46130 | B52: DIEGO ROJAS ABRIL 13 AL 18 | C52: 450000
B53: EIDER DE JESUS ABRIL 13 AL 18 | C53: 425000
B54: HORA Y MEDIA EXTRA EIDER | C54: 15000
B55: HORA Y MEDIA EXTRA DIEGO | C55: 15000
B56: MULTIACTIVA DE TAXIS Y TRANSPORTES LA GACELA | C56: 100000
A57: 46132 | B57: PAGO SERVICIO DE LUZ | C57: 127500
A58: 46133 | B58: PAGO MES DE MARZO 2026 LUNA SANCHEZ | C58: 148220
A59: 46134 | B59: FERRETERIA CAPITALIZ SAS FVE 33635 ( 2 KILOS SOLDADURA, 1 CINTA ENMASCARAR 4 PLIEGOS LIJA | C59: 48000
A60: 46135 | B60: FUL REPUESTOS FV FCO 2642 ( FVE 2642 ( LIQUIDO DE FRENOS, BOMBA PRINCIPAL EMBRAGUE) | C60: 330001
B61: MIS FRENOS NO 0721 ( MANO OBRA CAMBIO CLUCTH) | C61: 50000
B62: DOTACIONES MAGALY FV 1446 ( 1 BOTAS CP 34) | C62: 60000
B63: pago recibo agua bodega febrero 2026 | C63: 90300
B64: TKEO ACPM LATAS | C64: 150000
A65: 46137 | B65: LAVADO GENERAL CAMION JAC | C65: 70000
B66: PAGO ACARREO JAVIER CARMONA | C66: 25000
B67: DIEGO ROJAS SEMANA DEL 20 AL 25 ABRIL | C67: 550000
B68: EIDER DE JESUS SEMANA 20 AL 25 ABRIL | C68: 425000
B69: YANETH LUNA SEMANA 20 AL 25 ABRIL | C69: 410000
B70: HORAS EXTRAS DIEGO ROJAS SEMANA | C70: 20000
B71: HORAS EXTRAS EIDER DE JESUS SEMANA | C71: 20000
B72: HORAS EXTRAS YANETH LUNA SEMANA | C72: 10000
B73: MOVISTAR ABRIL | C73: 129555
A74: 46138 | B74: AUTOSDANDOVAL CAMBIOS DE ACEITE MOTOR Y FILTROSCAMBIO ACEITE JAC | C74: 262000
B75: SERVICIOS CONTABLES ABRIL 2026 | C75: 300000
B76: ABONO A FABRICACION CHAPETAS JAVIER PARRA | C76: 100000
B77: LUZ NELLY BALDOVINO | C77: 27000 | D77: NEQUI
B78: PRESTAMOLLEVO PAGO SERVICIOS PUBLICOS CASA DIAMANTE 2 | C78: 200000
B79: ANA MARLENY GARZON | C79: 12000
A80: 46139 | B80: ARRIENDO BODEGA FLOR ALBA CARRILLO | C80: 1246000 | D80: NEQUI
A81: 46139 | B81: ARRIENDO BODEGA JIMMY JAIMES | C81: 340000 | D81: NEQUI
A82: 46139 | B82: ARRIENDO BODEGA JHON JAIMES | C82: 340000 | D82: NEQUI
A83: 46139 | B83: ARRIENDO BODEGA HEIDEY JAIMES | C83: 340000 | D83: NEQUI
B84: DADOS A YANETH PAGO JOSE CANTILLO 27 AL 30 ABRIL 2026 | C84: 310000
B85: HORA EXTRA EIDER DE JESUS | C85: 20000
B86: SEMANA MAYO 4 AL 10 EIDER DE JESUS | C86: 425000
B87: YANETH SEMANA MAYO 4 AL 10 | C87: 410000
B88: SEMANA MAYO 4 AL 10 DIEGO ROJAS | C88: 550000
B89: HORA EXTRA SEMANA MAYO 4 AL 10 DIEGO ROJAS | C89: 20000
B90: DESPINCHADA LLANTA JAC | C90: 10000
B91: TKEO JAC | C91: 100000
B92: PAGO ALQUILER ABRIL LUNA SANCHEZ | C92: 287364
C93: =SUM(C40:C92) -> 11452290 | D93: =C36-C93 -> 1985533
C94: =C3+C36-C93 -> 6567088
C132: =+D112 -> 0
C133: */
C154: aq

Sheet MAYO
B1: INGRESOS
B2: MAYO 1 AL 31/ 2026
C3: =ABRIL!C94 -> 6567088
A5: 46149 | B5: DIEGO GUTIERREZ PAGO ALQUILER DE 8 MAYO EN ADELANTE POR 15 DIAS TABLEROS MADERA Y CERCHAS | C5: 387000
B6: SACADOS DE NEQUI | C6: 200000
A7: 46150 | B7: ALQUILER YESENIA MURILLO | C7: 135000
B8: ALQUILER RAMIRO DULCEY | C8: 180000
A9: 46151 | B9: alquiler 4 columnas 30 x 20 del 11 al 15 myo villa carmelo GUSTAVO AFANADOR RUBIO | C9: 77750
A10: 46151 | B10: pago abril a mayo 5 adrian bravo JOHANA GUTIERREZ MORELOS | C10: 781740
B11: MAESTRO VIDAL ALQUILER COLUMNAS PRIMER PIS9O MAYO 12 AL 17 | C11: 400000
A12: 46155 | B12: ALQUILER ANDAMIOS ALINA | C12: BBVA
B13: MAESTERO RIGOBWERTO VARELA | C13: 250000
B14: ABONO ALQUILER ANDAMIOS JUAN DAVID ANGARITSA GUTIERREZ | C14: 300000
B15: ALQUILER COLUMNAS ROSA MAYO 14 AL 18 | C15: 300000
A16: 46157 | B16: ABONO JHON JIMENEZ ALQUILER A PARTIR 19 MAYO | C16: 500000
B17: ANDAMIOS LADI | C17: 50000
B18: FIDEL CARO MAYO | C18: 89000
B19: PEDRO ALQUILER AL 22 ABRIL | C19: 407000
A20: 46163 | B20: ALQUILER COLUMNAS MAESTRORONDON | C20: 352000
A21: 46164 | B21: CESAR ANDAMIOS A 21 MAYO | C21: 302000
A22: 46165 | B22: SACADOS CDE NEQUI | C22: 1000000
B23: ESCALERA VERDE LIDA | C23: 30000
A24: 46168 | B24: ALQUILER DIANA PUERTO RICO A PARTIR 27 MAYO 2026 | C24: 500000
B25: ALQUILER PLACA DIANA PUERTO RICO | C25: 1000000
B26: GIOVANI SIERRA ALQUILER 18 PARALES 4 MTS | C26: 93000
A27: 46170 | B27: PAGO ALQUILER COLUMNAS MAESTRO VIDAL | C27: 171200
A28: 46171 | B28: FABIANH ANDRES GARCIA PORTILLA SALIDA 13759 DEL 29 MAYO AL 5 5 JUNIO 2026 | C28: 388400
B29: DIEGO ARMANDO GUTIERREZ FLOREZ 13 760 29 MAYO AL 4 JUNIO PARALES 6 MTS Y CERVHA 2 MTS | C29: 18000
B30: FREDDY ESCAMILLA SAL 13761 12 PARALES 3 MTS Y 4 CERCHAS 3 MTS | C30: 100000
B31: ALQUILER ELIAS RIOS ALQUILER MAYO 2026 | C31: 500000
B32: ALQUILER EDUARDO TOLOZA | C32: 690000
B33: ALQUILER ANDAMIOS PEDRO JULIO PABON ENTRADA 133358 | C33: 25000
B34: MAESTRO VIDAL ALQUILER PLACA MAYO 20 AL 29 | C34: 445000
A35: 46173 | B35: ALQUILER HERNAN TORRADO MES DE MAYO 2026 | C35: 617000
C36: =SUM(C5:C35) -> 10289090
B38: EGRESOS
B39: MAYO 1 AL 31/ 2026
A41: 46146 | B41: 3 DISCOS E CORTE FERRERIA LA 21 | C41: 7500
A42: 46147 | B42: DESPINCHE CAMION JAC | C42: 25000
B43: PAGO 2 LINEAS TIGO EQUIORIENTE | C43: 53900 | D43: NEQUI
B44: ABONO TABLAS ARREGLO TABLEROS | C44: 33000
B45: EL PUNTO FERRETERO GATO JAC | C45: 150000
A46: 46150 | B46: fv 1726 ( 21 tablas de 18 lineas x 3 mts x 30 cms) DEPOSITO DE MADERAS MIRANDA | C46: 533000
B47: PAGO ACARREO A JAVIER YESENIA MURILLO | C47: 25000 | D47: NEQUI
B48: COMPRA 32 CORBATAS muro de 20 cms y 10 TENSOrES JAVIER PARRA | C48: 176000
B49: YANETH LUNA | C49: 410000
B50: EIDER DE JESUS | C50: 375000
B51: DIEGO ROJASPAGO SEMANA DEL 4 AL 10MAYO | C51: 550000
B52: HORA EXTRA DIEGO | C52: 10000
B53: TKEO JAC | C53: 100000
B54: BONI PRIMERA QUINCENA MAYO DIEGO ROJAS | C54: 200000
A55: 46155 | B55: SOLUCIONES MAP SAS FVE BO1T-45381( BOLIGRAFO, CARTULINA, EGERSO, LAPICES) | C55: 44120
B56: TRAIDA ESCALERA YESENIA MURILLA | C56: 25000
A57: 46156 | B57: FERRETERIA FIXXY 25831 ( 3 LB PUNTILLAS ) | C57: 18000
A58: 46157 | B58: PAGO SERVICIO LUZ ESSA MES DE MAYO 2026 | C58: 110300
B59: TKEO JAC COOPERATIVA MULTIACTIVA DE TAXIS | C59: 100000
B60: TRAIDA ANDAMIOS YESENIA MURILLA | C60: 25000
A61: 46158 | B61: PAGO TRANSPORTE FIDEL CARO | C61: 20000
B62: EIDER DE JESUS PAGO DEL 11 AL 16 MATO 2026 | C62: 350000
B63: YANETH LUNA PAGO DEL 11 AL 15 MAYO 2026 | C63: 360000
B64: DIEGO ROJASPAGO SEMANA DEL 11 AL 17 MAYO | C64: 550000
B65: PAGO 2 HORAS EXTRAS EIDER | C65: 20000
B66: PAGO 3 HORAS EXTRAS DIEGO | C66: 30000
A67: 46161 | B67: PAGO GUANTES | C67: 15000
A68: 46163 | B68: PAGO LINEA TIGO 3005678638 | C68: 26950
B69: PAGO LINEA TIGO 3016032896 | C69: 26950
A70: 46165 | B70: MEGAREDIL A TU SERVIVIO FV 211F-102002 ( ASEO EMPRESA) | C70: 131855
B71: DIEGO ROJAS SEMANA DEL 19 AL 234 MAYO 2026 | C71: 450000
B72: EIDER DE JESUS SEMANA DEL 19 AL 23 MAYO 2026 | C72: 350000
B73: YANETH LUNA SEMANA DEL 19 AL 23 MAYO 2026 | C73: 338000
B74: EIDER DE JESUS 2 HORAS EXTRAS SEMANA 19 AL 23 MAYO 2026 | C74: 20000
B75: DIEGO ROJAS 2 HORAS EXTRAS SEMANA 19 AL 23 MAYO 2026 | C75: 20000
A76: 46163 | B76: TKEO JAC FEC 993867 | C76: 102000
A77: 46169 | B77: PAGO RECIBO AGUA MARZO 2026 | C77: 91310
B78: PAGO SERVICIO INTERNET Y LINEA FIJA MES DE MAYO | C78: 128990
B79: COMPRA 4 PARES DE GUANTES | C79: 20000
A80: 46170 | B80: TKEO JAC 1067781 | C80: 100000
A81: 46171 | B81: DEPOSITO DE MADERAS MIRANDA FV 173 0 ( 23 cercos 8 x 4 x 300 cm y tablas 18 mm de espesor sobrantes | C81: 440000
B82: BONI SEGUNDAQUINCENA MAYO DIEGO ROJAS | C82: 200000
B83: PAGO DIA DE TRABAJO CESAR | C83: 75000
A84: 46172 | B84: 1 PIMPINA ACEITE QUMADO | C84: 30000
B85: PAGO EIDER SEMANA TRABAJO 25 AL 31 MAYO | C85: 425000
B86: PAGO DIEGO ROJASSEMANA TRABAJO 25 AL 31 MAYO | C86: 550000
B87: PAGO YANETH LUNA SEMANA TRABAJO 25 AL 31 MAYO | C87: 410000
A88: 46173 | B88: ARRIENDO BODEGA EQUIORIENTE HEIDY MILENA JAIMES MAYO 2026 | C88: 340000
B89: ARIIENDO BODEGA EQUIORIENTE JHON JAIMES MAYO 2026 | C89: 340000
B90: ARRIENDO BODEGA EQUIORIENTE JIMMY JAIMES CARRILLO JAIMES MAYO 2026 | C90: 340000
B91: ARRIENDO BODEGA EQUIORIENTE FLOR ALBA CARRILLO DE JAINES MAYO 2026 | C91: 1246000
B92: SERVICIOS CONTABLES MAYO 2026 | C92: 300000 | D92: EFECTIVO
C93: =SUM(C41:C92) -> 10817875 | D93: =C36-C93 -> -528785
C94: =C3+C36-C93 -> 6038303
O101: 21780679
N113: 3800000
N114: 2865000
N115: =N113-N114 -> 935000

Sheet JUNIO
B1: INGRESOS
B2: JUNIO 1 AL 30/ 2026
C3: =MAYO!C94 -> 6038303
A5: 46174 | B5: ANTONIO GUTIERREZ ALQUILER PLACA BERLIN | C5: 1000000
B6: SERGIOP RUEDA ALQUILER PLACA METALICA | C6: 2000000
A7: 46176 | B7: SALDO ROSA A 29 MAYO | C7: 476000
B8: SALDO LUDWING MAYO 2026 | C8: 295700
A9: 46180 | B9: PAGO ALQUILER YURANIS | C9: 138100 | D9: BBVA
B10: BBVA DEPOSITO POR ALQUILER PLACA LA INDEPENDENCIA LUDWING | C10: 1500000 | D10: BBVA
B11: SALDO 7 MAYO A JUNIO 6 ELIAS RIOS | C11: 688000
B12: HERNAN TORRADO ALQUILER SECCIONES ANDAMIO CG Y TABLONES JUNIO 2 AL 8 | C12: 246300
B13: HERNAN TORRADO ALQUILER ANDAMIOS COLGANTES 9 DE JUNIO AL 23 | C13: 407500
B14: ALQUILER ESCALERA EXTENSION 6 MTS | C14: 90000
B15: EDUARDO TOLOZA MAYO 17 A JUNIO 5/2026 | C15: 1208000
B16: PAGO DE ALQUILER PLACA A JULIO 10 ANDREI | C16: 1000000 | D16: DAVIPLATA
A17: 46183 | B17: DEPOSITO POR NEQUI LUZ MARINAPEREZ ALQUILER POLEAS SALIDA 13792 | C17: 700000 | D17: NEQUI
B18: DEPOSITO POR NEQUI LUZ MARINA PEREZ ALQUILER POLEAS SALIDA 13792 | C18: 300000 | D18: NEQUI
B19: ALQUILER PRESTAMO ANDAMIOS SHIRLEY16 JUNIO2026 | C19: 151500 | D19: NEQUI | E19: 300000
A20: 46185 | B20: ALQUILER DE FORMALETA 60 X 120; FORMALETA 25 X 120 CSAR RINCON | C20: 273520 | D20: NEQUI
B21: ALQUILER YAZMIN PACHECO ALQUILER COLUMNAS DE 30 X 120 | C21: 277150 | D21: NEQUI | E21: 500000
A22: 46190 | B22: RETIRO NEQUI | C22: 1200000 | D22: NEQUI
B23: cesar augusto alquiler JUNIO 11 AL 17 | C23: 190600 | D23: EFECTIVO | E23: 500000 | F23: 339400
A24: 46191 | B24: ALQUILER FORMALETA COLUMNAS JOSE DAVID 19 AL 23 JUNIO | C24: 305500 | D24: NEQUI
B25: ALQUILER MAYO 29 A JUNIO 14 C ARLOS PINILLA | C25: 500000
B26: ALQUILER PLACA DOÑA ROSA SALIDA 13720 A PARTIR 19 JUNIO | C26: 1000000
B27: ELISEO ALQUILER ANDAMIOS JUNIO | C27: 257300
B28: RETIRO NEQUI | C28: 1300000 | D28: NEQUI
A29: 46197 | B29: ALQUILER FORMALETA COLUMNAS ELCY ANGELICA NIÑO AGUDELO | C29: 216000 | D29: NEQUI
B30: DEPOSITO ALQUILER FORMALETA COLUMNAS ELCY ANGELICA NIÑO AGUDELO | C30: 584800 | D30: NEQUI
B31: SALDO ADEUDADO JHON JIMENEZ A JUNIO 11 2026 | C31: 512500 | D31: NEQUI
A32: 46229 | B32: SALDO ALQUILER SAN FRANCISCO ANDREA A 19 JUNIO | C32: 184250 | D32: NEQUI
A33: 46200 | B33: ANTONIO GUTIERREZ PAGO 100 PARALES MAYO 7 A JUNIO 26 | C33: 845000
B34: NELSON PADILLA ALQUILER POLEAS JUNIO 14 AL 26 | C34: 445000
B35: JEFERSON ALQUILER JUNIO 22 AL 26 | C35: 82500
B36: ANTONIO GUTIERREZ ABONO PLACA MADERA JUNIO 5 AL 26 | C36: 500000
B37: FREDDY ESCAMILLA ALQUILER MAYO 29 A JUNIO 26 | C37: 39000
A38: 46203 | B38: PAGOSALDO PENDIENTE ALQUILER ROSA | C38: 316000
B39: PAGO REPOSICIONPENDIENTE ROSA | C39: 326000
B40: PAGO EN EFECTIVO EL 4 DE JULIO ALQUILER LUDWING JUNIO 9 AL 26 2026 | C40: 1957000
B41: PAGO ALQUILER PLACA CESAR RINCON | C41: 1500000 | D41: BBVA JIMMY
C42: =SUM(C5:C41) -> 23013220
B46: EGRESOS
B47: JUNIO 1 AL 30/ 2026
A48: 46173 | B48: ARRIENDO BODEGA EQUIORIENTE HEIDY MILENA JAIMES JUNIO 2026 | C48: 340000 | D48: EFECTIVO
A49: 46174 | B49: ARRIENDO JHON .AYO 2026 BODEGA | C49: 340000 | D49: NEQUI
B50: ARRIENDO JIMMYUNIO 2026 BODEGA | C50: 340000 | D50: NEQUI
A51: 46175 | B51: FLORALBA JUNIO 2026 BODEGA | C51: 1246000 | D51: NEQUI
A52: 46176 | B52: ZUNCHOS COMPRADOS | C52: 20000
B53: DIEGO ROJAS JUNIO 1 AL 6 2026 | C53: 550000
B54: EIDER DE JESUS JUNIO 1 AL 6 2026 | C54: 425000
B55: JANETH LUNA JUNIO 1 AL 6 2026 | C55: 410000
A56: 46179 | B56: PAGO 4 HORAS EXTRAS EIDER DE JESUS | C56: 40000
A57: 46182 | B57: ESTACION SANTA MARTA 1233257 TKEO JAC | C57: 100000
A58: 46184 | B58: FERRETERIA FIXXY 25697( 2 LBS PUNTILLA 3 " Y 2 AEROSOLES BERMELLON) | C58: 32000
A59: 46186 | B59: EIDER DE JESUS SEMANA JUNIO 8 AL 13 | C59: 425000
B60: JANETH LUNA JUNIO 8 AL 13 | C60: 338000
B61: DIEGO ROJASA SEMANA JUNIO 8 AL 13 | C61: 550000
B62: YESID SEMANA JUNIO 9 AL 13 | C62: 340000
B63: YESID HORAS EXTRAS 4, 5 HORAS | C63: 45000
B64: ALMACEN EL TORNILLO ETFE 137890 ( 7 TORNILLOS CON TUERCA Y RANDELA | C64: 17500
A65: 46188 | B65: 2 PIMPINAS DE 5 GALONES ACEITE QUEMADO | C65: 40000
B66: PRIMAS Y PARCIAL CESANTIAS EIDER DE JESUS A MITAD DE AÑO | C66: 1200000
B67: PAGO RECIBO LUZ MAYO 2026 | C67: 112706
B68: PAGO ALQUILER ALINEADORES EL OPERADOR ABRIL 6 A JUNIO 4 2026 OBRA CONSORCIO LA VICTORIA 2 | C68: 600000
B69: PAGO LUNA SANCHEZ MAYO | C69: 309200
B70: PAGO JUNIO 16 Y 17 YESID Y MEDIA EXTRA | C70: 155000
A71: 46190 | B71: COTAXI 1092479 ( TANKEO JAC | C71: 100000
A72: 46191 | B72: COMPRA DE ACEITE QUEMADO; Y 4 GALONES ACPM RESIDUAL | C72: 80000 | D72: nequi
A73: 46193 | B73: DIEGO ROJAS SEMANA LABORADA 15 AL 20 DE JUNIO | C73: 550000
B74: EIDER DE JESUS SEMANA 15 AL 20 DE JUNIO | C74: 425000
B75: BONIFICACION DIEGO ROJAS | C75: 200000
B76: JANETHY LUNA SEMANA 16 AL 20 JUNIO | C76: 338000
B77: HORAS EXTRAS DIEGO ROJAS | C77: 60000
A78: 46195 | B78: ALMACEN REYCOL SAS # 4A 35211 ( TUBERIA 3 / 16 HIERRO X MTS COLD ROLL 3 -TUH0845 | C78: 27286
B79: ANDRES MAURICIO SERRANO GUIZA FVE E 29602 ( 1 LIQUIDO DE FRENOS ATE DOT 4 SL X 1 LTRS | C79: 53000
B80: FERRETERIA FIXXY 25987 ( 3 AEROSOL BERMELLON | C80: 30000
B81: FERRETERIA FIXXY 25967 (2 LBS PUNTILLAS 3 "; 2 AEROSALES | C81: 32000
A82: 46196 | B82: DADOS A YANETH PAGO INTERNET Y AGUA | C82: 204000
A83: 46197 | B83: TKEO JAC | C83: 100000
A84: 46198 | B84: ABONO CUENTA EQUIORIENTE A POLIMIS MAYO 2026 | C84: 400000
B85: PAGO RECOGIDA JEFFERSON JAVIER | C85: 20000
B86: COMPRA 3 PARES DE GUANTES | C86: 15000
B87: PAGO LLEVADA ESCALERA FALLIDA JAVIER CARMONA SEGÚN SALIDA 13744 | C87: 20000 | D87: PENDIENTE COBRAR A ANDREA
B88: PAGO SEMANA A DIEGO ROJAS 22 AL 27 DE JUNIO 2026 | C88: 550000
B89: YANETH LUNA SEMANA 22 AL27 JUNIO 2026 | C89: 410000
B90: YANETH LUNA SEMANA 22 AL27 JUNIO 2026 1 HORA EXTRA | C90: 10000
B91: CESAR ROJAS SEMANA DEL 24AL 27 JUNIO | C91: 265000
B92: CESAR ROJAS SEMANA DEL 24 AL 27 JUNIO | C92: 25000
B93: EIDER DE JESUS SEMANA 22 AL 27 JUNIO 2026 | C93: 425000
A94: 46199 | B94: ABONO ALQUIER POLIMYS MES DE MAYO | C94: 92210
B95: SALDO POLIMYS MES DE ABRIL 2026 | C95: 7790
A96: 46201 | B96: COMPRA MULTIFUNCIONAL CANON | C96: 818350
A97: 46203 | B97: PAGO HORAS EXTYRAS DIEGO 4 Y 45 MINUTOS JUNIO 22 AL 30 2026 | C97: 47500
B98: PAGO BONIFICACION DIEGO ROJAS A JUNIO 28 AL 30/2026 | C98: 300000
B99: SERVICIOS CONTABLES JUNIO 026 | C99: 300000 | D99: EFECTIVO
C100: =SUM(C48:C99) -> 13880542 | D100: =C42-C100 -> 9132678
C101: =C3+C42-C100 -> 15170981

Sheet JULIO
B1: INGRESOS
B2: JULIO 1 AL 31/ 2026
C3: =JUNIO!C101 -> 15170981
A4: 46204 | B4: ALQUILER MAYO 29 A JUNIO 14 CARLOS MIGUEL MAYO | C4: 210840 | D4: NEQUI
B5: PAGO 10 CHAPETAS EXTRAVIADAS JUNIO CARLOS MIGUEL RAZON DE $3000 / UNIDAD | C5: 30000 | D5: NEQUI
B6: ABONO ALQUILER MATERIAL PLACA DE JULIO 1 AL 8 INCLUYE TRANSPORTE ANGELICA CONCORDIA | C6: 511000 | D6: NEQUI
B7: NELSON BERNAL JULIO | C7: 83000 | D7: NEQUI
A8: 46209 | B8: RECARGA DESDE BANCOLOMBIA POR ANDAMIOS | C8: 400000 | D8: NEQUI
B9: ANDREI CADENA ADICIONAL PLACA HASTA 10 DE JULIOY CIMENTACION DEL 8 AL 12 JULIO | C9: 804000 | D9: DAVIPLATA
A10: 46211 | B10: PAGO SALDO SERGIO JULIO 8 /2026 | C10: 2310880
B11: SACADOS DE NEQUI | C11: 630000 | D11: NEQUI
B12: ALFONSO GARCIA ALQUILER 5 DIAS COLUMNAS | C12: 237000
B13: ALFOSOL ALQUIKLER CORBATAS Y PLACA | C13: 215000
B14: HERNAN TORRADO ABONO ALQUILER JUNIO- JULIO 2026 | C14: 500000
B15: WILSON PAEZ DEPOS ITO POR ALQUILER | C15: 500000
B16: ALFONSO LIZCANO ESCALERA | C16: 30000
B17: JUAN DAVID ANGARITA | C17: 15000 | D17: EFECTIVO
A18: 46217 | B18: DEPOSITO WILSON PAEZ | C18: 200000 | D18: NEQUI
B19: SALDO ALQUIOBRAS A JUNIO 30 2026 | C19: 375550 | D19: NEQUI
A20: 46218 | B20: YURANIS JULIO 7 AL 13 | C20: 123400 | D20: NEQUI
B21: CONSIGNADO EN DAVIPLATA POR ANDREI | C21: 50000 | D21: DAVIPLATA
B22: WILSON PAEZ DEPOSITO | C22: 700000 | D22: NEQUI
B23: RETIRO BBVA PARA PAGO DIEGO ROJAS | C23: 1050000 | D23: BBVA EMPRESA
B24: PAGO ALQUILER TROMPO JAVIER MALDONADO | C24: 305000 | D24: BBVA JIMMY | E24: 1500000
B25: PAGO SALDO FVE 645 Y FVE 651 CICOM A JUNIO 30/2026 | C25: BBVA | D25: NEQUI503934
A26: 46219 | B26: ANGELICA SALDO VIEJO A 15 JULIO Y NUEVO A 31 JULIO | C26: 1717640 | D26: BBVA JIMMY
A27: 46220 | B27: ABONO ALQUILER PLACA WILSON PAEZ A PARTIR DEL 18 DE JULIO | C27: 1000000
A28: 46224 | B28: ALQUILER FORMALETA METALICA ALIRIO SUAREZ 22 JULIO EN ADELANTE | C28: 1000000
B29: ANDREI DAVIPLATA ABONO ALQUILER PLACA 11 AL 31 DE JULIO 2026 | C29: 1000000 | D29: DAVIPLATA | E29: SALDO $386,410
A30: 46225 | B30: SALDO A 31 JULIO ANDREI | C30: 313650 | D30: DAVIPLATA
B31: MIGUEL ANGEL FLOREZ CORREA ALQUILER ANDAMIOS JULIO | C31: 164000 | D31: NEQUI | E31: 300000
B32: DEPOSITO POR ALQUILER PLACA ALIRIO SUAREZ | C32: 101000
A33: 46226 | B33: DEPOSITO WILMER RONDON ALQUILER POLEAS | C33: 1000000 | D33: NEQUI
A34: 46227 | B34: RETIRO BBVA EMPRESA PARA COMPRA TRANSMISION | C34: 1500000 | D34: BBVA EMPRESA
B35: MAESTRO VIDAL ALQUILER POLEAS | C35: 900000 | D35: BBVA JIMMY
B36: 5 CONSTRUCCIONES ALQUILER RUEDAS DE ANDAMIO JUNIO | C36: BBVA EMPRESA | D36: NEQUI | E36: 190000
B37: MAESTRO JOSE ALQUILER PLACA 24 DE JULIO POR 14 DIAS CON TRANSPORTE | C37: 2050000 | D37: BBVA
B38: ALQUILER ALINA HACER FACTURA | D38: CONSIGNADO BBVA | E38: 44650
B39: HERNAN TORRADO SALDO ALQUILER A 24 JULIO 2026 | C39: 393000
A40: 46230 | B40: PAGO ALIRIO SUAREZ JULIO 27 A AGOSTO 7 | C40: 172680
B41: RETIRO NEQUI PAGO FACTURA POLIMYS Y FACTURA MOVISTAR | C41: 1000000
B42: SALDO ALQUILER AERO A POLIMYS MAYO 2026 | C42: 5770 | D42: 83300
B43: PAGO ALQUILER AEO A POLIMYS JUNIO 2026 | C43: 710300 | D43: 25730
A44: 46231 | B44: SALDO PENDIENT ANDAMIOS HARBEY JULIO | C44: 33000
B45: ALQUILER 14 TBLEROS MADERA 70 X 140 HARBEY | C45: 98000
B46: ABONO PLACA MADERA SERGIO LUIS A PARTIR 29 JULIO | C46: 1000000
B47: CARLOS MIGUEL SALDO JUNIO | C47: 48800 | D47: NEQUI
A48: 46234 | B48: ANTONIO GUTIERREZ ALQUILER JULIO | C48: 3012000
B49: RETIRO BBVA PARA CANCELAR SEGUNDA QUINCENA DIEGO ROJAS | C49: 950000
B50: ESCALERA ALQUILER 31 JULIO | C50: 20000
B51: JAIME LUNA ALQUILER JULO 2026 | C51: 289050
B52: ALQUILER COLUMNAS COLORADOS LUZ | C52: 270000
B53: ANDAMIOS JULIO MIGUEL | C53: 73500
B54: ABONO ALQUILER JULIO RUEDAS JHON ORIGUA | C54: 100000
C55: =SUM(C4:C54) -> 28203060
B59: EGRESOS
B60: JULIO 1 AL 31/ 2026
A61: 46205 | B61: DESPINCHADA LLANTE TRASERA | C61: 25000
B62: TKEO JAC COTAXI 1110787 | C62: 100000
A63: 46206 | B63: 2 LIBRAS PUNTILLAS 3 "FIXXY | C63: 6000
B64: TRANSPORTE NELSON BERNAL | C64: 17500
B65: PAGO LINEA CELULAR TIGO 3005678367 | C65: 26950 | D65: NEQUI
B66: PAGO LINEA CELULAR TIGO 3016032896 | C66: 26950 | D66: NEQUI
A67: 46207 | B67: DIEGO ROJAS BONIFICACION MES DE JULIO 2026 | C67: 200000
B68: YANETH LUNA 30 JUNIO AL 4 DE JULIO 2026 | C68: 338000
B69: EIDER DE JESUS JUNIO 29 AL 4 DE JULIO 2026 | C69: 425000
B70: CESAR ROJAS JUNIO 30 AL 4 JULIO 2026 | C70: 340000
B71: HORAS EXTRAS CESAR ROJAS SEMANA JUNIO 30 AJULIO 4 2026 | C71: 15000
B72: FERRETERIA CAPITALIZ 34950 ( 2 KILOS SOLDFADURA 6012 2 / 23 " | C72: 32000
A73: 46209 | B73: RECOGIDA ESCALERA TIJERA ANDREA | C73: 20000
A74: 46210 | B74: ACARREO A YURANIS COLORADOS | C74: 40000
B75: ACARREO LEONARDO ANDAMIO | C75: 20000
B76: ACARREO CESAR AUGUSTO MIRADORES DE LA UIS | C76: 30000
B77: ACARREO LA INDEPENDENCIA | C77: 35000
B78: ACARREO NELSON BERNAL | C78: 17500
A79: 46212 | B79: PAGO CESAR ROJAS JUNIO 7, 8 Y 9 | C79: 225000
B80: 1 TALONARIO CAJA MENOR 1 1 TALONARIO EGRESOS | C80: 15000
A81: 46213 | B81: FVE 1124 RABAC (10 TALONARIOS DE ENTRADA | C81: 130900 | D81: CON IVA
A82: 46214 | B82: YANETH LUNA SEMANA 6 AL 11 JULIO 2026 | C82: 410000
B83: EIDER DE JESUS SEMANA 6 AL 11 JULIO 2026 | C83: 425000
B84: MEDIA HORA EXTRA DIEGO | C84: 5000
B85: MEDIA HORA EXTRA EIDER | C85: 5000
B86: RECOGIDA DE POLEAS HERNAN TORRADO JAVIER CARMONA | C86: 20000
A87: 46217 | B87: EDGAR GIL PINZON FV 628 ( CAMBIO 4 CILINDORS RUEDA TRASERA IZQ. JAC | C87: 150000
A88: 46218 | B88: COMPRA 1 ROLLODUCTOLON | C88: 100100
B89: PAGO PRIMERA QUINCENA DIEGO ROJAS | C89: 930000 | D89: BBVA EMPRESA
B90: PASA A CAJA MENOR | C90: 15400 | D90: BBVA EMPRESA
B91: CCOP MULTIACTIVA TAXIS Y TRANSPORTES EDS COTAXI 1126231 TKEO JAC | C91: 100000
B92: PAGO A JAVIER CARMONARECOGIDA ESCALERA Y ANDAMIOS ANDREA | C92: 30000
B93: ARWFLO IMPRESORA SEGÚN FVE 26377INYECTINTAS | C93: 60000 | D93: NEQUI
A94: 46220 | B94: FRENO MUELLES DIMILUZ SAS FE 18548 ( 2 CILINDROS FRENOS LLANTA DELANTERA IZ Q Y 2 CILINDORS FRENOS LLANTA TRASERA IZQ) | C94: 410000
B95: PAGO A ENRIQUE LLEVADA PLACA Y RECOGIDA COLUMNAS WILSON PAEZ | C95: 250000
B96: CESAR ROJAS JULIO 14 AL 18 | C96: 265000
B97: CESAR ROJAS HORAS EXTRAS SEMANA JULIO 14 AL 18 | C97: 30000 | D97: =930000*2 -> 1860000
B98: EIDER DE JESUS JULO 14 AL 18 | C98: 350000
B99: EIDER DE JESUS HORAS EXTRAS SEMANA JULIO 14 AL 18 | C99: 30000
B100: JANET LUNA SEMANA JULIO 14 AL 18 | C100: 338000
B101: DIEGO ROJAS 3 HORAS EXTRAS SEMANA JULIO 14 AL 18 | C101: 30000
A102: 46224 | B102: RECIBO LUZ BODEGA JULIO | C102: 118500
B103: RECOGIDA TOLOZA PAGADOS A JAVIER CARMONA | C103: 35000
...

Sheet AGOSTO
B1: INGRESOS
B2: AGOSTO 1 AL 31/ 2026
C3: =JULIO!C150 -> 25373983
A5: 46238 | B5: SALDO ALQUILER ANGELICA A 31 DE JULIO 2026 | C5: 1803000 | D5: BBVA JIMMY
A6: 46239 | B6: ALQUILER ANDAMIOS Y TABLONES JUAN CARLOS BAUTISTA | C6: NEQUI | D6: 100000
B7: ANDREI PAGO ALQUILER COLUMNAS A PARTIR AGOSTO 10 AL 14 | C7: 1000000 | D7: DAVIPLATA
B8: ANDREI ABONO A PLACA A PARTIR DEL 1 DE AGOSTO 2026
B9: ABONO PLACA MADERA MAURICIO CACERES LUIS A PARTIR 3 DE AGOSTO | C9: 2500000 | D9: BBVA JIMMY
A10: 46240 | B10: ABONO ALQUILER WILSON PAEZ | C10: 500000
A11: 46244 | B11: ABONO JOSE REDIN PLACA 11 AL 23 AGOPSTO 2026 | C11: 1000000
B12: pago alquiler julio GIOVANI SIERRA | C12: NEQUI | D12: 544000
B13: PAGO SALDO SERGIO ALQUILER AGOSTO PLACA MADERA | C13: 102000
A14: 46245 | B14: PAGO DE 2FORMALETA 60 X120; 1 FORMALETAS DE 30X 120 SACAR DEL INVENTARIO CONSORCIO EN AGOSTO | C14: 660000 | D14: NEQUI
B15: ELIAS RIOS ALQUILER JULIO | C15: 163000
B16: ESCALERA | C16: 30000
B17: PAGO ALQUILER ANDAMIOS WILLIAM PARRA | C17: 68000
B18: PAGO ALDO ALIRIO SUAREZ | C18: 157000
B19: ABONO PEDRO ROSAS POLEAS JULIO | C19: 250000
A20: 46246 | B20: ALEXANDER BAUYTISTA ALQUILER SECCIONES ANDAMIO | C20: 57500 | D20: NEQUI
A21: 46248 | B21: sacados de nequi PRESTADO A DIEGO Y DEVOLVIO CON 1 BILLETE DE $100,000 | C21: 50000 | D21: NEQUI
B22: HERNAN TORRADO SALDO A AGOSTO 15 2026 | C22: 114000
A23: 46249 | B23: SACADOS BBVA PAGAR PRIMERA DIEGO ROJAS QUINCENA AGOSTO 2026 | C23: 950000 | D23: BBVA EMPRESA
B24: YORGUIN JAIMES ALQUILER COLUMNAS AGOSTO | C24: 110000
B25: FELIX CARRILLO ALQUILER JULIO | C25: 347600
B26: YORGUIN JAIMES ALQUILER ANDAMIOS | D26: 50000
B27: GUILLERMO HERNANDEZ ALQUILER ANDAMIOS 14 AL 18 AGOSTO | C27: 45000
A28: 46252 | B28: CRISTIAN RUGELES ALQUILER PLACA METALICA POR 15 DIAS | C28: 1500000 | D28: NEQUI
B29: ALQUILER ESCALERA YORGUIN JAIMES | C29: 20000
B30: PAGO ESCALERA EXTENSION 4M A 8 | C30: 30000
A31: 46253 | B31: ALQUILER COLUMNAS 14 AL 19 AGOSTO 2026 PEDRO JUAN PRADA | D31: 732000
B32: ANGELICA ALQUILER AGOSTO 1 AL 10 | C32: 690120 | D32: BANCOLOMBIA
B33: ANGELICA 1 PARAL 3, 1 CERCHA DE 1 MTS Y 19 CHAPETAS EXTRAVIADAS; DAÑO CERCHA 3 MTS | C33: 232500 | D33: BANCOLOMBIA
B34: ALEX BAUTISTA ALQUILER ESCALERA EXTENSION 2M A 8 M 20 Y 21| AGOSTO | C34: 40000
A35: 46255 | B35: PAGO ALQUILER PLACA PEQUEÑA VIDAL | C35: 348500
A36: 46256 | B36: ALQUILER LUZ MARINA CARREÑO AGOSTO 11 AL 22 | D36: 145500
B37: ABONO AL PRESTAMO DE EIDER | C37: 400000 | D37: NEQUI
B38: GUSTAVO ADOLFO RUBIO ABONO ALQUILER PLACA VILLACARMELO A PARTIR AGOSTO 25 2026 | C38: 1200000 | D38: BANCOLOMBIA
A39: 46258 | B39: ABONO ALQUILER 4 POLEAS FRANCY LILIANA | C39: 304000
B40: PAGO ALQUILER DE 5 DIAS OMAR PABON AGOSTO 24 AL 28 2026 | C40: 253600 | D40: NEQUI
B41: ALQUILER ROBINSON MUÑOZ CASTRO | D41: 127500
B42: ALQUILER ESCALERA JAME LUNA | C42: 90000
A43: 46259 | B43: SACADOS DE NEQUI | C43: 650000 | D43: NEQUI
B44: ALEX BAUTISTA ALQUILER ESCALERA EXTENSION 2M A 8 M 22 Y 24| AGOSTO | D44: 38000
B45: ALEX BAUTISTA ALQUILER 2 SECCIONES ANDAMIOS Y 4 TABLONES AGOSTO 25 AL 28 | D45: 28000
A46: 46261 | B46: MAESTRO VIDAL ALQUILO ALQUILER PLACA DEL 12 AL 26 AGOSTO 2026 | C46: 1346750
B47: MAESTRO VIDAL ALQUILER DE ANDAMIOS | C47: 240000
B48: HOLGUER ALQUILER COLUMNAS DIEGO ARMANDO NAVAS JAIMES | C48: 200000 | D48: NEQUI
B49: HOLGUER ALQUILER COLUMNAS DIEGO ARMANDO NAVAS JAIMES | C49: 40000 | D49: EFECTIVO
B50: DANIEL EDUARDO BAUTISTA JARAMILLO OBRA NOEL GUERRA DEPOSITP | C50: 400000 | D50: NEQUI
B51: WILSON PAEZ ABONO CON COMPRTA DE 221 CORBATAS MURO DE 20 CMS ENTRADA 13592 | C51: 221000 | D51: SALDO | E51: 304250
A52: 46262 | B52: PAGO ALQUILER 1 SECCION DE ANDAMIO | C52: 15000
B53: ,PAGO ALQUILER ANDAMIOS EDUARDO TOLOZA | D53: 152000
B54: MAESTRO VIDALL PAGO ALQUIKLER POLEAS AL 23 DE AGOSTO | C54: 900000 | D54: BBVA JIMMY
A55: 46264 | B55: PAGO DAVID REDIN ALQUILER PLACA MADERA AL 31 AGOSTO 206 INCLUIDA RECOGIDA | C55: 1480000
A56: 46265 | B56: SACADOS DE NEQUI | C56: 400000 | D56: nequi
B57: JOHANA PEDREGAL ALQUILER PLACA MADERA | C57: 2000000
B58: GIOVANI BESSINO ALQUILER COLUMNAS | C58: 453000
C59: =SUM(C5:C58) -> 23361570
B63: EGRESOS
B64: AGOSTO 1 AL 31/ 2026
A65: 46238 | B65: ELIZABETH NARANJO AMADO FVE GM 325( 1 TRONZADORA RANGER PRO DE 14 ";3 DISCOS CORT, 1 DESBASTE | C65: 687000 | D65: TIENE IVA
B66: EWSTACION DE SRVICIO SANTA MARTA EMANUEL (MANTENIMIENTO POLEAS) | C66: 16000
A67: 46239 | B67: PAGO DE ARREGLO Y PINTADA DE 5 POLEAS | C67: 200000
B68: PINTASMAS PQSF 45670 ( 1 AEROSOL AZUL ARREGLO ANGULOS) | C68: 9500
A69: 46241 | B69: heriberto florez diaz ( 1 silicona loctite grey x 70 ml) | C69: 27000 | D69: NEQUI
B70: jhonatan giraldo gelvez fve JGG 4619 ( 2 TORNILLOS LLANTA JAC Y 12 TORNILLOS CON ARANDELA TRANSMISION | C70: 25400 | D70: NEQUI
B71: RECTIFICADA DE HUEVO TRANSMISION Y SACADA DE TRORNILLO EN MAL ESTADO RUEDA TRASERA L.I JAC | C71: 50000 | D71: PENDEIENTE FACTURA
B72: 1 CUARTO DE VALVULINA 140 JAC | C72: 26000 | D72: PENDEIENTE FACTURA
A73: 8/098/2026 | B73: CESAR ROJAS PAGO AGOSTO 4 AL 6 | C73: 225000
B74: JANETH LUNA AGOSTO 3 AL 6 Y 8 AGOSTO | C74: 338000
B75: EIDER DE JESUS CAICEEDO | C75: 350000
B76: PRESTAMO DIEGO ROJAS | C76: 362500
B77: TKEO JAC EDS COTAXI | C77: 100000
A78: 46248 | B78: ABONO A 10 TALONARIOS SALIDA RABAC | C78: 50000
B79: PAGO INDUSTRIA Y COMERCIO TERCERA CUOTA | C79: 383000
B80: COSTAS COBRO COACTIVO INDUSTRIA Y COMERCIO | C80: 6000
B81: CESAR 10 AL 14 AGOSTO 2026 | C81: 375000
B82: CESAR HORAS EXTRAS SEMANA 10 AL 14 AGOSTO 2026 | C82: 70000
A83: 46249 | B83: PRIMERA DIEGO ROJAS QUINCENA AGOSTO 2026 | C83: 930000
B84: DIEGO ROJAS 3.75 HORAS EXTRAS SEMANA 10 AL 15 AGOSTO 2026 | C84: 37500 | D84: ABONADO A DEUDA
B85: EIDER DE JESUS SEMANA 10 AL 15 AGOSTO 2026 | C85: 425000
B86: EIDER DE JESUS 3 HORAS EXTRAS SEMANA 10 AL15 DE AGOSTO 2026 | C86: 30000
B87: JANETH LUNA DIAS LABORADOS 10, 12, 14 Y 15 AGOSTO | C87: 266000
B88: JANETH LUNA 6 HORAS EXTRAS 1 AL 15 AGOSTO 2026 | C88: 60000
A89: 46160 | B89: PAGO PINES CLAUDIA JERES | C89: 46000
A90: 46253 | B90: MULTIACTIVA DE TAXIS EDS 1169505 TKEO JAC | C90: 100000
B91: prestamo a diego rojas | C91: 20000 | D91: NEQUI
B92: PAGO 3 DIAS DE TRABAJO CESAR AGOSTO 18, 19 Y 20 | C92: 105000 | D92: NEQUI
B93: PAGO 1/2 HORA EXTRA 19 AGOSTO | C93: 5000 | D93: NEQUI
B94: COMPRA VASELINA ARREGLO BATERIA | C94: 7000
B95: LLEVO PAGO RECIBO LUZ | C95: 123800
A96: 46254 | B96: PRESTAMO JIMMY JAIMES | C96: 750000
A97: 46255 | B97: saldo dias 18,19,20 y 21 agosto cesar rojas | C97: 190000
A98: 46256 | B98: EIDER DE JESUS SEMANA 18 AL 22AGOSTO 2026 | C98: 350000
B99: FE -1273 SOLDAR1 A INGENIERIA SAS COMPRA DE 300 CHAPETAS, 150 PINES, 4 FORMALETAS 40 X60 | C99: 1451800 | D99: NEQUI
A100: 46259 | B100: CARROCERIAS NEW YORK FV 0901 ( 1 PAR DE COMPUERTAS CARROCERIA DE ESTACA CAMION JAC | C100: 450000
B101: PAGO FVE CICOM MES DE JULIO 656 CONSIGNADOS EN EÑL BBVA | D101: 712000
A102: 46260 | B102: PINTASMAS PQSF 8071 ( 1 GALON ESMALTE ALUMINIO MEZCLA, 1 GALON DE THINER, 1 BROCHA DE 2 1/2") | C102: 90500
B103: GALON DE GASOLINA MTTO POLEAS | C103: 15000
B104: TKEO JAC ESTACION LA HORMIGA FVE 48091 | C104: 125000
...

Sheet SEPTIEMBRE
B1: INGRESOS
B2: SEPTIEMBRE 1 AL 30/ 2026
C3: =AGOSTO!C146 -> 34228579
A4: 46266 | B4: ALQUILER ESCALERQA SEPTIEMBRE 1 Y 2 EDINSON JAIMES | C4: 30000
B5: SALDO JOHANA EL PEDREGAL | C5: 60240 | D5: NEQUI
B6: DEPOSITO FREDY LENGUA | C6: 500000 | D6: NEQUI
B7: MAESTRO VIDAL ALQUILER COLUMNAS | C7: 272000 | D7: NEQUI
A8: 46267 | B8: ENRIQUE PEREZ ALQUILER ANDAMIOS | C8: 122500
B9: JOSE MAURICIO CACERES ORTIZ SALDO PLACA | C9: 681300 | D9: NEQUI
A10: 46268 | B10: MIGUEL ANGEL FLOREZ DEPOSITO SAL 3988 | C10: 300000 | D10: NEQUI
B11: GONZALO PAGO ALQUILER2 SECCIONES Y 1 TABLON | C11: NEQUI | D11: 20000
B12: PAGO SALDO ELIAS PATIÑO | D12: 26000
A13: 46269 | B13: SACADOS DE NEQUI ( ENVIADOS A FRANCY LILIANA) | C13: 1000000 | D13: NEQUI
C22: =SUM(C4:C21) -> 2966040
B26: EGRESOS
B27: SEPTIEMBRE 1 AL 30/ 2026
A28: 46266 | B28: INDURRUEDAS COMPRA DE 25 LIBRAS PUNTILLAS CABALLO | C28: 201320
B29: ABONO HECHURA TABLAS | C29: 100000
A30: 46267 | B30: vueltos cristian rugeles | C30: 427960 | D30: nequi
B31: pago aldo rabac salidas | C31: 80900 | D31: pendiente factura
B32: FERRETERIA FIXXY 26233( 2 BERMELLON) | C32: 20000
B33: FEJG1930 SILENCIADORES LA 14 ( VENTA E INSTALACION DE FLEXIBLE ECUALIZABLE EN ACERO INOXIDABLE PO 2 | C33: 300000 | D33: IVA
B34: TRANSPORTE AMIGUEL ANGERL FLOREZ ALFONSO LOPEZ | C34: 50000 | D34: NEQUI
A35: 46268 | B35: FREDY LENGUA VUELTOS | C35: 407775 | D35: NEQUI
B36: PAGO RECOGIDA NOEL GUERRA | C36: 40000 | D36: NEQUI
B37: TODO ELCTRICOS FVE TDE50568 ( 1 VALCULA DE FRENO AHOGO JAC Y CONECTOR | C37: 150000
B38: ALMACEN REYCOL SAS 1 TUBERIA DE HIERRO Y SILICONA | C38: 51826
A39: 46269 | B39: ALMACEN REYCOL SAS COMP. No 5A 33131( PEDAZO DE MANGUERA Y DOS ABRAZADERAS) | C39: 6609
C105: =SUM(C28:C104) -> 1836390
C106: =C3+C22-C105 -> 35358229

Sheet ALQUILER NO FISCAL 
