Workbook

Sheet BALANCE DICIEMBRE
A1: EQUIORIENTE SAS
A2: SITUACION FINANCIERA
A3: FECHA: 31 de DICIEMBRE DE 2024
A6: 1 | C6: ACTIVO
A8: 11 | C8: Efectivo y equivalentes al efectivo
A9: 1105 | C9: Caja | E9: =+D10 -> 24386159
A10: 110505 | C10: Caja general | D10: 24386159
A12: 1120 | C12: Cuentas de ahorro
A13: 112005 | C13: Bancos | E13: =+D14 -> 10438236
A14: 11200501 | C14: BBVA | D14: 10438236
A18: 13 | C18: Cuentas por cobrar (instrumentos financieros)
A19: 1305 | C19: Clientes | E19: =+D20+D21+D22 -> 10456154
A20: 130505 | C20: Nacionales | D20: =+CARTERA!D29 -> 3733796
A21: 130505 | C21: Cuentas por debajo | D21: =+CARTERA!D16 -> 4343749
A22: 130505 | C22: Otras cuentas por cobrar | D22: 2378609
A24: 1330 | C24: ANTICIPO PROVEEDORES | E24: =+D25 -> 49352988
C25: Puerta de Oro etapa 3 | D25: =+Hoja2!H40 -> 49352988
A27: 1355 | C27: Anticipo de impuestos y contribuciones o saldos a favor | E27: =SUM(D28:D31) -> 4136993
A28: 135505 | C28: Anticipo de impuestos de renta y complementarios | D28: 2468000
A29: 135518 | C29: Reteica | D29: 178542
A30: 135515 | C30: Retención en la fuente | D30: 1022451
A31: 13559006 | C31: Autorretencion de renta | D31: 468000
A33: 15 | C33: Propiedades planta y equipo | E33: =SUM(D34:D42) -> 312866893
A34: 1516 | C34: Construcciones y edificaciones
A35: 151605 | C35: Apto sion | D35: 91000000
A36: 1520 | C36: MAQUINARIA Y EQUIPO | D36: 196269921 | H36: 187962965
A37: 152005 | C37: Formaleta | E37: GONZALEZ BOHORQUEZ | H37: 8306956
A38: 1528 | C38: Equipo de computación y comunicación | H38: =+H36+H37 -> 196269921
A39: 152805 | C39: Equipo de procesamiento de datos | D39: 2109000
A40: 1540 | C40: Flota y equipo de transporte | D40: 0
A41: 154008 | C41: Camiones, volquetas y furgones | D41: 34596000
A42: 1592 | C42: Depreciación acumulada | D42: -11108028
A44: 16 | C44: Intangibles | E44: =+D45 -> 2548980
A45: 1635 | C45: Licencias | D45: 2548980
A47: TOTAL ACTIVO | E47: =SUM(E9:E45) -> 414186403
A50: 2365 | C50: Retención en la fuente | E50: =+D51+D52 -> 186000
A51: 236525 | C51: Retención en la fuente | D51: 148000
A52: 236706 | C52: Autorretencion | D52: 38000
A54: 2370 | C54: Retenciones y aportes de nómina | E54: =+D55+D56+D57 -> 347900
A55: 237005 | C55: Aportes a entidades promotoras de salud EPS | D55: 162600
A56: 237006 | C56: Aportes a administradoras de riesgos profesionales arp | D56: 38400
A57: 237010 | C57: Aportes al i.c.b.f, sena y cajas compensación | D57: 146900
A59: 2380 | C59: Acreedores varios | E59: =+D60 -> 650000
A60: 238030 | C60: Fondos de cesantías y/o pensiones | D60: 650000
A63: 24 | C63: Impuestos, gravámenes y tasas | E63: =+D64+D65 -> 194000
A64: 2408 | C64: Impuesto sobre las ventas por pagar | D64: 194000
A65: 2412 | C65: industria y comercio | D65: 0
A68: 26 | C68: Provisión de pasivos
A69: 2610 | C69: Para obligaciones laborales | E69: =SUM(D70:D73) -> 2935000
A70: 261005 | C70: Cesantías | D70: 2935000
A71: 261010 | C71: Intereses sobre cesantías | D71: 0
A72: 261015 | C72: Vacaciones | D72: 0
A73: 261020 | C73: Prima | D73: 0
A75: 2895 | C75: OTRAS CUENTAS POR PAGAR
C76: Prestamos socios
A78: TOTAL PASIVO | E78: =SUM(E49:E77) -> 4312900
A81: 3 | C81: PATRIMONIO
A83: 31 | C83: Capital social | E83: =+D84 -> 405112927
A84: 3105 | C84: Capital suscrito y pagado | D84: 405112927
A85: 310505 | C85: Capital autorizado suscrito y pagado
A88: 36 | C88: Resultados del ejercicio | E88: =+D89 -> -3080054.9
A89: 361010 | C89: Perdida de ejercicio | D89: =+'pyg2024'!AR167 -> -3080054.9
A92: 37 | C92: UTILIDAD DEL EJERCICIO ANTERIORES | E92: =+D93 -> 7840631
A93: 370501 | C93: Utilidad de ejercicios anteriores | D93: =7840631 -> 7840631
A96: TOTAL PATRIMONIO | E96: =+E83+E88+E92 -> 4.098735e+08
A98: TOTAL PATRIMONIO Y PASIVO | E98: =+E96+E78 -> 4.141864e+08
E99: =+E47-E78-E96 -> -0.079999983
E100: 0
A105: NOTA: UTILIDADES SRA FLOR ALBA SE ENCUENTRA EN CDT
A106: 1 CDT COOMULTRASAN $12,500,000
A107: 1 CDT BBVA $11,000,000

Sheet pyg2024
B4: 45292 | F4: 45323 | I4: 45352 | L4: 45383 | O4: 45413 | R4: 45444 | V4: 45474 | Z4: 45505 | AD4: 45536 | AH4: 45566 | AL4: 45597 | AP4: 45627
B5: Mov. 02/01/2023 a 31/01/2023 | D5: Saldos a 31/01/23 | F5: 4 | H5: Saldos a 28/02/2023 | I5: Mov. 01/03/2023 a 31/03/2023 | K5: Saldos a 31/03/2023 | L5: Mov. 01/04/2023 a 30/04/2023 | N5: Saldos a 30/04/2023 | O5: Mov. 01/05/2023 a 31/05/2023 | Q5: Saldos a 31/05/2023 | R5: Mov. 01/06/2023 a 30/06/202 | T5: Saldos a 30/06/2023 | V5: Mov. 01/07/2023 a 31/07/2023 | X5: Saldos a 31/07/2022 | Z5: Mov. 01/08/2023 a 31/08/2023 | AB5: Saldos a 30/08/2022 | AD5: Mov. 01/09/2022 a 30/09/2022 | AF5: Saldos a 30/09/2022 | AH5: Mov. 01/10/2022 a 31/10/2022 | AJ5: Saldos a 31/10/2022 | AL5: Mov. 01/11/2022 a 30/11/2022 | AN5: Saldos a 30/11/2022 | AP5: Mov. 01/12/2024 a 31/12/2024 | AR5: Saldos a 31/12/2024
A6: Nombre | B6: Débitos | C6: Créditos | D6: Saldo actual | F6: Débitos | G6: Créditos | H6: Saldo actual | I6: Débitos | J6: Créditos | K6: Saldo actual | L6: Débitos | M6: Créditos | N6: Saldo actual | O6: Débitos | P6: Créditos | Q6: Saldo actual | R6: Débitos | S6: Créditos | T6: Saldo actual | V6: Débitos | W6: Créditos | X6: Saldo actual | Z6: Débitos | AA6: Créditos | AB6: Saldo actual | AD6: Débitos | AE6: Créditos | AF6: Saldo actual | AH6: Débitos | AI6: Créditos | AJ6: Saldo actual | AL6: Débitos | AM6: Créditos | AN6: Saldo actual | AP6: Débitos | AQ6: Créditos | AR6: Saldo actual
A7: INGRESOS | B7: 0 | C7: =C8+C16 -> 7389490 | D7: =D8+D16 -> 7389490 | F7: =F14 -> 0 | G7: =G8+G16 -> 8720667 | H7: =+D7+G7 -> 16110157 | I7: =+I8 -> 0 | J7: =J8+J16 -> 12280462 | K7: =+H7+J7 -> 28390619 | L7: =+L14 -> 0 | M7: =M8+M16 -> 17607136 | N7: =+K7+M7 -> 45997755 | O7: =+O8 -> 0 | P7: =P8+P16 -> 12093995 | Q7: =+N7+P7 -> 58091750 | R7: 0 | S7: =S8+S16 -> 8411424 | T7: =+Q7+S7 -> 66503174 | V7: =+V15 -> 0 | W7: =W8+W16 -> 6302884 | X7: =+T7+W7 -> 72806058 | Z7: =+Z14 -> 0 | AA7: =AA8+AA16 -> 15173848 | AB7: =+X7+AA7 -> 87979906 | AD7: =+AD14 -> 0 | AE7: =AE8+AE16 -> 14486836 | AF7: =+AB7+AE7 -> 102466742 | AH7: =+AH14 -> 0 | AI7: =AI8+AI16 -> 16134322 | AJ7: =+AF7+AI7 -> 118601064 | AL7: =+AL15 -> 1544330 | AM7: =AM8+AM16 -> 14740973 | AN7: =+AJ7+AM7-AL7 -> 131797707 | AP7: =+AP14 -> 0 | AQ7: =AQ8+AQ16 -> 14435564 | AR7: =+AN7+AQ7 -> 146233271
A8: Operacionales | B8: 0 | C8: =+C9 -> 2319055 | D8: =+D9+D14 -> 2319055 | F8: =F15 -> 0 | G8: =+G9 -> 2198885 | H8: =+H9+H14 -> 4517940 | I8: =+I14 -> 0 | J8: =+J9 -> 5345924 | K8: =+H8+J8 -> 9863864 | L8: 0 | M8: =+M9 -> 5705085 | N8: =+K8+M8 -> 15568949 | P8: =+P9 -> 6312190 | Q8: =+N8-O8+P8 -> 21881139 | R8: 0 | S8: =+S9 -> 5308821 | T8: =+T9+T14 -> 27189960 | V8: 0 | W8: =+W9 -> 1368000 | X8: =T8+W8 -> 28557960 | Z8: =+Z14 -> 0 | AA8: =+AA9 -> 1818800 | AB8: =+X8+AA8-Z8 -> 30376760 | AD8: =+AD14 -> 0 | AE8: =+AE9 -> 2263580 | AF8: =+AB8+AE8 -> 32640340 | AH8: =+AH14 -> 0 | AI8: =+AI9 -> 3401625 | AJ8: =+AF8+AI8 -> 36041965 | AL8: =+AL14 -> 1544330 | AM8: =+AM9 -> 4519220 | AN8: =+AJ8-AL8+AM8 -> 39016855 | AP8: =+AP14 -> 0 | AQ8: =+AQ9 -> 3456110 | AR8: =+AN8+AQ8 -> 42472965
A9: Actividades inmobiliarias, empresariales y de alquiler | B9: 0 | C9: =C10+C11+C12+C13 -> 2319055 | D9: =C9 -> 2319055 | F9: 0 | G9: =G10+G11+G12+G13 -> 2198885 | H9: =+D9+G9 -> 4517940 | I9: 0 | J9: =J10+J11+J12+J13 -> 5345924 | K9: =H9+J9 -> 9863864 | L9: 0 | M9: =M10+M11+M12+M13 -> 5705085 | N9: =+K9+M9 -> 15568949 | O9: 0 | P9: =P10+P11+P12+P13 -> 6312190 | Q9: =+N9+P9 -> 21881139 | R9: 0 | S9: =S10+S11+S12+S13 -> 5308821 | T9: =Q9+S9 -> 27189960 | V9: 0 | W9: =W10+W11+W12+W13 -> 1368000 | X9: =T9+W9 -> 28557960 | Z9: 0 | AA9: =AA10+AA11+AA12+AA13 -> 1818800 | AB9: =+X9+AA9-Z9 -> 30376760 | AD9: 0 | AE9: =AE10+AE11+AE12+AE13 -> 2263580 | AF9: =+AB9+AE9 -> 32640340 | AH9: 0 | AI9: =AI10+AI11+AI12+AI13 -> 3401625 | AJ9: =+AF9+AI9 -> 36041965 | AL9: 0 | AM9: =AM10+AM11+AM12+AM13 -> 4519220 | AN9: =AJ9+AM9 -> 40561185 | AP9: 0 | AQ9: =AQ10+AQ11+AQ12+AQ13 -> 3456110 | AR9: =+AN9+AQ9 -> 44017295
A10: Alquiler IVA | B10: 0 | C10: 2319055 | D10: =C10 -> 2319055 | F10: 0 | G10: 2073885 | H10: =+D10+G10 -> 4392940 | I10: 0 | J10: 4895924 | K10: =H10+J10 -> 9288864 | L10: 0 | M10: 5705085 | N10: =+K10+M10 -> 14993949 | O10: 0 | P10: 6107190 | Q10: =+N10+P10 -> 21101139 | R10: 0 | S10: 4913821 | T10: =Q10+S10 -> 26014960 | V10: 0 | W10: 1343000 | X10: =T10+W10 -> 27357960 | Z10: 0 | AA10: 1683800 | AB10: =+X10+AA10-Z10 -> 29041760 | AD10: 0 | AE10: 1773580 | AF10: =+AB10+AE10 -> 30815340 | AH10: 0 | AI10: 3089125 | AJ10: =+AF10+AI10 -> 33904465 | AL10: 0 | AM10: 4124220 | AN10: =AJ10+AM10 -> 38028685 | AP10: 0 | AQ10: 2931110 | AR10: =+AN10+AQ10 -> 40959795
A11: VENTA EQUIPO | C11: 0 | D11: =C11 -> 0 | F11: 0 | G11: 0 | H11: =+D11+G11 -> 0 | J11: 0 | K11: =H11+J11 -> 0 | L11: 0 | M11: 0 | N11: =+K11+M11 -> 0 | O11: 0 | P11: 0 | Q11: =+N11+P11 -> 0 | T11: =Q11+S11 -> 0 | X11: =T11+W11 -> 0 | AB11: =+X11+AA11-Z11 -> 0 | AF11: =+AB11+AE11 -> 0 | AJ11: =+AF11+AI11 -> 0 | AN11: =AJ11+AM11 -> 0 | AR11: =+AN11+AQ11 -> 0
A12: Transporte | B12: 0 | D12: =C12 -> 0 | F12: 0 | G12: 125000 | H12: =+D12+G12 -> 125000 | I12: 0 | J12: 450000 | K12: =H12+J12 -> 575000 | L12: 0 | N12: =+K12+M12 -> 575000 | O12: 0 | P12: 205000 | Q12: =+N12+P12 -> 780000 | R12: 0 | S12: 395000 | T12: =Q12+S12 -> 1175000 | V12: 0 | W12: 25000 | X12: =T12+W12 -> 1200000 | Z12: 0 | AA12: 135000 | AB12: =+X12+AA12-Z12 -> 1335000 | AD12: 0 | AE12: 490000 | AF12: =+AB12+AE12 -> 1825000 | AH12: 0 | AI12: 312500 | AJ12: =+AF12+AI12 -> 2137500 | AL12: 0 | AM12: 395000 | AN12: =AJ12+AM12 -> 2532500 | AP12: 0 | AQ12: 525000 | AR12: =+AN12+AQ12 -> 3057500
D13: =C13 -> 0 | H13: =+D13+G13 -> 0 | K13: =H13+J13 -> 0 | L13: 0 | N13: =+K13+M13 -> 0 | O13: 0 | Q13: =+N13+P13 -> 0 | T13: =Q13+S13 -> 0 | X13: =T13+W13 -> 0 | AB13: =+X13+AA13-Z13 -> 0 | AF13: =+AB13+AE13 -> 0 | AJ13: =+AF13+AI13 -> 0 | AN13: =AJ13+AM13 -> 0 | AR13: =+AN13+AQ13 -> 0
A14: Devoluciones en ventas (db) | D14: =C14 -> 0 | F14: =F15 -> 0 | G14: =G15 -> 0 | H14: =+D14+G14 -> 0 | I14: 0 | J14: =+J15 -> 0 | K14: =H14+J14 -> 0 | L14: 0 | N14: =+K14+M14 -> 0 | Q14: =+N14+P14 -> 0 | T14: =Q14+S14 -> 0 | X14: =T14+W14 -> 0 | AB14: =+X14+AA14-Z14 -> 0 | AD14: =+AD15 -> 0 | AF14: =+AB14+AE14 -> 0 | AH14: =+AH15 -> 0 | AJ14: =+AF14+AI14 -> 0 | AL14: 1544330 | AN14: =+AL14 -> 1544330 | AP14: 0 | AQ14: 0 | AR14: =+AN14+AQ14 -> 1544330
A15: Devoluciones en ventas (db) | D15: =C15 -> 0 | H15: =+D15+G15 -> 0 | I15: =+I14 -> 0 | K15: =H15+J15 -> 0 | L15: 0 | N15: =+K15+M15 -> 0 | Q15: =+N15+P15 -> 0 | T15: =Q15+S15 -> 0 | X15: =T15+W15 -> 0 | Z15: 0 | AB15: =+X15+AA15-Z15 -> 0 | AF15: =+AB15+AE15 -> 0 | AJ15: =+AF15+AI15 -> 0 | AL15: 1544330 | AM15: 0 | AN15: =+AL15 -> 1544330 | AP15: 0 | AQ15: 0 | AR15: =+AN15+AQ15 -> 1544330
A16: No operacionales | B16: 0 | C16: =C17+C21+C24+C26 -> 5070435 | D16: =+C16 -> 5070435 | F16: 0 | G16: =G17+G21+G24+G26 -> 6521782 | H16: =+F16+G16+D16 -> 11592217 | I16: 0 | J16: =J17+J21+J24 -> 6934538 | K16: =H16+J16 -> 18526755 | L16: 0 | M16: =M17+M21+M24+M26 -> 11902051 | N16: =+K16+M16 -> 30428806 | O16: 0 | P16: =P17+P21+P24+P26 -> 5781805 | Q16: =+N16+P16 -> 36210611 | R16: 0 | S16: =S17+S21+S24+S26 -> 3102603 | T16: =Q16+S16 -> 39313214 | V16: 0 | W16: =W17+W21+W24+W26 -> 4934884 | X16: =T16+W16 -> 44248098 | Z16: =Z17+Z21+Z24 -> 0 | AA16: =AA17+AA21+AA24+AA26 -> 13355048 | AB16: =X16+AA16 -> 57603146 | AD16: =AD17+AD21+AD24 -> 0 | AE16: =AE17+AE21+AE24+AE26 -> 12223256 | AF16: =AB16+AE16 -> 69826402 | AH16: =AH17+AH21+AH24 -> 0 | AI16: =AI17+AI21+AI24+AI26 -> 12732697 | AJ16: =AF16+AI16 -> 82559099 | AL16: =AL17+AL21+AL24 -> 0 | AM16: =AM17+AM21+AM24+AM26 -> 10221753 | AN16: =AJ16+AM16 -> 92780852 | AP16: =AP17+AP21+AP24 -> 0 | AQ16: =AQ17+AQ21+AQ24+AQ26 -> 10979454 | AR16: =AN16+AQ16 -> 103760306
A17: Financieros | B17: 0 | C17: =C18 -> 2035 | D17: =+C17 -> 2035 | F17: 0 | G17: =+G18 -> 1690 | H17: =+F17+G17+D17 -> 3725 | I17: 0 | J17: =J18+J19+J20 -> 318 | K17: =H17+J17 -> 4043 | L17: 0 | M17: =+M18+M19 -> 4977163 | N17: =+K17+M17 -> 4981206 | O17: 0 | P17: =P18+P19+P20 -> 621 | Q17: =+N17+P17 -> 4981827 | R17: 0 | S17: =S18+S19 -> 503 | T17: =Q17+S17 -> 4982330 | V17: 0 | W17: =+W18+W19 -> 315 | X17: =T17+W17 -> 4982645 | Z17: =Z18+Z19+Z20 -> 0 | AA17: =+AA18 -> 283 | AB17: =X17+AA17 -> 4982928 | AD17: =AD18+AD19+AD20 -> 0 | AE17: =+AE18+AE19 -> 296 | AF17: =AB17+AE17 -> 4983224 | AH17: =AH18+AH19+AH20 -> 0 | AI17: =+AI18+AI19 -> 244 | AJ17: =AF17+AI17 -> 4983468 | AL17: =AL18+AL19+AL20 -> 0 | AM17: =AM18+AM19 -> 223 | AN17: =AJ17+AM17 -> 4983691 | AP17: =AP18+AP19+AP20 -> 0 | AQ17: =AQ18+AQ19 -> 165 | AR17: =AN17+AQ17 -> 4983856
A18: Intereses | B18: 0 | C18: 2035 | D18: =+C18 -> 2035 | F18: 0 | G18: 1690 | H18: =+F18+G18+D18 -> 3725 | I18: 0 | J18: 318 | K18: =H18+J18 -> 4043 | L18: 0 | M18: 4977163 | N18: =+K18+M18 -> 4981206 | O18: 0 | P18: 621 | Q18: =+N18+P18 -> 4981827 | R18: 0 | S18: 503 | T18: =Q18+S18 -> 4982330 | V18: 0 | W18: 315 | X18: =T18+W18 -> 4982645 | Z18: 0 | AA18: 283 | AB18: =X18+AA18 -> 4982928 | AD18: 0 | AE18: 296 | AF18: =AB18+AE18 -> 4983224 | AH18: 0 | AI18: 244 | AJ18: =AF18+AI18 -> 4983468 | AL18: 0 | AM18: 223 | AN18: =AJ18+AM18 -> 4983691 | AP18: 0 | AQ18: 165 | AR18: =AN18+AQ18 -> 4983856
A19: intereses prestamos socios | D19: =+C19 -> 0 | G19: 0 | H19: =+F19+G19+D19 -> 0 | J19: 0 | K19: =H19+J19 -> 0 | L19: 0 | M19: 0 | N19: =+K19+M19 -> 0 | O19: 0 | P19: 0 | Q19: =+N19+P19 -> 0 | R19: 0 | S19: 0 | T19: =Q19+S19 -> 0 | V19: 0 | W19: 0 | X19: =T19+W19 -> 0 | Z19: 0 | AA19: 0 | AB19: =X19+AA19 -> 0 | AD19: 0 | AE19: 0 | AF19: =AB19+AE19 -> 0 | AH19: 0 | AJ19: =AF19+AI19 -> 0 | AL19: 0 | AM19: 0 | AN19: =AJ19+AM19 -> 0 | AP19: 0 | AQ19: 0 | AR19: =AN19+AQ19 -> 0
A20: Descuentos comerciales condicionados | H20: =+F20+G20+D20 -> 0 | K20: =H20+J20 -> 0 | N20: =+K20+M20 -> 0 | Q20: =+N20+P20 -> 0 | T20: =Q20+S20 -> 0 | AA20: 0
A21: RECUPERACION CARTERA | B21: 0 | C21: =C22 -> 0 | D21: =+C21 -> 0 | F21: 0 | G21: =+G22 -> 0 | H21: =+F21+G21+D21 -> 0 | I21: 0 | J21: =+J22 -> 0 | K21: =H21+J21 -> 0 | L21: 0 | M21: =M22 -> 0 | N21: =+K21+M21 -> 0 | O21: 0 | P21: =+P22 -> 0 | Q21: =+N21+P21 -> 0 | R21: 0 | S21: =+S22 -> 0 | T21: =Q21+S21 -> 0 | V21: 0 | W21: =W22 -> 0 | X21: =T21+W21 -> 0 | Z21: 0 | AA21: =AA22 -> 6535725 | AB21: =X21+AA21 -> 6535725 | AD21: 0 | AE21: =AE22 -> 0 | AF21: =AB21+AE21 -> 6535725 | AH21: 0 | AI21: =AI22 -> 0 | AJ21: =AF21+AI21 -> 6535725 | AL21: 0 | AM21: =AM22 -> 0 | AN21: =AJ21+AM21 -> 6535725 | AP21: 0 | AQ21: =AQ22 -> 0 | AR21: =AN21+AQ21 -> 6535725
A22: ASLQUILERES OLVIDADOS | B22: 0 | D22: =+C22 -> 0 | F22: 0 | H22: =+F22+G22+D22 -> 0 | I22: 0 | K22: =H22+J22 -> 0 | L22: 0 | N22: =+K22+M22 -> 0 | O22: 0 | Q22: =+N22+P22 -> 0 | R22: 0 | T22: =Q22+S22 -> 0 | V22: 0 | X22: =T22+W22 -> 0 | Z22: 0 | AA22: 6535725 | AB22: =X22+AA22 -> 6535725 | AD22: 0 | AF22: =AB22+AE22 -> 6535725 | AH22: 0 | AJ22: =AF22+AI22 -> 6535725 | AL22: 0 | AN22: =AJ22+AM22 -> 6535725 | AP22: 0 | AR22: =AN22+AQ22 -> 6535725
H23: =+F23+G23+D23 -> 0 | K23: =H23+J23 -> 0 | N23: =+K23+M23 -> 0 | Q23: =+N23+P23 -> 0 | T23: =Q23+S23 -> 0
A24: Servicios | B24: 0 | C24: =C25 -> 5068360 | D24: =+C24 -> 5068360 | F24: 0 | G24: =G25 -> 6520092 | H24: =+F24+G24+D24 -> 11588452 | I24: 0 | J24: =J25 -> 6934220 | K24: =H24+J24 -> 18522672 | L24: 0 | M24: =M25 -> 6924860 | N24: =+K24+M24 -> 25447532 | O24: 0 | P24: =+P25 -> 5781184 | Q24: =+N24+P24 -> 31228716 | R24: 0 | S24: =S25 -> 3102100 | T24: =Q24+S24 -> 34330816 | V24: 0 | W24: =W25 -> 4922830 | X24: =T24+W24 -> 39253646 | Z24: 0 | AA24: =AA25 -> 6819040 | AB24: =X24+AA24 -> 46072686 | AD24: 0 | AE24: =AE25 -> 12222960 | AF24: =AB24+AE24 -> 58295646 | AH24: 0 | AI24: =AI25 -> 12732453 | AJ24: =AF24+AI24 -> 71028099 | AL24: 0 | AM24: =AM25 -> 10221530 | AN24: =AJ24+AM24 -> 81249629 | AP24: 0 | AQ24: =AQ25 -> 10979289 | AR24: =AN24+AQ24 -> 92228918
A25: VENTAS SIN IVA | B25: 0 | C25: 5068360 | D25: =+C25 -> 5068360 | F25: 0 | G25: 6520092 | H25: =+F25+G25+D25 -> 11588452 | I25: 0 | J25: 6934220 | K25: =H25+J25 -> 18522672 | M25: 6924860 | N25: =+K25+M25 -> 25447532 | P25: 5781184 | Q25: =+N25+P25 -> 31228716 | R25: 0 | S25: 3102100 | T25: =Q25+S25 -> 34330816 | V25: 0 | W25: 4922830 | X25: =T25+W25 -> 39253646 | Z25: 0 | AA25: 6819040 | AB25: =X25+AA25 -> 46072686 | AD25: 0 | AE25: 12222960 | AF25: =AB25+AE25 -> 58295646 | AH25: 0 | AI25: 12732453 | AJ25: =AF25+AI25 -> 71028099 | AL25: 0 | AM25: 10221530 | AN25: =AJ25+AM25 -> 81249629 | AP25: 0 | AQ25: 10979289 | AR25: =AN25+AQ25 -> 92228918
A26: DIVERSOS | B26: 0 | C26: =+C27 -> 40 | D26: =+C26 -> 40 | F26: 0 | G26: =+G27 -> 0 | H26: =+F26+G26+D26 -> 40 | I26: 0 | J26: =+J27 -> 0 | K26: =H26+J26 -> 40 | L26: =L27 -> 0 | M26: =+M27 -> 28 | N26: =+K26+M26 -> 68 | O26: =O27 -> 0 | P26: =+P27 -> 0 | Q26: =+N26+P26 -> 68 | R26: =R27 -> 0 | S26: =+S27 -> 0 | T26: =Q26+S26 -> 68 | V26: =V27 -> 0 | W26: =+W27 -> 11739 | X26: =T26+W26 -> 11807 | Z26: 0 | AA26: =+AA27 -> 0 | AB26: =X26+AA26 -> 11807 | AD26: 0 | AE26: =+AE27 -> 0 | AF26: =AB26+AE26 -> 11807 | AH26: 0 | AJ26: =AF26+AI26 -> 11807 | AL26: 0 | AM26: =+AM27 -> 0 | AN26: =AJ26+AM26 -> 11807 | AP26: 0 | AQ26: =+AQ27 -> 0 | AR26: =AN26+AQ26 -> 11807
A27: Ajuste al peso | B27: 0 | C27: 40 | D27: =+C27 -> 40 | F27: 0 | H27: =+F27+G27+D27 -> 40 | I27: 0 | K27: =H27+J27 -> 40 | M27: 28 | N27: =+K27+M27 -> 68 | Q27: =+N27+P27 -> 68 | T27: =Q27+S27 -> 68 | W27: 11739 | X27: =T27+W27 -> 11807 | Z27: 0 | AB27: =X27+AA27 -> 11807 | AD27: 0 | AF27: =AB27+AE27 -> 11807 | AH27: 0 | AJ27: =AF27+AI27 -> 11807 | AL27: 0 | AN27: =AJ27+AM27 -> 11807 | AP27: 0 | AR27: =AN27+AQ27 -> 11807
H28: =+F28+G28+D28 -> 0 | K28: =H28+J28 -> 0
A29: GASTOS | B29: =B30+B145+B123 -> 9947041 | C29: 0 | D29: =+B29 -> 9947041 | F29: =F30+F145+F123 -> 13136716 | G29: 0 | H29: =+F29+G29+D29 -> 23083757 | I29: =I30+I145+I123 -> 11222288 | J29: 0 | K29: =+H29+I29 -> 34306045 | L29: =L30+L145+L123 -> 13880419 | M29: 0 | N29: =+K29+L29 -> 48186464 | O29: =O30+O145+O123 -> 12971414 | P29: 0 | Q29: =+N29+O29 -> 61157878 | R29: =R30+R145+R123 -> 10918657 | S29: 0 | T29: =+Q29+R29 -> 72076535 | V29: =V30+V145+V123 -> 11152404 | W29: 0 | X29: =T29+V29 -> 83228939 | Z29: =Z30+Z145+Z123 -> 11530628 | AA29: 0 | AB29: =X29+Z29 -> 94759567 | AD29: =AD30+AD145+AD123 -> 14014468 | AE29: 0 | AF29: =AB29+AD29 -> 1.0877403e+08 | AH29: =AH30+AH145+AH123 -> 14110605 | AI29: 0 | AJ29: =AF29+AH29 -> 1.2288464e+08 | AL29: =AL30+AL145+AL123 -> 12084858 | AM29: 0 | AN29: =AJ29+AL29 -> 1.349695e+08 | AP29: =AP30+AP145+AP123 -> 14343828 | AQ29: 0 | AR29: =AN29+AP29 -> 1.4931333e+08
A30: Operacionales de administración | B30: =+B31+B47+B52+B58+B62+B65+B70+B81+B87+B94+B100+B108 -> 9791435 | C30: 0 | D30: =+B30 -> 9791435 | F30: =+F31+F47+F52+F58+F62+F65+F70+F81+F87+F94+F100+F108 -> 12943164 | G30: 0 | H30: =+F30+G30+D30 -> 22734599 | I30: =+I31+I47+I52+I58+I62+I65+I70+I81+I87+I94+I100+I108 -> 11079523 | J30: 0 | K30: =H30+I30 -> 33814122 | L30: =+L31+L47+L52+L58+L62+L65+L70+L81+L87+L94+L100+L108 -> 13711828 | M30: =M31+M47+M58+M52+M65+M70+M81+M87+M94+M108+M62+M100 -> 0 | N30: =+K30+L30 -> 47525950 | O30: =+O31+O47+O52+O58+O62+O65+O70+O81+O87+O94+O100+O108 -> 12826136 | P30: =P31+P47+P58+P52+P65+P70+P81+P87+P94+P108+P62+P100 -> 0 | Q30: =+N30+O30 -> 60352086 | R30: =+R31+R47+R52+R58+R62+R65+R70+R81+R87+R94+R100+R108 -> 10570147 | S30: 0 | T30: =+Q30+R30 -> 70922233 | V30: =V31+V47+V52+V58+V62+V65+V70+V81+V87+V94+V100+V108 -> 10979169 | W30: 0 | X30: =T30+V30 -> 81901402 | Z30: =+Z31+Z47+Z52+Z58+Z62+Z65+Z70+Z81+Z87+Z94+Z100+Z108 -> 11383116 | AA30: 0 | AB30: =X30+Z30 -> 93284518 | AD30: =+AD31+AD47+AD52+AD58+AD62+AD65+AD70+AD81+AD87+AD94+AD100+AD108 -> 13862812 | AE30: 0 | AF30: =AB30+AD30 -> 107147330 | AH30: =+AH31+AH47+AH52+AH58+AH62+AH65+AH70+AH81+AH87+AH94+AH100+AH108 -> 13932449 | AI30: 0 | AJ30: =AF30+AH30 -> 121079779 | AL30: =+AL31+AL47+AL52+AL58+AL62+AL65+AL70+AL81+AL87+AL94+AL100+AL108 -> 11946350 | AN30: =AJ30+AL30 -> 133026129 | AP30: =+AP31+AP47+AP52+AP58+AP62+AP65+AP70+AP81+AP87+AP94+AP100+AP108 -> 14160457 | AR30: =AN30+AP30 -> 147186586
A31: Gastos de personal | B31: =B32+B33+B34+B35+B36+B37+B38+B39+B40+B41+B42+B43+B44+B45 -> 4336153 | C31: 0 | D31: =+B31 -> 4336153 | F31: =SUM(F32:F44) -> 6374656 | G31: 0 | H31: =+F31+G31+D31 -> 10710809 | I31: =SUM(I32:I44) -> 6312658 | J31: 0 | K31: =H31+I31 -> 17023467 | L31: =SUM(L32:L44) -> 6933725 | M31: 0 | N31: =+K31+L31 -> 23957192 | O31: =+O32+O33+O34+O35+O36+O37+O38+O39+O40+O41+O42+O43+O44+O45 -> 6244444 | P31: 0 | Q31: =+N31+O31 -> 30201636 | R31: =SUM(R32:R44) -> 6434444 | S31: 0 | T31: =+Q31+R31 -> 36636080 | V31: =V32+V33+V34+V35+V36+V37+V38+V39+V40+V41+V42+V43+V44+V45 -> 6090444 | W31: 0 | X31: =T31+V31 -> 42726524 | Z31: =Z32+Z33+Z34+Z35+Z36+Z37+Z38+Z39+Z40+Z41+Z42+Z43+Z44+Z45 -> 6234444 | AA31: 0 | AB31: =X31+Z31 -> 48960968 | AD31: =AD32+AD33+AD34+AD35+AD36+AD37+AD38+AD39+AD40+AD41+AD42+AD43+AD44 -> 6234444 | AE31: 0 | AF31: =AB31+AD31 -> 55195412 | AH31: =AH32+AH33+AH34+AH35+AH36+AH37+AH38+AH39+AH40+AH41+AH42+AH43+AH44+AH45 -> 6234444 | AI31: 0 | AJ31: =AF31+AH31 -> 61429856 | AL31: =AL32+AL33+AL34+AL35+AL36+AL37+AL38+AL39+AL40+AL41+AL42+AL43+AL44+AL45 -> 6234444 | AM31: =AM32+AM33+AM34+AM35+AM36+AM37+AM38+AM39+AM40+AM41+AM42+AM43+AM44 -> 0 | AN31: =AJ31+AL31 -> 67664300 | AP31: =AP32+AP33+AP34+AP35+AP36+AP37+AP38+AP39+AP40+AP41+AP42+AP43+AP44+AP45 -> 5963184 | AQ31: =AQ32+AQ33+AQ34+AQ35+AQ36+AQ37+AQ38+AQ39+AQ40+AQ41+AQ42+AQ43+AQ44 -> 0 | AR31: =AN31+AP31 -> 73627484
A32: Sueldos | B32: 3007833 | C32: 0 | D32: =+B32 -> 3007833 | F32: 4235000 | H32: =+F32+G32+D32 -> 7242833 | I32: 4235000 | K32: =H32+I32 -> 11477833 | L32: 4235000 | N32: =+K32+L32 -> 15712833 | O32: 4235000 | Q32: =+N32+O32 -> 19947833 | R32: 4235000 | T32: =+Q32+R32 -> 24182833 | V32: 4235000 | X32: =T32+V32 -> 28417833 | Z32: 4235000 | AB32: =X32+Z32 -> 32652833 | AD32: 4235000 | AF32: =AB32+AD32 -> 36887833 | AH32: 4235000 | AJ32: =AF32+AH32 -> 41122833 | AL32: 4235000 | AN32: =AJ32+AL32 -> 45357833 | AP32: 3670334 | AR32: =AN32+AP32 -> 49028167
A33: Horas extras | B33: 118800 | C33: 0 | D33: 0 | H33: =+F33+G33+D33 -> 0 | K33: =H33+I33 -> 0 | L33: 0 | N33: =+K33+L33 -> 0 | Q33: =+N33+O33 -> 0 | T33: =+Q33+R33 -> 0 | X33: =T33+V33 -> 0 | AB33: =X33+Z33 -> 0 | AF33: =AB33+AD33 -> 0 | AJ33: =AF33+AH33 -> 0 | AN33: =AJ33+AL33 -> 0 | AR33: =AN33+AP33 -> 0
A34: Auxilio de transporte | B34: 260448 | C34: 0 | D34: =+B34 -> 260448 | F34: 162000 | H34: =+F34+G34+D34 -> 422448 | I34: 162000 | K34: =H34+I34 -> 584448 | L34: 162000 | N34: =+K34+L34 -> 746448 | O34: 162000 | Q34: =+N34+O34 -> 908448 | R34: 162000 | T34: =+Q34+R34 -> 1070448 | V34: 162000 | X34: =T34+V34 -> 1232448 | Z34: 162000 | AB34: =X34+Z34 -> 1394448 | AD34: 162000 | AF34: =AB34+AD34 -> 1556448 | AH34: 162000 | AJ34: =AF34+AH34 -> 1718448 | AL34: 162000 | AN34: =AJ34+AL34 -> 1880448 | AP34: 140400 | AR34: =AN34+AP34 -> 2020848
A35: Cesantías | B35: 31257 | C35: 0 | D35: =+B35 -> 31257 | F35: 366270 | H35: =+F35+G35+D35 -> 397527 | I35: 366271 | K35: =H35+I35 -> 763798 | L35: 366271 | N35: =+K35+L35 -> 1130069 | O35: 366271 | Q35: =+N35+O35 -> 1496340 | R35: 366271 | T35: =+Q35+R35 -> 1862611 | V35: 366271 | X35: =T35+V35 -> 2228882 | Z35: 366271 | AB35: =X35+Z35 -> 2595153 | AD35: 366271 | AF35: =AB35+AD35 -> 2961424 | AH35: 366271 | AJ35: =AF35+AH35 -> 3327695 | AL35: 366271 | AN35: =AJ35+AL35 -> 3693966 | AP35: 317434 | AR35: =AN35+AP35 -> 4011400
A36: Intereses sobre cesantías | B36: 260448 | C36: 0 | D36: =+B36 -> 260448 | F36: 43952 | H36: =+F36+G36+D36 -> 304400 | I36: 43952 | K36: =H36+I36 -> 348352 | L36: 43952 | N36: =+K36+L36 -> 392304 | O36: 43952 | Q36: =+N36+O36 -> 436256 | R36: 43952 | T36: =+Q36+R36 -> 480208 | V36: 43952 | X36: =T36+V36 -> 524160 | Z36: 43952 | AB36: =X36+Z36 -> 568112 | AD36: 43952 | AF36: =AB36+AD36 -> 612064 | AH36: 43952 | AJ36: =AF36+AH36 -> 656016 | AL36: 43952 | AN36: =AJ36+AL36 -> 699968 | AP36: 38092 | AR36: =AN36+AP36 -> 738060
A37: Prima de servicios | B37: 125400 | C37: 0 | D37: =+B37 -> 125400 | F37: 366270 | H37: =+F37+G37+D37 -> 491670 | I37: 366271 | K37: =H37+I37 -> 857941 | L37: 366271 | N37: =+K37+L37 -> 1224212 | O37: 366271 | Q37: =+N37+O37 -> 1590483 | R37: 366271 | T37: =+Q37+R37 -> 1956754 | V37: 366271 | X37: =T37+V37 -> 2323025 | Z37: 366271 | AB37: =X37+Z37 -> 2689296 | AD37: 366271 | AF37: =AB37+AD37 -> 3055567 | AH37: 366271 | AJ37: =AF37+AH37 -> 3421838 | AL37: 366271 | AN37: =AJ37+AL37 -> 3788109 | AP37: 317434 | AR37: =AN37+AP37 -> 4105543
A38: Vacaciones | C38: 0 | D38: =+B38 -> 0 | F38: 176600 | H38: =+F38+G38+D38 -> 176600 | I38: 176600 | K38: =H38+I38 -> 353200 | L38: 176600 | N38: =+K38+L38 -> 529800 | O38: 176600 | Q38: =+N38+O38 -> 706400 | R38: 176600 | T38: =+Q38+R38 -> 883000 | V38: 176600 | X38: =T38+V38 -> 1059600 | Z38: 176600 | AB38: =X38+Z38 -> 1236200 | AD38: 176600 | AF38: =AB38+AD38 -> 1412800 | AH38: 176600 | AJ38: =AF38+AH38 -> 1589400 | AL38: 176600 | AN38: =AJ38+AL38 -> 1766000 | AP38: 153053 | AR38: =AN38+AP38 -> 1919053
A39: Bonificaciones | C39: 0 | D39: =+B39 -> 0 | F39: 245000 | G39: 0 | H39: =+F39+G39+D39 -> 245000 | I39: 185000 | K39: =H39+I39 -> 430000 | L39: 200000 | N39: =+K39+L39 -> 630000 | O39: 150000 | Q39: =+N39+O39 -> 780000 | R39: 350000 | T39: =+Q39+R39 -> 1130000 | X39: =T39+V39 -> 1130000 | Z39: 150000 | AB39: =X39+Z39 -> 1280000 | AD39: 150000 | AF39: =AB39+AD39 -> 1430000 | AH39: 150000 | AJ39: =AF39+AH39 -> 1580000 | AL39: 150000 | AN39: =AJ39+AL39 -> 1730000 | AP39: 650000 | AR39: =AN39+AP39 -> 2380000
A40: Dotación y elementos seguridad trabajadores | B40: 9500 | C40: 0 | D40: =+B40 -> 9500 | F40: 32000 | G40: 0 | H40: =+F40+G40+D40 -> 41500 | I40: 30000 | K40: =H40+I40 -> 71500 | L40: 636067 | N40: =+K40+L40 -> 707567 | O40: 10000 | Q40: =+N40+O40 -> 717567 | T40: =+Q40+R40 -> 717567 | X40: =T40+V40 -> 717567 | AB40: =X40+Z40 -> 717567 | AF40: =AB40+AD40 -> 717567 | AJ40: =AF40+AH40 -> 717567 | AN40: =AJ40+AL40 -> 717567 | AP40: 40000 | AR40: =AN40+AP40 -> 757567
A41: Aportes a administradoras de riesgos profesionales arp | B41: 28254 | C41: 0 | D41: =+B41 -> 28254 | F41: 44044 | G41: 0 | H41: =+F41+G41+D41 -> 72298 | I41: 44044 | K41: =H41+I41 -> 116342 | L41: 44044 | N41: =+K41+L41 -> 160386 | O41: 37310 | Q41: =+N41+O41 -> 197696 | R41: 37310 | T41: =+Q41+R41 -> 235006 | V41: 37310 | X41: =T41+V41 -> 272316 | Z41: 37310 | AB41: =X41+Z41 -> 309626 | AF41: =AB41+AD41 -> 309626 | AJ41: =AF41+AH41 -> 309626 | AN41: =AJ41+AL41 -> 309626 | AP41: 32335 | AR41: =AN41+AP41 -> 341961
A42: Aportes a entidades promotoras de salud eps | B42: 370660 | C42: 0 | D42: =+B42 -> 370660 | G42: 0 | H42: =+F42+G42+D42 -> 370660 | J42: 0 | K42: =H42+I42 -> 370660 | L42: =I42+J42 -> 0 | N42: =+K42+L42 -> 370660 | Q42: =+N42+O42 -> 370660 | S42: 0 | T42: =+Q42+R42 -> 370660 | W42: 0 | X42: =T42+V42 -> 370660 | AA42: 0 | AB42: =X42+Z42 -> 370660 | AD42: 37310 | AE42: 0 | AF42: =AB42+AD42 -> 407970 | AH42: 37310 | AI42: 0 | AJ42: =AF42+AH42 -> 445280 | AL42: 37310 | AN42: =AJ42+AL42 -> 482590 | AR42: =AN42+AP42 -> 482590
A43: Aportes a fondos de pensiones y/o cesantías | B43: 123553 | C43: 0 | D43: =+B43 -> 123553 | F43: 527640 | G43: 0 | H43: =+F43+G43+D43 -> 651193 | I43: 527640 | K43: =H43+I43 -> 1178833 | L43: 527640 | N43: =+K43+L43 -> 1706473 | O43: 527640 | Q43: =+N43+O43 -> 2234113 | R43: 527640 | T43: =+Q43+R43 -> 2761753 | V43: 527640 | X43: =T43+V43 -> 3289393 | Z43: 527640 | AB43: =X43+Z43 -> 3817033 | AD43: 527640 | AF43: =AB43+AD43 -> 4344673 | AH43: 527640 | AJ43: =AF43+AH43 -> 4872313 | AL43: 527640 | AN43: =AJ43+AL43 -> 5399953 | AP43: 457288 | AR43: =AN43+AP43 -> 5857241
A44: Aportes cajas de compensación familiar | C44: 0 | D44: =+B44 -> 0 | F44: 175880 | G44: 0 | H44: =+F44+G44+D44 -> 175880 | I44: 175880 | K44: =H44+I44 -> 351760 | L44: 175880 | N44: =+K44+L44 -> 527640 | O44: 169400 | Q44: =+N44+O44 -> 697040 | R44: 169400 | T44: =+Q44+R44 -> 866440 | V44: 169400 | X44: =T44+V44 -> 1035840 | Z44: 169400 | AB44: =X44+Z44 -> 1205240 | AD44: 169400 | AF44: =AB44+AD44 -> 1374640 | AH44: 169400 | AJ44: =AF44+AH44 -> 1544040 | AL44: 169400 | AN44: =AJ44+AL44 -> 1713440 | AP44: 146814 | AR44: =AN44+AP44 -> 1860254
A45: Drogas y medicamentos | D45: =+B45 -> 0 | H45: =+F45+G45+D45 -> 0 | K45: =H45+I45 -> 0 | N45: =+K45+L45 -> 0 | Q45: =+N45+O45 -> 0 | T45: =+Q45+R45 -> 0 | V45: 6000 | X45: =T45+V45 -> 6000 | AB45: =X45+Z45 -> 6000 | AF45: =AB45+AD45 -> 6000 | AJ45: =AF45+AH45 -> 6000 | AN45: =AJ45+AL45 -> 6000 | AR45: =AN45+AP45 -> 6000
H46: =+F46+G46+D46 -> 0 | K46: =H46+I46 -> 0 | N46: =+K46+L46 -> 0 | Q46: =+N46+O46 -> 0 | T46: =+Q46+R46 -> 0
A47: Honorarios | B47: =B48+B49+B50 -> 300000 | C47: 0 | D47: =+B47 -> 300000 | F47: =+F49 -> 300000 | G47: 0 | H47: =+F47+G47+D47 -> 600000 | I47: =I48+I49+I50 -> 300000 | J47: 0 | K47: =H47+I47 -> 900000 | L47: =L48+L49+L50 -> 300000 | M47: 0 | N47: =+K47+L47 -> 1200000 | O47: =O48+O49+O50 -> 300000 | P47: 0 | Q47: =+N47+O47 -> 1500000 | R47: =R48+R49+R50 -> 300000 | S47: 0 | T47: =+Q47+R47 -> 1800000 | V47: =V48+V49+V50 -> 300000 | W47: 0 | X47: =T47+V47 -> 2100000 | Z47: =Z48+Z49+Z50 -> 300000 | AA47: 0 | AB47: =X47+Z47 -> 2400000 | AD47: =AD48+AD49+AD50 -> 300000 | AE47: 0 | AF47: =AB47+AD47 -> 2700000 | AH47: =+AH49 -> 300000 | AI47: 0 | AJ47: =AF47+AH47 -> 3000000 | AL47: =AL48+AL49+AL50 -> 300000 | AM47: =AM48+AM49+AM50 -> 0 | AN47: =AJ47+AL47 -> 3300000 | AP47: =AP48+AP49+AP50 -> 300000 | AQ47: =AQ48+AQ49+AQ50 -> 0 | AR47: =AN47+AP47 -> 3600000
A48: Asesoria Juridica | C48: 0 | D48: =+B48 -> 0 | F48: 0 | G48: 0 | H48: =+F48+G48+D48 -> 0 | I48: 0 | J48: 0 | K48: =H48+I48 -> 0 | L48: 0 | M48: 0 | N48: =+K48+L48 -> 0 | O48: 0 | P48: 0 | Q48: =+N48+O48 -> 0 | S48: 0 | T48: =+Q48+R48 -> 0 | V48: 0 | W48: 0 | X48: =T48+V48 -> 0 | Z48: 0 | AA48: 0 | AB48: =X48+Z48 -> 0 | AD48: 0 | AE48: 0 | AF48: =AB48+AD48 -> 0 | AH48: 0 | AI48: 0 | AJ48: =AF48+AH48 -> 0 | AL48: 0 | AM48: 0 | AN48: =AJ48+AL48 -> 0 | AP48: 0 | AQ48: 0 | AR48: =AN48+AP48 -> 0
A49: Asesoría financiera | B49: 300000 | C49: 0 | D49: =+B49 -> 300000 | F49: 300000 | G49: 0 | H49: =+F49+G49+D49 -> 600000 | I49: 300000 | K49: =H49+I49 -> 900000 | L49: 300000 | N49: =+K49+L49 -> 1200000 | O49: 300000 | Q49: =+N49+O49 -> 1500000 | R49: 300000 | T49: =+Q49+R49 -> 1800000 | V49: 300000 | X49: =T49+V49 -> 2100000 | Z49: 300000 | AB49: =X49+Z49 -> 2400000 | AD49: 300000 | AF49: =AB49+AD49 -> 2700000 | AH49: 300000 | AJ49: =AF49+AH49 -> 3000000 | AL49: 300000 | AN49: =AJ49+AL49 -> 3300000 | AP49: 300000 | AR49: =AN49+AP49 -> 3600000
A50: EXOGENA | H50: =+F50+G50+D50 -> 0 | K50: =H50+I50 -> 0 | N50: =+K50+L50 -> 0 | Q50: =+N50+O50 -> 0 | T50: =+Q50+R50 -> 0 | X50: =T50+V50 -> 0 | AB50: =X50+Z50 -> 0 | AF50: =AB50+AD50 -> 0 | AJ50: =AF50+AH50 -> 0 | AN50: =AJ50+AL50 -> 0 | AR50: =AN50+AP50 -> 0
H51: =+F51+G51+D51 -> 0 | K51: =H51+I51 -> 0 | N51: =+K51+L51 -> 0 | Q51: =+N51+O51 -> 0 | T51: =+Q51+R51 -> 0 | X51: =T51+V51 -> 0 | AB51: =X51+Z51 -> 0 | AF51: =AB51+AD51 -> 0 | AJ51: =AF51+AH51 -> 0 | AN51: =AJ51+AL51 -> 0 | AR51: =AN51+AP51 -> 0
A52: Impuestos | B52: =+B53+B54+B55 -> 0 | C52: 0 | D52: =+B52 -> 0 | F52: =F55 -> 159890 | G52: 0 | H52: =+F52+G52+D52 -> 159890 | I52: =+I54+I53+I55+I56 -> 0 | J52: 0 | K52: =H52+I52 -> 159890 | L52: =+L53 -> 205000 | M52: 0 | N52: =+K52+L52 -> 364890 | O52: =+O53+O54+O55+O56 -> 0 | P52: 0 | Q52: =+N52+O52 -> 364890 | R52: =+R56 -> 0 | S52: 0 | T52: =+Q52+R52 -> 364890 | V52: =V53+V54+V55+V56 -> 414000 | W52: 0 | X52: =T52+V52 -> 778890 | Z52: =+Z56 -> 0 | AA52: 0 | AB52: =X52+Z52 -> 778890 | AD52: =+AD56 -> 0 | AE52: 0 | AF52: =AB52+AD52 -> 778890 | AH52: =+AH56 -> 0 | AI52: 0 | AJ52: =AF52+AH52 -> 778890 | AL52: =+AL56 -> 0 | AM52: 0 | AN52: =AJ52+AL52 -> 778890 | AP52: =+AP56 -> 0 | AQ52: 0 | AR52: =AN52+AP52 -> 778890
A53: Insdustria y Comercio | B53: 0 | C53: 0 | D53: =+B53 -> 0 | F53: 0 | G53: 0 | H53: =+F53+G53+D53 -> 0 | J53: 0 | K53: =H53+I53 -> 0 | L53: 205000 | N53: =+K53+L53 -> 205000 | Q53: =+N53+O53 -> 205000 | R53: 0 | T53: =+Q53+R53 -> 205000 | V53: 414000 | X53: =T53+V53 -> 619000 | Z53: 0 | AB53: =X53+Z53 -> 619000 | AD53: 0 | AF53: =AB53+AD53 -> 619000 | AH53: 0 | AJ53: =AF53+AH53 -> 619000 | AL53: 0 | AN53: =AJ53+AL53 -> 619000 | AP53: 0 | AR53: =AN53+AP53 -> 619000
A54: A la propiedad raiz | B54: 0 | C54: 0 | D54: =+B54 -> 0 | F54: 0 | G54: 0 | H54: =+F54+G54+D54 -> 0 | I54: 0 | J54: 0 | K54: =H54+I54 -> 0 | L54: 0 | M54: 0 | N54: =+K54+L54 -> 0 | O54: 0 | P54: 0 | Q54: =+N54+O54 -> 0 | R54: 0 | S54: 0 | T54: =+Q54+R54 -> 0 | V54: 0 | W54: 0 | X54: =T54+V54 -> 0 | Z54: 0 | AA54: 0 | AB54: =X54+Z54 -> 0 | AD54: 0 | AE54: 0 | AF54: =AB54+AD54 -> 0 | AH54: 0 | AI54: 0 | AJ54: =AF54+AH54 -> 0 | AL54: 0 | AM54: 0 | AN54: =AJ54+AL54 -> 0 | AP54: 0 | AQ54: 0 | AR54: =AN54+AP54 -> 0
A55: De vehículos | B55: 0 | C55: 0 | D55: =+B55 -> 0 | F55: 159890 | G55: 0 | H55: =+F55+G55+D55 -> 159890 | J55: 0 | K55: =H55+I55 -> 159890 | L55: 0 | M55: 0 | N55: =+K55+L55 -> 159890 | O55: 0 | P55: 0 | Q55: =+N55+O55 -> 159890 | R55: 0 | S55: 0 | T55: =+Q55+R55 -> 159890 | V55: 0 | W55: 0 | X55: =T55+V55 -> 159890 | Z55: 0 | AA55: 0 | AB55: =X55+Z55 -> 159890 | AD55: 0 | AE55: 0 | AF55: =AB55+AD55 -> 159890 | AH55: 0 | AI55: 0 | AJ55: =AF55+AH55 -> 159890 | AL55: 0 | AM55: 0 | AN55: =AJ55+AL55 -> 159890 | AP55: 0 | AQ55: 0 | AR55: =AN55+AP55 -> 159890
A56: Otros | B56: 0 | D56: =+B56 -> 0 | H56: =+F56+G56+D56 -> 0 | K56: =H56+I56 -> 0 | L56: 0 | N56: =+K56+L56 -> 0 | O56: 0 | Q56: =+N56+O56 -> 0 | R56: 0 | T56: =+Q56+R56 -> 0 | V56: 0 | X56: =T56+V56 -> 0 | Z56: 0 | AB56: =X56+Z56 -> 0 | AD56: 0 | AF56: =AB56+AD56 -> 0 | AH56: 0 | AJ56: =AF56+AH56 -> 0 | AL56: 0 | AN56: =AJ56+AL56 -> 0 | AP56: 0 | AR56: =AN56+AP56 -> 0
H57: =+F57+G57+D57 -> 0 | K57: =H57+I57 -> 0 | N57: =+K57+L57 -> 0 | Q57: =+N57+O57 -> 0 | T57: =+Q57+R57 -> 0
A58: Arrendamientos | B58: =+B59+B60 -> 2120000 | C58: 0 | D58: =+B58 -> 2120000 | F58: =+F59+F60 -> 2233000 | G58: 0 | H58: =+F58+G58+D58 -> 4353000 | I58: =I59+I60 -> 2609000 | J58: 0 | K58: =H58+I58 -> 6962000 | L58: =L59+L60 -> 2460000 | M58: 0 | N58: =+K58+L58 -> 9422000 | O58: =O59+O60 -> 2230240 | P58: 0 | Q58: =+N58+O58 -> 11652240 | R58: =R59+R60 -> 2120000 | S58: 0 | T58: =+Q58+R58 -> 13772240 | V58: =V59+V60 -> 2285200 | W58: 0 | X58: =T58+V58 -> 16057440 | Z58: =Z59+Z60 -> 2120000 | AA58: 0 | AB58: =X58+Z58 -> 18177440 | AD58: =AD59+AD60 -> 2270400 | AE58: 0 | AF58: =AB58+AD58 -> 20447840 | AH58: =AH59+AH60 -> 2207750 | AI58: 0 | AJ58: =AF58+AH58 -> 22655590 | AL58: =AL59+AL60 -> 2120000 | AM58: =AM59+AM60 -> 0 | AN58: =AJ58+AL58 -> 24775590 | AP58: =AP59+AP60 -> 2168000 | AQ58: =AQ59+AQ60 -> 0 | AR58: =AN58+AP58 -> 26943590
A59: Construcciones y edificaciones | B59: 2120000 | C59: 0 | D59: =+B59 -> 2120000 | F59: 2120000 | G59: 0 | H59: =+F59+G59+D59 -> 4240000 | I59: 2120000 | J59: 0 | K59: =H59+I59 -> 6360000 | L59: 2120000 | M59: 0 | N59: =+K59+L59 -> 8480000 | O59: 2120000 | P59: 0 | Q59: =+N59+O59 -> 10600000 | R59: 2120000 | T59: =+Q59+R59 -> 12720000 | V59: 2120000 | X59: =T59+V59 -> 14840000 | Z59: 2120000 | AB59: =X59+Z59 -> 16960000 | AD59: 2120000 | AF59: =AB59+AD59 -> 19080000 | AH59: 2120000 | AJ59: =AF59+AH59 -> 21200000 | AL59: 2120000 | AN59: =AJ59+AL59 -> 23320000 | AP59: 2120000 | AR59: =AN59+AP59 -> 25440000
A60: Maquinaria y equipo | C60: 0 | D60: =+B60 -> 0 | F60: 113000 | H60: =+F60+G60+D60 -> 113000 | I60: 489000 | K60: =H60+I60 -> 602000 | L60: 340000 | N60: =+K60+L60 -> 942000 | O60: 110240 | Q60: =+N60+O60 -> 1052240 | R60: 0 | T60: =+Q60+R60 -> 1052240 | V60: 165200 | X60: =T60+V60 -> 1217440 | AB60: =X60+Z60 -> 1217440 | AD60: 150400 | AF60: =AB60+AD60 -> 1367840 | AH60: 87750 | AJ60: =AF60+AH60 -> 1455590 | AL60: 0 | AN60: =AJ60+AL60 -> 1455590 | AP60: 48000 | AR60: =AN60+AP60 -> 1503590
H61: =+F61+G61+D61 -> 0 | K61: =H61+I61 -> 0 | N61: =+K61+L61 -> 0 | Q61: =+N61+O61 -> 0 | T61: =+Q61+R61 -> 0
A62: Afilicaciones y contribuciones | B62: =+B63 -> 0 | D62: =+D63 -> 0 | F62: =+F63 -> 0 | H62: =+F62+G62+D62 -> 0 | I62: =+I63 -> 0 | K62: =H62+I62 -> 0 | L62: 0 | N62: =+K62+L62 -> 0 | O62: =+O63 -> 0 | Q62: =+N62+O62 -> 0 | R62: 0 | T62: =+Q62+R62 -> 0 | V62: 0 | X62: =T62+V62 -> 0 | Z62: 0 | AB62: =X62+Z62 -> 0 | AD62: =AD63 -> 481583 | AF62: =AB62+AD62 -> 481583 | AH62: 0 | AJ62: =AF62+AH62 -> 481583 | AL62: 0 | AM62: =AM63 -> 0 | AN62: =AJ62+AL62 -> 481583 | AP62: 0 | AQ62: =AQ63 -> 0 | AR62: =AN62+AP62 -> 481583
A63: Afiliaciones | C63: 0 | D63: =+B63 -> 0 | H63: =+F63+G63+D63 -> 0 | I63: 0 | K63: =H63+I63 -> 0 | N63: =+K63+L63 -> 0 | Q63: =+N63+O63 -> 0 | R63: 0 | T63: =+Q63+R63 -> 0 | V63: 0 | X63: =T63+V63 -> 0 | Z63: 0 | AB63: =X63+Z63 -> 0 | AD63: 481583 | AF63: =AB63+AD63 -> 481583 | AH63: 0 | AJ63: =AF63+AH63 -> 481583 | AL63: 0 | AN63: =AJ63+AL63 -> 481583 | AP63: 0 | AR63: =AN63+AP63 -> 481583
H64: =+F64+G64+D64 -> 0 | K64: =H64+I64 -> 0 | N64: =+K64+L64 -> 0 | Q64: =+N64+O64 -> 0 | T64: =+Q64+R64 -> 0
A65: Seguros | B65: =+B66 -> 968800 | C65: 0 | D65: =+B65 -> 968800 | F65: =F68 -> 0 | G65: 0 | H65: =+F65+G65+D65 -> 968800 | I65: =I66+I67 -> 0 | J65: 0 | K65: =H65+I65 -> 968800 | L65: =L66+L67+L68 -> 0 | M65: 0 | N65: =+K65+L65 -> 968800 | O65: =O66+O67+O68 -> 0 | P65: 0 | Q65: =+N65+O65 -> 968800 | R65: =R66+R67+R68 -> 0 | S65: 0 | T65: =+Q65+R65 -> 968800 | V65: =V66+V67+V68 -> 0 | W65: 0 | X65: =T65+V65 -> 968800 | Z65: =Z66+Z67+Z68 -> 0 | AA65: 0 | AB65: =X65+Z65 -> 968800 | AD65: =AD66+AD67+AD68 -> 0 | AE65: 0 | AF65: =AB65+AD65 -> 968800 | AH65: =AH66+AH67+AH68 -> 0 | AI65: 0 | AJ65: =AF65+AH65 -> 968800 | AL65: =AL66+AL67+AL68 -> 0 | AM65: =AM66+AM67+AM68 -> 0 | AN65: =AJ65+AL65 -> 968800 | AP65: =AP66+AP67+AP68 -> 0 | AQ65: =AQ66+AQ67+AQ68 -> 0 | AR65: =AN65+AP65 -> 968800
A66: Flota y equipo de transporte | B66: 968800 | D66: =+B66 -> 968800 | H66: =+F66+G66+D66 -> 968800 | K66: =H66+I66 -> 968800 | N66: =+K66+L66 -> 968800 | Q66: =+N66+O66 -> 968800 | R66: 0 | T66: =+Q66+R66 -> 968800 | V66: 0 | X66: =T66+V66 -> 968800 | Z66: 0 | AB66: =X66+Z66 -> 968800 | AD66: 0 | AF66: =AB66+AD66 -> 968800 | AH66: 0 | AJ66: =AF66+AH66 -> 968800 | AL66: 0 | AN66: =AJ66+AL66 -> 968800 | AP66: 0 | AR66: =AN66+AP66 -> 968800
A67: Obligatorio accidente de transito | D67: =+B67 -> 0 | H67: =+F67+G67+D67 -> 0 | K67: =H67+I67 -> 0 | N67: =+K67+L67 -> 0 | Q67: =+N67+O67 -> 0 | R67: 0 | T67: =+Q67+R67 -> 0 | V67: 0 | X67: =T67+V67 -> 0 | Z67: 0 | AB67: =X67+Z67 -> 0 | AD67: 0 | AF67: =AB67+AD67 -> 0 | AH67: 0 | AJ67: =AF67+AH67 -> 0 | AL67: 0 | AN67: =AJ67+AL67 -> 0 | AP67: 0 | AR67: =AN67+AP67 -> 0
A68: Otros SOAT | C68: 0 | D68: =+B68 -> 0 | F68: 0 | G68: 0 | H68: =+F68+G68+D68 -> 0 | I68: 0 | J68: 0 | K68: =H68+I68 -> 0 | L68: 0 | M68: 0 | N68: =+K68+L68 -> 0 | O68: 0 | P68: 0 | Q68: =+N68+O68 -> 0 | R68: 0 | S68: 0 | T68: =+Q68+R68 -> 0 | V68: 0 | W68: 0 | X68: =T68+V68 -> 0 | Z68: 0 | AA68: 0 | AB68: =X68+Z68 -> 0 | AD68: 0 | AE68: 0 | AF68: =AB68+AD68 -> 0 | AH68: 0 | AI68: 0 | AJ68: =AF68+AH68 -> 0 | AL68: 0 | AM68: 0 | AN68: =AJ68+AL68 -> 0 | AP68: 0 | AQ68: 0 | AR68: =AN68+AP68 -> 0
H69: =+F69+G69+D69 -> 0 | K69: =H69+I69 -> 0 | N69: =+K69+L69 -> 0 | Q69: =+N69+O69 -> 0 | T69: =+Q69+R69 -> 0 | X69: =T69+V69 -> 0 | AB69: =X69+Z69 -> 0 | AF69: =AB69+AD69 -> 0 | AJ69: =AF69+AH69 -> 0 | AN69: =AJ69+AL69 -> 0 | AR69: =AN69+AP69 -> 0
A70: Servicios | B70: =B71+B72+B74+B75+B76+B78+B77+B79 -> 1361393 | C70: 0 | D70: =+B70 -> 1361393 | F70: =F71+F72+F74+F75+F76+F79 -> 1590675 | G70: 0 | H70: =+F70+G70+D70 -> 2952068 | I70: =I71+I72+I74+I75+I76+I79 -> 971060 | J70: 0 | K70: =H70+I70 -> 3923128 | L70: =SUM(L71:L79) -> 2300009 | M70: 0 | N70: =+K70+L70 -> 6223137 | O70: =SUM(O71:O79) -> 2373892 | P70: 0 | Q70: =+N70+O70 -> 8597029 | R70: =SUM(R71:R79) -> 1364300 | S70: 0 | T70: =+Q70+R70 -> 9961329 | V70: =SUM(V71:V79) -> 1435961 | W70: 0 | X70: =T70+V70 -> 11397290 | Z70: =SUM(Z71:Z79) -> 2196464 | AA70: 0 | AB70: =X70+Z70 -> 13593754 | AD70: =SUM(AD71:AD79) -> 3263868 | AE70: 0 | AF70: =AB70+AD70 -> 16857622 | AH70: =SUM(AH71:AH79) -> 3801387 | AI70: 0 | AJ70: =AF70+AH70 -> 20659009 | AL70: =SUM(AL71:AL79) -> 2584597 | AM70: 0 | AN70: =AJ70+AL70 -> 23243606 | AP70: =SUM(AP71:AP79) -> 2765994 | AQ70: 0 | AR70: =AN70+AP70 -> 26009600
A71: Aseo y vigilancia | C71: 0 | D71: =+B71 -> 0 | G71: 0 | H71: =+F71+G71+D71 -> 0 | I71: 0 | J71: 0 | K71: =H71+I71 -> 0 | L71: 0 | M71: 0 | N71: =+K71+L71 -> 0 | O71: 80000 | P71: 0 | Q71: =+N71+O71 -> 80000 | R71: 0 | S71: 0 | T71: =+Q71+R71 -> 80000 | V71: 0 | W71: 0 | X71: =T71+V71 -> 80000 | Z71: 0 | AA71: 0 | AB71: =X71+Z71 -> 80000 | AD71: 0 | AE71: 0 | AF71: =AB71+AD71 -> 80000 | AH71: 0 | AI71: 0 | AJ71: =AF71+AH71 -> 80000 | AM71: 0 | AN71: =AJ71+AL71 -> 80000 | AQ71: 0 | AR71: =AN71+AP71 -> 80000
A72: Temporales | B72: 1070000 | C72: 0 | D72: =+B72 -> 1070000 | F72: 1170000 | G72: 0 | H72: =+F72+G72+D72 -> 2240000 | I72: 740000 | K72: =H72+I72 -> 2980000 | L72: 1975000 | N72: =+K72+L72 -> 4955000 | O72: 1950000 | Q72: =+N72+O72 -> 6905000 | R72: 970000 | T72: =+Q72+R72 -> 7875000 | V72: 960000 | X72: =T72+V72 -> 8835000 | Z72: 1680000 | AB72: =X72+Z72 -> 10515000 | AD72: 2910000 | AF72: =AB72+AD72 -> 13425000 | AH72: 3190000 | AJ72: =AF72+AH72 -> 16615000 | AL72: 2300000 | AN72: =AJ72+AL72 -> 18915000 | AP72: 2460000 | AR72: =AN72+AP72 -> 21375000
A73: Procesamiento datos | H73: =+F73+G73+D73 -> 0 | K73: =H73+I73 -> 0 | L73: 0 | N73: =+K73+L73 -> 0 | Q73: =+N73+O73 -> 0 | R73: 0 | T73: =+Q73+R73 -> 0 | V73: 0 | Z73: 0 | AD73: 0 | AH73: 0 | AL73: 0 | AP73: 0
A74: Acueducto y alcantarillado | B74: 58800 | C74: 0 | D74: =+B74 -> 58800 | F74: 58970 | G74: 0 | H74: =+F74+G74+D74 -> 117770 | I74: 60010 | K74: =H74+I74 -> 177780 | L74: 68910 | N74: =+K74+L74 -> 246690 | O74: 189156 | Q74: =+N74+O74 -> 435846 | R74: 102710 | T74: =+Q74+R74 -> 538556 | V74: 102890 | X74: =T74+V74 -> 641446 | Z74: 61770 | AB74: =X74+Z74 -> 703216 | AD74: 63360 | AF74: =AB74+AD74 -> 766576 | AH74: 81770 | AJ74: =AF74+AH74 -> 848346 | AL74: 81030 | AN74: =AJ74+AL74 -> 929376 | AP74: 72320 | AR74: =AN74+AP74 -> 1001696
A75: Energía eléctrica | B75: 78900 | C75: 0 | D75: =+B75 -> 78900 | F75: 85120 | G75: 0 | H75: =+F75+G75+D75 -> 164020 | I75: 109264 | K75: =H75+I75 -> 273284 | L75: 90031 | N75: =+K75+L75 -> 363315 | Q75: =+N75+O75 -> 363315 | R75: 124223 | T75: =+Q75+R75 -> 487538 | V75: 124629 | X75: =T75+V75 -> 612167 | AB75: =X75+Z75 -> 612167 | AD75: 126973 | AF75: =AB75+AD75 -> 739140 | AH75: 154383 | AJ75: =AF75+AH75 -> 893523 | AL75: 141781 | AN75: =AJ75+AL75 -> 1035304 | AP75: 128760 | AR75: =AN75+AP75 -> 1164064
A76: Teléfono fijo y moviles | B76: 153693 | C76: 0 | D76: =+B76 -> 153693 | F76: 276585 | G76: 0 | H76: =+F76+G76+D76 -> 430278 | I76: 61786 | K76: =H76+I76 -> 492064 | L76: 166068 | N76: =+K76+L76 -> 658132 | O76: 154736 | Q76: =+N76+O76 -> 812868 | R76: 167367 | S76: 0 | T76: =+Q76+R76 -> 980235 | V76: 248442 | X76: =T76+V76 -> 1228677 | Z76: 154694 | AB76: =X76+Z76 -> 1383371 | AD76: 163535 | AF76: =AB76+AD76 -> 1546906 | AH76: 175234 | AJ76: =AF76+AH76 -> 1722140 | AL76: 61786 | AN76: =AJ76+AL76 -> 1783926 | AP76: 104914 | AR76: =AN76+AP76 -> 1888840
A77: Correo portes y telegrama | C77: 0 | D77: =+B77 -> 0 | F77: 0 | G77: 0 | H77: =+F77+G77+D77 -> 0 | I77: 0 | J77: 0 | K77: =H77+I77 -> 0 | L77: 0 | N77: =+K77+L77 -> 0 | O77: 0 | Q77: =+N77+O77 -> 0 | R77: 0 | S77: 0 | T77: =+Q77+R77 -> 0 | V77: 0 | W77: 0 | X77: =T77+V77 -> 0 | Z77: 0 | AA77: 0 | AB77: =X77+Z77 -> 0 | AD77: 0 | AE77: 0 | AF77: =AB77+AD77 -> 0 | AH77: 0 | AI77: 0 | AJ77: =AF77+AH77 -> 0 | AL77: 0 | AM77: 0 | AN77: =AJ77+AL77 -> 0 | AP77: 0 | AQ77: 0 | AR77: =AN77+AP77 -> 0
A78: Otros | C78: 0 | D78: =+B78 -> 0 | F78: 0 | G78: 0 | H78: =+F78+G78+D78 -> 0 | I78: 0 | J78: 0 | K78: =H78+I78 -> 0 | M78: 0 | N78: =+K78+L78 -> 0 | P78: 0 | Q78: =+N78+O78 -> 0 | R78: 0 | S78: 0 | T78: =+Q78+R78 -> 0 | V78: 0 | W78: 0 | X78: =T78+V78 -> 0 | Z78: 0 | AA78: 0 | AB78: =X78+Z78 -> 0 | AD78: 0 | AE78: 0 | AF78: =AB78+AD78 -> 0 | AH78: 0 | AI78: 0 | AJ78: =AF78+AH78 -> 0 | AL78: 0 | AM78: 0 | AN78: =AJ78+AL78 -> 0 | AP78: 0 | AQ78: 0 | AR78: =AN78+AP78 -> 0
A79: Transportes, fletes y acarreos | C79: 0 | D79: =+B79 -> 0 | F79: 0 | G79: 0 | H79: =+F79+G79+D79 -> 0 | I79: 0 | J79: 0 | K79: =H79+I79 -> 0 | M79: 0 | N79: =+K79+L79 -> 0 | P79: 0 | Q79: =+N79+O79 -> 0 | T79: =+Q79+R79 -> 0 | X79: =T79+V79 -> 0 | Z79: 300000 | AB79: =X79+Z79 -> 300000 | AF79: =AB79+AD79 -> 300000 | AH79: 200000 | AJ79: =AF79+AH79 -> 500000 | AN79: =AJ79+AL79 -> 500000 | AR79: =AN79+AP79 -> 500000
D80: =+B80 -> 0 | H80: =+F80+G80+D80 -> 0 | K80: =H80+I80 -> 0 | N80: =+K80+L80 -> 0 | Q80: =+N80+O80 -> 0 | T80: =+Q80+R80 -> 0 | X80: =T80+V80 -> 0 | AB80: =X80+Z80 -> 0 | AF80: =AB80+AD80 -> 0 | AJ80: =AF80+AH80 -> 0 | AN80: =AJ80+AL80 -> 0 | AR80: =AN80+AP80 -> 0
A81: Gastos legales | B81: =+B84 -> 25210 | C81: 0 | D81: =+B81 -> 25210 | F81: =F83+F84 -> 7900 | G81: 0 | H81: =+F81+G81+D81 -> 33110 | I81: =I82+I83+I84+I85 -> 0 | J81: 0 | K81: =H81+I81 -> 33110 | L81: =L83+L84 -> 0 | M81: 0 | N81: =+K81+L81 -> 33110 | O81: {=O83+O84:O85} -> 0 | P81: 0 | Q81: =+N81+O81 -> 33110 | R81: =R83+R84 -> 0 | S81: 0 | T81: =+Q81+R81 -> 33110 | V81: =V83+V84 -> 0 | W81: 0 | X81: =T81+V81 -> 33110 | Z81: =Z83+Z84 -> 7900 | AA81: 0 | AB81: =X81+Z81 -> 41010 | AD81: =SUM(AD82:AD84) -> 0 | AE81: 0 | AF81: =AB81+AD81 -> 41010 | AH81: =+AH82+AH84 -> 0 | AI81: 0 | AJ81: =AF81+AH81 -> 41010 | AL81: =AL83+AL84 -> 0 | AM81: 0 | AN81: =AJ81+AL81 -> 41010 | AP81: =AP83+AP84 -> 1817800 | AQ81: 0 | AR81: =AN81+AP81 -> 1858810
A82: Notariales | B82: 0 | C82: 0 | D82: =+B82 -> 0 | F82: 0 | G82: 0 | H82: =+F82+G82+D82 -> 0 | I82: 0 | J82: 0 | K82: =H82+I82 -> 0 | N82: =+K82+L82 -> 0 | O82: 0 | Q82: =+N82+O82 -> 0 | R82: 0 | S82: 0 | T82: =+Q82+R82 -> 0 | V82: 0 | W82: 0 | X82: =T82+V82 -> 0 | Z82: 0 | AA82: 0 | AB82: =X82+Z82 -> 0 | AE82: 0 | AF82: =AB82+AD82 -> 0 | AI82: 0 | AJ82: =AF82+AH82 -> 0 | AL82: 0 | AM82: 0 | AN82: =AJ82+AL82 -> 0 | AP82: 0 | AQ82: 0 | AR82: =AN82+AP82 -> 0
A83: Registro mercantil | B83: 0 | C83: 0 | D83: =+B83 -> 0 | F83: 7900 | G83: 0 | H83: =+F83+G83+D83 -> 7900 | J83: 0 | K83: =H83+I83 -> 7900 | N83: =+K83+L83 -> 7900 | Q83: =+N83+O83 -> 7900 | T83: =+Q83+R83 -> 7900 | X83: =T83+V83 -> 7900 | Z83: 7900 | AB83: =X83+Z83 -> 15800 | AF83: =AB83+AD83 -> 15800 | AH83: 0 | AI83: 0 | AJ83: =AF83+AH83 -> 15800 | AN83: =AJ83+AL83 -> 15800 | AP83: 1817800 | AR83: =AN83+AP83 -> 1833600
A84: Trámites y licencias | B84: 25210 | C84: 0 | D84: =+B84 -> 25210 | F84: 0 | G84: 0 | H84: =+F84+G84+D84 -> 25210 | J84: 0 | K84: =H84+I84 -> 25210 | L84: 0 | M84: 0 | N84: =+K84+L84 -> 25210 | P84: 0 | Q84: =+N84+O84 -> 25210 | R84: 0 | S84: 0 | T84: =+Q84+R84 -> 25210 | V84: 0 | W84: 0 | X84: =T84+V84 -> 25210 | AB84: =X84+Z84 -> 25210 | AF84: =AB84+AD84 -> 25210 | AI84: 0 | AJ84: =AF84+AH84 -> 25210 | AL84: 0 | AN84: =AJ84+AL84 -> 25210 | AP84: 0 | AR84: =AN84+AP84 -> 25210
A85: Otros | B85: 0 | C85: 0 | D85: =+B85 -> 0 | F85: 0 | G85: 0 | H85: =+F85+G85+D85 -> 0 | J85: 0 | K85: =H85+I85 -> 0 | N85: =+K85+L85 -> 0 | Q85: =+N85+O85 -> 0 | R85: 0 | T85: =+Q85+R85 -> 0 | V85: 0 | X85: =T85+V85 -> 0 | Z85: 0 | AB85: =X85+Z85 -> 0 | AF85: =AB85+AD85 -> 0 | AH85: 0 | AI85: 0 | AJ85: =AF85+AH85 -> 0 | AL85: 0 | AN85: =AJ85+AL85 -> 0 | AP85: 0 | AR85: =AN85+AP85 -> 0
D86: =+B86 -> 0 | H86: =+F86+G86+D86 -> 0 | K86: =H86+I86 -> 0 | N86: =+K86+L86 -> 0 | Q86: =+N86+O86 -> 0 | T86: =+Q86+R86 -> 0 | AJ86: =AF86+AH86 -> 0
A87: Mantenimiento y reparaciones | B87: =+B89+B90+B91+B92 -> 247307 | C87: 0 | D87: =+B87 -> 247307 | F87: =F89+F90+F92+F91 -> 1833234 | G87: 0 | H87: =+F87+G87+D87 -> 2080541 | I87: =I88+I89+I90+I91+I92 -> 404815 | J87: 0 | K87: =H87+I87 -> 2485356 | L87: =+L89+L90+L91+L92+L88 -> 1047694 | M87: 0 | N87: =+K87+L87 -> 3533050 | O87: =+O88+O89+O90+O91+O92 -> 1516442 | P87: 0 | Q87: =+N87+O87 -> 5049492 | R87: =+R89+R90+R91+R92+R88 -> 241865 | S87: 0 | T87: =+Q87+R87 -> 5291357 | V87: =+V89+V90+V91+V92+V88 -> 105000 | W87: 0 | X87: =T87+V87 -> 5396357 | Z87: =+Z89+Z90+Z91+Z92+Z88 -> 341742 | AA87: 0 | AB87: =X87+Z87 -> 5738099 | AD87: =+AD89+AD90+AD91+AD92+AD88 -> 859697 | AE87: 0 | AF87: =AB87+AD87 -> 6597796 | AH87: =+AH89+AH90+AH91+AH92+AH88 -> 1050368 | AI87: 0 | AJ87: =AF87+AH87 -> 7648164 | AL87: =+AL89+AL90+AL91+AL92+AL88 -> 61534 | AM87: 0 | AN87: =AJ87+AL87 -> 7709698 | AP87: =+AP89+AP90+AP91+AP92+AP88 -> 150000 | AQ87: 0 | AR87: =AN87+AP87 -> 7859698
A88: construcciones y edificaciones | H88: =+F88+G88+D88 -> 0 | K88: =H88+I88 -> 0 | N88: =+K88+L88 -> 0 | Q88: =+N88+O88 -> 0 | T88: =+Q88+R88 -> 0 | X88: =T88+V88 -> 0 | AB88: =X88+Z88 -> 0 | AF88: =AB88+AD88 -> 0 | AJ88: =AF88+AH88 -> 0 | AN88: =AJ88+AL88 -> 0 | AR88: =AN88+AP88 -> 0
A89: Maquinaria y equipo | B89: 217055 | C89: 0 | D89: =+B89 -> 217055 | F89: 1061259 | G89: 0 | H89: =+F89+G89+D89 -> 1278314 | I89: 404815 | K89: =H89+I89 -> 1683129 | L89: 947694 | N89: =+K89+L89 -> 2630823 | O89: 1186442 | Q89: =+N89+O89 -> 3817265 | R89: 241865 | T89: =+Q89+R89 -> 4059130 | V89: 105000 | X89: =T89+V89 -> 4164130 | Z89: 117910 | AB89: =X89+Z89 -> 4282040 | AD89: 252000 | AF89: =AB89+AD89 -> 4534040 | AH89: 856668 | AJ89: =AF89+AH89 -> 5390708 | AL89: 61534 | AN89: =AJ89+AL89 -> 5452242 | AR89: =AN89+AP89 -> 5452242
A90: Equipo de oficina | B90: 0 | C90: 0 | D90: =+B90 -> 0 | F90: 0 | G90: 0 | H90: =+F90+G90+D90 -> 0 | I90: 0 | J90: 0 | K90: =H90+I90 -> 0 | N90: =+K90+L90 -> 0 | Q90: =+N90+O90 -> 0 | R90: 0 | T90: =+Q90+R90 -> 0 | X90: =T90+V90 -> 0 | AB90: =X90+Z90 -> 0 | AD90: 0 | AF90: =AB90+AD90 -> 0 | AH90: 0 | AJ90: =AF90+AH90 -> 0 | AN90: =AJ90+AL90 -> 0 | AR90: =AN90+AP90 -> 0
A91: Equipo de computación y comunicación | C91: 0 | D91: =+B91 -> 0 | F91: 510294 | G91: 0 | H91: =+F91+G91+D91 -> 510294 | J91: 0 | K91: =H91+I91 -> 510294 | L91: 0 | N91: =+K91+L91 -> 510294 | Q91: =+N91+O91 -> 510294 | T91: =+Q91+R91 -> 510294 | V91: 0 | X91: =T91+V91 -> 510294 | AB91: =X91+Z91 -> 510294 | AF91: =AB91+AD91 -> 510294 | AH91: 193700 | AJ91: =AF91+AH91 -> 703994 | AN91: =AJ91+AL91 -> 703994 | AR91: =AN91+AP91 -> 703994
A92: Flota y equipo de transportes | B92: 30252 | C92: 0 | D92: =+B92 -> 30252 | F92: 261681 | G92: 0 | H92: =+F92+G92+D92 -> 291933 | J92: 0 | K92: =H92+I92 -> 291933 | L92: 100000 | N92: =+K92+L92 -> 391933 | O92: 330000 | Q92: =+N92+O92 -> 721933 | T92: =+Q92+R92 -> 721933 | X92: =T92+V92 -> 721933 | Z92: 223832 | AB92: =X92+Z92 -> 945765 | AD92: 607697 | AF92: =AB92+AD92 -> 1553462 | AJ92: =AF92+AH92 -> 1553462 | AN92: =AJ92+AL92 -> 1553462 | AP92: 150000 | AR92: =AN92+AP92 -> 1703462
D93: =+B93 -> 0 | H93: =+F93+G93+D93 -> 0 | K93: =H93+I93 -> 0 | N93: =+K93+L93 -> 0 | Q93: =+N93+O93 -> 0 | T93: =+Q93+R93 -> 0
A94: Adecuación e instalación | B94: =+B95+B96+B97+B98 -> 265300 | C94: 0 | D94: =+B94 -> 265300 | F94: =+F95+F96+F97+F98 -> 30000 | G94: 0 | H94: =+F94+G94+D94 -> 295300 | I94: =+I95+I96+I97 -> 65000 | J94: 0 | K94: =H94+I94 -> 360300 | L94: =L98+L97 -> 76000 | M94: 0 | N94: =+K94+L94 -> 436300 | O94: =O95+O96+O97+O98 -> 0 | P94: 0 | Q94: =+N94+O94 -> 436300 | R94: =R98+R97 -> 0 | S94: 0 | T94: =+Q94+R94 -> 436300 | V94: =V98+V97+V96+V95 -> 0 | W94: 0 | X94: =T94+V94 -> 436300 | Z94: =Z98+Z97 -> 0 | AA94: 0 | AB94: =X94+Z94 -> 436300 | AD94: =AD98+AD97 -> 0 | AE94: 0 | AF94: =AB94+AD94 -> 436300 | AH94: =AH95+AH96+AH97+AH98 -> 0 | AI94: 0 | AJ94: =AF94+AH94 -> 436300 | AL94: =AL98+AL97 -> 0 | AM94: 0 | AN94: =AJ94+AL94 -> 436300 | AP94: =AP98+AP97 -> 0 | AQ94: 0 | AR94: =AN94+AP94 -> 436300
A95: Instalaciones electricas | B95: 0 | C95: 0 | D95: =+B95 -> 0 | F95: 30000 | G95: 0 | H95: =+F95+G95+D95 -> 30000 | I95: 65000 | K95: =H95+I95 -> 95000 | M95: 0 | N95: =+K95+L95 -> 95000 | P95: 0 | Q95: =+N95+O95 -> 95000 | R95: 0 | S95: 0 | T95: =+Q95+R95 -> 95000 | X95: =T95+V95 -> 95000 | Z95: 0 | AB95: =X95+Z95 -> 95000 | AF95: =AB95+AD95 -> 95000 | AJ95: =AF95+AH95 -> 95000 | AL95: 0 | AN95: =AJ95+AL95 -> 95000 | AP95: 0 | AR95: =AN95+AP95 -> 95000
A96: Arreglos ornamentales | B96: 0 | C96: 0 | D96: =+B96 -> 0 | F96: 0 | G96: 0 | H96: =+F96+G96+D96 -> 0 | I96: 0 | J96: 0 | K96: =H96+I96 -> 0 | L96: 0 | M96: 0 | N96: =+K96+L96 -> 0 | P96: 0 | Q96: =+N96+O96 -> 0 | R96: 0 | S96: 0 | T96: =+Q96+R96 -> 0 | V96: 0 | W96: 0 | X96: =T96+V96 -> 0 | Z96: 0 | AA96: 0 | AB96: =X96+Z96 -> 0 | AE96: 0 | AF96: =AB96+AD96 -> 0 | AH96: 0 | AI96: 0 | AJ96: =AF96+AH96 -> 0 | AL96: 0 | AM96: 0 | AN96: =AJ96+AL96 -> 0 | AP96: 0 | AQ96: 0 | AR96: =AN96+AP96 -> 0
A97: Reparaciones locativas | B97: 265300 | C97: 0 | D97: =+B97 -> 265300 | G97: 0 | H97: =+F97+G97+D97 -> 265300 | J97: 0 | K97: =H97+I97 -> 265300 | L97: 76000 | N97: =+K97+L97 -> 341300 | Q97: =+N97+O97 -> 341300 | T97: =+Q97+R97 -> 341300 | X97: =T97+V97 -> 341300 | AB97: =X97+Z97 -> 341300 | AF97: =AB97+AD97 -> 341300 | AJ97: =AF97+AH97 -> 341300 | AN97: =AJ97+AL97 -> 341300 | AR97: =AN97+AP97 -> 341300
A98: Otros | B98: 0 | C98: 0 | D98: =+B98 -> 0 | F98: 0 | G98: 0 | H98: =+F98+G98+D98 -> 0 | I98: 0 | J98: 0 | K98: =H98+I98 -> 0 | N98: =+K98+L98 -> 0 | Q98: =+N98+O98 -> 0 | T98: =+Q98+R98 -> 0 | X98: =T98+V98 -> 0 | AB98: =X98+Z98 -> 0 | AF98: =AB98+AD98 -> 0 | AJ98: =AF98+AH98 -> 0 | AN98: =AJ98+AL98 -> 0 | AR98: =AN98+AP98 -> 0
D99: =+B99 -> 0 | H99: =+F99+G99+D99 -> 0 | K99: =H99+I99 -> 0 | N99: =+K99+L99 -> 0 | Q99: =+N99+O99 -> 0 | T99: =+Q99+R99 -> 0 | X99: =T99+V99 -> 0 | AB99: =X99+Z99 -> 0 | AF99: =AB99+AD99 -> 0 | AJ99: =AF99+AH99 -> 0 | AN99: =AJ99+AL99 -> 0 | AR99: =AN99+AP99 -> 0
A100: Depreciacion | B100: =+B101+B102+B103+B104+B105 -> 0 | D100: =+B100 -> 0 | F100: =+F101+F102+F103+F104+F105 -> 0 | H100: =+F100+G100+D100 -> 0 | I100: =+I101+I102+I103+I104+I105 -> 0 | K100: =H100+I100 -> 0 | N100: =+K100+L100 -> 0 | O100: =+O101+O102+O103+O104+O105 -> 0 | Q100: =+N100+O100 -> 0 | R100: =+R101+R102+R103+R104+R105 -> 0 | T100: =+Q100+R100 -> 0 | V100: =+V101+V102+V103+V104+V105 -> 0 | X100: =T100+V100 -> 0 | Z100: =+Z101+Z102+Z103+Z104+Z105 -> 0 | AB100: =X100+Z100 -> 0 | AD100: =+AD101+AD102+AD103+AD104+AD105 -> 0 | AF100: =AB100+AD100 -> 0 | AH100: =+AH101+AH102+AH103+AH104+AH105 -> 0 | AJ100: =AF100+AH100 -> 0 | AL100: =+AL101+AL102+AL103+AL104+AL105 -> 0 | AN100: =AJ100+AL100 -> 0 | AP100: =+AP101+AP102+AP103+AP104+AP105 -> 0 | AR100: =AN100+AP100 -> 0
A101: construcciones y edificaciones | B101: 0 | D101: =+B101 -> 0 | F101: 0 | H101: =+F101+G101+D101 -> 0 | I101: 0 | K101: =H101+I101 -> 0 | L101: 0 | N101: =+K101+L101 -> 0 | O101: 0 | Q101: =+N101+O101 -> 0 | R101: 0 | T101: =+Q101+R101 -> 0 | V101: 0 | X101: =T101+V101 -> 0 | Z101: 0 | AB101: =X101+Z101 -> 0 | AF101: =AB101+AD101 -> 0 | AJ101: =AF101+AH101 -> 0 | AN101: =AJ101+AL101 -> 0 | AR101: =AN101+AP101 -> 0
A102: maquinaria y equipo | B102: 0 | D102: =+B102 -> 0 | F102: 0 | H102: =+F102+G102+D102 -> 0 | I102: 0 | K102: =H102+I102 -> 0 | L102: 0 | N102: =+K102+L102 -> 0 | O102: 0 | Q102: =+N102+O102 -> 0 | R102: 0 | T102: =+Q102+R102 -> 0 | V102: 0 | X102: =T102+V102 -> 0 | Z102: 0 | AB102: =X102+Z102 -> 0 | AF102: =AB102+AD102 -> 0 | AJ102: =AF102+AH102 -> 0 | AN102: =AJ102+AL102 -> 0 | AR102: =AN102+AP102 -> 0
A103: equipo de oficina | B103: 0 | D103: =+B103 -> 0 | F103: 0 | H103: =+F103+G103+D103 -> 0 | I103: 0 | K103: =H103+I103 -> 0 | L103: 0 | N103: =+K103+L103 -> 0 | O103: 0 | Q103: =+N103+O103 -> 0 | R103: 0 | T103: =+Q103+R103 -> 0 | V103: 0 | X103: =T103+V103 -> 0 | Z103: 0 | AB103: =X103+Z103 -> 0 | AD103: 0 | AF103: =AB103+AD103 -> 0 | AH103: 0 | AJ103: =AF103+AH103 -> 0 | AL103: 0 | AN103: =AJ103+AL103 -> 0 | AP103: 0 | AR103: =AN103+AP103 -> 0
...

Sheet GRAFICAS PYG
B5: MES | C5: VENTAS FISCALES 2024 | D5: VENTAS FISCALES 2023 | E5: VENTAS FISCALES 2022 | F5: VENTAS FISCALES 2021 | G5: VENTAS FISCALES 2020 | H5: VENTAS FISCALES 2019 | I5: VENTAS FISCALES 2018 | J5: VENTAS FISCALES 2017 | K5: VENTAS SIN IVA 2024 | L5: VENTAS SIN IVA 2023 | M5: VENTAS SIN IVA 2022 | N5: VENTAS SIN IVA 2021 | O5: VENTAS SIN IVA 2020 | P5: VENTAS SIN IVA 2019 | Q5: VENTAS SIN IVA 2018 | R5: VENTAS SIN IVA 2017 | S5: GASTOS 2024 | T5: GASTOS 2023 | U5: GASTOS 2022 | V5: GASTOS 2021 | W5: GASTOS 2020 | X5: GASTOS 2019 | Y5: GASTOS 2018 | Z5: GASTOS 2017 | AA5: UTILIDAD 2024 | AB5: UTILIDAD 2023 | AC5: UTILIDAD 2022 | AD5: UTILIDAD 2021 | AE5: UTILIDAD 2020 | AF5: UTILIDAD 2019 | AG5: UTILIDAD 2018 | AH5: UTILIDAD 2017
B6: ENERO | C6: =+[1]pyg2023!D8 -> 2319055 | D6: 0 | E6: 6308768 | F6: 4088450 | G6: 9772741 | H6: 5232922 | I6: 20519674 | J6: 4068398 | K6: =+[1]pyg2023!D16 -> 5070435 | L6: 4878660 | M6: 3100823 | N6: 5295548 | O6: 4656136 | P6: 7998115 | Q6: 5489862 | R6: 3111549 | S6: =+'pyg2024'!B163 -> 9947041 | T6: 10152266 | U6: 8340075.4 | V6: 9031235 | W6: 11183760 | X6: 8192569 | Y6: 7055307 | Z6: 10452832
B7: FEBRERO | C7: =+[1]pyg2023!H8 -> 2198885 | D7: 4332104 | E7: 3904163 | F7: 3444630 | G7: 8662267 | H7: 6735984 | I7: 347610 | J7: 3781685 | K7: =+[1]pyg2023!H16 -> 6521782 | L7: 4693673 | M7: 7094524 | N7: 6881543 | O7: 7804429 | P7: 4974355 | Q7: 7374328 | R7: 8157506 | S7: =+'pyg2024'!F164 -> 13136716 | T7: 13410419 | U7: 9969598 | V7: 12420337 | W7: 13337610 | X7: 8084721 | Y7: 8975623 | Z7: 8843670
B8: MARZO | C8: =+[1]pyg2023!K8 -> 5345924 | D8: 11179580 | E8: 6104727 | F8: 4294490 | G8: 11213082 | H8: 4072345 | I8: 245528 | J8: 3264345 | K8: =+[1]pyg2023!K16 -> 6934538 | L8: 12062967 | M8: 11156171 | N8: 7901560 | O8: 5900305 | P8: 7130437 | Q8: 5439456 | R8: 5780617 | S8: =+'pyg2024'!I163 -> 11222288 | T8: 16907266 | U8: 11403558 | V8: 13591375 | W8: 10865138 | X8: 8025783 | Y8: 9788704 | Z8: 8621927
B9: ABRIL | C9: =+[1]pyg2023!N8 -> 5705085 | D9: 6476561 | E9: 4771392 | F9: 3094715 | G9: 109000 | H9: 8902568 | I9: 311788 | J9: 5714524 | K9: =+[1]pyg2023!N16 -> 11902051 | L9: 13101458 | M9: 11179990 | N9: 10475785 | O9: 121014 | P9: 6001004 | Q9: 7142915 | R9: 5636163 | S9: =+'pyg2024'!L163 -> 13880419 | T9: 12557124 | U9: 11689725 | V9: 17060981 | W9: 8424882 | X9: 11161681 | Y9: 9211395 | Z9: 6162384
B10: MAYO | C10: =+'pyg2024'!P8 -> 6312190 | D10: 2948466 | E10: 3195437 | F10: 3036250 | H10: 4831245 | I10: 2070588 | J10: 1563099 | K10: =+'pyg2024'!P16 -> 5781805 | L10: 11011958 | M10: 9141636 | N10: 9475619 | O10: 1804105 | P10: 7419178 | Q10: 5721041 | R10: 13796936 | S10: =+'pyg2024'!O163 -> 12971414 | T10: 15171959 | U10: 11286631 | V10: 11744517 | W10: 10909925 | X10: 10164486 | Y10: 8014528 | Z10: 10155182
B11: JUNIO | C11: =+'pyg2024'!S8 -> 5308821 | D11: 5460313 | E11: 3587643 | F11: 3220640 | G11: 15088775 | H11: 2541098 | I11: 4186225 | J11: 2504537 | K11: =+'pyg2024'!S16 -> 3102603 | L11: 9771991 | M11: 6890613 | N11: 14072478 | O11: 5883300 | P11: 6384585 | Q11: 4021740 | R11: 6565667 | S11: =+'pyg2024'!R163 -> 10918657 | T11: 10729339 | U11: 12304971 | V11: 12797380 | W11: 12990071 | X11: 8433671 | Y11: 7385244 | Z11: 14240736
B12: JULIO | C12: =+'pyg2024'!W8 -> 1368000 | D12: 5032261 | E12: 5002298 | F12: 2982171 | G12: 5107405 | H12: 2060928 | I12: 3502320 | J12: 14376812 | K12: =+'pyg2024'!W16 -> 4934884 | L12: 5870486 | M12: 8564817 | N12: 7847354 | O12: 9069381 | P12: 4374077 | Q12: 1959742 | R12: 6138041 | S12: =+'pyg2024'!V163 -> 11152404 | T12: 10792468 | U12: 12624706 | V12: 13357892 | W12: 11530572 | X12: 8752682 | Y12: 7676064 | Z12: 10531315
B13: AGOSTO | C13: =+'pyg2024'!AA8 -> 1818800 | D13: 7904377 | E13: 6292782 | F13: 2259634 | G13: 4348355 | H13: 722060 | I13: 13456626 | J13: 9843168 | K13: =+'pyg2024'!AA16 -> 13355048 | L13: 7730780 | M13: 12002561 | N13: 10482068 | O13: 6862717 | P13: 8088583 | Q13: 4820282 | R13: 5449400 | S13: =+'pyg2024'!Z163 -> 11530628 | T13: 10381456 | U13: 0 | V13: 12441445 | W13: 11013798 | X13: 10250005 | Y13: 9472439 | Z13: 10083753
B14: SEPTIEMBRE | C14: =+'pyg2024'!AE8 -> 2263580 | D14: =+[2]pyg2023!AG9 -> 60811795 | E14: 9534674 | F14: 4199993 | G14: 5343486 | H14: 1921510 | I14: 0 | J14: 6807513 | K14: =+'pyg2024'!AE16 -> 12223256 | L14: 12500720 | M14: 8694467 | N14: 12769758 | O14: 9114471 | P14: 5761435 | Q14: 6035931 | R14: 6941815 | S14: =+'pyg2024'!AD29 -> 14014468 | T14: 14685440 | U14: 10423141 | V14: 14262071 | W14: 11098718 | X14: 12341541 | Y14: 16476675 | Z14: 13656658
B15: OCTUBRE | C15: =+'pyg2024'!AI8 -> 3401625 | D15: =+[2]pyg2023!AK9 -> 70303543 | E15: 8627180 | F15: 5953903 | G15: 5206920 | H15: 1940050 | I15: 11000000 | J15: 3921439 | K15: =+'pyg2024'!AI16 -> 12732697 | L15: 7560400 | M15: 6596990 | N15: 11490263 | O15: 11912110 | P15: 5903667 | Q15: 10697305 | R15: 5541550 | S15: =+'pyg2024'!AH29 -> 14110605 | T15: 22974686 | U15: 10630364 | V15: 11384483 | W15: 14559398 | X15: 13788361 | Y15: 10699836 | Z15: 12463405
B16: NOVIEMBRE | C16: =+'pyg2024'!AM8-'pyg2024'!AL8 -> 2974890 | D16: =+[2]pyg2023!AO9 -> 76691258 | E16: 9834611 | F16: 3450527 | G16: 4539945 | H16: 6096979 | I16: 12000000 | J16: 2545390 | K16: =+'pyg2024'!AM16 -> 10221753 | L16: 7355430 | M16: 10351450 | N16: 13482352 | O16: 9403633 | P16: 6953987 | Q16: 7259988 | R16: 6901480 | S16: =+'pyg2024'!AL29 -> 12084858 | T16: 13205069 | U16: 13793441 | V16: 9460840 | W16: 15548745 | X16: 12146151 | Y16: 12696365 | Z16: 13179987
B17: DICIEMBRE | C17: =+'pyg2024'!AQ8 -> 3456110 | D17: =+[2]pyg2023!AS9 -> 85652181 | E17: 6687564 | F17: 3437926 | G17: 5671900 | H17: 10802895 | I17: 13000000 | J17: 68513641 | K17: =+'pyg2024'!AQ16 -> 10979454 | L17: 8377765 | M17: 10009636 | N17: 8072834 | O17: 11129725 | P17: 3580427 | Q17: 8230584 | R17: 7106144 | S17: =+'pyg2024'!AP29 -> 14343828 | T17: 19716602 | U17: 14685347 | V17: 10271878 | W17: 12796951 | X17: 9554095.8 | Y17: 8852048 | Z17: 27294325
B19: TOTAL | C19: =SUM(C6:C17) -> 42472965 | D19: =SUM(D6:D17) -> 336792439 | E19: =SUM(E6:E17) -> 73851239 | F19: =SUM(F6:F17) -> 43463329 | G19: =SUM(G6:G17) -> 75063876 | H19: =SUM(H6:H17) -> 55860584 | I19: =SUM(I6:I17) -> 80640359 | J19: =SUM(J6:J17) -> 126904551 | ... Z19: =SUM(Z6:Z17) -> 145686174 | AA19: =SUM(C130:C141) -> -3080054.9 | AB19: =SUM(D130:D141) -> 13769097 | AC19: =SUM(E130:E141) -> 21095450 | AD19: =SUM(F130:F141) -> 13887078 | AE19: =SUM(G130:G141) -> 14465634 | AF19: =SUM(H130:H141) -> 9534688 | AG19: =SUM(I130:I141) -> 18188372 | AH19: =SUM(J130:J141) -> 62345245
B44: MES | C44: VENTAS FISCALES 2024 | D44: VENTAS FISCALES 2023 | E44: VENTAS FISCALES 2022 | F44: VENTAS FISCALES 2021 | G44: VENTAS FISCALES 2020 | H44: VENTAS FISCALES 2019 | I44: VENTAS FISCALES 2018 | J44: VENTAS FISCALES 2017
B45: ENERO | C45: 2319055 | D45: 0 | E45: 6308768 | F45: 4088450 | G45: 9772741 | H45: 5232922 | I45: 20519674 | J45: 4068398
B46: FEBRERO | C46: 2198885 | D46: 4332104 | E46: 3904163 | F46: 3444630 | G46: 8662267 | H46: 6735984 | I46: 347610 | J46: 3781685
B47: MARZO | C47: 5345924 | D47: 11179580 | E47: 6104727 | F47: 4294490 | G47: 11213082 | H47: 4072345 | I47: 245528 | J47: 3264345
B48: ABRIL | C48: 5705085 | D48: 6476561 | E48: 4771392 | F48: 3094715 | G48: 109000 | H48: 8902568 | I48: 311788 | J48: 5714524
B49: MAYO | C49: 6312190 | D49: 2948466 | E49: 3195437 | F49: 3036250 | G49: 0 | H49: 4831245 | I49: 2070588 | J49: 1563099
B50: JUNIO | C50: 5308821 | D50: 5460313 | E50: 3587643 | F50: 3220640 | G50: 15088775 | H50: 2541098 | I50: 4186225 | J50: 2504537
B51: JULIO | C51: 1368000 | D51: 5032261 | E51: 5002298 | F51: 2982171 | G51: 5107405 | H51: 2060928 | I51: 3502320 | J51: 14376812
B52: AGOSTO | C52: 1818800 | D52: 7904377 | E52: 6292782 | F52: 2259634 | G52: 4348355 | H52: 722060 | I52: 13456626 | J52: 9843168
B53: SEPTIEMBRE | C53: 2263580 | D53: 60811795 | E53: 9534674 | F53: 4199993 | G53: 5343486 | H53: 1921510 | I53: 0 | J53: 6807513
B54: OCTUBRE | C54: 3401625 | D54: 70303543 | E54: 8627180 | F54: 5953903 | G54: 5206920 | H54: 1940050 | I54: 11000000 | J54: 3921439
B55: NOVIEMBRE | C55: 2974890 | D55: 76691258 | E55: 9834611 | F55: 3450527 | G55: 4539945 | H55: 6096979 | I55: 12000000 | J55: 2545390
B56: DICIEMBRE | C56: 3456110 | D56: 85652181 | E56: 6687564 | F56: 3437926 | G56: 5671900 | H56: 10802895 | I56: 13000000 | J56: 68513641
B58: TOTAL | C58: 42472965 | D58: 336792439 | E58: 73851239 | F58: 43463329 | G58: 75063876 | H58: 55860584 | I58: 80640359 | J58: 126904551
B70: MES | C70: VENTAS SIN IVA 2024 | D70: VENTAS SIN IVA 2023 | E70: VENTAS SIN IVA 2022 | F70: VENTAS SIN IVA 2021 | G70: VENTAS SIN IVA 2020 | H70: VENTAS SIN IVA 2019 | I70: VENTAS SIN IVA 2018 | J70: VENTAS SIN IVA 2017
B71: ENERO | C71: 5070435 | D71: 4878660 | E71: 3100823 | F71: 5295548 | G71: 4656136 | H71: 7998115 | I71: 5489862 | J71: 3111549
B72: FEBRERO | C72: 6521782 | D72: 4693673 | E72: 7094524 | F72: 6881543 | G72: 7804429 | H72: 4974355 | I72: 7374328 | J72: 8157506
B73: MARZO | C73: 6934538 | D73: 12062967 | E73: 11156171 | F73: 7901560 | G73: 5900305 | H73: 7130437 | I73: 5439456 | J73: 5780617
B74: ABRIL | C74: 11902051 | D74: 13101458 | E74: 11179990 | F74: 10475785 | G74: 121014 | H74: 6001004 | I74: 7142915 | J74: 5636163
B75: MAYO | C75: 5781805 | D75: 11011958 | E75: 9141636 | F75: 9475619 | G75: 1804105 | H75: 7419178 | I75: 5721041 | J75: 13796936
B76: JUNIO | C76: 3102603 | D76: 9771991 | E76: 6890613 | F76: 14072478 | G76: 5883300 | H76: 6384585 | I76: 4021740 | J76: 6565667
B77: JULIO | C77: 4934884 | D77: 5870486 | E77: 8564817 | F77: 7847354 | G77: 9069381 | H77: 4374077 | I77: 1959742 | J77: 6138041
B78: AGOSTO | C78: 13355048 | D78: 7730780 | E78: 12002561 | F78: 10482068 | G78: 6862717 | H78: 8088583 | I78: 4820282 | J78: 5449400
B79: SEPTIEMBRE | C79: 12223256 | D79: 12500720 | E79: 8694467 | F79: 12769758 | G79: 9114471 | H79: 5761435 | I79: 6035931 | J79: 6941815
B80: OCTUBRE | C80: 12732697 | D80: 7560400 | E80: 6596990 | F80: 11490263 | G80: 11912110 | H80: 5903667 | I80: 10697305 | J80: 5541550
B81: NOVIEMBRE | C81: 10221753 | D81: 7355430 | E81: 10351450 | F81: 13482352 | G81: 9403633 | H81: 6953987 | I81: 7259988 | J81: 6901480
B82: DICIEMBRE | C82: 10979454 | D82: 8377765 | E82: 10009636 | F82: 8072834 | G82: 11129725 | H82: 3580427 | I82: 8230584 | J82: 7106144
B84: TOTAL | C84: 103760306 | D84: 104916288 | E84: 104783678 | F84: 118247162 | G84: 83661326 | H84: 74569850 | I84: 74193174 | J84: 81126868
B103: MES | C103: GASTOS 2024 | D103: GASTOS 2023 | E103: GASTOS 2022 | F103: GASTOS 2021 | G103: GASTOS 2020 | H103: GASTOS 2019 | I103: GASTOS 2018 | J103: GASTOS 2017
B104: ENERO | C104: 9947041 | D104: 10152266 | E104: 8340075.4 | F104: 9031235 | G104: 11183760 | H104: 8192569 | I104: 7055307 | J104: 10452832
B105: FEBRERO | C105: 13136716 | D105: 13410419 | E105: 9969598 | F105: 12420337 | G105: 13337610 | H105: 8084721 | I105: 8975623 | J105: 8843670
B106: MARZO | C106: 11222288 | D106: 16907266 | E106: 11403558 | F106: 13591375 | G106: 10865138 | H106: 8025783 | I106: 9788704 | J106: 8621927
B107: ABRIL | C107: 13880419 | D107: 12557124 | E107: 11689725 | F107: 17060981 | G107: 8424882 | H107: 11161681 | I107: 9211395 | J107: 6162384
B108: MAYO | C108: 12971414 | D108: 15171959 | E108: 11286631 | F108: 11744517 | G108: 10909925 | H108: 10164486 | I108: 8014528 | J108: 10155182
B109: JUNIO | C109: 10918657 | D109: 10729339 | E109: 12304971 | F109: 12797380 | G109: 12990071 | H109: 8433671 | I109: 7385244 | J109: 14240736
B110: JULIO | C110: 11152404 | D110: 10792468 | E110: 12624706 | F110: 13357892 | G110: 11530572 | H110: 8752682 | I110: 7676064 | J110: 10531315
B111: AGOSTO | C111: 11530628 | D111: 10381456 | E111: 0 | F111: 12441445 | G111: 11013798 | H111: 10250005 | I111: 9472439 | J111: 10083753
B112: SEPTIEMBRE | C112: 14014468 | D112: 14685440 | E112: 10423141 | F112: 14262071 | G112: 11098718 | H112: 12341541 | I112: 16476675 | J112: 13656658
B113: OCTUBRE | C113: 14110605 | D113: 22974686 | E113: 10630364 | F113: 11384483 | G113: 14559398 | H113: 13788361 | I113: 10699836 | J113: 12463405
B114: NOVIEMBRE | C114: 12084858 | D114: 13205069 | E114: 13793441 | F114: 9460840 | G114: 15548745 | H114: 12146151 | I114: 12696365 | J114: 13179987
B115: DICIEMBRE | C115: 14343828 | D115: 19716602 | E115: 14685347 | F115: 10271878 | G115: 12796951 | H115: 9554095.8 | I115: 8852048 | J115: 27294325
B116: TOTAL | C116: =SUM(C104:C115) -> 1.4931333e+08 | D116: =SUM(D104:D115) -> 170684094 | E116: =SUM(E104:E115) -> 1.2715156e+08 | F116: =SUM(F104:F115) -> 1.4782443e+08 | G116: =SUM(G104:G115) -> 144259568 | H116: =SUM(H104:H115) -> 120895746 | I116: =SUM(I104:I115) -> 116304228 | J116: =SUM(J104:J115) -> 145686174
B129: MES | C129: UTILIDAD 2024 | D129: UTILIDAD 2023 | E129: UTILIDAD 2022 | F129: UTILIDAD 2021 | G129: UTILIDAD 2020 | H129: UTILIDAD 2019 | I129: UTILIDAD 2018 | J129: UTILIDAD 2017
B130: ENERO | C130: =+C6+K6-S6 -> -2557551 | D130: -5273606 | E130: -1150802.4 | F130: 352800 | G130: 3245117 | H130: 5038468 | I130: 18954229 | J130: -3272885
B131: FEBRERO | C131: =+C7+K7-S7 -> -4416049 | D131: -4384642 | E131: 569556 | F131: -2094164 | G131: 3129086 | H131: 3625618 | I131: -1253685 | J131: 3095521
B132: MARZO | C132: =+C8+K8-S8 -> 1058174.2 | D132: 6335281 | E132: 4047103 | F132: -1395325 | G132: 6248249 | H132: 3176999 | I132: -4103720 | J132: 423035
B133: ABRIL | C133: =+C9+K9-S9 -> 3726717 | D133: 7020895 | E133: 2584980 | F133: -3490481 | G133: -8194868 | H133: 3741891 | I133: -1756692 | J133: 5188303
B134: MAYO | C134: =+C10+K10-S10 -> -877419 | D134: -1211535 | E134: 891255 | F134: 767352.37 | G134: -9105820 | H134: 2085937 | I134: -222899 | J134: 5204853
B135: JUNIO | C135: =+C11+K11-S11 -> -2507233 | D135: 4502965 | E135: -2193718 | F135: 4495738 | G135: 7982004 | H135: 492012 | I135: 822721 | J135: -5170532
B136: JULIO | C136: =+C12+K12-S12 -> -4849520 | D136: 110279 | E136: -1077718 | F136: -2527014 | G136: 2646214 | H136: -2317677 | I136: -2214002 | J136: 9983538
B137: AGOSTO | C137: =+C13+K13-S13 -> 3643220 | D137: 5253701 | E137: 14262195 | F137: 299710 | G137: 197274 | H137: -1439362 | I137: 8804469 | J137: 5208815
B138: SEPTIEMBRE | C138: =+C14+K14-S14 -> 472368 | D138: 9178135 | E138: 2471319 | F138: 2707680 | G138: 3359239 | H138: -4658595.8 | I138: -10440744 | J138: 92670
B139: OCTUBRE | C139: =+C15+K15-S15 -> 2023717 | D139: -5922538 | E139: 1920529 | F139: 6059683 | G139: 2559631.8 | H139: -5944643.8 | I139: 4755101 | J139: -3000416
B140: NOVIEMBRE | C140: =+C16+K16-S16 -> 1111784.9 | D140: 538076 | E140: 8536 | F140: 7472128 | G140: -1605167 | H140: 904815.25 | I140: -380592 | J140: -3733117
B141: DICIEMBRE | C141: =+C17+K17-S17 -> 91736 | D141: -2377914 | E141: -1237785 | F141: 1238971 | G141: 4004674 | H141: 4829226.2 | I141: 5224186 | J141: 48325460
B143: TOTAL | C143: =SUM(C130:C142) -> -3080054.9 | D143: =SUM(D130:D142) -> 13769097 | E143: =SUM(E130:E142) -> 21095450 | F143: =SUM(F130:F142) -> 13887078 | G143: =SUM(G130:G142) -> 14465634 | H143: =SUM(H130:H142) -> 9534688 | I143: =SUM(I130:I142) -> 18188372 | J143: =SUM(J130:J142) -> 62345245

Sheet DISPONIBLE DICIEMBRE 
A2: RECURSOS DIC DE 2024
A4: CAJA | B4: =+'BALANCE DICIEMBRE'!D10 -> 24386159
A5: BANCO BBVA | B5: =+'BALANCE DICIEMBRE'!D14 -> 10438236
A7: TOTAL RECURSOS | C7: =+B4+B5 -> 34824395
A9: CUENTAS POR PAGAR A | C9: =+B11 -> 4312900
A10: CORTO PLAZO
A11: CUENTAS POR PAGAR | B11: =+'BALANCE DICIEMBRE'!E78 -> 4312900
A13: DISPONIBLE RECURSOS | C13: =+C7-C9 -> 30511495
A15: RECURSOS PARA PUERTA DE ORO | C15: 30911830 | D15: LO PENDIENTE PARA PUERTA DE ORO | F15: 20700000 | G15: cdt | H15: =+C15-F15 -> 10211830
A17: TOTAL DISPONIBLE EFECTIVO 30 DIC/24 ANTES DE CUENTAS POR COBRAR | C17: =+C13-C15 -> -400335
A19: DISPONIBLE RECURSOS EFECTIVO | C19: =+C17 -> -400335
A23: DISPONIBLE PARA OPERACIÓN 2024 | C23: =+C19 -> -400335
A27: CARTERA - CUENTAS POR COBRAR | C27: =+'BALANCE DICIEMBRE'!D20+'BALANCE DICIEMBRE'!D21 -> 8077545 | E27: CXC CLIENTE FISCAL Y NO FISCAL
A28: CUENTAS POR COBRAR PENDIENTE DE GASTOS DE ESCRITURACION | C28: =+'BALANCE DICIEMBRE'!D22 -> 2378609 | E28: PRESTAMO A LILIANA
A30: TOTAL RECURSOS | C30: =+C27+C28 -> 10456154 | D30: =+C23+C27+C28 -> 10055819

Sheet CARTERA
C3: DICIEMBRE 31 DE 2024
C4: CARTERA NO FISCAL
C5: DIEGO GUTIERREZ | D5: 1267750
C6: NILSON RUEDA | D6: 0
C7: PABLO JAIMES | D7: 0
C8: MAURICIO | D8: 0
C9: JUAN PABLO SARMIENTO | D9: 0
C10: CARLOS RIVERA | D10: 0
C11: GERARDO CONTRERAS | D11: 0
C12: REYNALDO ARDILA | D12: 0
C13: EDWIN
C14: JOSE LUIS CAMACHO | D14: 3026549
C15: ALQUIOBRAS | D15: 49450
C16: TOTAL | D16: =SUM(D5:D15) -> 4343749
B19: CARTERA FISCAL
B20: 546 | C20: INVERSIONS GYC 23 SAS | D20: 240000
B21: 545 | C21: INVERSIONS GYC 23 SAS | D21: 1309844
B22: 544 | C22: INVERSIONES ULLOA MONSALVE | D22: 25000
B23: 543 | C23: INVERSIONES ULLOA MONSALVE | D23: 148512
B24: 538 | C24: PERFOSANDER | D24: 150000
B25: 537 | C25: PERFOSANDER | D25: 742560
B26: 533 | C26: CUBYCO | D26: 514080
B27: 525 | C27: SALDO DYM INVERSIONES | D27: 103800
B28: 497 | C28: ROBERTO SANCHEZ | D28: 500000 | E28: 45837
D29: =SUM(D20:D28) -> 3733796 | G29: =D16+D29 -> 8077545

Sheet Hoja2
L4: AUTOR
G6: PUERTA DEL ORO
L7: ENER | M7: 26000 | N7: 2319000
G8: JUNIO | H8: 5087939 | L8: FEB | M8: 24000 | N8: 2199000
G9: JULIO | H9: 1526381 | L9: MARZ | M9: 59000 | N9: 5346000
G10: AGOSTO | H10: 1526381 | L10: ABRIL | M10: 63000 | N10: 5726000
G11: SEPT | H11: 1526381 | L11: MAY | M11: 69000 | N11: 6312000
G12: OCTUBRE | H12: 1526381 | L12: JUN | M12: 58000 | N12: 5309000
G13: NOVIEMBRE | H13: 1526381 | L13: JUL | M13: 16000 | N13: 1473000
G14: DIC | H14: 1526381 | L14: AGTO | M14: 20000 | N14: 1819000
G15: ENERO | H15: 1526381 | L15: SEPTI | M15: 25000 | N15: 2264000
G16: FEBRERO | H16: 1526381
G17: MARZO | H17: 1526381
G18: ABRIL | H18: 1526381 | L18: OCT | M18: 37000 | N18: 3402000
G19: MAYO | H19: 1526381 | L19: NOV | M19: 33000 | N19: 2975000
G20: JUNIO | H20: 1526381 | L20: DIC | M20: 38000 | N20: 3456000
G21: JULIO | H21: 1526381
G22: AGOSTO | H22: 1526381 | M22: =SUM(M7:M21) -> 468000
G23: SEPT | H23: 1526381
G24: OCTUBRE | H24: 1526381
G25: NOVIEMBRE | H25: 1526381
G26: DIC | H26: 1526381
G27: 45292 | H27: 1526381
G28: 45323 | H28: 1526381
G29: 45352 | H29: 1526381
G30: 45383 | H30: 1526381
G31: 45413 | H31: 1526381
G32: 45444 | H32: 1526381
G33: 45474 | H33: 1526381
G34: 45505 | H34: 1526381
G35: 45536 | H35: 1526381
G36: 45566 | H36: 1526381
G37: 45597 | H37: 1526381
G40: TOTAL | H40: =SUM(H8:H39) -> 49352988

Sheet RETE
A1: Fecha documento | B1: Documento # | C1: Cuenta - Cód. | D1: Cuenta - Nombre de la cuenta NIIF | E1: Tercero - Cód. | F1: Tercero - Nombre-apellido | G1: CC imputado - Cód. | H1: Débito | I1: Crédito | J1: Saldo
A2: 45381 | B2: CI-000137 | C2: 13551504 | D2: Ret. por servicios en general | E2: 900133059 | F2: CUBYCO CONSTRUCTORES SA | H2: 7142 | I2: 0 | J2: 7142
A3: 45381 | B3: CI-000137 | C3: 13551504 | D3: Ret. por servicios en general | E3: 900133059 | F3: CUBYCO CONSTRUCTORES SA | H3: 56240 | I3: 0 | J3: 56240
A4: 45412 | B4: CI-000141 | C4: 13551504 | D4: Ret. por servicios en general | E4: 900133059 | F4: CUBYCO CONSTRUCTORES SA | H4: 7142 | I4: 0 | J4: 7142
A5: 45412 | B5: CI-000141 | C5: 13551504 | D5: Ret. por servicios en general | E5: 900133059 | F5: CUBYCO CONSTRUCTORES SA | H5: 106765 | I5: 0 | J5: 106765
A6: 45412 | B6: CI-000141 | C6: 13551504 | D6: Ret. por servicios en general | E6: 900133059 | F6: CUBYCO CONSTRUCTORES SA | H6: 2800 | I6: 0 | J6: 2800
A7: 45412 | B7: CI-000141 | C7: 13551504 | D7: Ret. por servicios en general | E7: 900133059 | F7: CUBYCO CONSTRUCTORES SA | H7: 4173 | I7: 0 | J7: 4173
A8: 45443 | B8: CI-000143 | C8: 13551504 | D8: Ret. por servicios en general | E8: 900133059 | F8: CUBYCO CONSTRUCTORES SA | H8: 49831 | I8: 0 | J8: 49831
A9: 45443 | B9: CI-000143 | C9: 13551504 | D9: Ret. por servicios en general | E9: 900443315 | F9: GRUBINM SAS | H9: 51716 | I9: 0 | J9: 51716
A10: 45473 | B10: CI-000145 | C10: 13551504 | D10: Ret. por servicios en general | E10: 900133059 | F10: CUBYCO CONSTRUCTORES SA | H10: 52991 | I10: 0 | J10: 52991
A11: 45473 | B11: CI-000145 | C11: 13551504 | D11: Ret. por servicios en general | E11: 900133059 | F11: CUBYCO CONSTRUCTORES SA | H11: 14054 | I11: 0 | J11: 14054
A12: 45473 | B12: CI-000145 | C12: 13551504 | D12: Ret. por servicios en general | E12: 900502897 | F12: INDUSTRIAS CTS SAS | H12: 20738 | I12: 0 | J12: 20738
A13: 45473 | B13: CI-000145 | C13: 13551504 | D13: Ret. por servicios en general | E13: 900443315 | F13: GRUBINM SAS | H13: 158536 | I13: 0 | J13: 158536
... A32: 45657 | B32: CI-000157 | C32: 13551507 | D32: Ret. por ventas | E32: 901765638 | F32: INVERSIONES G Y C23 S.A.S. | H32: 67824 | I32: 0 | J32: 67824
H33: =SUM(H2:H32) -> 1022451
